Workbook

Sheet Construction
A1: Account / Project Details | B1: Description | D1: Notes
A2: Account Name | D2: Match Google Account Name
A3: Legal Account Name | D3: Legal name of the facility (only needed with A&E)
A4: Account Address | D4: Match Address from Google
A5: Project Name | D5: Match Project Description from CD Drawings
A6: Room Type
A7: Construction Type
A8: RFI Due Date
A9: Bid Due Date
A11: Construction Details | B11: Description | D11: Notes
A12: Takeoff or Hard Bids?
A13: Major Exclusions?
A14: Proposed Phasing?
A15: Below Slab Accessible?
A16: Any Floors Above?
A17: Deck Height
A18: Ceiling Height
A19: Nurse Call Vendor
A20: Mechanical Controls Vendor
A21: Preferred Data Vendor
A22: Preferred MEP Vendors
A23: Preferred Sprinkler Vendor
... A32: Plumbing / Med-Gas Scope of Work
A34: Quote Details | B34: Description | D34: Notes
A35: Pricing Display
A36: Quoting Format
A37: Deposit?
A38: Design Contingency?
A39: Construction Contingency?
A41: Account Contact Details | B41: Name | C41: Phone # | D41: Email Address
A42: Project Champion
A43: Project Manager
A44: Clinical Leader
A45: Invoicing
A46: Facilities
A47: ICRA
A48: Safety
A49: Equipment Vendor
A50: Physicist
A51: Architect
A52: Engineer
A54: Divisions Quoted | B54: Construction Quote Details | C54: Yes/No? | D54: Notes (Note what the scope is per section below)
A55: ="00" -> 00 | B55: Architectural
A56: ="00" -> 00 | B56: Engineering
A57: ="00" -> 00 | B57: Engineering (Structural)
A58: ="00" -> 00 | B58: Engineering (Civil)
A59: ="01" -> 01 | B59: General Conditions
A60: ="02" -> 02 | B60: Demolition
A61: ="03" -> 03 | B61: Concrete
A62: ="03" -> 03 | B62: Concrete Coring
A63: ="04" -> 04 | B63: Masonry
A64: ="05" -> 05 | B64: Structure
A65: ="05" -> 05 | B65: Metal Fabrication
A66: ="06" -> 06 | B66: Millwork
A67: ="06" -> 06 | B67: Countertops
A68: ="07" -> 07 | B68: Roofing
A69: ="08" -> 08 | B69: Doors
A70: ="08" -> 08 | B70: Auto Openers
A71: ="08" -> 08 | B71: Windows
A72: ="08" -> 08 | B72: Storefront
A73: ="09" -> 09 | B73: Finishes
A74: ="09" -> 09 | B74: Specialty Finishes
A75: ="09" -> 09 | B75: Painting
A76: ="09" -> 09 | B76: Flooring
A77: ="09" -> 09 | B77: Tile (Ceramic)
A78: ="10" -> 10 | B78: Signage
A79: ="10" -> 10 | B79: Window Shades
A80: ="10" -> 10 | B80: Bathroom Accessories
A81: ="10" -> 10 | B81: Wall Protection
A82: ="11" -> 11 | B82: Equipment
A83: ="12" -> 12 | B83: Furnishings
A84: ="13" -> 13 | B84: Special Construction
A85: ="14" -> 14 | B85: Conveying Equipment
A86: ="21" -> 21 | B86: Sprinklers
A87: ="22" -> 22 | B87: Plumbing
A88: ="22" -> 22 | B88: Medical Gas
A89: ="23" -> 23 | B89: Mechanical
A90: ="23" -> 23 | B90: Test and Balance
A91: ="23" -> 23 | B91: Mechanical Controls
A92: ="26" -> 26 | B92: Electrical
A93: ="27" -> 27 | B93: Data
A94: ="27" -> 27 | B94: Nurse Call
A95: ="28" -> 28 | B95: Fire Alarm
A96: ="28" -> 28 | B96: Access Controls

Sheet Install Pricelist
A1: Ondal SAP Description | B1: Price (US$) | C1: 2022 Pricing | D1: 2025 Pricing
A2: Install MediBoom Standard, XL, XXL | B2: 2425 | C2: =B2*1.05 -> 2546.25 | D2: =C2*1.1 -> 2800.875
A3: Install Motorized MediBoom Stand.,XL,XXL | B3: 2920 | C3: =B3*1.05 -> 3066 | D3: =C3*1.1 -> 3372.6
A4: Install CEMOR Large Monitor Carrier | B4: 2920 | C4: =B4*1.05 -> 3066 | D4: =C4*1.1 -> 3372.6
A5: Install MediSpace | B5: 2135 | C5: =B5*1.05 -> 2241.75 | D5: =C5*1.1 -> 2465.925
A6: Install SpacePoint System | B6: 1815 | C6: =B6*1.05 -> 1905.75 | D6: =C6*1.1 -> 2096.325
A7: Install Valia Single Arm Lighting System | B7: 1695 | C7: =B7*1.05 -> 1779.75 | D7: =C7*1.1 -> 1957.725
A8: Install Valia Single Arm Monitor System | B8: 1395 | C8: =B8*1.05 -> 1464.75 | D8: =C8*1.1 -> 1611.225
A9: Install Valia Dual Arm Lighting System | B9: 2235 | C9: =B9*1.05 -> 2346.75 | D9: =C9*1.1 -> 2581.425
A10: Install Valia Dual Arm Lighting/Monitor | B10: 2045 | C10: =B10*1.05 -> 2147.25 | D10: =C10*1.1 -> 2361.975
A11: Install Valia Triple Arm Lighting/Monito | B11: 2925 | C11: =B11*1.05 -> 3071.25 | D11: =C11*1.1 -> 3378.375
A12: Remove Existing Equip, Anes, Perf Boom | B12: 995 | C12: =B12*1.05 -> 1044.75 | D12: =C12*1.1 -> 1149.225
A13: Remove Motorized Equip,Anes,Perf Boom | B13: 1095 | C13: =B13*1.05 -> 1149.75 | D13: =C13*1.1 -> 1264.725
... A29: MB Standard, XL,XXL-Extended Warr.-1 yr | B29: 1395 | C29: =B29*1.05 -> 1464.75 | D29: =C29*1.1 -> 1611.225
A30: MB Standard, XL,XXL-Extended Warr.-2 yr | B30: =B29*2 -> 2790 | C30: =B30*1.05 -> 2929.5 | D30: =C30*1.1 -> 3222.45
A31: MB Standard, XL,XXL-Extended Warr.-3 yr | B31: =B29*3 -> 4185 | C31: =B31*1.05 -> 4394.25 | D31: =C31*1.1 -> 4833.675
A32: Motorized MediBoom Extended Warranty 1yr | B32: 1395 | C32: =B32*1.05 -> 1464.75 | D32: =C32*1.1 -> 1611.225
A33: Motorized MediBoom Extended Warranty 2yr | B33: =B32*2 -> 2790 | C33: =B33*1.05 -> 2929.5 | D33: =C33*1.1 -> 3222.45
A34: Motorized MediBoom Extended Warranty 3yr | B34: =B32*3 -> 4185 | C34: =B34*1.05 -> 4394.25 | D34: =C34*1.1 -> 4833.675
A35: CEMOR Large MC Extended Warranty 1yr | B35: 1395 | C35: =B35*1.05 -> 1464.75 | D35: =C35*1.1 -> 1611.225
A36: CEMOR Large MC Extended Warranty 2yr | B36: =B35*2 -> 2790 | C36: =B36*1.05 -> 2929.5 | D36: =C36*1.1 -> 3222.45
A37: CEMOR Large MC Extended Warranty 3yr | B37: =B35*3 -> 4185 | C37: =B37*1.05 -> 4394.25 | D37: =C37*1.1 -> 4833.675
A38: SpacePoint Extended Warranty - 1 Year | B38: 825 | C38: =B38*1.05 -> 866.25 | D38: =C38*1.1 -> 952.875
A39: SpacePoint Extended Warranty - 2 Year | B39: =B38*2 -> 1650 | C39: =B39*1.05 -> 1732.5 | D39: =C39*1.1 -> 1905.75
A40: SpacePoint Extended Warranty - 3 Year | B40: =B38*3 -> 2475 | C40: =B40*1.05 -> 2598.75 | D40: =C40*1.1 -> 2858.625
A41: Valia Single,Dual,Triple Arm Ext Warr 1y | B41: 825 | C41: =B41*1.05 -> 866.25 | D41: =C41*1.1 -> 952.875
A42: Valia Single,Dual,Triple Arm Ext Warr 2y | B42: =B41*2 -> 1650 | C42: =B42*1.05 -> 1732.5 | D42: =C42*1.1 -> 1905.75
A43: Valia Single,Dual,Triple Arm Ext Warr 3y | B43: =B41*3 -> 2475 | C43: =B43*1.05 -> 2598.75 | D43: =C43*1.1 -> 2858.625

Sheet Booms and Lights
A1: Room Name | B1: Phases | C1: Config #1 | D1: Config #2 | E1: Config #3 | F1: Config #4 | G1: Config #5 | H1: Config #6 | I1: Config #7 | J1: Config #8 | K1: Config #9 | L1: Config #10 | Q1: Room Name | R1: Totals
A2: Configuration Name | C2: =IF('Config #1'!B2="","",'Config #1'!B2) -> LED/FP (Patient Left): Camera Capable with Wall Control | D2: =IF('Config #2'!B2="","",'Config #2'!B2) -> LED/FP (Patient Right) | E2: =IF('Config #3'!B2="","",'Config #3'!B2) -> Equipment Boom (Patient Foot) | F2: =IF('Config #4'!B2="","",'Config #4'!B2) -> Anesthesia Boom (Patient Right Shoulder) | G2: =IF('Config #5'!B2="","",'Config #5'!B2) | H2: =IF('Config #6'!B2="","",'Config #6'!B2) | I2: =IF('Config #7'!B2="","",'Config #7'!B2) | J2: =IF('Config #8'!B2="","",'Config #8'!B2) | K2: =IF('Config #9'!B2="","",'Config #9'!B2) | L2: =IF('Config #10'!B2="","",'Config #10'!B2) | N2: Shipping Per Phase | O2: Installation Per Phase | P2: Shipping and Installation Total | Q2: Configuration Name | R2: COG Total
A3: OR1 | B3: 1 | C3: 1 | D3: 1 | E3: 1 | F3: 1 | N3: =SUM(C3:L3)*250 -> 1000 | O3: =SUM(C3:L3)*2500 -> 10000 | P3: =N3*B3+O3*B3 -> 11000 | Q3: OR1 | R3: =SUM(C24*C3)+(D24*D3)+(E24*E3)+(F24*F3)+(G24*G3)+(H24*H3)+(I24*I3)+(J24*J3)+(K24*K3)+(L24*L3) -> 63322.521
N4: =SUM(C4:L4)*250 -> 0 | O4: =SUM(C4:L4)*2500 -> 0 | P4: =N4*B4+O4*B4 -> 0 | R4: =SUM(C24*C4)+(D24*D4)+(E24*E4)+(F24*F4)+(G24*G4)+(H24*H4)+(I24*I4)+(J24*J4)+(K24*K4)+(L24*L4) -> 0
N5: =SUM(C5:L5)*250 -> 0 | O5: =SUM(C5:L5)*2500 -> 0 | P5: =N5*B5+O5*B5 -> 0 | R5: =SUM(C24*C5)+(D24*D5)+(E24*E5)+(F24*F5)+(G24*G5)+(H24*H5)+(I24*I5)+(J24*J5)+(K24*K5)+(L24*L5) -> 0
N6: =SUM(C6:L6)*250 -> 0 | O6: =SUM(C6:L6)*2500 -> 0 | P6: =N6*B6+O6*B6 -> 0 | R6: =SUM(C24*C6)+(D24*D6)+(E24*E6)+(F24*F6)+(G24*G6)+(H24*H6)+(I24*I6)+(J24*J6)+(K24*K6)+(L24*L6) -> 0
N7: =SUM(C7:L7)*250 -> 0 | O7: =SUM(C7:L7)*2500 -> 0 | P7: =N7*B7+O7*B7 -> 0 | R7: =SUM(C24*C7)+(D24*D7)+(E24*E7)+(F24*F7)+(G24*G7)+(H24*H7)+(I24*I7)+(J24*J7)+(K24*K7)+(L24*L7) -> 0
N8: =SUM(C8:L8)*250 -> 0 | O8: =SUM(C8:L8)*2500 -> 0 | P8: =N8*B8+O8*B8 -> 0 | R8: =SUM(C3*C8)+(D3*D8)+(E3*E8)+(F3*F8)+(G3*G8)+(H3*H8)+(I3*I8)+(J3*J8)+(K3*K8)+(L3*L8) -> 0
N9: =SUM(C9:L9)*250 -> 0 | O9: =SUM(C9:L9)*2500 -> 0 | P9: =N9*B9+O9*B9 -> 0 | R9: =SUM(C4*C9)+(D4*D9)+(E4*E9)+(F4*F9)+(G4*G9)+(H4*H9)+(I4*I9)+(J4*J9)+(K4*K9)+(L4*L9) -> 0
N10: =SUM(C10:L10)*250 -> 0 | O10: =SUM(C10:L10)*2500 -> 0 | P10: =N10*B10+O10*B10 -> 0 | R10: =SUM(C5*C10)+(D5*D10)+(E5*E10)+(F5*F10)+(G5*G10)+(H5*H10)+(I5*I10)+(J5*J10)+(K5*K10)+(L5*L10) -> 0
N11: =SUM(C11:L11)*250 -> 0 | O11: =SUM(C11:L11)*2500 -> 0 | P11: =N11*B11+O11*B11 -> 0 | R11: =SUM(C6*C11)+(D6*D11)+(E6*E11)+(F6*F11)+(G6*G11)+(H6*H11)+(I6*I11)+(J6*J11)+(K6*K11)+(L6*L11) -> 0
N12: =SUM(C12:L12)*250 -> 0 | O12: =SUM(C12:L12)*2500 -> 0 | P12: =N12*B12+O12*B12 -> 0 | R12: =SUM(C7*C12)+(D7*D12)+(E7*E12)+(F7*F12)+(G7*G12)+(H7*H12)+(I7*I12)+(J7*J12)+(K7*K12)+(L7*L12) -> 0
A13: TOTAL CONFIGURATIONS | C13: =IF(SUM(C3:C12)=0,"",(SUM(C3:C12))) -> 1 | D13: =IF(SUM(D3:D12)=0,"",(SUM(D3:D12))) -> 1 | E13: =IF(SUM(E3:E12)=0,"",(SUM(E3:E12))) -> 1 | F13: =IF(SUM(F3:F12)=0,"",(SUM(F3:F12))) -> 1 | G13: =IF(SUM(G3:G12)=0,"",(SUM(G3:G12))) | H13: =IF(SUM(H3:H12)=0,"",(SUM(H3:H12))) | I13: =IF(SUM(I3:I12)=0,"",(SUM(I3:I12))) | J13: =IF(SUM(J3:J12)=0,"",(SUM(J3:J12))) | ... L13: =IF(SUM(L3:L12)=0,"",(SUM(L3:L12))) | Q13: TOTAL CONFIGURATIONS | R13: =SUM(C13:L13) -> 4
A14: Simeon COG | C14: =SUM('Config #1'!E67) -> 19747.706 | D14: =SUM('Config #2'!E67) -> 16767.65 | E14: =SUM('Config #3'!E67) -> 0 | F14: =SUM('Config #4'!E67) -> 0 | G14: =SUM('Config #5'!E67) -> 0 | H14: =SUM('Config #6'!E67) -> 0 | I14: =SUM('Config #7'!E67) -> 0 | J14: =SUM('Config #8'!E67) -> 16856.855 | K14: =SUM('Config #9'!E67) -> 0 | L14: =SUM('Config #10'!E67) -> 0
A15: Ondal COG | C15: =('Config #1'!E27)+('Config #1'!E51) -> 0 | D15: =SUM('Config #2'!E27)+('Config #2'!E51) -> 0 | E15: =SUM('Config #3'!E27)+('Config #3'!E51) -> 15494.532 | F15: =SUM('Config #4'!E27)+('Config #4'!E51) -> 11312.632 | G15: =SUM('Config #5'!E27)+('Config #5'!E51) -> 0 | H15: =SUM('Config #6'!E27)+('Config #6'!E51) -> 0 | I15: =SUM('Config #7'!E27)+('Config #7'!E51) -> 0 | J15: =SUM('Config #8'!E27)+('Config #8'!E51) -> 0 | K15: =SUM('Config #9'!E27)+('Config #9'!E51) -> 0 | L15: =SUM('Config #10'!E27)+('Config #10'!E51) -> 0
A16: Ext. Simeon COG | C16: =SUM(C3:C7)*C14 -> 19747.706 | D16: =SUM(D3:D7)*D14 -> 16767.65 | E16: =SUM(E3:E7)*E14 -> 0 | F16: =SUM(F3:F7)*F14 -> 0 | G16: =SUM(G3:G7)*G14 -> 0 | H16: =SUM(H3:H7)*H14 -> 0 | I16: =SUM(I3:I7)*I14 -> 0 | J16: =SUM(J3:J7)*J14 -> 0 | ... L16: =SUM(L3:L7)*L14 -> 0 | Q16: Ext. Simeon COG | R16: =SUM(C16:L16) -> 36515.356
A17: Ext. Ondal COG | C17: =SUM(C3:C7)*C15 -> 0 | D17: =SUM(D3:D7)*D15 -> 0 | E17: =SUM(E3:E7)*E15 -> 15494.532 | F17: =SUM(F3:F7)*F15 -> 11312.632 | G17: =SUM(G3:G7)*G15 -> 0 | H17: =SUM(H3:H7)*H15 -> 0 | I17: =SUM(I3:I7)*I15 -> 0 | J17: =SUM(J3:J7)*J15 -> 0 | ... L17: =SUM(L3:L7)*L15 -> 0 | Q17: Ext. Ondal COG | R17: =SUM(C17:L17) -> 26807.165
A18: Ext. Simeon and Ondal COG | C18: =C24*SUM(C3:C12) -> 19747.706 | D18: =D24*SUM(D3:D12) -> 16767.65 | E18: =E24*SUM(E3:E12) -> 15494.532 | F18: =F24*SUM(F3:F12) -> 11312.632 | G18: =G24*SUM(G3:G12) -> 0 | H18: =H24*SUM(H3:H12) -> 0 | I18: =I24*SUM(I3:I12) -> 0 | J18: =J24*SUM(J3:J12) -> 0 | ... L18: =L24*SUM(L3:L12) -> 0 | Q18: Ext. Simeon & Ondal COG | R18: =SUM(C18:L18) -> 63322.521
Q19: Tarriffs (10%) | R19: =R18*0.1 -> 6332.2521
Q20: Equipment Total | R20: =SUM(R18:R19) -> 69654.773
Q21: Shipping & Install COG | R21: =SUM(P3:P12) -> 11000
Q22: Grand Total COG | R22: =SUM(R20:R21) -> 80654.773
A23: V-- BNL SUPPLIER UNIT COG --V | Q23: List Price @ 40% CM | R23: =R22/(1-0.4) -> 134424.62
A24: Simeon and Ondal COG | C24: =SUM(C14:C15) -> 19747.706 | D24: =SUM(D14:D15) -> 16767.65 | E24: =SUM(E14:E15) -> 15494.532 | F24: =SUM(F14:F15) -> 11312.632 | G24: =SUM(G14:G15) -> 0 | H24: =SUM(H14:H15) -> 0 | I24: =SUM(I14:I15) -> 0 | J24: =SUM(J14:J15) -> 16856.855 | ... L24: =SUM(L14:L15) -> 0 | N24: Shipping | O24: Installation | P24: Total
A25: Configuration List Price | C25: =IF(ISBLANK('Config #1'!B70),0,'Config #1'!B70) -> 65825.687 | D25: =IF(ISBLANK('Config #2'!B70),0,'Config #2'!B70) -> 55892.167 | E25: =IF(ISBLANK('Config #3'!B70),0,'Config #3'!B70) -> 51648.442 | F25: =IF(ISBLANK('Config #4'!B70),0,'Config #4'!B70) -> 37708.775 | G25: =IF(ISBLANK('Config #5'!B70),0,'Config #5'!B70) -> 0 | H25: =IF(ISBLANK('Config #6'!B70),0,'Config #6'!B70) -> 0 | I25: =IF(ISBLANK('Config #7'!B70),0,'Config #7'!B70) -> 0 | J25: =IF(ISBLANK('Config #8'!B70),0,'Config #8'!B70) -> 56189.517 | K25: =IF(ISBLANK('Config #9'!B70),0,'Config #9'!B70) -> 0 | L25: =IF(ISBLANK('Config #10'!B70),0,'Config #10'!B70) -> 0
A26: Ext. Config List Total | C26: =C25*SUM(C3:C12) -> 65825.687 | D26: =D25*SUM(D3:D12) -> 55892.167 | E26: =E25*SUM(E3:E12) -> 51648.442 | F26: =F25*SUM(F3:F12) -> 37708.775 | G26: =G25*SUM(G3:G12) -> 0 | H26: =H25*SUM(H3:H12) -> 0 | I26: =I25*SUM(I3:I12) -> 0 | J26: =J25*SUM(J3:J12) -> 0 | ... L26: =L25*SUM(L3:L12) -> 0
A29: Boom and Light Details
A30: 3D Configurations Link
A31: Competitor Quotes Link
A32: Power Type
A33: Gas Connection Type
A34: Ceiling Height
A35: Pricing Displayed
A36: Summary Page Details
A37: General Notes
A40: Additional Items | B40: Included? | C40: Quote Display
A41: Support+ | Promise
A42: Support+ | In-Case
A43: Support+ | Bio-Med
A44: Project Management
A45: Installation
A46: Shipping

Sheet Estimating Drop Downs
A1: Divisons Included? | B1: Pricing Format | C1: Pricing Shown | D1: Quantity | E1: Feet | F1: Inches | G1: On-Grade? | H1: Floors Above? | I1: Room Type | J1: Construction Type | K1: Deposit | L1: Nurse Call | M1: HVAC Controls | N1: Power Type | O1: Gas Connection Type
A3: Yes | B3: Standard | C3: Lump Sum | D3: 1 | E3: 1 ft | F3: 0.5 in | G3: No | H3: No | I3: Cath / IR | J3: Finishes Refresh | K3: No, 0% | L3: Hill-Rom | M3: Johnson Controls | N3: Isolated (Orange Brown) | O3: Ohmeda
A4: No | B4: Baylor | C4: Groups Only | D4: 2 | E4: 2 ft | F4: 1 in | G4: Yes | H4: Yes | I4: Clinic Support Space | J4: Equipment Replacement | K4: Yes, 5% | L4: Rauland | M4: Siemens | N4: Non-Isolated (Black/White) | O4: Chemetron
A5: TBD | B5: HCA | C5: Line item Pricing | D5: 3 | E5: 3 ft | F5: 1.5 in | I5: CT | J5: Space Conversion | K5: Yes, 10% | M5: Trane | O5: Puritan Bennett
D6: 4 | E6: 4 ft | F6: 2 in | I6: Imaging Renovation | J6: New Build / Addition | K6: Yes, 15% | M6: Other | O6: DISS
D7: 5 | E7: 5 ft | F7: 2.5 in | I7: Linear Accelerator | K7: Yes, 20% | O7: Other
D8: 6 | E8: 6 ft | F8: 3 in | I8: Lobby/Non-Critical | K8: Yes, 25%
D9: 7 | E9: 7 ft | F9: 3.5 in | I9: Medical Office Building | K9: Yes, 30%
D10: 8 | E10: 8 ft | F10: 4 in | I10: MRI | K10: Yes, 35%
D11: 9 | E11: 9 ft | F11: 4.5 in | I11: New Build | K11: Other
D12: 10 | E12: 10 ft | F12: 5 in | I12: OR Renovation
D13: 11 | E13: 11 ft | F13: 5.5 in | I13: Other
D14: 12 | E14: 12 ft | F14: 6 in | I14: Patient Rooms
D15: 13 | E15: 13 ft | F15: 6.5 in | I15: Pharmacy / Lab
D16: 14 | E16: 14 ft | F16: 7 in | I16: Shell Buildout
D17: 15 | E17: 15 ft | F17: 7.5 in | I17: SPD
D18: 16 | E18: 16 ft | F18: 8 in | I18: Tenant Improvement
D19: 17 | E19: 17 ft | F19: 8.5 in | I19: X-Ray
D20: 18 | E20: 18 ft | F20: 9 in
D21: 19 | E21: 19 ft | F21: 9.5 in
D22: 20 | E22: 20 ft | F22: 10 in
F23: 10.5 in
F24: 11 in
F25: 11.5 in

Sheet BnL Drop Downs
A1: Service Types | B1: Service Head Height | C1: Rear Selection | D1: Connection Type | E1: Power Type | F1: Ceiling Tube | G1: Ceiling Cover
B2: Articulating | C2: ="--Not Selected--" -> --Not Selected--
A3: (2) Duplexes | B3: 600mm | C3: Data Pass Thru | D3: Ohmeda | E3: Isolated | F3: 100mm | G3: Single
A4: (3) Duplexes | B4: 800mm | C4: Nitrogen Regulator | D4: Chemetron | E4: Non-Isolated | F4: 300mm | G4: Tandem (1st Position)
A5: Oxygen | B5: 1000mm | D5: Puritan Bennett | F5: 500mm | G5: Tandem (2nd Position)
A6: Medical Air | B6: 1200mm | D6: DISS
A7: Nitrous Oxide | B7: 1400mm
A8: Vacuum | B8: 1600mm
A9: Nitrogen
A10: Carbon Dioxide
A11: WAGD
A12: Data
A13: Storz 4in1
A14: Blank

Sheet Ondal Booms
A2: Base Model | B2: Base Model Sales Price | C2: Ondal List | D2: Ondal Sales | E2: Imagine List | H2: Ondal Discount | I2: Imagine Margin
B3: =""
A4: 1 | B4: Spring | C4: =C14-$C$206 -> 10983.36 | D4: =C4*(1-$H$4) -> 8237.52 | E4: =D4/(1-$I$4)*2 -> 27458.4 | H4: 0.25 | I4: 0.4
A5: 2 | B5: Spring XL | C5: =C15-$C$206 -> 12891.69 | D5: =C5*(1-$H$4) -> 9668.7675 | E5: =D5/(1-$I$4)*2 -> 32229.225
A6: 3 | B6: Powered | C6: =C16-$C$206 -> 11815.05 | D6: =C6*(1-$H$4) -> 8861.2875 | E6: =D6/(1-$I$4)*2 -> 29537.625
A7: 4 | B7: Powered XL | C7: =C17-$C$206 -> 13425.94 | D7: =C7*(1-$H$4) -> 10069.455 | E7: =D7/(1-$I$4)*2 -> 33564.85
A8: 5 | B8: Fixed | C8: =C18-$C$206 -> 7473.19 | D8: =C8*(1-$H$4) -> 5604.8925 | E8: =D8/(1-$I$4)*2 -> 18682.975
A9: 6 | B9: Fixed XL | C9: =C19-$C$206 -> 8900.5 | D9: =C9*(1-$H$4) -> 6675.375 | E9: =D9/(1-$I$4)*2 -> 22251.25
A10: 7 | B10: Fixed XXL | C10: =C20-$C$206 -> 10274.96 | D10: =C10*(1-$H$4) -> 7706.22 | E10: =D10/(1-$I$4)*2 -> 25687.4
B12: Base Model | C12: Ondal List | D12: Ondal Sales | E12: Imagine List | F12: Price Adder | H12: Ceiling Cover | I12: Ceiling Flange | J12: Top Arm | K12: Bottom Arm | L12: Service Head | M12: Misc
B13: =""
A14: 1 | B14: Spring | C14: 11372.18 | D14: =C14*(1-$H$4) -> 8529.135 | E14: =D14/(1-$I$4)*2 -> 28430.45 | F14: 0 | H14: Single | I14: 100mm | J14: =B68 -> 1200mm | K14: Spring | L14: 400mm
A15: 2 | B15: Spring XL | C15: 13280.51 | D15: =C15*(1-$H$4) -> 9960.3825 | E15: =D15/(1-$I$4)*2 -> 33201.275 | F15: 0 | H15: Single | I15: 100mm XL | J15: =B72 -> 1200mm XL | K15: Spring | L15: 400mm
A16: 3 | B16: Powered | C16: 12203.87 | D16: =C16*(1-$H$4) -> 9152.9025 | E16: =D16/(1-$I$4)*2 -> 30509.675 | F16: 0 | H16: Single | I16: 100mm | J16: =B68 -> 1200mm | K16: Powered | L16: 400mm
A17: 4 | B17: Powered XL | C17: 13814.76 | D17: =C17*(1-$H$4) -> 10361.07 | E17: =D17/(1-$I$4)*2 -> 34536.9 | F17: 0 | H17: Single | I17: 100mm XL | J17: =B72 -> 1200mm XL | K17: Powered | L17: 400mm
A18: 5 | B18: Fixed | C18: 7862.01 | D18: =C18*(1-$H$4) -> 5896.5075 | E18: =D18/(1-$I$4)*2 -> 19655.025 | F18: 0 | H18: Single | I18: 100mm | J18: =B68 -> 1200mm | K18: Fixed | L18: 400mm
A19: 6 | B19: Fixed XL | C19: 9289.32 | D19: =C19*(1-$H$4) -> 6966.99 | E19: =D19/(1-$I$4)*2 -> 23223.3 | F19: 0 | H19: Single | I19: 100mm XL | J19: =B72 -> 1200mm XL | K19: Fixed | L19: 400mm
A20: 7 | B20: Fixed XXL | C20: 10663.78 | D20: =C20*(1-$H$4) -> 7997.835 | E20: =D20/(1-$I$4)*2 -> 26659.45 | F20: 0 | H20: Single | I20: 100mm XL | J20: =B72 -> 1200mm XL | K20: Fixed | L20: 400mm
B22: Spring - Large Monitor Boom | C22: =16600.73 -> 16600.73 | D22: =C22*(1-$H$4) -> 12450.548 | E22: =D22/(1-$I$4)*2 -> 41501.825 | F22: =C22-C14 -> 5228.55 | H22: Single | I22: 100mm | J22: =B68 -> 1200mm | K22: Spring | L22: =B106 -> Large Monitor Carrier
B23: Spring XL - Large Monitor Boom | C23: =18509.06 -> 18509.06 | D23: =C23*(1-$H$4) -> 13881.795 | E23: =D23/(1-$I$4)*2 -> 46272.65 | F23: =C23-C15 -> 5228.55 | H23: Single | I23: 100mm XL | J23: =B72 -> 1200mm XL | K23: Spring | L23: Large Monitor Carrier
B24: Powered - 200SH | C24: 11707.68 | D24: =C24*(1-$H$4) -> 8780.76 | E24: =D24/(1-$I$4)*2 -> 29269.2 | F24: =(C24-$C$16) -> -496.19 | H24: Single | I24: 100mm | J24: =$B$68 -> 1200mm | K24: Spring | L24: 200mm
B25: Powered - 600SH | C25: 12701.91 | D25: =C25*(1-$H$4) -> 9526.4325 | E25: =D25/(1-$I$4)*2 -> 31754.775 | F25: =(C25-$C$16) -> 498.04 | H25: Single | I25: 100mm | J25: =$B$68 -> 1200mm | K25: Spring | L25: 600mm
B26: Powered - 800SH | C26: 13222.18 | D26: =C26*(1-$H$4) -> 9916.635 | E26: =D26/(1-$I$4)*2 -> 33055.45 | F26: =(C26-$C$16) -> 1018.31 | H26: Single | I26: 100mm | J26: =$B$68 -> 1200mm | K26: Spring | L26: 800mm
B27: Powered - 1000SH | C27: 13740.59 | D27: =C27*(1-$H$4) -> 10305.443 | E27: =D27/(1-$I$4)*2 -> 34351.475 | F27: =(C27-$C$16) -> 1536.72 | H27: Single | I27: 100mm | J27: =$B$68 -> 1200mm | K27: Spring | L27: 1000mm
B28: Powered - N2 Regulator | C28: 12993.59 | D28: =C28*(1-$H$4) -> 9745.1925 | E28: =D28/(1-$I$4)*2 -> 32483.975 | F28: =(C28-$C$16) -> 789.72 | H28: Single | I28: 100mm | J28: =$B$68 -> 1200mm | K28: Spring | L28: 1000mm
B29: Powered - (3) 500 Shelves | C29: 13746.19 | D29: =C29*(1-$H$4) -> 10309.642 | E29: =D29/(1-$I$4)*2 -> 34365.475 | F29: =(C29-$C$16) -> 1542.32 | H29: Single | I29: 100mm | J29: =$B$68 -> 1200mm | K29: Spring | L29: 100mm
B30: Powered - (3) 750 Shelves | C30: 14534.92 | D30: =C30*(1-$H$4) -> 10901.19 | E30: =D30/(1-$I$4)*2 -> 36337.3 | F30: =(C30-$C$16) -> 2331.05 | H30: Single | I30: 100mm | J30: =$B$68 -> 1200mm | K30: Spring | L30: 100mm
B31: Powered - 300mm Ceiling Flange | C31: 12258.3 | D31: =C31*(1-$H$4) -> 9193.725 | E31: =D31/(1-$I$4)*2 -> 30645.75 | F31: =(C31-$C$16) -> 54.43 | H31: Single | I31: 100mm | J31: =$B$68 -> 1200mm | K31: Spring | L31: 100mm
B32: Powered - 500mm Ceiling Flange | C32: 12389.02 | D32: =C32*(1-$H$4) -> 9291.765 | E32: =D32/(1-$I$4)*2 -> 30972.55 | F32: =(C32-$C$16) -> 185.15 | H32: Single | I32: 100mm | J32: =$B$68 -> 1200mm | K32: Spring | L32: 100mm
B33: Powered - One O2 Outlet | C33: 12590.84 | D33: =C33*(1-$H$4) -> 9443.13 | E33: =D33/(1-$I$4)*2 -> 31477.1 | F33: =(C33-$C$16) -> 386.97 | H33: Single | I33: 100mm | J33: 1200mm XL | K33: Spring | L33: 100mm
B34: Powered - Two O2 Outlet | C34: 12855.61 | D34: =C34*(1-$H$4) -> 9641.7075 | E34: =D34/(1-$I$4)*2 -> 32139.025 | F34: =(C34-$C$16) -> 651.74 | H34: Single | I34: 100mm | J34: 1200mm XL | K34: Spring | L34: 100mm
B35: Powered - Three O2 Outlet | C35: 13120.38 | D35: =C35*(1-$H$4) -> 9840.285 | E35: =D35/(1-$I$4)*2 -> 32800.95 | F35: =(C35-$C$16) -> 916.51 | H35: Single | I35: 100mm | J35: 1200mm XL | K35: Spring | L35: 100mm
B36: Powered - Four O2 Outlet | C36: 13385.15 | D36: =C36*(1-$H$4) -> 10038.862 | E36: =D36/(1-$I$4)*2 -> 33462.875 | F36: =(C36-$C$16) -> 1181.28 | H36: Single | I36: 100mm | J36: 1200mm XL | K36: Spring | L36: 100mm
B37: Powered - Four Duplex | C37: 12529.74 | D37: =C37*(1-$H$4) -> 9397.305 | E37: =D37/(1-$I$4)*2 -> 31324.35 | F37: =(C37-$C$16) -> 325.87 | H37: Single | I37: 100mm | J37: 1200mm XL | K37: Spring | L37: 100mm
B38: Powered - Six Duplex | C38: 12700.07 | D38: =C38*(1-$H$4) -> 9525.0525 | E38: =D38/(1-$I$4)*2 -> 31750.175 | F38: =(C38-$C$16) -> 496.2 | H38: Single | I38: 100mm | J38: 1200mm XL | K38: Spring | L38: 100mm
B39: Powered - Eight Duplex | C39: 12855.61 | D39: =C39*(1-$H$4) -> 9641.7075 | E39: =D39/(1-0.4)*2 -> 32139.025 | F39: =(C39-$C$16) -> 651.74 | H39: Single | I39: 100mm | J39: 1200mm XL | K39: Spring | L39: 100mm
B40: Powered - Twelve Duplex | C40: 13125.91 | D40: =C40*(1-$H$4) -> 9844.4325 | E40: =D40/(1-0.4)*2 -> 32814.775 | F40: =(C40-$C$16) -> 922.04 | H40: Single | I40: 100mm | J40: 1200mm XL | K40: Spring | L40: 100mm
B41: Powered XL - 300mm XL Ceiling Flange | C41: 13471.21 | D41: =C41*(1-$H$4) -> 10103.407 | E41: =D41/(1-$I$4)*2 -> 33678.025 | F41: =(C41-$C$15) -> 190.7 | H41: Single | I41: 100mm | J41: 1200mm XL | K41: Spring | L41: 100mm
B42: Powered XL - 500mm XL Ceiling Flange | C42: 13735.58 | D42: =C42*(1-$H$4) -> 10301.685 | E42: =D42/(1-$I$4)*2 -> 34338.95 | F42: =(C42-$C$15) -> 455.07 | H42: Single | I42: 100mm | J42: 1200mm XL | K42: Spring | L42: 100mm
B43: Spring XL - 1400mm XL Top Arm | C43: 13937.61 | D43: =C43*(1-$H$4) -> 10453.208 | E43: =D43/(1-$I$4)*2 -> 34844.025 | F43: =(C43-$C$15) -> 657.1 | H43: Single | I43: 100mm | J43: 1200mm XL | K43: Spring | L43: 100mm
B44: Spring XL - 1600mm XL Top Arm | C44: 14633.59 | D44: =C44*(1-$H$4) -> 10975.193 | E44: =D44/(1-$I$4)*2 -> 36583.975 | F44: =(C44-$C$15) -> 1353.08 | H44: Single | I44: 100mm | J44: 1200mm XL | K44: Spring | L44: 100mm
A47: Ondal Options | B47: Ceiling Cover | C47: Ondal List | D47: Ondal Sales | E47: Imagine List | H47: Mounting Plate | I47: Ceiling Cover | J47: Reducing Ring
A49: 11-300-603 | B49: Single Mount (Round) | C49: =SUM(H49:K49) -> 1616.36 | D49: =C49*(1-$H$4) -> 1212.27 | E49: =D49/(1-$I$4)*2 -> 4040.9 | H49: =C205 -> 1005.36 | I49: =C208 -> 611 | J49: 0
A50: 11-300-604 | B50: Single Mount (Square) | C50: =SUM(H50:K50) -> 1393.89 | D50: =C50*(1-$H$4) -> 1045.4175 | E50: =D50/(1-$I$4)*2 -> 3484.725 | H50: =C205 -> 1005.36 | I50: =C207 -> 388.53 | J50: 0
A51: 11-300-611 | B51: Tandem (1st Position) | C51: =SUM(C210:C212) -> 1646.49 | D51: =C51*(1-$H$4) -> 1234.8675 | E51: =D51/(1-$I$4)*2 -> 4116.225 | H51: =C210 -> 1005.36 | I51: =C211 -> 379.56 | J51: =C212 -> 261.57
A52: 11-300-612 | B52: Tandem (2nd Position) | C52: 0 | D52: =C52*(1-$H$4) -> 0 | E52: =D52/(1-$I$4)*2 -> 0 | H52: =C206 -> 388.82 | I52: =C210 -> 1005.36 | J52: 0
B54: Ceiling Tube
C55: Ondal List | D55: Ondal Sales | E55: Imagine List
B56: 100mm | C56: 0 | D56: =C56*(1-$H$4) -> 0 | E56: =D56/(1-$I$4)*2 -> 0
B57: 300mm | C57: =F31 -> 54.43 | D57: =C57*(1-$H$4) -> 40.8225 | E57: =D57/(1-$I$4)*2 -> 136.075
B58: 500mm | C58: =F32 -> 185.15 | D58: =C58*(1-$H$4) -> 138.8625 | E58: =D58/(1-$I$4)*2 -> 462.875
B59: 100mm XL | C59: 0 | D59: =C59*(1-$H$4) -> 0 | E59: =D59/(1-$I$4)*2 -> 0
B60: 300mm XL | C60: =F41 -> 190.7 | D60: =C60*(1-$H$4) -> 143.025 | E60: =D60/(1-$I$4)*2 -> 476.75
B61: 500mm XL | C61: =F42 -> 455.07 | D61: =C61*(1-$H$4) -> 341.3025 | E61: =D61/(1-$I$4)*2 -> 1137.675
B63: Top Arm
C64: Ondal List | D64: Ondal Sales | E64: Imagine List
B65: 600mm | C65: 0 | D65: =C65*(1-$H$4) -> 0 | E65: =D65/(1-$I$4)*2 -> 0
B66: 800mm | C66: 0 | D66: =C66*(1-$H$4) -> 0 | E66: =D66/(1-$I$4)*2 -> 0
B67: 1000mm | C67: 0 | D67: =C67*(1-$H$4) -> 0 | E67: =D67/(1-$I$4)*2 -> 0
B68: 1200mm | C68: 0 | D68: =C68*(1-$H$4) -> 0 | E68: =D68/(1-$I$4)*2 -> 0
B69: 600mm XL | C69: 0 | D69: =C69*(1-$H$4) -> 0 | E69: =D69/(1-$I$4)*2 -> 0 | F69: XL
B70: 800mm XL | C70: 0 | D70: =C70*(1-$H$4) -> 0 | E70: =D70/(1-$I$4)*2 -> 0 | F70: XL
B71: 1000mm XL | C71: 0 | D71: =C71*(1-$H$4) -> 0 | E71: =D71/(1-$I$4)*2 -> 0 | F71: XL
B72: 1200mm XL | C72: 0 | D72: =C72*(1-$H$4) -> 0 | E72: =D72/(1-$I$4)*2 -> 0 | F72: XL
B73: 1400mm XL | C73: =C43-C15 -> 657.1 | D73: =C73*(1-$H$4) -> 492.825 | E73: =D73/(1-$I$4)*2 -> 1642.75 | F73: XL
B74: 1600mm XL | C74: =C44-C15 -> 1353.08 | D74: =C74*(1-$H$4) -> 1014.81 | E74: =D74/(1-$I$4)*2 -> 3382.7 | F74: XL
B76: Bottom Arm
C77: Ondal List | D77: Ondal Sales | E77: Imagine List
B78: Powered Articulating | C78: 0 | D78: =C78*(1-$H$4) -> 0 | E78: =D78/(1-$I$4)*2 -> 0 | F78: Powered
B79: Spring Articulating | C79: 0 | D79: =C79*(1-$H$4) -> 0 | E79: =D79/(1-$I$4)*2 -> 0 | F79: Spring
B80: 600mm Fixed | C80: 0 | D80: =C80*(1-$H$4) -> 0 | E80: =D80/(1-$I$4)*2 -> 0 | F80: Fixed
B81: 800mm Fixed | C81: 0 | D81: =C81*(1-$H$4) -> 0 | E81: =D81/(1-$I$4)*2 -> 0 | F81: Fixed
B82: 1000mm Fixed | C82: 0 | D82: =C82*(1-$H$4) -> 0 | E82: =D82/(1-$I$4)*2 -> 0 | F82: Fixed
B83: 1200mm Fixed | C83: 0 | D83: =C83*(1-$H$4) -> 0 | E83: =D83/(1-$I$4)*2 -> 0 | F83: Fixed
B84: 600mm Fixed XL | C84: 0 | D84: =C84*(1-$H$4) -> 0 | E84: =D84/(1-$I$4)*2 -> 0 | F84: Fixed X
B85: 800mm Fixed XL | C85: 0 | D85: =C85*(1-$H$4) -> 0 | E85: =D85/(1-$I$4)*2 -> 0 | F85: Fixed X
B86: 1000mm Fixed XL | C86: 0 | D86: =C86*(1-$H$4) -> 0 | E86: =D86/(1-$I$4)*2 -> 0 | F86: Fixed X
B87: 1200mm Fixed XL | C87: 0 | D87: =C87*(1-$H$4) -> 0 | E87: =D87/(1-$I$4)*2 -> 0 | F87: Fixed X
B89: Column Tube
C90: Ondal List | D90: Ondal Sales | E90: Imagine List
B91: 120mm Column Tube | C91: 0 | D91: =C91*(1-$H$4) -> 0 | E91: =D91/(1-$I$4)*2 -> 0
B92: 200mm Column Tube | C92: 0 | D92: =C92*(1-$H$4) -> 0 | E92: =D92/(1-$I$4)*2 -> 0
B93: 300mm Column Tube | C93: 0 | D93: =C93*(1-$H$4) -> 0 | E93: =D93/(1-$I$4)*2 -> 0
B94: 400mm Column Tube | C94: 0 | D94: =C94*(1-$H$4) -> 0 | E94: =D94/(1-$I$4)*2 -> 0
B95: 500mm Column Tube | C95: 0 | D95: =C95*(1-$H$4) -> 0 | E95: =D95/(1-$I$4)*2 -> 0
B96: 600mm Column Tube | C96: 0 | D96: =C96*(1-$H$4) -> 0 | E96: =D96/(1-$I$4)*2 -> 0
B98: Top Arm
B99: Service Head
C100: Ondal List | D100: Ondal Sales | E100: Imagine List | F100: Actual Price
B101: 200mm Service Head | C101: 0 | D101: =C101*(1-$H$4) -> 0 | E101: =D101/(1-$I$4)*2 -> 0
B102: 400mm Service Head | C102: 0 | D102: =C102*(1-$H$4) -> 0 | E102: =D102/(1-$I$4)*2 -> 0 | F102: =C24-$C$14 -> 335.5
B103: 600mm Service Head | C103: 0 | D103: =C103*(1-$H$4) -> 0 | E103: =D103/(1-$I$4)*2 -> 0 | F103: =C25-$C$14 -> 1329.73
B104: 800mm Service Head | C104: 0 | D104: =C104*(1-$H$4) -> 0 | E104: =D104/(1-$I$4)*2 -> 0 | F104: =C26-$C$14 -> 1850
B105: 1000mm Service Head | C105: 0 | D105: =C105*(1-$H$4) -> 0 | E105: =D105/(1-$I$4)*2 -> 0 | F105: =C27-C14 -> 2368.41
B106: Large Monitor Carrier | C106: =F22 -> 5228.55 | D106: =C106*(1-$H$4) -> 3921.4125 | E106: =D106/(1-$I$4)*2 -> 13071.375
B108: Services
C109: Ondal List | D109: Ondal Sales | E109: Imagine List
B110: =F110&" Duplexes" -> 0 Duplexes | C110: =F110*93.88 -> 0 | D110: =C110*(1-$H$4) -> 0 | E110: =D110/(1-$I$4)*2 -> 0 | F110: 0
B111: =F111&" Duplexes" -> 1 Duplexes | C111: =F111*93.88 -> 93.88 | D111: =C111*(1-$H$4) -> 70.41 | E111: =D111/(1-$I$4)*2 -> 234.7 | F111: 1
B112: =F112&" Duplexes" -> 2 Duplexes | C112: =F112*93.88 -> 187.76 | D112: =C112*(1-$H$4) -> 140.82 | E112: =D112/(1-$I$4)*2 -> 469.4 | F112: 2
...

Sheet Simeon Lights
A1: Base Model(s) | D1: 0 | N1: DISCOUNTS | R1: MARGIN
B2: Part # | C2: Base Model | D2: # of Lights | E2: TC Mount? | F2: Simeon List | G2: Simeon Sales | H2: Imagine List | I2: Ceiling Tube | J2: Central Axis | K2: Turning Cover | M2: Surgical Light | N2: Camera Systems | O2: Exam Lights | P2: Client Discount | R2: Imagine Margin
B4: 11-100-101 | C4: LED | D4: 1 | E4: No | F4: =G4/(1-$M$4) -> 4142.87 | G4: =SUM(I4:K4) -> 2071.435 | H4: =G4/(1-$R$4)*2 -> 6904.7833 | I4: =G225 -> 351.69 | J4: =G124 -> 1719.745 | K4: 0 | M4: 0.5 | N4: 0.45 | O4: 0.45 | P4: 0.5 | R4: 0.4
B5: 11-100-102 | C5: LED / LED | D5: 2 | E5: No | F5: =G5/(1-$M$4) -> 7827.25 | G5: =SUM(I5:K5) -> 3913.625 | H5: =G5/(1-$R$4)*2 -> 13045.417 | I5: =G225 -> 351.69 | J5: =G134 -> 3561.935 | K5: 0
B6: 11-100-103 | C6: LED / LED / LED | D6: 3 | E6: No | F6: =G6/(1-$M$4) -> 10639.91 | G6: =SUM(I6:K6) -> 5319.955 | H6: =G6/(1-$R$4)*2 -> 17733.183 | I6: =G225 -> 351.69 | J6: =G143 -> 4968.265 | K6: 0
B7: 11-100-104 | C7: LED / FP | D7: 1 | E7: No | F7: =G7/(1-$M$4) -> 5874.23 | G7: =SUM(I7:K7) -> 2937.115 | H7: =G7/(1-$R$4)*2 -> 9790.3833 | I7: =G225 -> 351.69 | J7: =G132 -> 2585.425 | K7: =0 -> 0
B8: 11-100-105 | C8: FP / LED | D8: 1 | E8: No | F8: =G8/(1-$M$4) -> 6214.45 | G8: =SUM(I8:K8) -> 3107.225 | H8: =G8/(1-$R$4)*2 -> 10357.417 | I8: =G225 -> 351.69 | J8: =G133 -> 2574.84 | K8: =G181 -> 180.695
B9: 11-100-106 | C9: LED / LED / FP | D9: 2 | E9: No | F9: =G9/(1-$M$4) -> 8860.93 | G9: =SUM(I9:K9) -> 4430.465 | H9: =G9/(1-$R$4)*2 -> 14768.217 | I9: =G225 -> 351.69 | J9: =G141 -> 4078.775 | K9: =0 -> 0
B10: 11-100-107 | C10: FP / LED / FP | D10: 1 | E10: No | F10: =G10/(1-$M$4) -> 8244.23 | G10: =SUM(I10:K10) -> 4122.115 | H10: =G10/(1-$R$4)*2 -> 13740.383 | I10: =G225 -> 351.69 | J10: =G142 -> 3589.73 | K10: =G181 -> 180.695
B11: 11-100-108 | C11: LED / LS | D11: 1 | E11: No | F11: =G11/(1-$M$4) -> 7827.25 | G11: =SUM(I11:K11) -> 3913.625 | H11: =G11/(1-$R$4)*2 -> 13045.417 | I11: =G225 -> 351.69 | J11: =G134 -> 3561.935 | K11: 0
B12: 11-100-109 | C12: LED / LED / LS | D12: 2 | E12: No | F12: =G12/(1-$M$4) -> 10639.91 | G12: =SUM(I12:K12) -> 5319.955 | H12: =G12/(1-$R$4)*2 -> 17733.183 | I12: =G225 -> 351.69 | J12: =G143 -> 4968.265 | K12: 0
B13: 11-100-110 | C13: FP | D13: 0 | E13: No | F13: =G13/(1-$M$4) -> 3442.5 | G13: =SUM(I13:K13) -> 1721.25 | H13: =G13/(1-$R$4)*2 -> 5737.5 | I13: =G225 -> 351.69 | J13: =G125 -> 1369.56 | K13: 0
B14: 11-100-111 | C14: LS | D14: 0 | E14: No | F14: =G14/(1-$M$4) -> 4142.87 | G14: =SUM(I14:K14) -> 2071.435 | H14: =G14/(1-$R$4)*2 -> 6904.7833 | I14: =G225 -> 351.69 | J14: =G124 -> 1719.745 | K14: 0
B15: 11-100-112 | C15: FP / FP | D15: 0 | E15: No | F15: =G15/(1-$M$4) -> 5388.37 | G15: =SUM(I15:K15) -> 2694.185 | H15: =G15/(1-$R$4)*2 -> 8980.6167 | I15: =G225 -> 351.69 | J15: =G135 -> 2161.8 | K15: =G181 -> 180.695
B16: 11-100-113 | C16: LS / LS | D16: 0 | E16: No | F16: =G16/(1-$M$4) -> 7827.25 | G16: =SUM(I16:K16) -> 3913.625 | H16: =G16/(1-$R$4)*2 -> 13045.417 | I16: =G225 -> 351.69 | J16: =G134 -> 3561.935 | K16: 0
B17: 11-100-114 | C17: FP / LS | D17: 0 | E17: No | F17: =G17/(1-$M$4) -> 5853.06 | G17: =SUM(I17:K17) -> 2926.53 | H17: =G17/(1-$R$4)*2 -> 9755.1 | I17: =G225 -> 351.69 | J17: =G133 -> 2574.84 | K17: 0
B18: 11-100-115 | C18: LS / FP | D18: 0 | E18: No | F18: =G18/(1-$M$4) -> 6235.62 | G18: =SUM(I18:K18) -> 3117.81 | H18: =G18/(1-$R$4)*2 -> 10392.7 | I18: =G225 -> 351.69 | J18: =G132 -> 2585.425 | K18: =G181 -> 180.695
B19: 11-100-116 | C19: (3P) LED | D19: 1 | E19: No | F19: =G19/(1-$M$4) -> 2878.16 | G19: =SUM(I19:K19) -> 1439.08 | H19: =G19/(1-$R$4)*2 -> 4796.9333 | I19: =G225 -> 351.69 | J19: =G126 -> 1087.39 | K19: 0
B20: 11-100-117 | C20: (3P) LED / LED | F20: =G20/(1-$M$4) -> 4532.29 | G20: =SUM(I20:K20) -> 2266.145 | H20: =G20/(1-$R$4)*2 -> 7553.8167 | I20: =G226 -> 351.69 | J20: =G136 -> 1914.455
B21: 11-100-118 | C21: UPGRADE | D21: 1 | E21: No | F21: =G21/(1-$M$4) -> 0 | G21: =SUM(I21:K21) -> 0 | H21: =G21/(1-$R$4)*2 -> 0 | I21: 0 | J21: 0 | K21: 0 | M21: 0.5 | N21: 0.4 | O21: 0.45 | P21: 0.5 | R21: 0.4
B22: 11-100-119 | C22: UPGRADE / UPGRADE | D22: 2 | E22: No | F22: =G22/(1-$M$4) -> 0 | G22: =SUM(I22:K22) -> 0 | H22: =G22/(1-$R$4)*2 -> 0 | I22: 0 | J22: 0 | K22: 0
B23: 11-100-120 | C23: UPGRADE / UPGRADE / UPGRADE | D23: 3 | E23: No | F23: =G23/(1-$M$4) -> 0 | G23: =SUM(I23:K23) -> 0 | H23: =G23/(1-$R$4)*2 -> 0 | I23: 0 | J23: 0 | K23: 0
A25: Priced Option(s)
B26: Part # | C26: Arm Selections | D26: Type | F26: Simeon List | G26: Imagine Cost | H26: Imagine List Price | I26: Spring Arm | J26: Lighthead | K26: Flat Panel | L26: Lead Shield | M26: Power Supply | N26: Power Cable | O26: Control Cable | P26: Patch Cable | Q26: Flat Panel Power Cable
B28: 11-200-101 | C28: ="7000 Standard" -> 7000 Standard | D28: LED | F28: =G28/(1-$M$4) -> 16918.19 | G28: =SUM(I28:Q28) -> 8459.095 | H28: =G28/(1-$R$4)*2 -> 28196.983 | I28: =G148 -> 1071.595 | J28: =G160 -> 6461.05 | K28: 0 | L28: 0 | M28: =$G$188 -> 744.63 | N28: =$G$189 -> 87.91 | O28: =$G$190 -> 60.27 | P28: =$G$191 -> 33.64 | Q28: 0
B29: 11-200-102 | C29: 7000 Low Ceiling | D29: LED | F29: =G29/(1-$M$4) -> 18316.85 | G29: =SUM(I29:Q29) -> 9158.425 | H29: =G29/(1-$R$4)*2 -> 30528.083 | I29: =G149 -> 1859.51 | J29: =G161 -> 6372.465 | K29: 0 | L29: 0 | M29: =$G$188 -> 744.63 | N29: =$G$189 -> 87.91 | O29: =$G$190 -> 60.27 | P29: =$G$191 -> 33.64 | Q29: 0
B30: 11-200-103 | C30: ="8000 Standard" -> 8000 Standard | D30: LED | F30: =G30/(1-$M$4) -> 18041.85 | G30: =SUM(I30:Q30) -> 9020.925 | H30: =G30/(1-$R$4)*2 -> 30069.75 | I30: =G148 -> 1071.595 | J30: =G155 -> 7022.88 | K30: 0 | L30: 0 | M30: =$G$188 -> 744.63 | N30: =$G$189 -> 87.91 | O30: =$G$190 -> 60.27 | P30: =$G$191 -> 33.64 | Q30: 0
B31: 11-200-104 | C31: 8000 Low Ceiling | D31: LED | F31: =G31/(1-$M$4) -> 19425.11 | G31: =SUM(I31:Q31) -> 9712.555 | H31: =G31/(1-$R$4)*2 -> 32375.183 | I31: =G149 -> 1859.51 | J31: =G156 -> 6926.595 | K31: 0 | L31: 0 | M31: =$G$188 -> 744.63 | N31: =$G$189 -> 87.91 | O31: =$G$190 -> 60.27 | P31: =$G$191 -> 33.64 | Q31: 0
B32: 11-200-105 | C32: 32in Flat Panel | D32: FP | F32: =G32/(1-$M$4) -> 8150.37 | G32: =SUM(I32:Q32) -> 4075.185 | H32: =G32/(1-$R$4)*2 -> 13583.95 | I32: =G150 -> 1850.235 | J32: =G210 -> 2195.955 | K32: 0 | L32: 0 | M32: 0 | N32: 0 | O32: 0 | P32: 0 | Q32: =G211 -> 28.995
B33: 11-200-106 | C33: Lead Shield | D33: LS | F33: =G33 -> 6449.6 | G33: =SUM(I33:Q33) -> 6449.6 | H33: =G33/(1-$R$4)*2 -> 21498.667 | I33: 0 | J33: 0 | K33: 0 | L33: =G214 -> 6449.6 | M33: 0 | N33: 0 | O33: 0 | P33: 0 | Q33: 0
C35: V-- NON-STANDARD --V | F35: =G35/(1-$M$4) -> 0 | G35: =SUM(I35:Q35) -> 0 | H35: =G35/(1-$R$4)*2 -> 0
B36: 11-200-107 | C36: 500 Standard | D36: LED | F36: =G36/(1-$M$4) -> 10337.15 | G36: =SUM(I36:Q36) -> 5168.575 | H36: =G36/(1-$R$4)*2 -> 17228.583 | I36: =G148 -> 1071.595 | J36: =G168 -> 4096.98
B37: 11-200-108 | C37: 500 Low Ceiling | D37: LED | F37: =G37/(1-$M$4) -> 11735.81 | G37: =SUM(I37:Q37) -> 5867.905 | H37: =G37/(1-$R$4)*2 -> 19559.683 | I37: =G149 -> 1859.51 | J37: =G169 -> 4008.395
B38: 11-200-109 | C38: 500 Standard (3P) | D38: LED | F38: =G38/(1-$M$4) -> 10726.83 | G38: =SUM(I38:Q38) -> 5363.415 | H38: =G38/(1-$R$4)*2 -> 17878.05 | I38: =G146 -> 561.445 | J38: =G166 -> 3875.52 | K38: 0 | L38: 0 | M38: =$G$188 -> 744.63 | N38: =$G$189 -> 87.91 | O38: =$G$190 -> 60.27 | P38: =$G$191 -> 33.64 | Q38: 0
B39: 11-200-110 | C39: 500 Low Ceiling (3P) | D39: LED | F39: =G39/(1-$M$4) -> 11633.12 | G39: =SUM(I39:Q39) -> 5816.56 | H39: =G39/(1-$R$4)*2 -> 19388.533 | I39: =G147 -> 1103.18 | J39: =G167 -> 3786.93 | K39: 0 | L39: 0 | M39: =$G$188 -> 744.63 | N39: =$G$189 -> 87.91 | O39: =$G$190 -> 60.27 | P39: =$G$191 -> 33.64 | Q39: 0
B40: 11-200-111 | C40: 7000 Standard (3P) | D40: LED | F40: =G40/(1-$M$4) -> 15468.27 | G40: =SUM(I40:Q40) -> 7734.135 | H40: =G40/(1-$R$4)*2 -> 25780.45 | I40: =G146 -> 561.445 | J40: =G162 -> 6246.24 | K40: 0 | L40: 0 | M40: =$G$188 -> 744.63 | N40: =$G$189 -> 87.91 | O40: =$G$190 -> 60.27 | P40: =$G$191 -> 33.64 | Q40: 0
B41: 11-200-112 | C41: 7000 Low Ceiling (3P) | D41: LED | F41: =G41/(1-$M$4) -> 16372.35 | G41: =SUM(I41:Q41) -> 8186.175 | H41: =G41/(1-$R$4)*2 -> 27287.25 | I41: =G147 -> 1103.18 | J41: =G163 -> 6156.545 | K41: 0 | L41: 0 | M41: =$G$188 -> 744.63 | N41: =$G$189 -> 87.91 | O41: =$G$190 -> 60.27 | P41: =$G$191 -> 33.64 | Q41: 0
B42: 11-200-113 | C42: 8000 Standard (3P) | D42: LED | F42: =G42/(1-$M$4) -> 16554.57 | G42: =SUM(I42:Q42) -> 8277.285 | H42: =G42/(1-$R$4)*2 -> 27590.95 | I42: =G146 -> 561.445 | J42: =G153 -> 6789.39 | K42: 0 | L42: 0 | M42: =$G$188 -> 744.63 | N42: =$G$189 -> 87.91 | O42: =$G$190 -> 60.27 | P42: =$G$191 -> 33.64 | Q42: 0
B43: 11-200-114 | C43: 8000 Low Ceiling (3P) | D43: LED | F43: =G43/(1-$M$4) -> 17443.06 | G43: =SUM(I43:Q43) -> 8721.53 | H43: =G43/(1-$R$4)*2 -> 29071.767 | I43: =G147 -> 1103.18 | J43: =G154 -> 6691.9 | K43: 0 | L43: 0 | M43: =$G$188 -> 744.63 | N43: =$G$189 -> 87.91 | O43: =$G$190 -> 60.27 | P43: =$G$191 -> 33.64 | Q43: 0
B44: 11-200-115 | C44: ="UPGRADE - SPECIAL PRICING" -> UPGRADE - SPECIAL PRICING | D44: LED | F44: =G44/(1-$M$4) -> 15000 | G44: =SUM(I44:Q44) -> 7500 | H44: =G44/(1-$R$4)*2 -> 25000 | I44: 0 | J44: =G159 -> 7500 | K44: 0 | L44: 0 | M44: 0 | N44: 0 | O44: 0 | P44: 0 | Q44: 0
B45: 11-200-116 | C45: FP (TC-Ondal) | F45: =G45/(1-$M$4) -> 6750 | G45: =SUM(I45:Q45) -> 3375 | H45: =G45/(1-$R$4)*2 -> 11250 | I45: 0 | J45: =G217 -> 3375 | K45: 0 | L45: 0 | M45: 0 | N45: 0 | O45: 0 | P45: 0 | Q45: 0
B46: 11-200-117 | C46: 4500 Exam Light | F46: =G46/(1-$M$4) -> 6059.35 | G46: =SUM(I46:Q46) -> 3029.675 | H46: =G46/(1-$R$4)*2 -> 10098.917 | I46: 0 | J46: =G172 -> 3029.675 | K46: 0 | L46: 0 | M46: 0 | N46: 0 | O46: 0 | P46: 0 | Q46: 0
C48: Ceiling Drop Tubes | F48: Simeon List | G48: Imagine Cost | H48: Imagine List Price
B50: 11-300-001 | C50: 150mm | F50: =G50/(1-$M$4) -> 0 | G50: =SUM(I50:O50) -> 0 | H50: =G50/(1-$R$4)*2 -> 0 | I50: 0 | J50: 0 | K50: 0 | L50: 0 | M50: 0 | N50: 0 | O50: 0
B51: 11-300-002 | C51: 200mm | F51: =G51/(1-$M$4) -> 0 | G51: =SUM(I51:O51) -> 0 | H51: =G51/(1-$R$4)*2 -> 0 | I51: 0 | J51: 0 | K51: 0 | L51: 0 | M51: 0 | N51: 0 | O51: 0
B52: 11-300-003 | C52: 250mm | F52: =G52/(1-$M$4) -> 0 | G52: =SUM(I52:O52) -> 0 | H52: =G52/(1-$R$4)*2 -> 0 | I52: 0 | J52: 0 | K52: 0 | L52: 0 | M52: 0 | N52: 0 | O52: 0
B53: 11-300-004 | C53: 300mm | F53: =G53/(1-$M$4) -> 0 | G53: =SUM(I53:O53) -> 0 | H53: =G53/(1-$R$4)*2 -> 0 | I53: 0 | J53: 0 | K53: 0 | L53: 0 | M53: 0 | N53: 0 | O53: 0
B54: 11-300-005 | C54: 350mm | F54: =G54/(1-$M$4) -> 0 | G54: =SUM(I54:O54) -> 0 | H54: =G54/(1-$R$4)*2 -> 0 | I54: 0 | J54: 0 | K54: 0 | L54: 0 | M54: 0 | N54: 0 | O54: 0
B55: 11-300-006 | C55: 400mm | F55: =G55/(1-$M$4) -> 0 | G55: =SUM(I55:O55) -> 0 | H55: =G55/(1-$R$4)*2 -> 0 | I55: 0 | J55: 0 | K55: 0 | L55: 0 | M55: 0 | N55: 0 | O55: 0
B56: 11-300-007 | C56: 450mm | F56: =G56/(1-$M$4) -> 0 | G56: =SUM(I56:O56) -> 0 | H56: =G56/(1-$R$4)*2 -> 0 | I56: 0 | J56: 0 | K56: 0 | L56: 0 | M56: 0 | N56: 0 | O56: 0
B57: 11-300-008 | C57: 500mm | F57: =G57/(1-$M$4) -> 0 | G57: =SUM(I57:O57) -> 0 | H57: =G57/(1-$R$4)*2 -> 0 | I57: 0 | J57: 0 | K57: 0 | L57: 0 | M57: 0 | N57: 0 | O57: 0
B58: 11-300-010 | C58: Upgrade Only | F58: =G58/(1-$M$4) -> 0 | G58: =SUM(I58:O58) -> 0 | H58: =G58/(1-$R$4)*2 -> 0 | I58: 0 | J58: 0 | K58: 0 | L58: 0 | M58: 0 | N58: 0
B59: 11-300-009 | C59: Ondal TC Flange | F59: =G59/(1-$M$4) -> 0 | G59: =SUM(I59:O59) -> 0 | H59: =G59/(1-$R$4)*2 -> 0 | I59: 0 | J59: 0 | K59: 0 | L59: 0 | M59: 0 | N59: 0 | O59: 0
B61: Part # | C61: Wall Control | F61: Simeon List | G61: Imagine Cost | H61: Imagine List Price | I61: Handle Adapter | J61: Lintex Parts | K61: Wall Control | L61: Installation | M61: Sim.Flex Arms | N61: Mounting Plate | O61: Ceiling Cover | P61: Wall Control Back Box
C63: No Wall Control | F63: =G63/(1-$M$4) -> 0 | G63: =SUM(I63:O63) -> 0 | H63: =G63/(1-$R$4)*2 -> 0 | I63: 0 | J63: 0 | K63: 0 | L63: 0 | M63: 0 | N63: 0
B64: 11-300-101 | C64: Wall Control in Separate Config | F64: =G64/(1-$M$4) -> 0 | G64: =SUM(I64:O64) -> 0 | H64: =G64/(1-$R$4)*2 -> 0 | I64: 0 | J64: 0 | K64: 0 | L64: 0 | M64: 0 | N64: 0
B65: 11-300-102 | C65: Wall Control (Touch) | F65: =G65/(1-$M$4) -> 2995.37 | G65: =SUM(I65:P65) -> 1497.685 | H65: =G65/(1-$R$4)*2 -> 4992.2833 | I65: 0 | J65: 0 | K65: =G194 -> 1302.685 | L65: 0 | M65: 0 | N65: 0 | O65: 0 | P65: =$G$186 -> 195
B66: 11-300-103 | C66: Wall Control (Single) | F66: =G66/(1-$M$4) -> 1577.44 | G66: =SUM(I66:P66) -> 788.72 | H66: =G66/(1-$R$4)*2 -> 2629.0667 | I66: 0 | J66: 0 | K66: =G195 -> 593.72 | L66: 0 | M66: 0 | N66: 0 | O66: 0 | P66: =$G$186 -> 195
B67: 11-300-104 | C67: Wall Control (Dual) | F67: =G67/(1-$M$4) -> 2163.1 | G67: =SUM(I67:P67) -> 1081.55 | H67: =G67/(1-$R$4)*2 -> 3605.1667 | I67: 0 | J67: 0 | K67: =G196 -> 886.55 | L67: 0 | M67: 0 | N67: 0 | O67: 0 | P67: =$G$186 -> 195
B68: 11-300-105 | C68: Wall Control (Triple) | F68: =G68/(1-$M$4) -> 3074.91 | G68: =SUM(I68:P68) -> 1537.455 | H68: =G68/(1-$R$4)*2 -> 5124.85 | I68: 0 | J68: 0 | K68: =G197 -> 1342.455 | L68: 0 | M68: 0 | N68: 0 | O68: 0 | P68: =$G$186 -> 195
B69: 11-300-106 | C69: Wall Control (Single w/ Cam) | F69: =G69/(1-$M$4) -> 2228.94 | G69: =SUM(I69:P69) -> 1114.47 | H69: =G69/(1-$R$4)*2 -> 3714.9 | I69: 0 | J69: 0 | K69: =G198 -> 919.47 | L69: 0 | M69: 0 | N69: 0 | O69: 0 | P69: =$G$186 -> 195
B70: 11-300-107 | C70: Wall Control (Dual w/ Cam) | F70: =G70/(1-$M$4) -> 2971.34 | G70: =SUM(I70:P70) -> 1485.67 | H70: =G70/(1-$R$4)*2 -> 4952.2333 | I70: 0 | J70: 0 | K70: =G199 -> 1290.67 | L70: 0 | M70: 0 | N70: 0 | O70: 0 | P70: =$G$186 -> 195
B71: 11-300-108 | C71: Wall Control (Triple w/ Cam) | F71: =G71/(1-$M$4) -> 3803.26 | G71: =SUM(I71:P71) -> 1901.63 | H71: =G71/(1-$R$4)*2 -> 6338.7667 | I71: 0 | J71: 0 | K71: =G200 -> 1706.63 | L71: 0 | M71: 0 | N71: 0 | O71: 0 | P71: =$G$186 -> 195
C73: Device Control | F73: Simeon List | G73: Imagine Cost | H73: Imagine List Price
C75: No Integration Control | F75: =G75/(1-$M$4) -> 0 | G75: =SUM(I75:O75) -> 0 | H75: =G75/(1-$R$4)*2 -> 0 | I75: 0 | J75: 0 | K75: 0 | L75: 0 | M75: 0 | N75: 0 | O75: 0 | P75: 0
B76: 11-300-201 | C76: Storz Integration Control | F76: =G76/(1-$M$4) -> 1705.22 | G76: =SUM(I76:O76) -> 852.61 | H76: =G76/(1-$R$4)*2 -> 2842.0333 | I76: 0 | J76: 0 | K76: =G220 -> 852.61 | L76: 0 | M76: 0 | N76: 0 | O76: 0 | P76: 0
C78: In-Light Camera | F78: Simeon List | G78: Imagine Cost | H78: Imagine List Price | K78: Camera Pkg | P78: BNC Cable
C80: No Camera Prep | F80: =G80/(1-$N$4) -> 0 | G80: =SUM(I80:Q80) -> 0 | H80: =G80/(1-$R$4)*2 -> 0 | I80: 0 | J80: 0 | K80: 0 | L80: 0 | M80: 0 | N80: 0 | O80: 0 | P80: 0
B81: 11-300-301 | C81: Wired Camera Prep | F81: =G81/(1-$N$4) -> 2695.22 | G81: =SUM(I81:Q81) -> 1482.371 | H81: =G81/(1-$R$4)*2 -> 4941.2367 | I81: 0 | J81: 0 | K81: =G203 -> 1435.159 | L81: 0 | M81: 0 | N81: 0 | O81: 0 | P81: =G207 -> 47.212
B82: 11-300-302 | C82: Wired Camera | F82: =G82/(1-$N$4) -> 14195.04 | G82: =SUM(I82:Q82) -> 7807.272 | H82: =G82/(1-$R$4)*2 -> 26024.24 | I82: 0 | J82: 0 | K82: =G204 -> 7807.272 | L82: 0 | M82: 0 | N82: 0 | O82: 0 | P82: 0
B83: 11-300-303 | C83: Wireless Camera | F83: =G83/(1-$N$4) -> 19831.3 | G83: =SUM(I83:Q83) -> 10907.215 | H83: =G83/(1-$R$4)*2 -> 36357.383 | I83: 0 | J83: 0 | K83: =G205 -> 10907.215 | L83: 0 | M83: 0 | N83: 0 | O83: 0 | P83: 0
C85: Disposable Adapters | F85: Simeon List | G85: Imagine Cost | H85: Imagine List Price
C87: No Handle Adapter(s) | F87: =G87/(1-$M$4) -> 0 | G87: =SUM(I87:O87) -> 0 | H87: =G87/(1-$R$4)*2 -> 0 | I87: 0 | J87: 0 | K87: 0 | L87: 0 | M87: 0 | N87: 0 | O87: 0
B88: 11-300-401 | C88: (1) Screw-On Adapters | F88: =G88/(1-$M$4) -> 264 | G88: =SUM(I88:O88) -> 132 | H88: =G88/(1-$R$4)*2 -> 440 | I88: 0 | J88: =G177*1 -> 132 | K88: 0 | L88: 0 | M88: 0 | N88: 0 | O88: 0
B89: 11-300-401 | C89: (2) Screw-On Adapters | F89: =G89/(1-$M$4) -> 528 | G89: =SUM(I89:O89) -> 264 | H89: =G89/(1-$R$4)*2 -> 880 | I89: 0 | J89: =G177*2 -> 264 | K89: 0 | L89: 0 | M89: 0 | N89: 0 | O89: 0
B90: 11-300-401 | C90: (3) Screw-On Adapters | F90: =G90/(1-$M$4) -> 792 | G90: =SUM(I90:O90) -> 396 | H90: =G90/(1-$R$4)*2 -> 1320 | I90: 0 | J90: =G177*3 -> 396 | K90: 0 | L90: 0 | M90: 0 | N90: 0 | O90: 0
B91: 11-300-401 | C91: (1) Slip-On Adapter | F91: =G91/(1-$M$4) -> 264 | G91: =SUM(I91:O91) -> 132 | H91: =G91/(1-$R$4)*2 -> 440 | I91: 0 | J91: =G176*1 -> 132 | K91: 0 | L91: 0 | M91: 0 | N91: 0 | O91: 0
B92: 11-300-401 | C92: (2) Slip-On Adapters | F92: =G92/(1-$M$4) -> 528 | G92: =SUM(I92:O92) -> 264 | H92: =G92/(1-$R$4)*2 -> 880 | I92: 0 | J92: =G176*2 -> 264 | K92: 0 | L92: 0 | M92: 0 | N92: 0 | O92: 0
B93: 11-300-402 | C93: (3) Slip-On Adapters | F93: =G93/(1-$M$4) -> 792 | G93: =SUM(I93:O93) -> 396 | H93: =G93/(1-$R$4)*2 -> 1320 | I93: 0 | J93: =G176*3 -> 396 | K93: 0 | L93: 0 | M93: 0 | N93: 0 | O93: 0
C95: Sim.Flex Arm(s) | F95: Simeon List | G95: Imagine Cost | H95: Imagine List Price
C97: Standard Armset | F97: =G97/(1-$M$4) -> 0 | G97: =SUM(I97:O97) -> 0 | H97: =G97/(1-$R$4)*2 -> 0 | I97: 0 | J97: 0 | K97: 0 | L97: 0 | M97: 0 | N97: 0 | O97: 0
B98: 11-300-501 | C98: Sim.Flex (1 Arm) | F98: =G98/(1-$M$4) -> 3500 | G98: =SUM(I98:O98) -> 1750 | H98: =G98/(1-$R$4)*2 -> 5833.3333 | I98: 0 | J98: 0 | K98: 0 | L98: 0 | M98: 1750 | N98: 0 | O98: 0
B99: 11-300-502 | C99: Sim.Flex (2 Arms) | F99: =G99/(1-$M$4) -> 5500 | G99: =SUM(I99:O99) -> 2750 | H99: =G99/(1-$R$4)*2 -> 9166.6667 | I99: 0 | J99: 0 | K99: 0 | L99: 0 | M99: 2750 | N99: 0 | O99: 0
B100: 11-300-503 | C100: Sim.Flex (3 Arms) | F100: =G100/(1-$M$4) -> 7500 | G100: =SUM(I100:O100) -> 3750 | H100: =G100/(1-$R$4)*2 -> 12500 | I100: 0 | J100: 0 | K100: 0 | L100: 0 | M100: 3750 | N100: 0 | O100: 0
C102: Pre-Installation | F102: Simeon List | G102: Imagine Cost | H102: Imagine List Price | N102: Ceiling Cover | O102: Mounting Plate
G103: =SUM(I103:O103) -> 0
B104: 11-300-601 | C104: Single Mount (Standard) | F104: =G104/(1-$M$4) -> 864.63 | G104: =SUM(I104:O104) -> 432.315 | H104: =G104/(1-$R$4)*2 -> 1441.05 | I104: 0 | J104: 0 | K104: 0 | L104: 0 | M104: 0 | N104: =G180 -> 156.435 | O104: =G182 -> 275.88
B105: 11-300-602 | C105: Single Mount (Universal) | F105: =G105/(1-$M$4) -> 2012.85 | G105: =SUM(I105:O105) -> 1006.425 | H105: =G105/(1-$R$4)*2 -> 3354.75 | I105: 0 | J105: 0 | K105: 0 | L105: 0 | M105: 0 | N105: =G180 -> 156.435 | O105: =G183 -> 849.99
B106: 11-300-611 | C106: Tandem (1st Position) | F106: =G106/(1-$M$4) -> 2469.735 | G106: =SUM(I106:O106) -> 1234.8675 | H106: =G106/(1-$R$4)*2 -> 4116.225 | I106: 0 | J106: 0 | K106: 0 | L106: 0 | M106: 0 | N106: ='Ondal Booms'!D211+'Ondal Booms'!D212 -> 480.8475 | O106: ='Ondal Booms'!D210 -> 754.02
B107: 11-300-612 | C107: Tandem (2nd Position) | F107: =G107/(1-$M$4) -> 0 | G107: =SUM(I107:O107) -> 0 | H107: =G107/(1-$R$4)*2 -> 0 | I107: 0 | J107: 0 | K107: 0 | L107: 0 | M107: 0 | N107: 0 | O107: 0
B108: 11-300-613 | C108: Upgrade Only | F108: =G108/(1-$M$4) -> 0 | G108: =SUM(I108:O108) -> 0 | H108: =G108/(1-$R$4)*2 -> 0 | I108: 0 | J108: 0 | K108: 0 | L108: 0 | M108: 0 | N108: 0 | O108: 0
C110: Installation | F110: Simeon List | G110: Imagine Cost | H110: Imagine List Price
B112: 11-400-101 | C112: Installation | F112: =G112/(1-$M$4) -> 1800 | G112: 900 | H112: =G112/(1-$R$4)*2 -> 3000 | I112: 0 | J112: 0 | K112: 0 | L112: 1000 | M112: 0 | N112: 0 | O112: 0
C114: Shipping | F114: Simeon List | G114: Imagine Cost | H114: Imagine List Price
B116: 11-500-101 | C116: Shipping | F116: =G116/(1-$M$4) -> 600 | G116: 300 | H116: =G116/(1-$R$4)*2 -> 1000 | I116: 0 | J116: 0 | K116: 0 | L116: 500 | M116: 0 | N116: 0 | O116: 0
A119: SIMEON PART NUMBERS
B121: Single Armsets | C121: Description | F121: 2025 Simeon List | G121: 2025 Simeon Sales | I121: 2024 Simeon List Price | J121: 2024 Cost of Goods | K121: Notes
B122: 111-0017102 | C122: Central axis single - 9-pole | F122: 3280.9 | G122: =F122*(1-$M$4) -> 1640.45 | I122: 2715.32 | J122: =I122*(1-$C$284) -> 1357.66 | K122: LED (Standard)
B123: 111-0017104 | C123: Central axis single - TFT AC3000 | F123: 2493.5 | G123: =F123*(1-$M$4) -> 1246.75 | I123: 2657.42 | J123: =I123*(1-$C$284) -> 1328.71 | K123: FP (Standard)
B124: 111-0017139 | C124: Central axis single - 9-pole SL 1300mm | F124: 3439.49 | G124: =F124*(1-$M$4) -> 1719.745 | I124: 3387.27 | J124: =I124*(1-$C$284) -> 1693.635 | K124: LED (Extended)
...

Sheet Cost Analysis
C2: CONFIGURATION DESCRIPTION | D2: ONDAL QUOTE | E2: IMAGINE EXCEL | F2: DELTA | H2: SIMEON QUOTE | I2: TANDEM | J2: HANDLE ADT. | K2: WCP BACKBOX | L2: IMAGINE EXCEL | M2: DELTA
B3: Config #1 | C3: =IF(ISBLANK('Config #1'!B2),"",'Config #1'!B2) -> LED/FP (Patient Left): Camera Capable with Wall Control | D3: 0 | E3: ='Config #1'!E27 -> 0 | F3: =E3-O3 -> 0 | I3: =IF('Config #1'!B55="Tandem (1st Position)",1317.19,0) -> 0 | J3: ='Config #1'!E63 -> 132 | K3: =IF(RIGHT('Config #1'!B60,1)=")",195,0) -> 195 | L3: ='Config #1'!E67 -> 19747.706 | M3: =L3-SUM(H3:K3) -> 19420.706
B4: Config #2 | C4: =IF(ISBLANK('Config #2'!B2),"",'Config #2'!B2) -> LED/FP (Patient Right) | D4: 0 | E4: ='Config #2'!E27 -> 0 | F4: =E4-O4 -> 0 | H4: 0 | I4: =IF('Config #2'!B55="Tandem (1st Position)",1317.19,0) -> 0 | J4: ='Config #2'!E63 -> 132 | K4: =IF(RIGHT('Config #2'!B60,1)=")",195,0) -> 0 | L4: ='Config #2'!E67 -> 16767.65 | M4: =L4-SUM(H4:K4) -> 16635.65
B5: Config #3 | C5: =IF(ISBLANK('Config #3'!B2),"",'Config #3'!B2) -> Equipment Boom (Patient Foot) | D5: 0 | E5: ='Config #3'!E27 -> 15494.532 | F5: =E5-O5 -> 15494.532 | H5: 0 | I5: =IF('Config #3'!B55="Tandem (1st Position)",1317.19,0) -> 0 | J5: ='Config #3'!E63 -> 0 | K5: =IF(RIGHT('Config #3'!B60,1)=")",195,0) -> 0 | L5: ='Config #3'!E67 -> 0 | M5: =L5-SUM(H5:K5) -> 0
B6: Config #4 | C6: =IF(ISBLANK('Config #4'!B2),"",'Config #4'!B2) -> Anesthesia Boom (Patient Right Shoulder) | D6: 0 | E6: ='Config #4'!E27 -> 11312.632 | F6: =E6-O6 -> 11312.632 | H6: 0 | I6: =IF('Config #4'!B55="Tandem (1st Position)",1317.19,0) -> 0 | J6: ='Config #4'!E63 -> 0 | K6: =IF(RIGHT('Config #4'!B60,1)=")",195,0) -> 0 | L6: ='Config #4'!E67 -> 0 | M6: =L6-SUM(H6:K6) -> 0
B7: Config #5 | C7: =IF(ISBLANK('Config #5'!B2),"",'Config #5'!B2) | D7: 0 | E7: ='Config #5'!E27 -> 0 | F7: =E7-O7 -> 0 | H7: 0 | I7: =IF('Config #5'!B55="Tandem (1st Position)",1317.19,0) -> 0 | J7: ='Config #5'!E63 -> 0 | K7: =IF(RIGHT('Config #5'!B60,1)=")",195,0) -> 0 | L7: ='Config #5'!E67 -> 0 | M7: =L7-SUM(H7:K7) -> 0
B8: Config #6 | C8: =IF(ISBLANK('Config #6'!B2),"",'Config #6'!B2) | D8: 0 | E8: ='Config #6'!E27 -> 0 | F8: =E8-O8 -> 0 | H8: 0 | I8: =IF('Config #6'!B55="Tandem (1st Position)",1317.19,0) -> 0 | J8: ='Config #6'!E63 -> 0 | K8: =IF(RIGHT('Config #6'!B60,1)=")",195,0) -> 0 | L8: ='Config #6'!E67 -> 0
B9: Config #7 | C9: =IF(ISBLANK('Config #7'!B2),"",'Config #7'!B2) | D9: 0 | E9: ='Config #7'!E27 -> 0 | F9: =E9-O9 -> 0 | H9: 0 | I9: =IF('Config #7'!B55="Tandem (1st Position)",1317.19,0) -> 0 | J9: ='Config #7'!E63 -> 0 | K9: =IF(RIGHT('Config #7'!B60,1)=")",195,0) -> 0 | L9: ='Config #7'!E67 -> 0
B10: Config #8 | C10: =IF(ISBLANK('Config #8'!B2),"",'Config #8'!B2) | D10: 0 | E10: ='Config #8'!E27 -> 0 | F10: =E10-O10 -> 0 | H10: 0 | I10: =IF('Config #8'!B55="Tandem (1st Position)",1317.19,0) -> 0 | J10: ='Config #8'!E63 -> 132 | K10: =IF(RIGHT('Config #8'!B60,1)=")",195,0) -> 0 | L10: ='Config #8'!E67 -> 16856.855
B11: Config #9 | C11: =IF(ISBLANK('Config #9'!B2),"",'Config #9'!B2) | D11: 0 | E11: ='Config #9'!E27 -> 0 | F11: =E11-O11 -> 0 | H11: 0 | I11: =IF('Config #9'!B55="Tandem (1st Position)",1317.19,0) -> 0 | J11: ='Config #9'!E63 -> 0 | K11: =IF(RIGHT('Config #9'!B60,1)=")",195,0) -> 0 | L11: ='Config #9'!E67 -> 0
B12: Config #10 | C12: =IF(ISBLANK('Config #10'!B2),"",'Config #10'!B2) | D12: 0 | E12: ='Config #10'!E27 -> 0 | F12: =E12-O12 -> 0 | H12: 0 | I12: =IF('Config #10'!B55="Tandem (1st Position)",1317.19,0) -> 0 | J12: ='Config #10'!E63 -> 0 | K12: =IF(RIGHT('Config #10'!B60,1)=")",195,0) -> 0 | L12: ='Config #10'!E67 -> 0
L14: Imagine Excel Total | M14: =SUM(E3:E12,L3:L12) -> 80179.376
L15: Ondal / Simeon Total | M15: =SUM(D3:D12,H3:K12) -> 591
L16: Delta Total | M16: =M14-M15 -> 79588.376
L17: Delta % | M17: =M16/M14 -> 0.99262903

Sheet Config #1
A1: CONFIGURATION #1 | B1: DESCRIPTION
A2: Configuration Name | B2: LED/FP (Patient Left): Camera Capable with Wall Control
A4: BOOM (SINGLE OR TANDEM) | B4: SELECTION | C4: IMAGINE LIST | D4: ONDAL LIST | E4: ONDAL COG | G4: HV Services | H4: Count | J4: Layer | K4: Selection | L4: FRONT | Q4: Selection | S4: Selection | T4: BACK | Y4: Selection | AE4: =COUNTIF(K5,"(2) Duplexes")+COUNTIF(Y5,"(2) Duplexes") -> 0 | AF4: =COUNTIF(Q5:S5,"(2) Duplexes") -> 0 | AG4: =COUNTIF(K5,"(3) Duplexes")+COUNTIF(Y5,"(3) Duplexes") -> 0 | AH4: =COUNTIF(Q5:S5,"(3) Duplexes") -> 0
A5: Model | B5: =IF(OR(ISBLANK(B8),ISBLANK(B9)),"",IF(ISBLANK(B9),0,(VLOOKUP(B9,'Ondal Booms'!B:F,5,FALSE)))&IF(ISBLANK(B8),0,(VLOOKUP(B8,'Ondal Booms'!B:F,5,FALSE)))) | C5: =IF(OR(ISBLANK(B5),B5=""),0,VLOOKUP(B5,'Ondal Booms'!B:G,4,FALSE)) -> 0 | D5: =IF(OR(ISBLANK(B5),B5=""),0,VLOOKUP(B5,'Ondal Booms'!B:G,2,FALSE)) -> 0 | E5: =IF(OR(ISBLANK(B5),B5=""),0,VLOOKUP(B5,'Ondal Booms'!B:G,3,FALSE)) -> 0 | G5: Duplex Count | H5: =COUNTIF(K5:Y14,"(2) Duplexes")*2+COUNTIF(K5:Y14,"(3) Duplexes")*3 -> 0 | J5: 1 Left | Z5: =15-COUNTIFS(K5:Y5,"") -> 0
A6: Ceiling Cover | C6: =IF(OR(ISBLANK(B6),B6=""),0,VLOOKUP(B6,'Ondal Booms'!B:G,4,FALSE)) -> 0 | D6: =IF(OR(ISBLANK(B6),B6=""),0,VLOOKUP(B6,'Ondal Booms'!B:G,2,FALSE)) -> 0 | E6: =IF(OR(ISBLANK(B6),B6=""),0,VLOOKUP(B6,'Ondal Booms'!B:G,3,FALSE)) -> 0 | J6: 1 Right | Z6: =15-COUNTIFS(K6:Y6,"") -> 0 | AE6: =COUNTIF(K7,"(2) Duplexes")+COUNTIF(Y7,"(2) Duplexes") -> 0 | AF6: =COUNTIF(Q7:S7,"(2) Duplexes") -> 0 | AG6: =COUNTIF(K7,"(3) Duplexes")+COUNTIF(Y7,"(3) Duplexes") -> 0 | AH6: =COUNTIF(Q7:S7,"(3) Duplexes") -> 0
A7: Ceiling Flange | C7: =IF(OR(ISBLANK(B7),B7=""),0,VLOOKUP(B7,'Ondal Booms'!B:G,4,FALSE)) -> 0 | D7: =IF(OR(ISBLANK(B7),B7=""),0,VLOOKUP(B7,'Ondal Booms'!B:G,2,FALSE)) -> 0 | E7: =IF(OR(ISBLANK(B7),B7=""),0,VLOOKUP(B7,'Ondal Booms'!B:G,3,FALSE)) -> 0 | G7: LV Services | H7: Count | J7: 2 Left | Z7: =15-COUNTIFS(K7:Y7,"") -> 0
A8: Top Arm | C8: =IF(OR(ISBLANK(B8),B8=""),0,VLOOKUP(B8,'Ondal Booms'!B:G,4,FALSE)) -> 0 | D8: =IF(OR(ISBLANK(B8),B8=""),0,VLOOKUP(B8,'Ondal Booms'!B:G,2,FALSE)) -> 0 | E8: =IF(OR(ISBLANK(B8),B8=""),0,VLOOKUP(B8,'Ondal Booms'!B:G,3,FALSE)) -> 0 | G8: Data Count | H8: =(COUNTIF(K5:Y14,"Data")) -> 0 | J8: 2 Right | Z8: =15-COUNTIFS(K8:Y8,"") -> 0 | AE8: =COUNTIF(K9,"(2) Duplexes")+COUNTIF(Y9,"(2) Duplexes") -> 0 | AF8: =COUNTIF(Q9:S9,"(2) Duplexes") -> 0 | AG8: =COUNTIF(K9,"(3) Duplexes")+COUNTIF(Y9,"(3) Duplexes") -> 0 | AH8: =COUNTIF(Q9:S9,"(3) Duplexes") -> 0
A9: Bottom Arm | C9: =IF(OR(ISBLANK(B9),B9=""),0,VLOOKUP(B9,'Ondal Booms'!B:G,4,FALSE)) -> 0 | D9: =IF(OR(ISBLANK(B9),B9=""),0,VLOOKUP(B9,'Ondal Booms'!B:G,2,FALSE)) -> 0 | E9: =IF(OR(ISBLANK(B9),B9=""),0,VLOOKUP(B9,'Ondal Booms'!B:G,3,FALSE)) -> 0 | G9: Storz 4in1 Count | H9: =(COUNTIF(K5:Y14,"Storz 4in1")) -> 0 | J9: 3 Left | Z9: =15-COUNTIFS(K9:Y9,"") -> 0
A10: Column Tube | C10: =IF(OR(ISBLANK(B10),B10=""),0,VLOOKUP(B10,'Ondal Booms'!B:G,4,FALSE)) -> 0 | D10: =IF(OR(ISBLANK(B10),B10=""),0,VLOOKUP(B10,'Ondal Booms'!B:G,2,FALSE)) -> 0 | E10: =IF(OR(ISBLANK(B10),B10=""),0,VLOOKUP(B10,'Ondal Booms'!B:G,3,FALSE)) -> 0 | J10: 3 Right | Z10: =15-COUNTIFS(K10:Y10,"") -> 0 | AE10: =COUNTIF(K11,"(2) Duplexes")+COUNTIF(Y11,"(2) Duplexes") -> 0 | AF10: =COUNTIF(Q11:S11,"(2) Duplexes") -> 0 | AG10: =COUNTIF(K11,"(3) Duplexes")+COUNTIF(Y11,"(3) Duplexes") -> 0 | AH10: =COUNTIF(Q11:S11,"(3) Duplexes") -> 0
A11: Service Head | C11: =IF(OR(ISBLANK(B11),B11=""),0,VLOOKUP(B11,'Ondal Booms'!B:G,4,FALSE)) -> 0 | D11: =IF(OR(ISBLANK(B11),B11=""),0,VLOOKUP(B11,'Ondal Booms'!B:G,2,FALSE)) -> 0 | E11: =IF(OR(ISBLANK(B11),B11=""),0,VLOOKUP(B11,'Ondal Booms'!B:G,3,FALSE)) -> 0 | G11: Medical Gases | H11: Count | J11: 4 Left | Z11: =15-COUNTIFS(K11:Y11,"") -> 0
A12: Electrical | B12: =IF(OR(H5=0,ISBLANK(H5)),"",H5&" Duplexes") | C12: =IF(OR(ISBLANK(B12),B12=""),0,VLOOKUP(B12,'Ondal Booms'!B:G,4,FALSE)) -> 0 | D12: =IF(OR(ISBLANK(B12),B12=""),0,VLOOKUP(B12,'Ondal Booms'!B:G,2,FALSE)) -> 0 | E12: =IF(OR(ISBLANK(B12),B12=""),0,VLOOKUP(B12,'Ondal Booms'!B:G,3,FALSE)) -> 0 | G12: Oxygen Count | H12: =(COUNTIF(K5:Y14,"Oxygen")) -> 0 | J12: 4 Right | Z12: =15-COUNTIFS(K12:Y12,"") -> 0 | AE12: =COUNTIF(K13,"(2) Duplexes")+COUNTIF(Y13,"(2) Duplexes") -> 0 | AF12: =COUNTIF(Q13:S13,"(2) Duplexes") -> 0 | AG12: =COUNTIF(K13,"(3) Duplexes")+COUNTIF(Y13,"(3) Duplexes") -> 0 | AH12: =COUNTIF(Q13:S13,"(3) Duplexes") -> 0
A13: Medical Gas | B13: =IF(OR(SUM(H12:H18)=0,ISBLANK(SUM(H12:H18))),"",SUM(H12:H18)&" Outlets") | C13: =IF(OR(ISBLANK(B13),B13=""),0,VLOOKUP(B13,'Ondal Booms'!B:G,4,FALSE)) -> 0 | D13: =IF(OR(ISBLANK(B13),B13=""),0,VLOOKUP(B13,'Ondal Booms'!B:G,2,FALSE)) -> 0 | E13: =IF(OR(ISBLANK(B13),B13=""),0,VLOOKUP(B13,'Ondal Booms'!B:G,3,FALSE)) -> 0 | G13: Med Air Count | H13: =COUNTIF(K5:Y14,"Medical Air") -> 0 | J13: 5 Left | Z13: =15-COUNTIFS(K13:Y13,"") -> 0
A14: # of Outlet Circuits | C14: =IF(OR(ISBLANK(B14),B14=""),0,VLOOKUP(B14,'Ondal Booms'!B:G,4,FALSE)) -> 0 | D14: =IF(OR(ISBLANK(B14),B14=""),0,VLOOKUP(B14,'Ondal Booms'!B:G,2,FALSE)) -> 0 | E14: =IF(OR(ISBLANK(B14),B14=""),0,VLOOKUP(B14,'Ondal Booms'!B:G,3,FALSE)) -> 0 | G14: Nitrous Count | H14: =COUNTIF(K5:Y14,"Nitrous Oxide") -> 0 | J14: 5 Right | Z14: =15-COUNTIFS(K14:Y14,"") -> 0
A15: Shelf (500mm) | C15: =IF(OR(ISBLANK(B15),B15=""),0,VLOOKUP(B15,'Ondal Booms'!B:G,4,FALSE)) -> 0 | D15: =IF(OR(ISBLANK(B15),B15=""),0,VLOOKUP(B15,'Ondal Booms'!B:G,2,FALSE)) -> 0 | E15: =IF(OR(ISBLANK(B15),B15=""),0,VLOOKUP(B15,'Ondal Booms'!B:G,3,FALSE)) -> 0 | G15: WAGD Count | H15: =COUNTIF(K5:Y14,"WAGD") -> 0
A16: Shelf (750mm) | C16: =IF(OR(ISBLANK(B16),B16=""),0,VLOOKUP(B16,'Ondal Booms'!B:G,4,FALSE)) -> 0 | D16: =IF(OR(ISBLANK(B16),B16=""),0,VLOOKUP(B16,'Ondal Booms'!B:G,2,FALSE)) -> 0 | E16: =IF(OR(ISBLANK(B16),B16=""),0,VLOOKUP(B16,'Ondal Booms'!B:G,3,FALSE)) -> 0 | G16: Vacuum Count | H16: =COUNTIF(K5:Y14,"Vacuum") -> 0
A17: Accessory 1 | C17: =IF(OR(ISBLANK(B17),B17=""),0,VLOOKUP(B17,'Ondal Booms'!B:G,4,FALSE)) -> 0 | D17: =IF(OR(ISBLANK(B17),B17=""),0,VLOOKUP(B17,'Ondal Booms'!B:G,2,FALSE)) -> 0 | E17: =IF(OR(ISBLANK(B17),B17=""),0,VLOOKUP(B17,'Ondal Booms'!B:G,3,FALSE)) -> 0 | G17: Nitrogen Count | H17: =COUNTIF(K5:Y14,"Nitrogen") -> 0
A18: Accessory 2 | C18: =IF(OR(ISBLANK(B18),B18=""),0,VLOOKUP(B18,'Ondal Booms'!B:G,4,FALSE)) -> 0 | D18: =IF(OR(ISBLANK(B18),B18=""),0,VLOOKUP(B18,'Ondal Booms'!B:G,2,FALSE)) -> 0 | E18: =IF(OR(ISBLANK(B18),B18=""),0,VLOOKUP(B18,'Ondal Booms'!B:G,3,FALSE)) -> 0 | G18: CO2 Count | H18: =COUNTIF(K5:Y14,"Carbon Dioxide") -> 0
A19: Accessory 3 | C19: =IF(OR(ISBLANK(B19),B19=""),0,VLOOKUP(B19,'Ondal Booms'!B:G,4,FALSE)) -> 0 | D19: =IF(OR(ISBLANK(B19),B19=""),0,VLOOKUP(B19,'Ondal Booms'!B:G,2,FALSE)) -> 0 | E19: =IF(OR(ISBLANK(B19),B19=""),0,VLOOKUP(B19,'Ondal Booms'!B:G,3,FALSE)) -> 0
A20: Accessory 4 | C20: =IF(OR(ISBLANK(B20),B20=""),0,VLOOKUP(B20,'Ondal Booms'!B:G,4,FALSE)) -> 0 | D20: =IF(OR(ISBLANK(B20),B20=""),0,VLOOKUP(B20,'Ondal Booms'!B:G,2,FALSE)) -> 0 | E20: =IF(OR(ISBLANK(B20),B20=""),0,VLOOKUP(B20,'Ondal Booms'!B:G,3,FALSE)) -> 0
A21: Accessory 5 | C21: =IF(OR(ISBLANK(B21),B21=""),0,VLOOKUP(B21,'Ondal Booms'!B:G,4,FALSE)) -> 0 | D21: =IF(OR(ISBLANK(B21),B21=""),0,VLOOKUP(B21,'Ondal Booms'!B:G,2,FALSE)) -> 0 | E21: =IF(OR(ISBLANK(B21),B21=""),0,VLOOKUP(B21,'Ondal Booms'!B:G,3,FALSE)) -> 0
A22: Accessory 6 | C22: =IF(OR(ISBLANK(B22),B22=""),0,VLOOKUP(B22,'Ondal Booms'!B:G,4,FALSE)) -> 0 | D22: =IF(OR(ISBLANK(B22),B22=""),0,VLOOKUP(B22,'Ondal Booms'!B:G,2,FALSE)) -> 0 | E22: =IF(OR(ISBLANK(B22),B22=""),0,VLOOKUP(B22,'Ondal Booms'!B:G,3,FALSE)) -> 0
A23: Accessory 7 | C23: =IF(OR(ISBLANK(B23),B23=""),0,VLOOKUP(B23,'Ondal Booms'!B:G,4,FALSE)) -> 0 | D23: =IF(OR(ISBLANK(B23),B23=""),0,VLOOKUP(B23,'Ondal Booms'!B:G,2,FALSE)) -> 0 | E23: =IF(OR(ISBLANK(B23),B23=""),0,VLOOKUP(B23,'Ondal Booms'!B:G,3,FALSE)) -> 0
A25: Errors? | B25: =IF(OR(ISBLANK(B5),B5=""),"", IF(OR(AND(B11="200mm Service Head",SUM(Z7:Z14)>0),AND(B11="400mm Service Head",SUM(Z9:Z14)>0),AND(B11="600mm Service Head",SUM(Z11:Z14)>0),AND(B11="800mm Service Head",SUM(Z13:Z14)>0)),"Select Longer Service Head or Remove Services", IF(AND(RIGHT(B9,2)="XL",RIGHT(B8,2)<>"XL"),"BOTTOM XL ARM REQUIRES TOP XL ARM", IF(OR(ISBLANK(B6),ISBLANK(B7),ISBLANK(B8),ISBLANK(B9),ISBLANK(B10),ISBLANK(B11),ISBLANK(B15),ISBLANK(B16),ISBLANK(B14)),"Missing Selections for Configuration", IF(AND(B11="Large Monitor Carrier",B9<>"Spring Articulating"),"Large Monitor Requires Spring Bottom Arm", IF(OR(AND(RIGHT(B7,2)="XL",RIGHT(B8,2)<>"XL"),AND(RIGHT(B8,2)="XL",RIGHT(B7,2)<>"XL")),"Both Top Arm and Ceiling Flange Must Be XL", IF(COUNTIF(AE4:AH12,1)>1,"Mismatch Electrical Configuration", "")))))) )
C26: IMAGINE LIST | D26: ONDAL LIST | E26: ONDAL SALES
A27: Equipment List Price | B27: =IF(OR(B6="",ISBLANK(B6)),"NO CONFIGURATION SELECTED",C27) -> NO CONFIGURATION SELECTED | C27: =SUM(C5:C23) -> 0 | D27: =SUM(D5:D23) -> 0 | E27: =SUM(E5:E23) -> 0 | J27: ="<-- EXPAND TO SHOW OPTIONS / SERVICE HEAD" -> <-- EXPAND TO SHOW OPTIONS / SERVICE HEAD
AE28: =COUNTIF(K30,"(2) Duplexes")+COUNTIF(Y30,"(2) Duplexes") -> 0 | AF28: =COUNTIF(Q30:S30,"(2) Duplexes") -> 0 | AG28: =COUNTIF(K30,"(3) Duplexes")+COUNTIF(Y30,"(3) Duplexes") -> 0 | AH28: =COUNTIF(Q30:S30,"(3) Duplexes") -> 0
A29: BOOM (TANDEM 2ND ONLY) | B29: SELECTION | C29: IMAGINE LIST | D29: ONDAL LIST | E29: ONDAL COG | G29: HV Services | H29: Count | J29: Layer | K29: Selection | L29: FRONT | Q29: Selection | S29: Selection | T29: BACK | Y29: Selection
A30: Model | B30: =IF(OR(ISBLANK(B32),ISBLANK(B33)),"",IF(ISBLANK(B33),0,(VLOOKUP(B33,'Ondal Booms'!B:F,5,FALSE)))&IF(ISBLANK(B32),0,(VLOOKUP(B32,'Ondal Booms'!B:F,5,FALSE)))) | C30: =IF(OR(ISBLANK(B30),B30=""),0,VLOOKUP(B30,'Ondal Booms'!B:G,4,FALSE)) -> 0 | D30: =IF(OR(ISBLANK(B30),B30=""),0,VLOOKUP(B30,'Ondal Booms'!B:G,2,FALSE)) -> 0 | E30: =IF(OR(ISBLANK(B30),B30=""),0,VLOOKUP(B30,'Ondal Booms'!B:G,3,FALSE)) -> 0 | G30: Duplex Count | H30: =COUNTIF(K30:Y39,"(2) Duplexes")*2+COUNTIF(K30:Y39,"(3) Duplexes")*3 -> 0 | J30: 1 Left | Z30: =15-COUNTIFS(K30:Y30,"") -> 0
A31: Ceiling Flange | C31: =IF(OR(ISBLANK(B31),B31=""),0,VLOOKUP(B31,'Ondal Booms'!B:G,4,FALSE)) -> 0 | D31: =IF(OR(ISBLANK(B31),B31=""),0,VLOOKUP(B31,'Ondal Booms'!B:G,2,FALSE)) -> 0 | E31: =IF(OR(ISBLANK(B31),B31=""),0,VLOOKUP(B31,'Ondal Booms'!B:G,3,FALSE)) -> 0 | G31: LV Services | H31: Count | J31: 1 Right | Z31: =15-COUNTIFS(K31:Y31,"") -> 0 | AE31: =COUNTIF(K32,"(2) Duplexes")+COUNTIF(Y32,"(2) Duplexes") -> 0 | AF31: =COUNTIF(Q32:S32,"(2) Duplexes") -> 0 | AG31: =COUNTIF(K32,"(3) Duplexes")+COUNTIF(Y32,"(3) Duplexes") -> 0 | AH31: =COUNTIF(Q32:S32,"(3) Duplexes") -> 0
A32: Top Arm | C32: =IF(OR(ISBLANK(B32),B32=""),0,VLOOKUP(B32,'Ondal Booms'!B:G,4,FALSE)) -> 0 | D32: =IF(OR(ISBLANK(B32),B32=""),0,VLOOKUP(B32,'Ondal Booms'!B:G,2,FALSE)) -> 0 | E32: =IF(OR(ISBLANK(B32),B32=""),0,VLOOKUP(B32,'Ondal Booms'!B:G,3,FALSE)) -> 0 | G32: Data Count | H32: =(COUNTIF(K30:Y39,"Data")) -> 0 | J32: 2 Left | Z32: =15-COUNTIFS(K32:Y32,"") -> 0
A33: Bottom Arm | C33: =IF(OR(ISBLANK(B33),B33=""),0,VLOOKUP(B33,'Ondal Booms'!B:G,4,FALSE)) -> 0 | D33: =IF(OR(ISBLANK(B33),B33=""),0,VLOOKUP(B33,'Ondal Booms'!B:G,2,FALSE)) -> 0 | E33: =IF(OR(ISBLANK(B33),B33=""),0,VLOOKUP(B33,'Ondal Booms'!B:G,3,FALSE)) -> 0 | G33: Storz 4in1 Count | H33: =(COUNTIF(K30:Y39,"Storz 4in1")) -> 0 | J33: 2 Right | Z33: =15-COUNTIFS(K33:Y33,"") -> 0 | AE33: =COUNTIF(K34,"(2) Duplexes")+COUNTIF(Y34,"(2) Duplexes") -> 0 | AF33: =COUNTIF(Q34:S34,"(2) Duplexes") -> 0 | AG33: =COUNTIF(K34,"(3) Duplexes")+COUNTIF(Y34,"(3) Duplexes") -> 0 | AH33: =COUNTIF(Q34:S34,"(3) Duplexes") -> 0
A34: Column Tube | C34: =IF(OR(ISBLANK(B34),B34=""),0,VLOOKUP(B34,'Ondal Booms'!B:G,4,FALSE)) -> 0 | D34: =IF(OR(ISBLANK(B34),B34=""),0,VLOOKUP(B34,'Ondal Booms'!B:G,2,FALSE)) -> 0 | E34: =IF(OR(ISBLANK(B34),B34=""),0,VLOOKUP(B34,'Ondal Booms'!B:G,3,FALSE)) -> 0 | J34: 3 Left | Z34: =15-COUNTIFS(K34:Y34,"") -> 0
A35: Service Head | C35: =IF(OR(ISBLANK(B35),B35=""),0,VLOOKUP(B35,'Ondal Booms'!B:G,4,FALSE)) -> 0 | D35: =IF(OR(ISBLANK(B35),B35=""),0,VLOOKUP(B35,'Ondal Booms'!B:G,2,FALSE)) -> 0 | E35: =IF(OR(ISBLANK(B35),B35=""),0,VLOOKUP(B35,'Ondal Booms'!B:G,3,FALSE)) -> 0 | G35: Medical Gases | H35: Count | J35: 3 Right | Z35: =15-COUNTIFS(K35:Y35,"") -> 0 | AE35: =COUNTIF(K36,"(2) Duplexes")+COUNTIF(Y36,"(2) Duplexes") -> 0 | AF35: =COUNTIF(Q36:S36,"(2) Duplexes") -> 0 | AG35: =COUNTIF(K36,"(3) Duplexes")+COUNTIF(Y36,"(3) Duplexes") -> 0 | AH35: =COUNTIF(Q36:S36,"(3) Duplexes") -> 0
A36: Electrical | B36: =IF(OR(H30=0,ISBLANK(H30)),"",H30&" Duplexes") | C36: =IF(OR(ISBLANK(B36),B36=""),0,VLOOKUP(B36,'Ondal Booms'!B:G,4,FALSE)) -> 0 | D36: =IF(OR(ISBLANK(B36),B36=""),0,VLOOKUP(B36,'Ondal Booms'!B:G,2,FALSE)) -> 0 | E36: =IF(OR(ISBLANK(B36),B36=""),0,VLOOKUP(B36,'Ondal Booms'!B:G,3,FALSE)) -> 0 | G36: Oxygen Count | H36: =(COUNTIF(K30:Y39,"Oxygen")) -> 0 | J36: 4 Left | Z36: =15-COUNTIFS(K36:Y36,"") -> 0
A37: Medical Gas | B37: =IF(OR(SUM(H36:H42)=0,ISBLANK(SUM(H36:H42))),"",SUM(H36:H42)&" Outlets") | C37: =IF(OR(ISBLANK(B37),B37=""),0,VLOOKUP(B37,'Ondal Booms'!B:G,4,FALSE)) -> 0 | D37: =IF(OR(ISBLANK(B37),B37=""),0,VLOOKUP(B37,'Ondal Booms'!B:G,2,FALSE)) -> 0 | E37: =IF(OR(ISBLANK(B37),B37=""),0,VLOOKUP(B37,'Ondal Booms'!B:G,3,FALSE)) -> 0 | G37: Med Air Count | H37: =COUNTIF(K30:Y39,"Medical Air") -> 0 | J37: 4 Right | Z37: =15-COUNTIFS(K37:Y37,"") -> 0 | AE37: =COUNTIF(K38,"(2) Duplexes")+COUNTIF(Y38,"(2) Duplexes") -> 0 | AF37: =COUNTIF(Q38:S38,"(2) Duplexes") -> 0 | AG37: =COUNTIF(K38,"(3) Duplexes")+COUNTIF(Y38,"(3) Duplexes") -> 0 | AH37: =COUNTIF(Q38:S38,"(3) Duplexes") -> 0
A38: # of Outlet Circuits | C38: =IF(OR(ISBLANK(B38),B38=""),0,VLOOKUP(B38,'Ondal Booms'!B:G,4,FALSE)) -> 0 | D38: =IF(OR(ISBLANK(B38),B38=""),0,VLOOKUP(B38,'Ondal Booms'!B:G,2,FALSE)) -> 0 | E38: =IF(OR(ISBLANK(B38),B38=""),0,VLOOKUP(B38,'Ondal Booms'!B:G,3,FALSE)) -> 0 | G38: Nitrous Count | H38: =COUNTIF(K30:Y39,"Nitrous Oxide") -> 0 | J38: 5 Left | Z38: =15-COUNTIFS(K38:Y38,"") -> 0
A39: Shelf (500mm) | C39: =IF(OR(ISBLANK(B39),B39=""),0,VLOOKUP(B39,'Ondal Booms'!B:G,4,FALSE)) -> 0 | D39: =IF(OR(ISBLANK(B39),B39=""),0,VLOOKUP(B39,'Ondal Booms'!B:G,2,FALSE)) -> 0 | E39: =IF(OR(ISBLANK(B39),B39=""),0,VLOOKUP(B39,'Ondal Booms'!B:G,3,FALSE)) -> 0 | G39: WAGD Count | H39: =COUNTIF(K30:Y39,"WAGD") -> 0 | J39: 5 Right | Z39: =15-COUNTIFS(K39:Y39,"") -> 0
A40: Shelf (750mm) | C40: =IF(OR(ISBLANK(B40),B40=""),0,VLOOKUP(B40,'Ondal Booms'!B:G,4,FALSE)) -> 0 | D40: =IF(OR(ISBLANK(B40),B40=""),0,VLOOKUP(B40,'Ondal Booms'!B:G,2,FALSE)) -> 0 | E40: =IF(OR(ISBLANK(B40),B40=""),0,VLOOKUP(B40,'Ondal Booms'!B:G,3,FALSE)) -> 0 | G40: Vacuum Count | H40: =COUNTIF(K30:Y39,"Vacuum") -> 0
A41: Accessory 1 | C41: =IF(OR(ISBLANK(B41),B41=""),0,VLOOKUP(B41,'Ondal Booms'!B:G,4,FALSE)) -> 0 | D41: =IF(OR(ISBLANK(B41),B41=""),0,VLOOKUP(B41,'Ondal Booms'!B:G,2,FALSE)) -> 0 | E41: =IF(OR(ISBLANK(B41),B41=""),0,VLOOKUP(B41,'Ondal Booms'!B:G,3,FALSE)) -> 0 | G41: Nitrogen Count | H41: =COUNTIF(K30:Y39,"Nitrogen") -> 0
A42: Accessory 2 | C42: =IF(OR(ISBLANK(B42),B42=""),0,VLOOKUP(B42,'Ondal Booms'!B:G,4,FALSE)) -> 0 | D42: =IF(OR(ISBLANK(B42),B42=""),0,VLOOKUP(B42,'Ondal Booms'!B:G,2,FALSE)) -> 0 | E42: =IF(OR(ISBLANK(B42),B42=""),0,VLOOKUP(B42,'Ondal Booms'!B:G,3,FALSE)) -> 0 | G42: CO2 Count | H42: =COUNTIF(K30:Y39,"Carbon Dioxide") -> 0
A43: Accessory 3 | C43: =IF(OR(ISBLANK(B43),B43=""),0,VLOOKUP(B43,'Ondal Booms'!B:G,4,FALSE)) -> 0 | D43: =IF(OR(ISBLANK(B43),B43=""),0,VLOOKUP(B43,'Ondal Booms'!B:G,2,FALSE)) -> 0 | E43: =IF(OR(ISBLANK(B43),B43=""),0,VLOOKUP(B43,'Ondal Booms'!B:G,3,FALSE)) -> 0
A44: Accessory 4 | C44: =IF(OR(ISBLANK(B44),B44=""),0,VLOOKUP(B44,'Ondal Booms'!B:G,4,FALSE)) -> 0 | D44: =IF(OR(ISBLANK(B44),B44=""),0,VLOOKUP(B44,'Ondal Booms'!B:G,2,FALSE)) -> 0 | E44: =IF(OR(ISBLANK(B44),B44=""),0,VLOOKUP(B44,'Ondal Booms'!B:G,3,FALSE)) -> 0
A45: Accessory 5 | C45: =IF(OR(ISBLANK(B45),B45=""),0,VLOOKUP(B45,'Ondal Booms'!B:G,4,FALSE)) -> 0 | D45: =IF(OR(ISBLANK(B45),B45=""),0,VLOOKUP(B45,'Ondal Booms'!B:G,2,FALSE)) -> 0 | E45: =IF(OR(ISBLANK(B45),B45=""),0,VLOOKUP(B45,'Ondal Booms'!B:G,3,FALSE)) -> 0
A46: Accessory 6 | C46: =IF(OR(ISBLANK(B46),B46=""),0,VLOOKUP(B46,'Ondal Booms'!B:G,4,FALSE)) -> 0 | D46: =IF(OR(ISBLANK(B46),B46=""),0,VLOOKUP(B46,'Ondal Booms'!B:G,2,FALSE)) -> 0 | E46: =IF(OR(ISBLANK(B46),B46=""),0,VLOOKUP(B46,'Ondal Booms'!B:G,3,FALSE)) -> 0
A47: Accessory 7 | C47: =IF(OR(ISBLANK(B47),B47=""),0,VLOOKUP(B47,'Ondal Booms'!B:G,4,FALSE)) -> 0 | D47: =IF(OR(ISBLANK(B47),B47=""),0,VLOOKUP(B47,'Ondal Booms'!B:G,2,FALSE)) -> 0 | E47: =IF(OR(ISBLANK(B47),B47=""),0,VLOOKUP(B47,'Ondal Booms'!B:G,3,FALSE)) -> 0
A49: Errors? | B49: =IF(OR(ISBLANK(B30),B30=""),"", IF(OR(AND(B35="200mm Service Head",SUM(Z32:Z39)>0),AND(B35="400mm Service Head",SUM(Z34:Z39)>0),AND(B35="600mm Service Head",SUM(Z36:Z39)>0),AND(B35="800mm Service Head",SUM(Z38:Z39)>0)),"Select Longer Service Head or Remove Services", IF(AND(RIGHT(B33,2)="XL",RIGHT(B32,2)<>"XL"),"BOTTOM XL ARM REQUIRES TOP XL ARM", IF(OR(ISBLANK(#REF!),ISBLANK(B31),ISBLANK(B32),ISBLANK(B33),ISBLANK(B34),ISBLANK(B35),ISBLANK(B39),ISBLANK(B40),ISBLANK(B38)),"Missing Selections for Configuration", IF(AND(B35="Large Monitor Carrier",B33<>"Spring Articulating"),"Large Monitor Requires Spring Bottom Arm", IF(OR(AND(RIGHT(B31,2)="XL",RIGHT(B32,2)<>"XL"),AND(RIGHT(B32,2)="XL",RIGHT(B31,2)<>"XL")),"Both Top Arm and Ceiling Flange Must Be XL", IF(COUNTIF(AE29:AH37,1)>1,"Mismatch Electrical Configuration", "")))))) )
C50: IMAGINE LIST | D50: ONDAL LIST | E50: ONDAL SALES
A51: Equipment List Price | B51: =IF(OR(B30="",ISBLANK(B30)),"NO CONFIGURATION SELECTED",C51) -> NO CONFIGURATION SELECTED | C51: =SUM(C30:C47) -> 0 | D51: =SUM(D30:D47) -> 0 | E51: =SUM(E30:E47) -> 0 | J51: ="<-- EXPAND TO SHOW OPTIONS / SERVICE HEAD" -> <-- EXPAND TO SHOW OPTIONS / SERVICE HEAD
A53: LIGHT (SINGLE OR TANDEM) | B53: SELECTION | C53: IMAGINE LIST | D53: SIMEON LIST | E53: SIMEON COG
A54: Model | B54: =IF(AND(ISBLANK(B57),ISBLANK(B58),ISBLANK(B59)),"", IF(B55="Upgrade Only","UPGRADE", IF(RIGHT(B57,4)="(3P)","(3P) ","")& IF(ISBLANK(B57),"",VLOOKUP(B57,'Simeon Lights'!C:H,2,FALSE))& IF(ISBLANK(B58),""," / "&VLOOKUP(B58,'Simeon Lights'!C:H,2,FALSE))& IF(ISBLANK(B59),""," / "&VLOOKUP(B59,'Simeon Lights'!C:H,2,FALSE)))) -> FP / LED | C54: =IF(ISBLANK(B57),0,(VLOOKUP(B54,'Simeon Lights'!C:J,6,FALSE))) -> 10357.417 | D54: =IF(ISBLANK(B57),0,(VLOOKUP(B54,'Simeon Lights'!C:J,4,FALSE))) -> 6214.45 | E54: =IF(ISBLANK(B57),0,(VLOOKUP(B54,'Simeon Lights'!C:J,5,FALSE))) -> 3107.225
A55: Ceiling Cover | B55: Single Mount (Standard) | C55: =IF(ISBLANK(B55),0,VLOOKUP(B55,'Simeon Lights'!C:J,6,FALSE)) -> 1441.05 | D55: =IF(ISBLANK(B55),0,VLOOKUP(B55,'Simeon Lights'!C:J,4,FALSE)) -> 864.63 | E55: =IF(ISBLANK(B55),0,VLOOKUP(B55,'Simeon Lights'!C:J,5,FALSE)) -> 432.315
A56: Ceiling Drop Tube | B56: 250mm | C56: =IF(ISBLANK(B56),0,VLOOKUP(B56,'Simeon Lights'!C:J,6,FALSE)) -> 0 | D56: =IF(ISBLANK(B56),0,VLOOKUP(B56,'Simeon Lights'!C:J,4,FALSE)) -> 0 | E56: =IF(ISBLANK(B56),0,VLOOKUP(B56,'Simeon Lights'!C:J,5,FALSE)) -> 0
A57: Arm 1 (Top Arm) | B57: 32in Flat Panel | C57: =IF(ISBLANK(B57),0,VLOOKUP(B57,'Simeon Lights'!C:J,6,FALSE)) -> 13583.95 | D57: =IF(ISBLANK(B57),0,VLOOKUP(B57,'Simeon Lights'!C:J,4,FALSE)) -> 8150.37 | E57: =IF(ISBLANK(B57),0,VLOOKUP(B57,'Simeon Lights'!C:J,5,FALSE)) -> 4075.185
A58: Arm 2 | B58: 8000 Standard | C58: =IF(ISBLANK(B58),0,VLOOKUP(B58,'Simeon Lights'!C:J,6,FALSE)) -> 30069.75 | D58: =IF(ISBLANK(B58),0,VLOOKUP(B58,'Simeon Lights'!C:J,4,FALSE)) -> 18041.85 | E58: =IF(ISBLANK(B58),0,VLOOKUP(B58,'Simeon Lights'!C:J,5,FALSE)) -> 9020.925
A59: Arm 3 | C59: =IF(ISBLANK(B59),0,VLOOKUP(B59,'Simeon Lights'!C:J,6,FALSE)) -> 0 | D59: =IF(ISBLANK(B59),0,VLOOKUP(B59,'Simeon Lights'!C:J,4,FALSE)) -> 0 | E59: =IF(ISBLANK(B59),0,VLOOKUP(B59,'Simeon Lights'!C:J,5,FALSE)) -> 0
A60: Wall Control | B60: Wall Control (Touch) | C60: =IF(ISBLANK(B60),0,VLOOKUP(B60,'Simeon Lights'!C:J,6,FALSE)) -> 4992.2833 | D60: =IF(ISBLANK(B60),0,VLOOKUP(B60,'Simeon Lights'!C:J,4,FALSE)) -> 2995.37 | E60: =IF(ISBLANK(B60),0,VLOOKUP(B60,'Simeon Lights'!C:J,5,FALSE)) -> 1497.685
A61: Integration Control | B61: No Integration Control | C61: =IF(ISBLANK(B61),0,VLOOKUP(B61,'Simeon Lights'!C:J,6,FALSE)) -> 0 | D61: =IF(ISBLANK(B61),0,VLOOKUP(B61,'Simeon Lights'!C:J,4,FALSE)) -> 0 | E61: =IF(ISBLANK(B61),0,VLOOKUP(B61,'Simeon Lights'!C:J,5,FALSE)) -> 0
A62: In-Light Camera | B62: Wired Camera Prep | C62: =IF(ISBLANK(B62),0,VLOOKUP(B62,'Simeon Lights'!C:J,6,FALSE)) -> 4941.2367 | D62: =IF(ISBLANK(B62),0,VLOOKUP(B62,'Simeon Lights'!C:J,4,FALSE)) -> 2695.22 | E62: =IF(ISBLANK(B62),0,VLOOKUP(B62,'Simeon Lights'!C:J,5,FALSE)) -> 1482.371
A63: Disposable Adpaters | B63: (1) Screw-On Adapters | C63: =IF(ISBLANK(B63),0,VLOOKUP(B63,'Simeon Lights'!C:J,6,FALSE)) -> 440 | D63: =IF(ISBLANK(B63),0,VLOOKUP(B63,'Simeon Lights'!C:J,4,FALSE)) -> 264 | E63: =IF(ISBLANK(B63),0,VLOOKUP(B63,'Simeon Lights'!C:J,5,FALSE)) -> 132
A65: Errors? | B65: =IF(AND(ISBLANK(B57),ISBLANK(B58),ISBLANK(B59)),"", IF(AND(ISBLANK(B57),B58<>""),"ARM 1 MISSING", IF(AND(ISBLANK(B57),B59<>""),"ARM 1 MISSING", IF(ISBLANK(B58)&ISBLANK(B59)="TRUEFALSE","ARM 2 MISSING", IF(AND(B57<>"",B58="32in Flat Panel",B59<>""),"FP CANNOT BE MIDDLE ARM", IF(OR(ISBLANK(B55),ISBLANK(B56),ISBLANK(B60),ISBLANK(B61),ISBLANK(B62),ISBLANK(B63)),"Missing Selections",""))))))
C66: IMAGINE LIST | D66: SIMEON LIST | E66: SIMEON COG
A67: Equipment List Price | B67: =IF(OR(ISBLANK(B57),ISBLANK(B58)&ISBLANK(B59)="TRUEFALSE"),"NO CONFIGURATION SELECTED",IF(B65<>"","ERROR IN CONFIGURATION",IF(B57="",0,SUM(C54:C63)))) -> 65825.687 | C67: =SUM(C54:C65) -> 65825.687 | D67: =SUM(D54:D65) -> 39225.89 | E67: =SUM(E54:E65) -> 19747.706 | J67: ="<-- EXPAND TO SHOW OPTIONS" -> <-- EXPAND TO SHOW OPTIONS
B69: CONFIGRATION LIST PRICE | E69: TOAL COG
A70: Total List Price | B70: =IF(OR(B27="Error in Configuration",B27="No Configuration Selected"),0,B27)+IF(OR(B51="Error in Configuration",B51="No Configuration Selected"),0,B51)+IF(OR(B67="Error in Configuration",B67="No Configuration Selected"),0,B67) -> 65825.687 | E70: =SUM(E67,E51,E27) -> 19747.706

Sheet Config #2
A1: CONFIGURATION #2 | B1: DESCRIPTION
A2: Configuration Name | B2: LED/FP (Patient Right)
A4: BOOM (SINGLE OR TANDEM) | B4: SELECTION | C4: IMAGINE LIST | D4: ONDAL LIST | E4: ONDAL COG | G4: HV Services | H4: Count | J4: Layer | K4: Selection | L4: FRONT | Q4: Selection | S4: Selection | T4: BACK | Y4: Selection | AE4: =COUNTIF(K5,"(2) Duplexes")+COUNTIF(Y5,"(2) Duplexes") -> 0 | AF4: =COUNTIF(Q5:S5,"(2) Duplexes") -> 0 | AG4: =COUNTIF(K5,"(3) Duplexes")+COUNTIF(Y5,"(3) Duplexes") -> 0 | AH4: =COUNTIF(Q5:S5,"(3) Duplexes") -> 0
A5: Model | B5: =IF(OR(ISBLANK(B8),ISBLANK(B9)),"",IF(ISBLANK(B9),0,(VLOOKUP(B9,'Ondal Booms'!B:F,5,FALSE)))&IF(ISBLANK(B8),0,(VLOOKUP(B8,'Ondal Booms'!B:F,5,FALSE)))) | C5: =IF(OR(ISBLANK(B5),B5=""),0,VLOOKUP(B5,'Ondal Booms'!B:G,4,FALSE)) -> 0 | D5: =IF(OR(ISBLANK(B5),B5=""),0,VLOOKUP(B5,'Ondal Booms'!B:G,2,FALSE)) -> 0 | E5: =IF(OR(ISBLANK(B5),B5=""),0,VLOOKUP(B5,'Ondal Booms'!B:G,3,FALSE)) -> 0 | G5: Duplex Count | H5: =COUNTIF(K5:Y14,"(2) Duplexes")*2+COUNTIF(K5:Y14,"(3) Duplexes")*3 -> 0 | J5: 1 Left | Z5: =15-COUNTIFS(K5:Y5,"") -> 0
A6: Ceiling Cover | C6: =IF(OR(ISBLANK(B6),B6=""),0,VLOOKUP(B6,'Ondal Booms'!B:G,4,FALSE)) -> 0 | D6: =IF(OR(ISBLANK(B6),B6=""),0,VLOOKUP(B6,'Ondal Booms'!B:G,2,FALSE)) -> 0 | E6: =IF(OR(ISBLANK(B6),B6=""),0,VLOOKUP(B6,'Ondal Booms'!B:G,3,FALSE)) -> 0 | J6: 1 Right | Z6: =15-COUNTIFS(K6:Y6,"") -> 0 | AE6: =COUNTIF(K7,"(2) Duplexes")+COUNTIF(Y7,"(2) Duplexes") -> 0 | AF6: =COUNTIF(Q7:S7,"(2) Duplexes") -> 0 | AG6: =COUNTIF(K7,"(3) Duplexes")+COUNTIF(Y7,"(3) Duplexes") -> 0 | AH6: =COUNTIF(Q7:S7,"(3) Duplexes") -> 0
A7: Ceiling Flange | C7: =IF(OR(ISBLANK(B7),B7=""),0,VLOOKUP(B7,'Ondal Booms'!B:G,4,FALSE)) -> 0 | D7: =IF(OR(ISBLANK(B7),B7=""),0,VLOOKUP(B7,'Ondal Booms'!B:G,2,FALSE)) -> 0 | E7: =IF(OR(ISBLANK(B7),B7=""),0,VLOOKUP(B7,'Ondal Booms'!B:G,3,FALSE)) -> 0 | G7: LV Services | H7: Count | J7: 2 Left | Z7: =15-COUNTIFS(K7:Y7,"") -> 0
A8: Top Arm | C8: =IF(OR(ISBLANK(B8),B8=""),0,VLOOKUP(B8,'Ondal Booms'!B:G,4,FALSE)) -> 0 | D8: =IF(OR(ISBLANK(B8),B8=""),0,VLOOKUP(B8,'Ondal Booms'!B:G,2,FALSE)) -> 0 | E8: =IF(OR(ISBLANK(B8),B8=""),0,VLOOKUP(B8,'Ondal Booms'!B:G,3,FALSE)) -> 0 | G8: Data Count | H8: =(COUNTIF(K5:Y14,"Data")) -> 0 | J8: 2 Right | Z8: =15-COUNTIFS(K8:Y8,"") -> 0 | AE8: =COUNTIF(K9,"(2) Duplexes")+COUNTIF(Y9,"(2) Duplexes") -> 0 | AF8: =COUNTIF(Q9:S9,"(2) Duplexes") -> 0 | AG8: =COUNTIF(K9,"(3) Duplexes")+COUNTIF(Y9,"(3) Duplexes") -> 0 | AH8: =COUNTIF(Q9:S9,"(3) Duplexes") -> 0
A9: Bottom Arm | C9: =IF(OR(ISBLANK(B9),B9=""),0,VLOOKUP(B9,'Ondal Booms'!B:G,4,FALSE)) -> 0 | D9: =IF(OR(ISBLANK(B9),B9=""),0,VLOOKUP(B9,'Ondal Booms'!B:G,2,FALSE)) -> 0 | E9: =IF(OR(ISBLANK(B9),B9=""),0,VLOOKUP(B9,'Ondal Booms'!B:G,3,FALSE)) -> 0 | G9: Storz 4in1 Count | H9: =(COUNTIF(K5:Y14,"Storz 4in1")) -> 0 | J9: 3 Left | Z9: =15-COUNTIFS(K9:Y9,"") -> 0
A10: Column Tube | C10: =IF(OR(ISBLANK(B10),B10=""),0,VLOOKUP(B10,'Ondal Booms'!B:G,4,FALSE)) -> 0 | D10: =IF(OR(ISBLANK(B10),B10=""),0,VLOOKUP(B10,'Ondal Booms'!B:G,2,FALSE)) -> 0 | E10: =IF(OR(ISBLANK(B10),B10=""),0,VLOOKUP(B10,'Ondal Booms'!B:G,3,FALSE)) -> 0 | J10: 3 Right | Z10: =15-COUNTIFS(K10:Y10,"") -> 0 | AE10: =COUNTIF(K11,"(2) Duplexes")+COUNTIF(Y11,"(2) Duplexes") -> 0 | AF10: =COUNTIF(Q11:S11,"(2) Duplexes") -> 0 | AG10: =COUNTIF(K11,"(3) Duplexes")+COUNTIF(Y11,"(3) Duplexes") -> 0 | AH10: =COUNTIF(Q11:S11,"(3) Duplexes") -> 0
A11: Service Head | C11: =IF(OR(ISBLANK(B11),B11=""),0,VLOOKUP(B11,'Ondal Booms'!B:G,4,FALSE)) -> 0 | D11: =IF(OR(ISBLANK(B11),B11=""),0,VLOOKUP(B11,'Ondal Booms'!B:G,2,FALSE)) -> 0 | E11: =IF(OR(ISBLANK(B11),B11=""),0,VLOOKUP(B11,'Ondal Booms'!B:G,3,FALSE)) -> 0 | G11: Medical Gases | H11: Count | J11: 4 Left | Z11: =15-COUNTIFS(K11:Y11,"") -> 0
A12: Electrical | B12: =IF(OR(H5=0,ISBLANK(H5)),"",H5&" Duplexes") | C12: =IF(OR(ISBLANK(B12),B12=""),0,VLOOKUP(B12,'Ondal Booms'!B:G,4,FALSE)) -> 0 | D12: =IF(OR(ISBLANK(B12),B12=""),0,VLOOKUP(B12,'Ondal Booms'!B:G,2,FALSE)) -> 0 | E12: =IF(OR(ISBLANK(B12),B12=""),0,VLOOKUP(B12,'Ondal Booms'!B:G,3,FALSE)) -> 0 | G12: Oxygen Count | H12: =(COUNTIF(K5:Y14,"Oxygen")) -> 0 | J12: 4 Right | Z12: =15-COUNTIFS(K12:Y12,"") -> 0 | AE12: =COUNTIF(K13,"(2) Duplexes")+COUNTIF(Y13,"(2) Duplexes") -> 0 | AF12: =COUNTIF(Q13:S13,"(2) Duplexes") -> 0 | AG12: =COUNTIF(K13,"(3) Duplexes")+COUNTIF(Y13,"(3) Duplexes") -> 0 | AH12: =COUNTIF(Q13:S13,"(3) Duplexes") -> 0
A13: Medical Gas | B13: =IF(OR(SUM(H12:H18)=0,ISBLANK(SUM(H12:H18))),"",SUM(H12:H18)&" Outlets") | C13: =IF(OR(ISBLANK(B13),B13=""),0,VLOOKUP(B13,'Ondal Booms'!B:G,4,FALSE)) -> 0 | D13: =IF(OR(ISBLANK(B13),B13=""),0,VLOOKUP(B13,'Ondal Booms'!B:G,2,FALSE)) -> 0 | E13: =IF(OR(ISBLANK(B13),B13=""),0,VLOOKUP(B13,'Ondal Booms'!B:G,3,FALSE)) -> 0 | G13: Med Air Count | H13: =COUNTIF(K5:Y14,"Medical Air") -> 0 | J13: 5 Left | Z13: =15-COUNTIFS(K13:Y13,"") -> 0
A14: # of Outlet Circuits | C14: =IF(OR(ISBLANK(B14),B14=""),0,VLOOKUP(B14,'Ondal Booms'!B:G,4,FALSE)) -> 0 | D14: =IF(OR(ISBLANK(B14),B14=""),0,VLOOKUP(B14,'Ondal Booms'!B:G,2,FALSE)) -> 0 | E14: =IF(OR(ISBLANK(B14),B14=""),0,VLOOKUP(B14,'Ondal Booms'!B:G,3,FALSE)) -> 0 | G14: Nitrous Count | H14: =COUNTIF(K5:Y14,"Nitrous Oxide") -> 0 | J14: 5 Right | Z14: =15-COUNTIFS(K14:Y14,"") -> 0
A15: Shelf (500mm) | C15: =IF(OR(ISBLANK(B15),B15=""),0,VLOOKUP(B15,'Ondal Booms'!B:G,4,FALSE)) -> 0 | D15: =IF(OR(ISBLANK(B15),B15=""),0,VLOOKUP(B15,'Ondal Booms'!B:G,2,FALSE)) -> 0 | E15: =IF(OR(ISBLANK(B15),B15=""),0,VLOOKUP(B15,'Ondal Booms'!B:G,3,FALSE)) -> 0 | G15: WAGD Count | H15: =COUNTIF(K5:Y14,"WAGD") -> 0
A16: Shelf (750mm) | C16: =IF(OR(ISBLANK(B16),B16=""),0,VLOOKUP(B16,'Ondal Booms'!B:G,4,FALSE)) -> 0 | D16: =IF(OR(ISBLANK(B16),B16=""),0,VLOOKUP(B16,'Ondal Booms'!B:G,2,FALSE)) -> 0 | E16: =IF(OR(ISBLANK(B16),B16=""),0,VLOOKUP(B16,'Ondal Booms'!B:G,3,FALSE)) -> 0 | G16: Vacuum Count | H16: =COUNTIF(K5:Y14,"Vacuum") -> 0
A17: Accessory 1 | C17: =IF(OR(ISBLANK(B17),B17=""),0,VLOOKUP(B17,'Ondal Booms'!B:G,4,FALSE)) -> 0 | D17: =IF(OR(ISBLANK(B17),B17=""),0,VLOOKUP(B17,'Ondal Booms'!B:G,2,FALSE)) -> 0 | E17: =IF(OR(ISBLANK(B17),B17=""),0,VLOOKUP(B17,'Ondal Booms'!B:G,3,FALSE)) -> 0 | G17: Nitrogen Count | H17: =COUNTIF(K5:Y14,"Nitrogen") -> 0
A18: Accessory 2 | C18: =IF(OR(ISBLANK(B18),B18=""),0,VLOOKUP(B18,'Ondal Booms'!B:G,4,FALSE)) -> 0 | D18: =IF(OR(ISBLANK(B18),B18=""),0,VLOOKUP(B18,'Ondal Booms'!B:G,2,FALSE)) -> 0 | E18: =IF(OR(ISBLANK(B18),B18=""),0,VLOOKUP(B18,'Ondal Booms'!B:G,3,FALSE)) -> 0 | G18: CO2 Count | H18: =COUNTIF(K5:Y14,"Carbon Dioxide") -> 0
A19: Accessory 3 | C19: =IF(OR(ISBLANK(B19),B19=""),0,VLOOKUP(B19,'Ondal Booms'!B:G,4,FALSE)) -> 0 | D19: =IF(OR(ISBLANK(B19),B19=""),0,VLOOKUP(B19,'Ondal Booms'!B:G,2,FALSE)) -> 0 | E19: =IF(OR(ISBLANK(B19),B19=""),0,VLOOKUP(B19,'Ondal Booms'!B:G,3,FALSE)) -> 0
A20: Accessory 4 | C20: =IF(OR(ISBLANK(B20),B20=""),0,VLOOKUP(B20,'Ondal Booms'!B:G,4,FALSE)) -> 0 | D20: =IF(OR(ISBLANK(B20),B20=""),0,VLOOKUP(B20,'Ondal Booms'!B:G,2,FALSE)) -> 0 | E20: =IF(OR(ISBLANK(B20),B20=""),0,VLOOKUP(B20,'Ondal Booms'!B:G,3,FALSE)) -> 0
A21: Accessory 5 | C21: =IF(OR(ISBLANK(B21),B21=""),0,VLOOKUP(B21,'Ondal Booms'!B:G,4,FALSE)) -> 0 | D21: =IF(OR(ISBLANK(B21),B21=""),0,VLOOKUP(B21,'Ondal Booms'!B:G,2,FALSE)) -> 0 | E21: =IF(OR(ISBLANK(B21),B21=""),0,VLOOKUP(B21,'Ondal Booms'!B:G,3,FALSE)) -> 0
A22: Accessory 6 | C22: =IF(OR(ISBLANK(B22),B22=""),0,VLOOKUP(B22,'Ondal Booms'!B:G,4,FALSE)) -> 0 | D22: =IF(OR(ISBLANK(B22),B22=""),0,VLOOKUP(B22,'Ondal Booms'!B:G,2,FALSE)) -> 0 | E22: =IF(OR(ISBLANK(B22),B22=""),0,VLOOKUP(B22,'Ondal Booms'!B:G,3,FALSE)) -> 0
A23: Accessory 7 | C23: =IF(OR(ISBLANK(B23),B23=""),0,VLOOKUP(B23,'Ondal Booms'!B:G,4,FALSE)) -> 0 | D23: =IF(OR(ISBLANK(B23),B23=""),0,VLOOKUP(B23,'Ondal Booms'!B:G,2,FALSE)) -> 0 | E23: =IF(OR(ISBLANK(B23),B23=""),0,VLOOKUP(B23,'Ondal Booms'!B:G,3,FALSE)) -> 0
A25: Errors? | B25: =IF(OR(ISBLANK(B5),B5=""),"", IF(OR(AND(B11="200mm Service Head",SUM(Z7:Z14)>0),AND(B11="400mm Service Head",SUM(Z9:Z14)>0),AND(B11="600mm Service Head",SUM(Z11:Z14)>0),AND(B11="800mm Service Head",SUM(Z13:Z14)>0)),"Select Longer Service Head or Remove Services", IF(AND(RIGHT(B9,2)="XL",RIGHT(B8,2)<>"XL"),"BOTTOM XL ARM REQUIRES TOP XL ARM", IF(OR(ISBLANK(B6),ISBLANK(B7),ISBLANK(B8),ISBLANK(B9),ISBLANK(B10),ISBLANK(B11),ISBLANK(B15),ISBLANK(B16),ISBLANK(B14)),"Missing Selections for Configuration", IF(AND(B11="Large Monitor Carrier",B9<>"Spring Articulating"),"Large Monitor Requires Spring Bottom Arm", IF(OR(AND(RIGHT(B7,2)="XL",RIGHT(B8,2)<>"XL"),AND(RIGHT(B8,2)="XL",RIGHT(B7,2)<>"XL")),"Both Top Arm and Ceiling Flange Must Be XL", IF(COUNTIF(AE4:AH12,1)>1,"Mismatch Electrical Configuration", "")))))) )
C26: IMAGINE LIST | D26: ONDAL LIST | E26: ONDAL SALES
A27: Equipment List Price | B27: =IF(OR(B6="",ISBLANK(B6)),"NO CONFIGURATION SELECTED",C27) -> NO CONFIGURATION SELECTED | C27: =SUM(C5:C23) -> 0 | D27: =SUM(D5:D23) -> 0 | E27: =SUM(E5:E23) -> 0 | J27: ="<-- EXPAND TO SHOW OPTIONS / SERVICE HEAD" -> <-- EXPAND TO SHOW OPTIONS / SERVICE HEAD
AE28: =COUNTIF(K30,"(2) Duplexes")+COUNTIF(Y30,"(2) Duplexes") -> 0 | AF28: =COUNTIF(Q30:S30,"(2) Duplexes") -> 0 | AG28: =COUNTIF(K30,"(3) Duplexes")+COUNTIF(Y30,"(3) Duplexes") -> 0 | AH28: =COUNTIF(Q30:S30,"(3) Duplexes") -> 0
A29: BOOM (TANDEM 2ND ONLY) | B29: SELECTION | C29: IMAGINE LIST | D29: ONDAL LIST | E29: ONDAL COG | G29: HV Services | H29: Count | J29: Layer | K29: Selection | L29: FRONT | Q29: Selection | S29: Selection | T29: BACK | Y29: Selection
A30: Model | B30: =IF(OR(ISBLANK(B32),ISBLANK(B33)),"",IF(ISBLANK(B33),0,(VLOOKUP(B33,'Ondal Booms'!B:F,5,FALSE)))&IF(ISBLANK(B32),0,(VLOOKUP(B32,'Ondal Booms'!B:F,5,FALSE)))) | C30: =IF(OR(ISBLANK(B30),B30=""),0,VLOOKUP(B30,'Ondal Booms'!B:G,4,FALSE)) -> 0 | D30: =IF(OR(ISBLANK(B30),B30=""),0,VLOOKUP(B30,'Ondal Booms'!B:G,2,FALSE)) -> 0 | E30: =IF(OR(ISBLANK(B30),B30=""),0,VLOOKUP(B30,'Ondal Booms'!B:G,3,FALSE)) -> 0 | G30: Duplex Count | H30: =COUNTIF(K30:Y39,"(2) Duplexes")*2+COUNTIF(K30:Y39,"(3) Duplexes")*3 -> 0 | J30: 1 Left | Z30: =15-COUNTIFS(K30:Y30,"") -> 0
A31: Ceiling Flange | C31: =IF(OR(ISBLANK(B31),B31=""),0,VLOOKUP(B31,'Ondal Booms'!B:G,4,FALSE)) -> 0 | D31: =IF(OR(ISBLANK(B31),B31=""),0,VLOOKUP(B31,'Ondal Booms'!B:G,2,FALSE)) -> 0 | E31: =IF(OR(ISBLANK(B31),B31=""),0,VLOOKUP(B31,'Ondal Booms'!B:G,3,FALSE)) -> 0 | G31: LV Services | H31: Count | J31: 1 Right | Z31: =15-COUNTIFS(K31:Y31,"") -> 0 | AE31: =COUNTIF(K32,"(2) Duplexes")+COUNTIF(Y32,"(2) Duplexes") -> 0 | AF31: =COUNTIF(Q32:S32,"(2) Duplexes") -> 0 | AG31: =COUNTIF(K32,"(3) Duplexes")+COUNTIF(Y32,"(3) Duplexes") -> 0 | AH31: =COUNTIF(Q32:S32,"(3) Duplexes") -> 0
A32: Top Arm | C32: =IF(OR(ISBLANK(B32),B32=""),0,VLOOKUP(B32,'Ondal Booms'!B:G,4,FALSE)) -> 0 | D32: =IF(OR(ISBLANK(B32),B32=""),0,VLOOKUP(B32,'Ondal Booms'!B:G,2,FALSE)) -> 0 | E32: =IF(OR(ISBLANK(B32),B32=""),0,VLOOKUP(B32,'Ondal Booms'!B:G,3,FALSE)) -> 0 | G32: Data Count | H32: =(COUNTIF(K30:Y39,"Data")) -> 0 | J32: 2 Left | Z32: =15-COUNTIFS(K32:Y32,"") -> 0
A33: Bottom Arm | C33: =IF(OR(ISBLANK(B33),B33=""),0,VLOOKUP(B33,'Ondal Booms'!B:G,4,FALSE)) -> 0 | D33: =IF(OR(ISBLANK(B33),B33=""),0,VLOOKUP(B33,'Ondal Booms'!B:G,2,FALSE)) -> 0 | E33: =IF(OR(ISBLANK(B33),B33=""),0,VLOOKUP(B33,'Ondal Booms'!B:G,3,FALSE)) -> 0 | G33: Storz 4in1 Count | H33: =(COUNTIF(K30:Y39,"Storz 4in1")) -> 0 | J33: 2 Right | Z33: =15-COUNTIFS(K33:Y33,"") -> 0 | AE33: =COUNTIF(K34,"(2) Duplexes")+COUNTIF(Y34,"(2) Duplexes") -> 0 | AF33: =COUNTIF(Q34:S34,"(2) Duplexes") -> 0 | AG33: =COUNTIF(K34,"(3) Duplexes")+COUNTIF(Y34,"(3) Duplexes") -> 0 | AH33: =COUNTIF(Q34:S34,"(3) Duplexes") -> 0
A34: Column Tube | C34: =IF(OR(ISBLANK(B34),B34=""),0,VLOOKUP(B34,'Ondal Booms'!B:G,4,FALSE)) -> 0 | D34: =IF(OR(ISBLANK(B34),B34=""),0,VLOOKUP(B34,'Ondal Booms'!B:G,2,FALSE)) -> 0 | E34: =IF(OR(ISBLANK(B34),B34=""),0,VLOOKUP(B34,'Ondal Booms'!B:G,3,FALSE)) -> 0 | J34: 3 Left | Z34: =15-COUNTIFS(K34:Y34,"") -> 0
A35: Service Head | C35: =IF(OR(ISBLANK(B35),B35=""),0,VLOOKUP(B35,'Ondal Booms'!B:G,4,FALSE)) -> 0 | D35: =IF(OR(ISBLANK(B35),B35=""),0,VLOOKUP(B35,'Ondal Booms'!B:G,2,FALSE)) -> 0 | E35: =IF(OR(ISBLANK(B35),B35=""),0,VLOOKUP(B35,'Ondal Booms'!B:G,3,FALSE)) -> 0 | G35: Medical Gases | H35: Count | J35: 3 Right | Z35: =15-COUNTIFS(K35:Y35,"") -> 0 | AE35: =COUNTIF(K36,"(2) Duplexes")+COUNTIF(Y36,"(2) Duplexes") -> 0 | AF35: =COUNTIF(Q36:S36,"(2) Duplexes") -> 0 | AG35: =COUNTIF(K36,"(3) Duplexes")+COUNTIF(Y36,"(3) Duplexes") -> 0 | AH35: =COUNTIF(Q36:S36,"(3) Duplexes") -> 0
A36: Electrical | B36: =IF(OR(H30=0,ISBLANK(H30)),"",H30&" Duplexes") | C36: =IF(OR(ISBLANK(B36),B36=""),0,VLOOKUP(B36,'Ondal Booms'!B:G,4,FALSE)) -> 0 | D36: =IF(OR(ISBLANK(B36),B36=""),0,VLOOKUP(B36,'Ondal Booms'!B:G,2,FALSE)) -> 0 | E36: =IF(OR(ISBLANK(B36),B36=""),0,VLOOKUP(B36,'Ondal Booms'!B:G,3,FALSE)) -> 0 | G36: Oxygen Count | H36: =(COUNTIF(K30:Y39,"Oxygen")) -> 0 | J36: 4 Left | Z36: =15-COUNTIFS(K36:Y36,"") -> 0
A37: Medical Gas | B37: =IF(OR(SUM(H36:H42)=0,ISBLANK(SUM(H36:H42))),"",SUM(H36:H42)&" Outlets") | C37: =IF(OR(ISBLANK(B37),B37=""),0,VLOOKUP(B37,'Ondal Booms'!B:G,4,FALSE)) -> 0 | D37: =IF(OR(ISBLANK(B37),B37=""),0,VLOOKUP(B37,'Ondal Booms'!B:G,2,FALSE)) -> 0 | E37: =IF(OR(ISBLANK(B37),B37=""),0,VLOOKUP(B37,'Ondal Booms'!B:G,3,FALSE)) -> 0 | G37: Med Air Count | H37: =COUNTIF(K30:Y39,"Medical Air") -> 0 | J37: 4 Right | Z37: =15-COUNTIFS(K37:Y37,"") -> 0 | AE37: =COUNTIF(K38,"(2) Duplexes")+COUNTIF(Y38,"(2) Duplexes") -> 0 | AF37: =COUNTIF(Q38:S38,"(2) Duplexes") -> 0 | AG37: =COUNTIF(K38,"(3) Duplexes")+COUNTIF(Y38,"(3) Duplexes") -> 0 | AH37: =COUNTIF(Q38:S38,"(3) Duplexes") -> 0
A38: # of Outlet Circuits | C38: =IF(OR(ISBLANK(B38),B38=""),0,VLOOKUP(B38,'Ondal Booms'!B:G,4,FALSE)) -> 0 | D38: =IF(OR(ISBLANK(B38),B38=""),0,VLOOKUP(B38,'Ondal Booms'!B:G,2,FALSE)) -> 0 | E38: =IF(OR(ISBLANK(B38),B38=""),0,VLOOKUP(B38,'Ondal Booms'!B:G,3,FALSE)) -> 0 | G38: Nitrous Count | H38: =COUNTIF(K30:Y39,"Nitrous Oxide") -> 0 | J38: 5 Left | Z38: =15-COUNTIFS(K38:Y38,"") -> 0
A39: Shelf (500mm) | C39: =IF(OR(ISBLANK(B39),B39=""),0,VLOOKUP(B39,'Ondal Booms'!B:G,4,FALSE)) -> 0 | D39: =IF(OR(ISBLANK(B39),B39=""),0,VLOOKUP(B39,'Ondal Booms'!B:G,2,FALSE)) -> 0 | E39: =IF(OR(ISBLANK(B39),B39=""),0,VLOOKUP(B39,'Ondal Booms'!B:G,3,FALSE)) -> 0 | G39: WAGD Count | H39: =COUNTIF(K30:Y39,"WAGD") -> 0 | J39: 5 Right | Z39: =15-COUNTIFS(K39:Y39,"") -> 0
A40: Shelf (750mm) | C40: =IF(OR(ISBLANK(B40),B40=""),0,VLOOKUP(B40,'Ondal Booms'!B:G,4,FALSE)) -> 0 | D40: =IF(OR(ISBLANK(B40),B40=""),0,VLOOKUP(B40,'Ondal Booms'!B:G,2,FALSE)) -> 0 | E40: =IF(OR(ISBLANK(B40),B40=""),0,VLOOKUP(B40,'Ondal Booms'!B:G,3,FALSE)) -> 0 | G40: Vacuum Count | H40: =COUNTIF(K30:Y39,"Vacuum") -> 0
A41: Accessory 1 | C41: =IF(OR(ISBLANK(B41),B41=""),0,VLOOKUP(B41,'Ondal Booms'!B:G,4,FALSE)) -> 0 | D41: =IF(OR(ISBLANK(B41),B41=""),0,VLOOKUP(B41,'Ondal Booms'!B:G,2,FALSE)) -> 0 | E41: =IF(OR(ISBLANK(B41),B41=""),0,VLOOKUP(B41,'Ondal Booms'!B:G,3,FALSE)) -> 0 | G41: Nitrogen Count | H41: =COUNTIF(K30:Y39,"Nitrogen") -> 0
A42: Accessory 2 | C42: =IF(OR(ISBLANK(B42),B42=""),0,VLOOKUP(B42,'Ondal Booms'!B:G,4,FALSE)) -> 0 | D42: =IF(OR(ISBLANK(B42),B42=""),0,VLOOKUP(B42,'Ondal Booms'!B:G,2,FALSE)) -> 0 | E42: =IF(OR(ISBLANK(B42),B42=""),0,VLOOKUP(B42,'Ondal Booms'!B:G,3,FALSE)) -> 0 | G42: CO2 Count | H42: =COUNTIF(K30:Y39,"Carbon Dioxide") -> 0
A43: Accessory 3 | C43: =IF(OR(ISBLANK(B43),B43=""),0,VLOOKUP(B43,'Ondal Booms'!B:G,4,FALSE)) -> 0 | D43: =IF(OR(ISBLANK(B43),B43=""),0,VLOOKUP(B43,'Ondal Booms'!B:G,2,FALSE)) -> 0 | E43: =IF(OR(ISBLANK(B43),B43=""),0,VLOOKUP(B43,'Ondal Booms'!B:G,3,FALSE)) -> 0
A44: Accessory 4 | C44: =IF(OR(ISBLANK(B44),B44=""),0,VLOOKUP(B44,'Ondal Booms'!B:G,4,FALSE)) -> 0 | D44: =IF(OR(ISBLANK(B44),B44=""),0,VLOOKUP(B44,'Ondal Booms'!B:G,2,FALSE)) -> 0 | E44: =IF(OR(ISBLANK(B44),B44=""),0,VLOOKUP(B44,'Ondal Booms'!B:G,3,FALSE)) -> 0
A45: Accessory 5 | C45: =IF(OR(ISBLANK(B45),B45=""),0,VLOOKUP(B45,'Ondal Booms'!B:G,4,FALSE)) -> 0 | D45: =IF(OR(ISBLANK(B45),B45=""),0,VLOOKUP(B45,'Ondal Booms'!B:G,2,FALSE)) -> 0 | E45: =IF(OR(ISBLANK(B45),B45=""),0,VLOOKUP(B45,'Ondal Booms'!B:G,3,FALSE)) -> 0
A46: Accessory 6 | C46: =IF(OR(ISBLANK(B46),B46=""),0,VLOOKUP(B46,'Ondal Booms'!B:G,4,FALSE)) -> 0 | D46: =IF(OR(ISBLANK(B46),B46=""),0,VLOOKUP(B46,'Ondal Booms'!B:G,2,FALSE)) -> 0 | E46: =IF(OR(ISBLANK(B46),B46=""),0,VLOOKUP(B46,'Ondal Booms'!B:G,3,FALSE)) -> 0
A47: Accessory 7 | C47: =IF(OR(ISBLANK(B47),B47=""),0,VLOOKUP(B47,'Ondal Booms'!B:G,4,FALSE)) -> 0 | D47: =IF(OR(ISBLANK(B47),B47=""),0,VLOOKUP(B47,'Ondal Booms'!B:G,2,FALSE)) -> 0 | E47: =IF(OR(ISBLANK(B47),B47=""),0,VLOOKUP(B47,'Ondal Booms'!B:G,3,FALSE)) -> 0
A49: Errors? | B49: =IF(OR(ISBLANK(B30),B30=""),"", IF(OR(AND(B35="200mm Service Head",SUM(Z32:Z39)>0),AND(B35="400mm Service Head",SUM(Z34:Z39)>0),AND(B35="600mm Service Head",SUM(Z36:Z39)>0),AND(B35="800mm Service Head",SUM(Z38:Z39)>0)),"Select Longer Service Head or Remove Services", IF(AND(RIGHT(B33,2)="XL",RIGHT(B32,2)<>"XL"),"BOTTOM XL ARM REQUIRES TOP XL ARM", IF(OR(ISBLANK(#REF!),ISBLANK(B31),ISBLANK(B32),ISBLANK(B33),ISBLANK(B34),ISBLANK(B35),ISBLANK(B39),ISBLANK(B40),ISBLANK(B38)),"Missing Selections for Configuration", IF(AND(B35="Large Monitor Carrier",B33<>"Spring Articulating"),"Large Monitor Requires Spring Bottom Arm", IF(OR(AND(RIGHT(B31,2)="XL",RIGHT(B32,2)<>"XL"),AND(RIGHT(B32,2)="XL",RIGHT(B31,2)<>"XL")),"Both Top Arm and Ceiling Flange Must Be XL", IF(COUNTIF(AE29:AH37,1)>1,"Mismatch Electrical Configuration", "")))))) )
C50: IMAGINE LIST | D50: ONDAL LIST | E50: ONDAL SALES
A51: Equipment List Price | B51: =IF(OR(B30="",ISBLANK(B30)),"NO CONFIGURATION SELECTED",C51) -> NO CONFIGURATION SELECTED | C51: =SUM(C30:C47) -> 0 | D51: =SUM(D30:D47) -> 0 | E51: =SUM(E30:E47) -> 0 | J51: ="<-- EXPAND TO SHOW OPTIONS / SERVICE HEAD" -> <-- EXPAND TO SHOW OPTIONS / SERVICE HEAD
A53: LIGHT (SINGLE OR TANDEM) | B53: SELECTION | C53: IMAGINE LIST | D53: SIMEON LIST | E53: SIMEON COG
A54: Model | B54: =IF(AND(ISBLANK(B57),ISBLANK(B58),ISBLANK(B59)),"", IF(B55="Upgrade Only","UPGRADE", IF(RIGHT(B57,4)="(3P)","(3P) ","")& IF(ISBLANK(B57),"",VLOOKUP(B57,'Simeon Lights'!C:H,2,FALSE))& IF(ISBLANK(B58),""," / "&VLOOKUP(B58,'Simeon Lights'!C:H,2,FALSE))& IF(ISBLANK(B59),""," / "&VLOOKUP(B59,'Simeon Lights'!C:H,2,FALSE)))) -> FP / LED | C54: =IF(ISBLANK(B57),0,(VLOOKUP(B54,'Simeon Lights'!C:J,6,FALSE))) -> 10357.417 | D54: =IF(ISBLANK(B57),0,(VLOOKUP(B54,'Simeon Lights'!C:J,4,FALSE))) -> 6214.45 | E54: =IF(ISBLANK(B57),0,(VLOOKUP(B54,'Simeon Lights'!C:J,5,FALSE))) -> 3107.225
A55: Ceiling Cover | B55: Single Mount (Standard) | C55: =IF(ISBLANK(B55),0,VLOOKUP(B55,'Simeon Lights'!C:J,6,FALSE)) -> 1441.05 | D55: =IF(ISBLANK(B55),0,VLOOKUP(B55,'Simeon Lights'!C:J,4,FALSE)) -> 864.63 | E55: =IF(ISBLANK(B55),0,VLOOKUP(B55,'Simeon Lights'!C:J,5,FALSE)) -> 432.315
A56: Ceiling Drop Tube | B56: 250mm | C56: =IF(ISBLANK(B56),0,VLOOKUP(B56,'Simeon Lights'!C:J,6,FALSE)) -> 0 | D56: =IF(ISBLANK(B56),0,VLOOKUP(B56,'Simeon Lights'!C:J,4,FALSE)) -> 0 | E56: =IF(ISBLANK(B56),0,VLOOKUP(B56,'Simeon Lights'!C:J,5,FALSE)) -> 0
A57: Arm 1 (Top Arm) | B57: 32in Flat Panel | C57: =IF(ISBLANK(B57),0,VLOOKUP(B57,'Simeon Lights'!C:J,6,FALSE)) -> 13583.95 | D57: =IF(ISBLANK(B57),0,VLOOKUP(B57,'Simeon Lights'!C:J,4,FALSE)) -> 8150.37 | E57: =IF(ISBLANK(B57),0,VLOOKUP(B57,'Simeon Lights'!C:J,5,FALSE)) -> 4075.185
A58: Arm 2 | B58: 8000 Standard | C58: =IF(ISBLANK(B58),0,VLOOKUP(B58,'Simeon Lights'!C:J,6,FALSE)) -> 30069.75 | D58: =IF(ISBLANK(B58),0,VLOOKUP(B58,'Simeon Lights'!C:J,4,FALSE)) -> 18041.85 | E58: =IF(ISBLANK(B58),0,VLOOKUP(B58,'Simeon Lights'!C:J,5,FALSE)) -> 9020.925
A59: Arm 3 | C59: =IF(ISBLANK(B59),0,VLOOKUP(B59,'Simeon Lights'!C:J,6,FALSE)) -> 0 | D59: =IF(ISBLANK(B59),0,VLOOKUP(B59,'Simeon Lights'!C:J,4,FALSE)) -> 0 | E59: =IF(ISBLANK(B59),0,VLOOKUP(B59,'Simeon Lights'!C:J,5,FALSE)) -> 0
A60: Wall Control | B60: Wall Control in Separate Config | C60: =IF(ISBLANK(B60),0,VLOOKUP(B60,'Simeon Lights'!C:J,6,FALSE)) -> 0 | D60: =IF(ISBLANK(B60),0,VLOOKUP(B60,'Simeon Lights'!C:J,4,FALSE)) -> 0 | E60: =IF(ISBLANK(B60),0,VLOOKUP(B60,'Simeon Lights'!C:J,5,FALSE)) -> 0
A61: Integration Control | B61: No Integration Control | C61: =IF(ISBLANK(B61),0,VLOOKUP(B61,'Simeon Lights'!C:J,6,FALSE)) -> 0 | D61: =IF(ISBLANK(B61),0,VLOOKUP(B61,'Simeon Lights'!C:J,4,FALSE)) -> 0 | E61: =IF(ISBLANK(B61),0,VLOOKUP(B61,'Simeon Lights'!C:J,5,FALSE)) -> 0
A62: In-Light Camera | B62: No Camera Prep | C62: =IF(ISBLANK(B62),0,VLOOKUP(B62,'Simeon Lights'!C:J,6,FALSE)) -> 0 | D62: =IF(ISBLANK(B62),0,VLOOKUP(B62,'Simeon Lights'!C:J,4,FALSE)) -> 0 | E62: =IF(ISBLANK(B62),0,VLOOKUP(B62,'Simeon Lights'!C:J,5,FALSE)) -> 0
A63: Disposable Adpaters | B63: (1) Screw-On Adapters | C63: =IF(ISBLANK(B63),0,VLOOKUP(B63,'Simeon Lights'!C:J,6,FALSE)) -> 440 | D63: =IF(ISBLANK(B63),0,VLOOKUP(B63,'Simeon Lights'!C:J,4,FALSE)) -> 264 | E63: =IF(ISBLANK(B63),0,VLOOKUP(B63,'Simeon Lights'!C:J,5,FALSE)) -> 132
A65: Errors? | B65: =IF(AND(ISBLANK(B57),ISBLANK(B58),ISBLANK(B59)),"", IF(AND(ISBLANK(B57),B58<>""),"ARM 1 MISSING", IF(AND(ISBLANK(B57),B59<>""),"ARM 1 MISSING", IF(ISBLANK(B58)&ISBLANK(B59)="TRUEFALSE","ARM 2 MISSING", IF(AND(B57<>"",B58="32in Flat Panel",B59<>""),"FP CANNOT BE MIDDLE ARM", IF(OR(ISBLANK(B55),ISBLANK(B56),ISBLANK(B60),ISBLANK(B61),ISBLANK(B62),ISBLANK(B63)),"Missing Selections",""))))))
C66: IMAGINE LIST | D66: SIMEON LIST | E66: SIMEON COG
A67: Equipment List Price | B67: =IF(OR(ISBLANK(B57),ISBLANK(B58)&ISBLANK(B59)="TRUEFALSE"),"NO CONFIGURATION SELECTED",IF(B65<>"","ERROR IN CONFIGURATION",IF(B57="",0,SUM(C54:C63)))) -> 55892.167 | C67: =SUM(C54:C65) -> 55892.167 | D67: =SUM(D54:D65) -> 33535.3 | E67: =SUM(E54:E65) -> 16767.65 | J67: ="<-- EXPAND TO SHOW OPTIONS" -> <-- EXPAND TO SHOW OPTIONS
B69: CONFIGRATION LIST PRICE | E69: TOTAL COG
A70: Total List Price | B70: =IF(OR(B27="Error in Configuration",B27="No Configuration Selected"),0,B27)+IF(OR(B51="Error in Configuration",B51="No Configuration Selected"),0,B51)+IF(OR(B67="Error in Configuration",B67="No Configuration Selected"),0,B67) -> 55892.167 | E70: =SUM(E67,E51,E27) -> 16767.65

Sheet Config #3
A1: CONFIGURATION #3 | B1: DESCRIPTION
A2: Configuration Name | B2: Equipment Boom (Patient Foot)
A4: BOOM (SINGLE OR TANDEM) | B4: SELECTION | C4: IMAGINE LIST | D4: ONDAL LIST | E4: ONDAL COG | G4: HV Services | H4: Count | J4: Layer | K4: Selection | L4: FRONT | Q4: Selection | S4: Selection | T4: BACK | Y4: Selection | AE4: =COUNTIF(K5,"(2) Duplexes")+COUNTIF(Y5,"(2) Duplexes") -> 0 | AF4: =COUNTIF(Q5:S5,"(2) Duplexes") -> 2 | AG4: =COUNTIF(K5,"(3) Duplexes")+COUNTIF(Y5,"(3) Duplexes") -> 0 | AH4: =COUNTIF(Q5:S5,"(3) Duplexes") -> 0
A5: Model | B5: =IF(OR(ISBLANK(B8),ISBLANK(B9)),"",IF(ISBLANK(B9),0,(VLOOKUP(B9,'Ondal Booms'!B:F,5,FALSE)))&IF(ISBLANK(B8),0,(VLOOKUP(B8,'Ondal Booms'!B:F,5,FALSE)))) -> Powered XL | C5: =IF(OR(ISBLANK(B5),B5=""),0,VLOOKUP(B5,'Ondal Booms'!B:G,4,FALSE)) -> 33564.85 | D5: =IF(OR(ISBLANK(B5),B5=""),0,VLOOKUP(B5,'Ondal Booms'!B:G,2,FALSE)) -> 13425.94 | E5: =IF(OR(ISBLANK(B5),B5=""),0,VLOOKUP(B5,'Ondal Booms'!B:G,3,FALSE)) -> 10069.455 | G5: Duplex Count | H5: =COUNTIF(K5:Y14,"(2) Duplexes")*2+COUNTIF(K5:Y14,"(3) Duplexes")*3 -> 12 | J5: 1 Left | K5: Blank | Q5: (2) Duplexes | S5: (2) Duplexes | Y5: Storz 4in1 | Z5: =15-COUNTIFS(K5:Y5,"") -> 4
A6: Ceiling Cover | B6: Single Mount (Square) | C6: =IF(OR(ISBLANK(B6),B6=""),0,VLOOKUP(B6,'Ondal Booms'!B:G,4,FALSE)) -> 3484.725 | D6: =IF(OR(ISBLANK(B6),B6=""),0,VLOOKUP(B6,'Ondal Booms'!B:G,2,FALSE)) -> 1393.89 | E6: =IF(OR(ISBLANK(B6),B6=""),0,VLOOKUP(B6,'Ondal Booms'!B:G,3,FALSE)) -> 1045.4175 | J6: 1 Right | K6: Blank | Y6: Data | Z6: =15-COUNTIFS(K6:Y6,"") -> 2 | AE6: =COUNTIF(K7,"(2) Duplexes")+COUNTIF(Y7,"(2) Duplexes") -> 0 | AF6: =COUNTIF(Q7:S7,"(2) Duplexes") -> 2 | AG6: =COUNTIF(K7,"(3) Duplexes")+COUNTIF(Y7,"(3) Duplexes") -> 0 | AH6: =COUNTIF(Q7:S7,"(3) Duplexes") -> 0
A7: Ceiling Flange | B7: 100mm XL | C7: =IF(OR(ISBLANK(B7),B7=""),0,VLOOKUP(B7,'Ondal Booms'!B:G,4,FALSE)) -> 0 | D7: =IF(OR(ISBLANK(B7),B7=""),0,VLOOKUP(B7,'Ondal Booms'!B:G,2,FALSE)) -> 0 | E7: =IF(OR(ISBLANK(B7),B7=""),0,VLOOKUP(B7,'Ondal Booms'!B:G,3,FALSE)) -> 0 | G7: LV Services | H7: Count | J7: 2 Left | K7: Blank | Q7: (2) Duplexes | S7: (2) Duplexes | Y7: Nitrogen | Z7: =15-COUNTIFS(K7:Y7,"") -> 4
A8: Top Arm | B8: 1600mm XL | C8: =IF(OR(ISBLANK(B8),B8=""),0,VLOOKUP(B8,'Ondal Booms'!B:G,4,FALSE)) -> 3382.7 | D8: =IF(OR(ISBLANK(B8),B8=""),0,VLOOKUP(B8,'Ondal Booms'!B:G,2,FALSE)) -> 1353.08 | E8: =IF(OR(ISBLANK(B8),B8=""),0,VLOOKUP(B8,'Ondal Booms'!B:G,3,FALSE)) -> 1014.81 | G8: Data Count | H8: =(COUNTIF(K5:Y14,"Data")) -> 1 | J8: 2 Right | K8: Blank | Y8: Blank | Z8: =15-COUNTIFS(K8:Y8,"") -> 2 | AE8: =COUNTIF(K9,"(2) Duplexes")+COUNTIF(Y9,"(2) Duplexes") -> 0 | AF8: =COUNTIF(Q9:S9,"(2) Duplexes") -> 2 | AG8: =COUNTIF(K9,"(3) Duplexes")+COUNTIF(Y9,"(3) Duplexes") -> 0 | AH8: =COUNTIF(Q9:S9,"(3) Duplexes") -> 0
A9: Bottom Arm | B9: Powered Articulating | C9: =IF(OR(ISBLANK(B9),B9=""),0,VLOOKUP(B9,'Ondal Booms'!B:G,4,FALSE)) -> 0 | D9: =IF(OR(ISBLANK(B9),B9=""),0,VLOOKUP(B9,'Ondal Booms'!B:G,2,FALSE)) -> 0 | E9: =IF(OR(ISBLANK(B9),B9=""),0,VLOOKUP(B9,'Ondal Booms'!B:G,3,FALSE)) -> 0 | G9: Storz 4in1 Count | H9: =(COUNTIF(K5:Y14,"Storz 4in1")) -> 1 | J9: 3 Left | K9: Carbon Dioxide | Q9: (2) Duplexes | S9: (2) Duplexes | Y9: Vacuum | Z9: =15-COUNTIFS(K9:Y9,"") -> 4
A10: Column Tube | B10: 200mm Column Tube | C10: =IF(OR(ISBLANK(B10),B10=""),0,VLOOKUP(B10,'Ondal Booms'!B:G,4,FALSE)) -> 0 | D10: =IF(OR(ISBLANK(B10),B10=""),0,VLOOKUP(B10,'Ondal Booms'!B:G,2,FALSE)) -> 0 | E10: =IF(OR(ISBLANK(B10),B10=""),0,VLOOKUP(B10,'Ondal Booms'!B:G,3,FALSE)) -> 0 | J10: 3 Right | K10: Blank | Y10: Vacuum | Z10: =15-COUNTIFS(K10:Y10,"") -> 2 | AE10: =COUNTIF(K11,"(2) Duplexes")+COUNTIF(Y11,"(2) Duplexes") -> 0 | AF10: =COUNTIF(Q11:S11,"(2) Duplexes") -> 0 | AG10: =COUNTIF(K11,"(3) Duplexes")+COUNTIF(Y11,"(3) Duplexes") -> 0 | AH10: =COUNTIF(Q11:S11,"(3) Duplexes") -> 0
A11: Service Head | B11: 600mm Service Head | C11: =IF(OR(ISBLANK(B11),B11=""),0,VLOOKUP(B11,'Ondal Booms'!B:G,4,FALSE)) -> 0 | D11: =IF(OR(ISBLANK(B11),B11=""),0,VLOOKUP(B11,'Ondal Booms'!B:G,2,FALSE)) -> 0 | E11: =IF(OR(ISBLANK(B11),B11=""),0,VLOOKUP(B11,'Ondal Booms'!B:G,3,FALSE)) -> 0 | G11: Medical Gases | H11: Count | J11: 4 Left | Z11: =15-COUNTIFS(K11:Y11,"") -> 0
A12: Electrical | B12: =IF(OR(H5=0,ISBLANK(H5)),"",H5&" Duplexes") -> 12 Duplexes | C12: =IF(OR(ISBLANK(B12),B12=""),0,VLOOKUP(B12,'Ondal Booms'!B:G,4,FALSE)) -> 2816.4 | D12: =IF(OR(ISBLANK(B12),B12=""),0,VLOOKUP(B12,'Ondal Booms'!B:G,2,FALSE)) -> 1126.56 | E12: =IF(OR(ISBLANK(B12),B12=""),0,VLOOKUP(B12,'Ondal Booms'!B:G,3,FALSE)) -> 844.92 | G12: Oxygen Count | H12: =(COUNTIF(K5:Y14,"Oxygen")) -> 0 | J12: 4 Right | Z12: =15-COUNTIFS(K12:Y12,"") -> 0 | AE12: =COUNTIF(K13,"(2) Duplexes")+COUNTIF(Y13,"(2) Duplexes") -> 0 | AF12: =COUNTIF(Q13:S13,"(2) Duplexes") -> 0 | AG12: =COUNTIF(K13,"(3) Duplexes")+COUNTIF(Y13,"(3) Duplexes") -> 0 | AH12: =COUNTIF(Q13:S13,"(3) Duplexes") -> 0
A13: Medical Gas | B13: =IF(OR(SUM(H12:H18)=0,ISBLANK(SUM(H12:H18))),"",SUM(H12:H18)&" Outlets") -> 4 Outlets | C13: =IF(OR(ISBLANK(B13),B13=""),0,VLOOKUP(B13,'Ondal Booms'!B:G,4,FALSE)) -> 3258.7 | D13: =IF(OR(ISBLANK(B13),B13=""),0,VLOOKUP(B13,'Ondal Booms'!B:G,2,FALSE)) -> 1303.48 | E13: =IF(OR(ISBLANK(B13),B13=""),0,VLOOKUP(B13,'Ondal Booms'!B:G,3,FALSE)) -> 977.61 | G13: Med Air Count | H13: =COUNTIF(K5:Y14,"Medical Air") -> 0 | J13: 5 Left | Z13: =15-COUNTIFS(K13:Y13,"") -> 0
A14: # of Outlet Circuits | B14: (6) Circuits | C14: =IF(OR(ISBLANK(B14),B14=""),0,VLOOKUP(B14,'Ondal Booms'!B:G,4,FALSE)) -> 0 | D14: =IF(OR(ISBLANK(B14),B14=""),0,VLOOKUP(B14,'Ondal Booms'!B:G,2,FALSE)) -> 0 | E14: =IF(OR(ISBLANK(B14),B14=""),0,VLOOKUP(B14,'Ondal Booms'!B:G,3,FALSE)) -> 0 | G14: Nitrous Count | H14: =COUNTIF(K5:Y14,"Nitrous Oxide") -> 0 | J14: 5 Right | Z14: =15-COUNTIFS(K14:Y14,"") -> 0
A15: Shelf (500mm) | B15: (4) 500mm Shelves | C15: =IF(OR(ISBLANK(B15),B15=""),0,VLOOKUP(B15,'Ondal Booms'!B:G,4,FALSE)) -> 5141.0667 | D15: =IF(OR(ISBLANK(B15),B15=""),0,VLOOKUP(B15,'Ondal Booms'!B:G,2,FALSE)) -> 2056.4267 | E15: =IF(OR(ISBLANK(B15),B15=""),0,VLOOKUP(B15,'Ondal Booms'!B:G,3,FALSE)) -> 1542.32 | G15: WAGD Count | H15: =COUNTIF(K5:Y14,"WAGD") -> 0
A16: Shelf (750mm) | B16: (0) 750mm Shelves | C16: =IF(OR(ISBLANK(B16),B16=""),0,VLOOKUP(B16,'Ondal Booms'!B:G,4,FALSE)) -> 0 | D16: =IF(OR(ISBLANK(B16),B16=""),0,VLOOKUP(B16,'Ondal Booms'!B:G,2,FALSE)) -> 0 | E16: =IF(OR(ISBLANK(B16),B16=""),0,VLOOKUP(B16,'Ondal Booms'!B:G,3,FALSE)) -> 0 | G16: Vacuum Count | H16: =COUNTIF(K5:Y14,"Vacuum") -> 2
A17: Accessory 1 | C17: =IF(OR(ISBLANK(B17),B17=""),0,VLOOKUP(B17,'Ondal Booms'!B:G,4,FALSE)) -> 0 | D17: =IF(OR(ISBLANK(B17),B17=""),0,VLOOKUP(B17,'Ondal Booms'!B:G,2,FALSE)) -> 0 | E17: =IF(OR(ISBLANK(B17),B17=""),0,VLOOKUP(B17,'Ondal Booms'!B:G,3,FALSE)) -> 0 | G17: Nitrogen Count | H17: =COUNTIF(K5:Y14,"Nitrogen") -> 1
A18: Accessory 2 | C18: =IF(OR(ISBLANK(B18),B18=""),0,VLOOKUP(B18,'Ondal Booms'!B:G,4,FALSE)) -> 0 | D18: =IF(OR(ISBLANK(B18),B18=""),0,VLOOKUP(B18,'Ondal Booms'!B:G,2,FALSE)) -> 0 | E18: =IF(OR(ISBLANK(B18),B18=""),0,VLOOKUP(B18,'Ondal Booms'!B:G,3,FALSE)) -> 0 | G18: CO2 Count | H18: =COUNTIF(K5:Y14,"Carbon Dioxide") -> 1
A19: Accessory 3 | C19: =IF(OR(ISBLANK(B19),B19=""),0,VLOOKUP(B19,'Ondal Booms'!B:G,4,FALSE)) -> 0 | D19: =IF(OR(ISBLANK(B19),B19=""),0,VLOOKUP(B19,'Ondal Booms'!B:G,2,FALSE)) -> 0 | E19: =IF(OR(ISBLANK(B19),B19=""),0,VLOOKUP(B19,'Ondal Booms'!B:G,3,FALSE)) -> 0
A20: Accessory 4 | C20: =IF(OR(ISBLANK(B20),B20=""),0,VLOOKUP(B20,'Ondal Booms'!B:G,4,FALSE)) -> 0 | D20: =IF(OR(ISBLANK(B20),B20=""),0,VLOOKUP(B20,'Ondal Booms'!B:G,2,FALSE)) -> 0 | E20: =IF(OR(ISBLANK(B20),B20=""),0,VLOOKUP(B20,'Ondal Booms'!B:G,3,FALSE)) -> 0
A21: Accessory 5 | C21: =IF(OR(ISBLANK(B21),B21=""),0,VLOOKUP(B21,'Ondal Booms'!B:G,4,FALSE)) -> 0 | D21: =IF(OR(ISBLANK(B21),B21=""),0,VLOOKUP(B21,'Ondal Booms'!B:G,2,FALSE)) -> 0 | E21: =IF(OR(ISBLANK(B21),B21=""),0,VLOOKUP(B21,'Ondal Booms'!B:G,3,FALSE)) -> 0
A22: Accessory 6 | C22: =IF(OR(ISBLANK(B22),B22=""),0,VLOOKUP(B22,'Ondal Booms'!B:G,4,FALSE)) -> 0 | D22: =IF(OR(ISBLANK(B22),B22=""),0,VLOOKUP(B22,'Ondal Booms'!B:G,2,FALSE)) -> 0 | E22: =IF(OR(ISBLANK(B22),B22=""),0,VLOOKUP(B22,'Ondal Booms'!B:G,3,FALSE)) -> 0
A23: Accessory 7 | C23: =IF(OR(ISBLANK(B23),B23=""),0,VLOOKUP(B23,'Ondal Booms'!B:G,4,FALSE)) -> 0 | D23: =IF(OR(ISBLANK(B23),B23=""),0,VLOOKUP(B23,'Ondal Booms'!B:G,2,FALSE)) -> 0 | E23: =IF(OR(ISBLANK(B23),B23=""),0,VLOOKUP(B23,'Ondal Booms'!B:G,3,FALSE)) -> 0
A25: Errors? | B25: =IF(OR(ISBLANK(B5),B5=""),"", IF(OR(AND(B11="200mm Service Head",SUM(Z7:Z14)>0),AND(B11="400mm Service Head",SUM(Z9:Z14)>0),AND(B11="600mm Service Head",SUM(Z11:Z14)>0),AND(B11="800mm Service Head",SUM(Z13:Z14)>0)),"Select Longer Service Head or Remove Services", IF(AND(RIGHT(B9,2)="XL",RIGHT(B8,2)<>"XL"),"BOTTOM XL ARM REQUIRES TOP XL ARM", IF(OR(ISBLANK(B6),ISBLANK(B7),ISBLANK(B8),ISBLANK(B9),ISBLANK(B10),ISBLANK(B11),ISBLANK(B15),ISBLANK(B16),ISBLANK(B14)),"Missing Selections for Configuration", IF(AND(B11="Large Monitor Carrier",B9<>"Spring Articulating"),"Large Monitor Requires Spring Bottom Arm", IF(OR(AND(RIGHT(B7,2)="XL",RIGHT(B8,2)<>"XL"),AND(RIGHT(B8,2)="XL",RIGHT(B7,2)<>"XL")),"Both Top Arm and Ceiling Flange Must Be XL", IF(COUNTIF(AE4:AH12,1)>1,"Mismatch Electrical Configuration", "")))))) )
C26: IMAGINE LIST | D26: ONDAL LIST | E26: ONDAL SALES
A27: Equipment List Price | B27: =IF(OR(B6="",ISBLANK(B6)),"NO CONFIGURATION SELECTED",C27) -> 51648.442 | C27: =SUM(C5:C23) -> 51648.442 | D27: =SUM(D5:D23) -> 20659.377 | E27: =SUM(E5:E23) -> 15494.532 | J27: ="<-- EXPAND TO SHOW OPTIONS / SERVICE HEAD" -> <-- EXPAND TO SHOW OPTIONS / SERVICE HEAD
AE28: =COUNTIF(K30,"(2) Duplexes")+COUNTIF(Y30,"(2) Duplexes") -> 0 | AF28: =COUNTIF(Q30:S30,"(2) Duplexes") -> 0 | AG28: =COUNTIF(K30,"(3) Duplexes")+COUNTIF(Y30,"(3) Duplexes") -> 0 | AH28: =COUNTIF(Q30:S30,"(3) Duplexes") -> 0
A29: BOOM (TANDEM 2ND ONLY) | B29: SELECTION | C29: IMAGINE LIST | D29: ONDAL LIST | E29: ONDAL COG | G29: HV Services | H29: Count | J29: Layer | K29: Selection | L29: FRONT | Q29: Selection | S29: Selection | T29: BACK | Y29: Selection
A30: Model | B30: =IF(OR(ISBLANK(B32),ISBLANK(B33)),"",IF(ISBLANK(B33),0,(VLOOKUP(B33,'Ondal Booms'!B:F,5,FALSE)))&IF(ISBLANK(B32),0,(VLOOKUP(B32,'Ondal Booms'!B:F,5,FALSE)))) | C30: =IF(OR(ISBLANK(B30),B30=""),0,VLOOKUP(B30,'Ondal Booms'!B:G,4,FALSE)) -> 0 | D30: =IF(OR(ISBLANK(B30),B30=""),0,VLOOKUP(B30,'Ondal Booms'!B:G,2,FALSE)) -> 0 | E30: =IF(OR(ISBLANK(B30),B30=""),0,VLOOKUP(B30,'Ondal Booms'!B:G,3,FALSE)) -> 0 | G30: Duplex Count | H30: =COUNTIF(K30:Y39,"(2) Duplexes")*2+COUNTIF(K30:Y39,"(3) Duplexes")*3 -> 0 | J30: 1 Left | Z30: =15-COUNTIFS(K30:Y30,"") -> 0
A31: Ceiling Flange | C31: =IF(OR(ISBLANK(B31),B31=""),0,VLOOKUP(B31,'Ondal Booms'!B:G,4,FALSE)) -> 0 | D31: =IF(OR(ISBLANK(B31),B31=""),0,VLOOKUP(B31,'Ondal Booms'!B:G,2,FALSE)) -> 0 | E31: =IF(OR(ISBLANK(B31),B31=""),0,VLOOKUP(B31,'Ondal Booms'!B:G,3,FALSE)) -> 0 | G31: LV Services | H31: Count | J31: 1 Right | Z31: =15-COUNTIFS(K31:Y31,"") -> 0 | AE31: =COUNTIF(K32,"(2) Duplexes")+COUNTIF(Y32,"(2) Duplexes") -> 0 | AF31: =COUNTIF(Q32:S32,"(2) Duplexes") -> 0 | AG31: =COUNTIF(K32,"(3) Duplexes")+COUNTIF(Y32,"(3) Duplexes") -> 0 | AH31: =COUNTIF(Q32:S32,"(3) Duplexes") -> 0
A32: Top Arm | C32: =IF(OR(ISBLANK(B32),B32=""),0,VLOOKUP(B32,'Ondal Booms'!B:G,4,FALSE)) -> 0 | D32: =IF(OR(ISBLANK(B32),B32=""),0,VLOOKUP(B32,'Ondal Booms'!B:G,2,FALSE)) -> 0 | E32: =IF(OR(ISBLANK(B32),B32=""),0,VLOOKUP(B32,'Ondal Booms'!B:G,3,FALSE)) -> 0 | G32: Data Count | H32: =(COUNTIF(K30:Y39,"Data")) -> 0 | J32: 2 Left | Z32: =15-COUNTIFS(K32:Y32,"") -> 0
A33: Bottom Arm | C33: =IF(OR(ISBLANK(B33),B33=""),0,VLOOKUP(B33,'Ondal Booms'!B:G,4,FALSE)) -> 0 | D33: =IF(OR(ISBLANK(B33),B33=""),0,VLOOKUP(B33,'Ondal Booms'!B:G,2,FALSE)) -> 0 | E33: =IF(OR(ISBLANK(B33),B33=""),0,VLOOKUP(B33,'Ondal Booms'!B:G,3,FALSE)) -> 0 | G33: Storz 4in1 Count | H33: =(COUNTIF(K30:Y39,"Storz 4in1")) -> 0 | J33: 2 Right | Z33: =15-COUNTIFS(K33:Y33,"") -> 0 | AE33: =COUNTIF(K34,"(2) Duplexes")+COUNTIF(Y34,"(2) Duplexes") -> 0 | AF33: =COUNTIF(Q34:S34,"(2) Duplexes") -> 0 | AG33: =COUNTIF(K34,"(3) Duplexes")+COUNTIF(Y34,"(3) Duplexes") -> 0 | AH33: =COUNTIF(Q34:S34,"(3) Duplexes") -> 0
A34: Column Tube | C34: =IF(OR(ISBLANK(B34),B34=""),0,VLOOKUP(B34,'Ondal Booms'!B:G,4,FALSE)) -> 0 | D34: =IF(OR(ISBLANK(B34),B34=""),0,VLOOKUP(B34,'Ondal Booms'!B:G,2,FALSE)) -> 0 | E34: =IF(OR(ISBLANK(B34),B34=""),0,VLOOKUP(B34,'Ondal Booms'!B:G,3,FALSE)) -> 0 | J34: 3 Left | Z34: =15-COUNTIFS(K34:Y34,"") -> 0
A35: Service Head | C35: =IF(OR(ISBLANK(B35),B35=""),0,VLOOKUP(B35,'Ondal Booms'!B:G,4,FALSE)) -> 0 | D35: =IF(OR(ISBLANK(B35),B35=""),0,VLOOKUP(B35,'Ondal Booms'!B:G,2,FALSE)) -> 0 | E35: =IF(OR(ISBLANK(B35),B35=""),0,VLOOKUP(B35,'Ondal Booms'!B:G,3,FALSE)) -> 0 | G35: Medical Gases | H35: Count | J35: 3 Right | Z35: =15-COUNTIFS(K35:Y35,"") -> 0 | AE35: =COUNTIF(K36,"(2) Duplexes")+COUNTIF(Y36,"(2) Duplexes") -> 0 | AF35: =COUNTIF(Q36:S36,"(2) Duplexes") -> 0 | AG35: =COUNTIF(K36,"(3) Duplexes")+COUNTIF(Y36,"(3) Duplexes") -> 0 | AH35: =COUNTIF(Q36:S36,"(3) Duplexes") -> 0
A36: Electrical | B36: =IF(OR(H30=0,ISBLANK(H30)),"",H30&" Duplexes") | C36: =IF(OR(ISBLANK(B36),B36=""),0,VLOOKUP(B36,'Ondal Booms'!B:G,4,FALSE)) -> 0 | D36: =IF(OR(ISBLANK(B36),B36=""),0,VLOOKUP(B36,'Ondal Booms'!B:G,2,FALSE)) -> 0 | E36: =IF(OR(ISBLANK(B36),B36=""),0,VLOOKUP(B36,'Ondal Booms'!B:G,3,FALSE)) -> 0 | G36: Oxygen Count | H36: =(COUNTIF(K30:Y39,"Oxygen")) -> 0 | J36: 4 Left | Z36: =15-COUNTIFS(K36:Y36,"") -> 0
A37: Medical Gas | B37: =IF(OR(SUM(H36:H42)=0,ISBLANK(SUM(H36:H42))),"",SUM(H36:H42)&" Outlets") | C37: =IF(OR(ISBLANK(B37),B37=""),0,VLOOKUP(B37,'Ondal Booms'!B:G,4,FALSE)) -> 0 | D37: =IF(OR(ISBLANK(B37),B37=""),0,VLOOKUP(B37,'Ondal Booms'!B:G,2,FALSE)) -> 0 | E37: =IF(OR(ISBLANK(B37),B37=""),0,VLOOKUP(B37,'Ondal Booms'!B:G,3,FALSE)) -> 0 | G37: Med Air Count | H37: =COUNTIF(K30:Y39,"Medical Air") -> 0 | J37: 4 Right | Z37: =15-COUNTIFS(K37:Y37,"") -> 0 | AE37: =COUNTIF(K38,"(2) Duplexes")+COUNTIF(Y38,"(2) Duplexes") -> 0 | AF37: =COUNTIF(Q38:S38,"(2) Duplexes") -> 0 | AG37: =COUNTIF(K38,"(3) Duplexes")+COUNTIF(Y38,"(3) Duplexes") -> 0 | AH37: =COUNTIF(Q38:S38,"(3) Duplexes") -> 0
A38: # of Outlet Circuits | C38: =IF(OR(ISBLANK(B38),B38=""),0,VLOOKUP(B38,'Ondal Booms'!B:G,4,FALSE)) -> 0 | D38: =IF(OR(ISBLANK(B38),B38=""),0,VLOOKUP(B38,'Ondal Booms'!B:G,2,FALSE)) -> 0 | E38: =IF(OR(ISBLANK(B38),B38=""),0,VLOOKUP(B38,'Ondal Booms'!B:G,3,FALSE)) -> 0 | G38: Nitrous Count | H38: =COUNTIF(K30:Y39,"Nitrous Oxide") -> 0 | J38: 5 Left | Z38: =15-COUNTIFS(K38:Y38,"") -> 0
A39: Shelf (500mm) | C39: =IF(OR(ISBLANK(B39),B39=""),0,VLOOKUP(B39,'Ondal Booms'!B:G,4,FALSE)) -> 0 | D39: =IF(OR(ISBLANK(B39),B39=""),0,VLOOKUP(B39,'Ondal Booms'!B:G,2,FALSE)) -> 0 | E39: =IF(OR(ISBLANK(B39),B39=""),0,VLOOKUP(B39,'Ondal Booms'!B:G,3,FALSE)) -> 0 | G39: WAGD Count | H39: =COUNTIF(K30:Y39,"WAGD") -> 0 | J39: 5 Right | Z39: =15-COUNTIFS(K39:Y39,"") -> 0
A40: Shelf (750mm) | C40: =IF(OR(ISBLANK(B40),B40=""),0,VLOOKUP(B40,'Ondal Booms'!B:G,4,FALSE)) -> 0 | D40: =IF(OR(ISBLANK(B40),B40=""),0,VLOOKUP(B40,'Ondal Booms'!B:G,2,FALSE)) -> 0 | E40: =IF(OR(ISBLANK(B40),B40=""),0,VLOOKUP(B40,'Ondal Booms'!B:G,3,FALSE)) -> 0 | G40: Vacuum Count | H40: =COUNTIF(K30:Y39,"Vacuum") -> 0
A41: Accessory 1 | C41: =IF(OR(ISBLANK(B41),B41=""),0,VLOOKUP(B41,'Ondal Booms'!B:G,4,FALSE)) -> 0 | D41: =IF(OR(ISBLANK(B41),B41=""),0,VLOOKUP(B41,'Ondal Booms'!B:G,2,FALSE)) -> 0 | E41: =IF(OR(ISBLANK(B41),B41=""),0,VLOOKUP(B41,'Ondal Booms'!B:G,3,FALSE)) -> 0 | G41: Nitrogen Count | H41: =COUNTIF(K30:Y39,"Nitrogen") -> 0
A42: Accessory 2 | C42: =IF(OR(ISBLANK(B42),B42=""),0,VLOOKUP(B42,'Ondal Booms'!B:G,4,FALSE)) -> 0 | D42: =IF(OR(ISBLANK(B42),B42=""),0,VLOOKUP(B42,'Ondal Booms'!B:G,2,FALSE)) -> 0 | E42: =IF(OR(ISBLANK(B42),B42=""),0,VLOOKUP(B42,'Ondal Booms'!B:G,3,FALSE)) -> 0 | G42: CO2 Count | H42: =COUNTIF(K30:Y39,"Carbon Dioxide") -> 0
A43: Accessory 3 | C43: =IF(OR(ISBLANK(B43),B43=""),0,VLOOKUP(B43,'Ondal Booms'!B:G,4,FALSE)) -> 0 | D43: =IF(OR(ISBLANK(B43),B43=""),0,VLOOKUP(B43,'Ondal Booms'!B:G,2,FALSE)) -> 0 | E43: =IF(OR(ISBLANK(B43),B43=""),0,VLOOKUP(B43,'Ondal Booms'!B:G,3,FALSE)) -> 0
A44: Accessory 4 | C44: =IF(OR(ISBLANK(B44),B44=""),0,VLOOKUP(B44,'Ondal Booms'!B:G,4,FALSE)) -> 0 | D44: =IF(OR(ISBLANK(B44),B44=""),0,VLOOKUP(B44,'Ondal Booms'!B:G,2,FALSE)) -> 0 | E44: =IF(OR(ISBLANK(B44),B44=""),0,VLOOKUP(B44,'Ondal Booms'!B:G,3,FALSE)) -> 0
A45: Accessory 5 | C45: =IF(OR(ISBLANK(B45),B45=""),0,VLOOKUP(B45,'Ondal Booms'!B:G,4,FALSE)) -> 0 | D45: =IF(OR(ISBLANK(B45),B45=""),0,VLOOKUP(B45,'Ondal Booms'!B:G,2,FALSE)) -> 0 | E45: =IF(OR(ISBLANK(B45),B45=""),0,VLOOKUP(B45,'Ondal Booms'!B:G,3,FALSE)) -> 0
A46: Accessory 6 | C46: =IF(OR(ISBLANK(B46),B46=""),0,VLOOKUP(B46,'Ondal Booms'!B:G,4,FALSE)) -> 0 | D46: =IF(OR(ISBLANK(B46),B46=""),0,VLOOKUP(B46,'Ondal Booms'!B:G,2,FALSE)) -> 0 | E46: =IF(OR(ISBLANK(B46),B46=""),0,VLOOKUP(B46,'Ondal Booms'!B:G,3,FALSE)) -> 0
A47: Accessory 7 | C47: =IF(OR(ISBLANK(B47),B47=""),0,VLOOKUP(B47,'Ondal Booms'!B:G,4,FALSE)) -> 0 | D47: =IF(OR(ISBLANK(B47),B47=""),0,VLOOKUP(B47,'Ondal Booms'!B:G,2,FALSE)) -> 0 | E47: =IF(OR(ISBLANK(B47),B47=""),0,VLOOKUP(B47,'Ondal Booms'!B:G,3,FALSE)) -> 0
A49: Errors? | B49: =IF(OR(ISBLANK(B30),B30=""),"", IF(OR(AND(B35="200mm Service Head",SUM(Z32:Z39)>0),AND(B35="400mm Service Head",SUM(Z34:Z39)>0),AND(B35="600mm Service Head",SUM(Z36:Z39)>0),AND(B35="800mm Service Head",SUM(Z38:Z39)>0)),"Select Longer Service Head or Remove Services", IF(AND(RIGHT(B33,2)="XL",RIGHT(B32,2)<>"XL"),"BOTTOM XL ARM REQUIRES TOP XL ARM", IF(OR(ISBLANK(#REF!),ISBLANK(B31),ISBLANK(B32),ISBLANK(B33),ISBLANK(B34),ISBLANK(B35),ISBLANK(B39),ISBLANK(B40),ISBLANK(B38)),"Missing Selections for Configuration", IF(AND(B35="Large Monitor Carrier",B33<>"Spring Articulating"),"Large Monitor Requires Spring Bottom Arm", IF(OR(AND(RIGHT(B31,2)="XL",RIGHT(B32,2)<>"XL"),AND(RIGHT(B32,2)="XL",RIGHT(B31,2)<>"XL")),"Both Top Arm and Ceiling Flange Must Be XL", IF(COUNTIF(AE29:AH37,1)>1,"Mismatch Electrical Configuration", "")))))) )
C50: IMAGINE LIST | D50: ONDAL LIST | E50: ONDAL SALES
A51: Equipment List Price | B51: =IF(OR(B30="",ISBLANK(B30)),"NO CONFIGURATION SELECTED",C51) -> NO CONFIGURATION SELECTED | C51: =SUM(C30:C47) -> 0 | D51: =SUM(D30:D47) -> 0 | E51: =SUM(E30:E47) -> 0 | J51: ="<-- EXPAND TO SHOW OPTIONS / SERVICE HEAD" -> <-- EXPAND TO SHOW OPTIONS / SERVICE HEAD
A53: LIGHT (SINGLE OR TANDEM) | B53: SELECTION | C53: IMAGINE LIST | D53: SIMEON LIST | E53: SIMEON COG
A54: Model | B54: =IF(AND(ISBLANK(B57),ISBLANK(B58),ISBLANK(B59)),"", IF(B55="Upgrade Only","UPGRADE", IF(RIGHT(B57,4)="(3P)","(3P) ","")& IF(ISBLANK(B57),"",VLOOKUP(B57,'Simeon Lights'!C:H,2,FALSE))& IF(ISBLANK(B58),""," / "&VLOOKUP(B58,'Simeon Lights'!C:H,2,FALSE))& IF(ISBLANK(B59),""," / "&VLOOKUP(B59,'Simeon Lights'!C:H,2,FALSE)))) | C54: =IF(ISBLANK(B57),0,(VLOOKUP(B54,'Simeon Lights'!C:J,6,FALSE))) -> 0 | D54: =IF(ISBLANK(B57),0,(VLOOKUP(B54,'Simeon Lights'!C:J,4,FALSE))) -> 0 | E54: =IF(ISBLANK(B57),0,(VLOOKUP(B54,'Simeon Lights'!C:J,5,FALSE))) -> 0
A55: Ceiling Cover | C55: =IF(ISBLANK(B55),0,VLOOKUP(B55,'Simeon Lights'!C:J,6,FALSE)) -> 0 | D55: =IF(ISBLANK(B55),0,VLOOKUP(B55,'Simeon Lights'!C:J,4,FALSE)) -> 0 | E55: =IF(ISBLANK(B55),0,VLOOKUP(B55,'Simeon Lights'!C:J,5,FALSE)) -> 0
A56: Ceiling Drop Tube | C56: =IF(ISBLANK(B56),0,VLOOKUP(B56,'Simeon Lights'!C:J,6,FALSE)) -> 0 | D56: =IF(ISBLANK(B56),0,VLOOKUP(B56,'Simeon Lights'!C:J,4,FALSE)) -> 0 | E56: =IF(ISBLANK(B56),0,VLOOKUP(B56,'Simeon Lights'!C:J,5,FALSE)) -> 0
A57: Arm 1 (Top Arm) | C57: =IF(ISBLANK(B57),0,VLOOKUP(B57,'Simeon Lights'!C:J,6,FALSE)) -> 0 | D57: =IF(ISBLANK(B57),0,VLOOKUP(B57,'Simeon Lights'!C:J,4,FALSE)) -> 0 | E57: =IF(ISBLANK(B57),0,VLOOKUP(B57,'Simeon Lights'!C:J,5,FALSE)) -> 0
A58: Arm 2 | C58: =IF(ISBLANK(B58),0,VLOOKUP(B58,'Simeon Lights'!C:J,6,FALSE)) -> 0 | D58: =IF(ISBLANK(B58),0,VLOOKUP(B58,'Simeon Lights'!C:J,4,FALSE)) -> 0 | E58: =IF(ISBLANK(B58),0,VLOOKUP(B58,'Simeon Lights'!C:J,5,FALSE)) -> 0
A59: Arm 3 | C59: =IF(ISBLANK(B59),0,VLOOKUP(B59,'Simeon Lights'!C:J,6,FALSE)) -> 0 | D59: =IF(ISBLANK(B59),0,VLOOKUP(B59,'Simeon Lights'!C:J,4,FALSE)) -> 0 | E59: =IF(ISBLANK(B59),0,VLOOKUP(B59,'Simeon Lights'!C:J,5,FALSE)) -> 0
A60: Wall Control | C60: =IF(ISBLANK(B60),0,VLOOKUP(B60,'Simeon Lights'!C:J,6,FALSE)) -> 0 | D60: =IF(ISBLANK(B60),0,VLOOKUP(B60,'Simeon Lights'!C:J,4,FALSE)) -> 0 | E60: =IF(ISBLANK(B60),0,VLOOKUP(B60,'Simeon Lights'!C:J,5,FALSE)) -> 0
A61: Integration Control | C61: =IF(ISBLANK(B61),0,VLOOKUP(B61,'Simeon Lights'!C:J,6,FALSE)) -> 0 | D61: =IF(ISBLANK(B61),0,VLOOKUP(B61,'Simeon Lights'!C:J,4,FALSE)) -> 0 | E61: =IF(ISBLANK(B61),0,VLOOKUP(B61,'Simeon Lights'!C:J,5,FALSE)) -> 0
A62: In-Light Camera | C62: =IF(ISBLANK(B62),0,VLOOKUP(B62,'Simeon Lights'!C:J,6,FALSE)) -> 0 | D62: =IF(ISBLANK(B62),0,VLOOKUP(B62,'Simeon Lights'!C:J,4,FALSE)) -> 0 | E62: =IF(ISBLANK(B62),0,VLOOKUP(B62,'Simeon Lights'!C:J,5,FALSE)) -> 0
A63: Disposable Adpaters | C63: =IF(ISBLANK(B63),0,VLOOKUP(B63,'Simeon Lights'!C:J,6,FALSE)) -> 0 | D63: =IF(ISBLANK(B63),0,VLOOKUP(B63,'Simeon Lights'!C:J,4,FALSE)) -> 0 | E63: =IF(ISBLANK(B63),0,VLOOKUP(B63,'Simeon Lights'!C:J,5,FALSE)) -> 0
A65: Errors? | B65: =IF(AND(ISBLANK(B57),ISBLANK(B58),ISBLANK(B59)),"", IF(AND(ISBLANK(B57),B58<>""),"ARM 1 MISSING", IF(AND(ISBLANK(B57),B59<>""),"ARM 1 MISSING", IF(ISBLANK(B58)&ISBLANK(B59)="TRUEFALSE","ARM 2 MISSING", IF(AND(B57<>"",B58="32in Flat Panel",B59<>""),"FP CANNOT BE MIDDLE ARM", IF(OR(ISBLANK(B55),ISBLANK(B56),ISBLANK(B60),ISBLANK(B61),ISBLANK(B62),ISBLANK(B63)),"Missing Selections",""))))))
C66: IMAGINE LIST | D66: SIMEON LIST | E66: SIMEON COG
A67: Equipment List Price | B67: =IF(OR(ISBLANK(B57),ISBLANK(B58)&ISBLANK(B59)="TRUEFALSE"),"NO CONFIGURATION SELECTED",IF(B65<>"","ERROR IN CONFIGURATION",IF(B57="",0,SUM(C54:C63)))) -> NO CONFIGURATION SELECTED | C67: =SUM(C54:C65) -> 0 | D67: =SUM(D54:D65) -> 0 | E67: =SUM(E54:E65) -> 0 | J67: ="<-- EXPAND TO SHOW OPTIONS" -> <-- EXPAND TO SHOW OPTIONS
B69: CONFIGRATION LIST PRICE | E69: TOTAL COG
A70: Total List Price | B70: =IF(OR(B27="Error in Configuration",B27="No Configuration Selected"),0,B27)+IF(OR(B51="Error in Configuration",B51="No Configuration Selected"),0,B51)+IF(OR(B67="Error in Configuration",B67="No Configuration Selected"),0,B67) -> 51648.442 | E70: =SUM(E67,E51,E27) -> 15494.532

Sheet Config #4
A1: CONFIGURATION #4 | B1: DESCRIPTION
A2: Configuration Name | B2: Anesthesia Boom (Patient Right Shoulder)
A4: BOOM (SINGLE OR TANDEM) | B4: SELECTION | C4: IMAGINE LIST | D4: ONDAL LIST | E4: ONDAL COG | G4: HV Services | H4: Count | J4: Layer | K4: Selection | L4: FRONT | Q4: Selection | S4: Selection | T4: BACK | Y4: Selection | AE4: =COUNTIF(K5,"(2) Duplexes")+COUNTIF(Y5,"(2) Duplexes") -> 0 | AF4: =COUNTIF(Q5:S5,"(2) Duplexes") -> 2 | AG4: =COUNTIF(K5,"(3) Duplexes")+COUNTIF(Y5,"(3) Duplexes") -> 0 | AH4: =COUNTIF(Q5:S5,"(3) Duplexes") -> 0
A5: Model | B5: =IF(OR(ISBLANK(B8),ISBLANK(B9)),"",IF(ISBLANK(B9),0,(VLOOKUP(B9,'Ondal Booms'!B:F,5,FALSE)))&IF(ISBLANK(B8),0,(VLOOKUP(B8,'Ondal Booms'!B:F,5,FALSE)))) -> Spring | C5: =IF(OR(ISBLANK(B5),B5=""),0,VLOOKUP(B5,'Ondal Booms'!B:G,4,FALSE)) -> 27458.4 | D5: =IF(OR(ISBLANK(B5),B5=""),0,VLOOKUP(B5,'Ondal Booms'!B:G,2,FALSE)) -> 10983.36 | E5: =IF(OR(ISBLANK(B5),B5=""),0,VLOOKUP(B5,'Ondal Booms'!B:G,3,FALSE)) -> 8237.52 | G5: Duplex Count | H5: =COUNTIF(K5:Y14,"(2) Duplexes")*2+COUNTIF(K5:Y14,"(3) Duplexes")*3 -> 8 | J5: 1 Left | K5: Oxygen | Q5: (2) Duplexes | S5: (2) Duplexes | Y5: Storz 4in1 | Z5: =15-COUNTIFS(K5:Y5,"") -> 4
A6: Ceiling Cover | B6: Single Mount (Square) | C6: =IF(OR(ISBLANK(B6),B6=""),0,VLOOKUP(B6,'Ondal Booms'!B:G,4,FALSE)) -> 3484.725 | D6: =IF(OR(ISBLANK(B6),B6=""),0,VLOOKUP(B6,'Ondal Booms'!B:G,2,FALSE)) -> 1393.89 | E6: =IF(OR(ISBLANK(B6),B6=""),0,VLOOKUP(B6,'Ondal Booms'!B:G,3,FALSE)) -> 1045.4175 | J6: 1 Right | K6: Medical Air | Y6: Data | Z6: =15-COUNTIFS(K6:Y6,"") -> 2 | AE6: =COUNTIF(K7,"(2) Duplexes")+COUNTIF(Y7,"(2) Duplexes") -> 0 | AF6: =COUNTIF(Q7:S7,"(2) Duplexes") -> 2 | AG6: =COUNTIF(K7,"(3) Duplexes")+COUNTIF(Y7,"(3) Duplexes") -> 0 | AH6: =COUNTIF(Q7:S7,"(3) Duplexes") -> 0
A7: Ceiling Flange | B7: 100mm | C7: =IF(OR(ISBLANK(B7),B7=""),0,VLOOKUP(B7,'Ondal Booms'!B:G,4,FALSE)) -> 0 | D7: =IF(OR(ISBLANK(B7),B7=""),0,VLOOKUP(B7,'Ondal Booms'!B:G,2,FALSE)) -> 0 | E7: =IF(OR(ISBLANK(B7),B7=""),0,VLOOKUP(B7,'Ondal Booms'!B:G,3,FALSE)) -> 0 | G7: LV Services | H7: Count | J7: 2 Left | K7: Nitrous Oxide | Q7: (2) Duplexes | S7: (2) Duplexes | Y7: Vacuum | Z7: =15-COUNTIFS(K7:Y7,"") -> 4
A8: Top Arm | B8: 800mm | C8: =IF(OR(ISBLANK(B8),B8=""),0,VLOOKUP(B8,'Ondal Booms'!B:G,4,FALSE)) -> 0 | D8: =IF(OR(ISBLANK(B8),B8=""),0,VLOOKUP(B8,'Ondal Booms'!B:G,2,FALSE)) -> 0 | E8: =IF(OR(ISBLANK(B8),B8=""),0,VLOOKUP(B8,'Ondal Booms'!B:G,3,FALSE)) -> 0 | G8: Data Count | H8: =(COUNTIF(K5:Y14,"Data")) -> 1 | J8: 2 Right | K8: WAGD | Y8: Vacuum | Z8: =15-COUNTIFS(K8:Y8,"") -> 2 | AE8: =COUNTIF(K9,"(2) Duplexes")+COUNTIF(Y9,"(2) Duplexes") -> 0 | AF8: =COUNTIF(Q9:S9,"(2) Duplexes") -> 0 | AG8: =COUNTIF(K9,"(3) Duplexes")+COUNTIF(Y9,"(3) Duplexes") -> 0 | AH8: =COUNTIF(Q9:S9,"(3) Duplexes") -> 0
A9: Bottom Arm | B9: Spring Articulating | C9: =IF(OR(ISBLANK(B9),B9=""),0,VLOOKUP(B9,'Ondal Booms'!B:G,4,FALSE)) -> 0 | D9: =IF(OR(ISBLANK(B9),B9=""),0,VLOOKUP(B9,'Ondal Booms'!B:G,2,FALSE)) -> 0 | E9: =IF(OR(ISBLANK(B9),B9=""),0,VLOOKUP(B9,'Ondal Booms'!B:G,3,FALSE)) -> 0 | G9: Storz 4in1 Count | H9: =(COUNTIF(K5:Y14,"Storz 4in1")) -> 1 | J9: 3 Left | Z9: =15-COUNTIFS(K9:Y9,"") -> 0
A10: Column Tube | B10: 120mm Column Tube | C10: =IF(OR(ISBLANK(B10),B10=""),0,VLOOKUP(B10,'Ondal Booms'!B:G,4,FALSE)) -> 0 | D10: =IF(OR(ISBLANK(B10),B10=""),0,VLOOKUP(B10,'Ondal Booms'!B:G,2,FALSE)) -> 0 | E10: =IF(OR(ISBLANK(B10),B10=""),0,VLOOKUP(B10,'Ondal Booms'!B:G,3,FALSE)) -> 0 | J10: 3 Right | Z10: =15-COUNTIFS(K10:Y10,"") -> 0 | AE10: =COUNTIF(K11,"(2) Duplexes")+COUNTIF(Y11,"(2) Duplexes") -> 0 | AF10: =COUNTIF(Q11:S11,"(2) Duplexes") -> 0 | AG10: =COUNTIF(K11,"(3) Duplexes")+COUNTIF(Y11,"(3) Duplexes") -> 0 | AH10: =COUNTIF(Q11:S11,"(3) Duplexes") -> 0
A11: Service Head | B11: 400mm Service Head | C11: =IF(OR(ISBLANK(B11),B11=""),0,VLOOKUP(B11,'Ondal Booms'!B:G,4,FALSE)) -> 0 | D11: =IF(OR(ISBLANK(B11),B11=""),0,VLOOKUP(B11,'Ondal Booms'!B:G,2,FALSE)) -> 0 | E11: =IF(OR(ISBLANK(B11),B11=""),0,VLOOKUP(B11,'Ondal Booms'!B:G,3,FALSE)) -> 0 | G11: Medical Gases | H11: Count | J11: 4 Left | Z11: =15-COUNTIFS(K11:Y11,"") -> 0
A12: Electrical | B12: =IF(OR(H5=0,ISBLANK(H5)),"",H5&" Duplexes") -> 8 Duplexes | C12: =IF(OR(ISBLANK(B12),B12=""),0,VLOOKUP(B12,'Ondal Booms'!B:G,4,FALSE)) -> 1877.6 | D12: =IF(OR(ISBLANK(B12),B12=""),0,VLOOKUP(B12,'Ondal Booms'!B:G,2,FALSE)) -> 751.04 | E12: =IF(OR(ISBLANK(B12),B12=""),0,VLOOKUP(B12,'Ondal Booms'!B:G,3,FALSE)) -> 563.28 | G12: Oxygen Count | H12: =(COUNTIF(K5:Y14,"Oxygen")) -> 1 | J12: 4 Right | Z12: =15-COUNTIFS(K12:Y12,"") -> 0 | AE12: =COUNTIF(K13,"(2) Duplexes")+COUNTIF(Y13,"(2) Duplexes") -> 0 | AF12: =COUNTIF(Q13:S13,"(2) Duplexes") -> 0 | AG12: =COUNTIF(K13,"(3) Duplexes")+COUNTIF(Y13,"(3) Duplexes") -> 0 | AH12: =COUNTIF(Q13:S13,"(3) Duplexes") -> 0
A13: Medical Gas | B13: =IF(OR(SUM(H12:H18)=0,ISBLANK(SUM(H12:H18))),"",SUM(H12:H18)&" Outlets") -> 6 Outlets | C13: =IF(OR(ISBLANK(B13),B13=""),0,VLOOKUP(B13,'Ondal Booms'!B:G,4,FALSE)) -> 4888.05 | D13: =IF(OR(ISBLANK(B13),B13=""),0,VLOOKUP(B13,'Ondal Booms'!B:G,2,FALSE)) -> 1955.22 | E13: =IF(OR(ISBLANK(B13),B13=""),0,VLOOKUP(B13,'Ondal Booms'!B:G,3,FALSE)) -> 1466.415 | G13: Med Air Count | H13: =COUNTIF(K5:Y14,"Medical Air") -> 1 | J13: 5 Left | Z13: =15-COUNTIFS(K13:Y13,"") -> 0
A14: # of Outlet Circuits | B14: (4) Circuits | C14: =IF(OR(ISBLANK(B14),B14=""),0,VLOOKUP(B14,'Ondal Booms'!B:G,4,FALSE)) -> 0 | D14: =IF(OR(ISBLANK(B14),B14=""),0,VLOOKUP(B14,'Ondal Booms'!B:G,2,FALSE)) -> 0 | E14: =IF(OR(ISBLANK(B14),B14=""),0,VLOOKUP(B14,'Ondal Booms'!B:G,3,FALSE)) -> 0 | G14: Nitrous Count | H14: =COUNTIF(K5:Y14,"Nitrous Oxide") -> 1 | J14: 5 Right | Z14: =15-COUNTIFS(K14:Y14,"") -> 0
A15: Shelf (500mm) | B15: (0) 500mm Shelves | C15: =IF(OR(ISBLANK(B15),B15=""),0,VLOOKUP(B15,'Ondal Booms'!B:G,4,FALSE)) -> 0 | D15: =IF(OR(ISBLANK(B15),B15=""),0,VLOOKUP(B15,'Ondal Booms'!B:G,2,FALSE)) -> 0 | E15: =IF(OR(ISBLANK(B15),B15=""),0,VLOOKUP(B15,'Ondal Booms'!B:G,3,FALSE)) -> 0 | G15: WAGD Count | H15: =COUNTIF(K5:Y14,"WAGD") -> 1
A16: Shelf (750mm) | B16: (0) 750mm Shelves | C16: =IF(OR(ISBLANK(B16),B16=""),0,VLOOKUP(B16,'Ondal Booms'!B:G,4,FALSE)) -> 0 | D16: =IF(OR(ISBLANK(B16),B16=""),0,VLOOKUP(B16,'Ondal Booms'!B:G,2,FALSE)) -> 0 | E16: =IF(OR(ISBLANK(B16),B16=""),0,VLOOKUP(B16,'Ondal Booms'!B:G,3,FALSE)) -> 0 | G16: Vacuum Count | H16: =COUNTIF(K5:Y14,"Vacuum") -> 2
A17: Accessory 1 | C17: =IF(OR(ISBLANK(B17),B17=""),0,VLOOKUP(B17,'Ondal Booms'!B:G,4,FALSE)) -> 0 | D17: =IF(OR(ISBLANK(B17),B17=""),0,VLOOKUP(B17,'Ondal Booms'!B:G,2,FALSE)) -> 0 | E17: =IF(OR(ISBLANK(B17),B17=""),0,VLOOKUP(B17,'Ondal Booms'!B:G,3,FALSE)) -> 0 | G17: Nitrogen Count | H17: =COUNTIF(K5:Y14,"Nitrogen") -> 0
A18: Accessory 2 | C18: =IF(OR(ISBLANK(B18),B18=""),0,VLOOKUP(B18,'Ondal Booms'!B:G,4,FALSE)) -> 0 | D18: =IF(OR(ISBLANK(B18),B18=""),0,VLOOKUP(B18,'Ondal Booms'!B:G,2,FALSE)) -> 0 | E18: =IF(OR(ISBLANK(B18),B18=""),0,VLOOKUP(B18,'Ondal Booms'!B:G,3,FALSE)) -> 0 | G18: CO2 Count | H18: =COUNTIF(K5:Y14,"Carbon Dioxide") -> 0
A19: Accessory 3 | C19: =IF(OR(ISBLANK(B19),B19=""),0,VLOOKUP(B19,'Ondal Booms'!B:G,4,FALSE)) -> 0 | D19: =IF(OR(ISBLANK(B19),B19=""),0,VLOOKUP(B19,'Ondal Booms'!B:G,2,FALSE)) -> 0 | E19: =IF(OR(ISBLANK(B19),B19=""),0,VLOOKUP(B19,'Ondal Booms'!B:G,3,FALSE)) -> 0
A20: Accessory 4 | C20: =IF(OR(ISBLANK(B20),B20=""),0,VLOOKUP(B20,'Ondal Booms'!B:G,4,FALSE)) -> 0 | D20: =IF(OR(ISBLANK(B20),B20=""),0,VLOOKUP(B20,'Ondal Booms'!B:G,2,FALSE)) -> 0 | E20: =IF(OR(ISBLANK(B20),B20=""),0,VLOOKUP(B20,'Ondal Booms'!B:G,3,FALSE)) -> 0
A21: Accessory 5 | C21: =IF(OR(ISBLANK(B21),B21=""),0,VLOOKUP(B21,'Ondal Booms'!B:G,4,FALSE)) -> 0 | D21: =IF(OR(ISBLANK(B21),B21=""),0,VLOOKUP(B21,'Ondal Booms'!B:G,2,FALSE)) -> 0 | E21: =IF(OR(ISBLANK(B21),B21=""),0,VLOOKUP(B21,'Ondal Booms'!B:G,3,FALSE)) -> 0
A22: Accessory 6 | C22: =IF(OR(ISBLANK(B22),B22=""),0,VLOOKUP(B22,'Ondal Booms'!B:G,4,FALSE)) -> 0 | D22: =IF(OR(ISBLANK(B22),B22=""),0,VLOOKUP(B22,'Ondal Booms'!B:G,2,FALSE)) -> 0 | E22: =IF(OR(ISBLANK(B22),B22=""),0,VLOOKUP(B22,'Ondal Booms'!B:G,3,FALSE)) -> 0
A23: Accessory 7 | C23: =IF(OR(ISBLANK(B23),B23=""),0,VLOOKUP(B23,'Ondal Booms'!B:G,4,FALSE)) -> 0 | D23: =IF(OR(ISBLANK(B23),B23=""),0,VLOOKUP(B23,'Ondal Booms'!B:G,2,FALSE)) -> 0 | E23: =IF(OR(ISBLANK(B23),B23=""),0,VLOOKUP(B23,'Ondal Booms'!B:G,3,FALSE)) -> 0
A25: Errors? | B25: =IF(OR(ISBLANK(B5),B5=""),"", IF(OR(AND(B11="200mm Service Head",SUM(Z7:Z14)>0),AND(B11="400mm Service Head",SUM(Z9:Z14)>0),AND(B11="600mm Service Head",SUM(Z11:Z14)>0),AND(B11="800mm Service Head",SUM(Z13:Z14)>0)),"Select Longer Service Head or Remove Services", IF(AND(RIGHT(B9,2)="XL",RIGHT(B8,2)<>"XL"),"BOTTOM XL ARM REQUIRES TOP XL ARM", IF(OR(ISBLANK(B6),ISBLANK(B7),ISBLANK(B8),ISBLANK(B9),ISBLANK(B10),ISBLANK(B11),ISBLANK(B15),ISBLANK(B16),ISBLANK(B14)),"Missing Selections for Configuration", IF(AND(B11="Large Monitor Carrier",B9<>"Spring Articulating"),"Large Monitor Requires Spring Bottom Arm", IF(OR(AND(RIGHT(B7,2)="XL",RIGHT(B8,2)<>"XL"),AND(RIGHT(B8,2)="XL",RIGHT(B7,2)<>"XL")),"Both Top Arm and Ceiling Flange Must Be XL", IF(COUNTIF(AE4:AH12,1)>1,"Mismatch Electrical Configuration", "")))))) )
C26: IMAGINE LIST | D26: ONDAL LIST | E26: ONDAL COG
A27: Equipment List Price | B27: =IF(OR(B6="",ISBLANK(B6)),"NO CONFIGURATION SELECTED",C27) -> 37708.775 | C27: =SUM(C5:C23) -> 37708.775 | D27: =SUM(D5:D23) -> 15083.51 | E27: =SUM(E5:E23) -> 11312.632 | J27: ="<-- EXPAND TO SHOW OPTIONS / SERVICE HEAD" -> <-- EXPAND TO SHOW OPTIONS / SERVICE HEAD
AE28: =COUNTIF(K30,"(2) Duplexes")+COUNTIF(Y30,"(2) Duplexes") -> 0 | AF28: =COUNTIF(Q30:S30,"(2) Duplexes") -> 0 | AG28: =COUNTIF(K30,"(3) Duplexes")+COUNTIF(Y30,"(3) Duplexes") -> 0 | AH28: =COUNTIF(Q30:S30,"(3) Duplexes") -> 0
A29: BOOM (TANDEM 2ND ONLY) | B29: SELECTION | C29: IMAGINE LIST | D29: ONDAL LIST | E29: ONDAL COG | G29: HV Services | H29: Count | J29: Layer | K29: Selection | L29: FRONT | Q29: Selection | S29: Selection | T29: BACK | Y29: Selection
A30: Model | B30: =IF(OR(ISBLANK(B32),ISBLANK(B33)),"",IF(ISBLANK(B33),0,(VLOOKUP(B33,'Ondal Booms'!B:F,5,FALSE)))&IF(ISBLANK(B32),0,(VLOOKUP(B32,'Ondal Booms'!B:F,5,FALSE)))) | C30: =IF(OR(ISBLANK(B30),B30=""),0,VLOOKUP(B30,'Ondal Booms'!B:G,4,FALSE)) -> 0 | D30: =IF(OR(ISBLANK(B30),B30=""),0,VLOOKUP(B30,'Ondal Booms'!B:G,2,FALSE)) -> 0 | E30: =IF(OR(ISBLANK(B30),B30=""),0,VLOOKUP(B30,'Ondal Booms'!B:G,3,FALSE)) -> 0 | G30: Duplex Count | H30: =COUNTIF(K30:Y39,"(2) Duplexes")*2+COUNTIF(K30:Y39,"(3) Duplexes")*3 -> 0 | J30: 1 Left | Z30: =15-COUNTIFS(K30:Y30,"") -> 0
A31: Ceiling Flange | C31: =IF(OR(ISBLANK(B31),B31=""),0,VLOOKUP(B31,'Ondal Booms'!B:G,4,FALSE)) -> 0 | D31: =IF(OR(ISBLANK(B31),B31=""),0,VLOOKUP(B31,'Ondal Booms'!B:G,2,FALSE)) -> 0 | E31: =IF(OR(ISBLANK(B31),B31=""),0,VLOOKUP(B31,'Ondal Booms'!B:G,3,FALSE)) -> 0 | G31: LV Services | H31: Count | J31: 1 Right | Z31: =15-COUNTIFS(K31:Y31,"") -> 0 | AE31: =COUNTIF(K32,"(2) Duplexes")+COUNTIF(Y32,"(2) Duplexes") -> 0 | AF31: =COUNTIF(Q32:S32,"(2) Duplexes") -> 0 | AG31: =COUNTIF(K32,"(3) Duplexes")+COUNTIF(Y32,"(3) Duplexes") -> 0 | AH31: =COUNTIF(Q32:S32,"(3) Duplexes") -> 0
A32: Top Arm | C32: =IF(OR(ISBLANK(B32),B32=""),0,VLOOKUP(B32,'Ondal Booms'!B:G,4,FALSE)) -> 0 | D32: =IF(OR(ISBLANK(B32),B32=""),0,VLOOKUP(B32,'Ondal Booms'!B:G,2,FALSE)) -> 0 | E32: =IF(OR(ISBLANK(B32),B32=""),0,VLOOKUP(B32,'Ondal Booms'!B:G,3,FALSE)) -> 0 | G32: Data Count | H32: =(COUNTIF(K30:Y39,"Data")) -> 0 | J32: 2 Left | Z32: =15-COUNTIFS(K32:Y32,"") -> 0
A33: Bottom Arm | C33: =IF(OR(ISBLANK(B33),B33=""),0,VLOOKUP(B33,'Ondal Booms'!B:G,4,FALSE)) -> 0 | D33: =IF(OR(ISBLANK(B33),B33=""),0,VLOOKUP(B33,'Ondal Booms'!B:G,2,FALSE)) -> 0 | E33: =IF(OR(ISBLANK(B33),B33=""),0,VLOOKUP(B33,'Ondal Booms'!B:G,3,FALSE)) -> 0 | G33: Storz 4in1 Count | H33: =(COUNTIF(K30:Y39,"Storz 4in1")) -> 0 | J33: 2 Right | Z33: =15-COUNTIFS(K33:Y33,"") -> 0 | AE33: =COUNTIF(K34,"(2) Duplexes")+COUNTIF(Y34,"(2) Duplexes") -> 0 | AF33: =COUNTIF(Q34:S34,"(2) Duplexes") -> 0 | AG33: =COUNTIF(K34,"(3) Duplexes")+COUNTIF(Y34,"(3) Duplexes") -> 0 | AH33: =COUNTIF(Q34:S34,"(3) Duplexes") -> 0
A34: Column Tube | C34: =IF(OR(ISBLANK(B34),B34=""),0,VLOOKUP(B34,'Ondal Booms'!B:G,4,FALSE)) -> 0 | D34: =IF(OR(ISBLANK(B34),B34=""),0,VLOOKUP(B34,'Ondal Booms'!B:G,2,FALSE)) -> 0 | E34: =IF(OR(ISBLANK(B34),B34=""),0,VLOOKUP(B34,'Ondal Booms'!B:G,3,FALSE)) -> 0 | J34: 3 Left | Z34: =15-COUNTIFS(K34:Y34,"") -> 0
A35: Service Head | C35: =IF(OR(ISBLANK(B35),B35=""),0,VLOOKUP(B35,'Ondal Booms'!B:G,4,FALSE)) -> 0 | D35: =IF(OR(ISBLANK(B35),B35=""),0,VLOOKUP(B35,'Ondal Booms'!B:G,2,FALSE)) -> 0 | E35: =IF(OR(ISBLANK(B35),B35=""),0,VLOOKUP(B35,'Ondal Booms'!B:G,3,FALSE)) -> 0 | G35: Medical Gases | H35: Count | J35: 3 Right | Z35: =15-COUNTIFS(K35:Y35,"") -> 0 | AE35: =COUNTIF(K36,"(2) Duplexes")+COUNTIF(Y36,"(2) Duplexes") -> 0 | AF35: =COUNTIF(Q36:S36,"(2) Duplexes") -> 0 | AG35: =COUNTIF(K36,"(3) Duplexes")+COUNTIF(Y36,"(3) Duplexes") -> 0 | AH35: =COUNTIF(Q36:S36,"(3) Duplexes") -> 0
A36: Electrical | B36: =IF(OR(H30=0,ISBLANK(H30)),"",H30&" Duplexes") | C36: =IF(OR(ISBLANK(B36),B36=""),0,VLOOKUP(B36,'Ondal Booms'!B:G,4,FALSE)) -> 0 | D36: =IF(OR(ISBLANK(B36),B36=""),0,VLOOKUP(B36,'Ondal Booms'!B:G,2,FALSE)) -> 0 | E36: =IF(OR(ISBLANK(B36),B36=""),0,VLOOKUP(B36,'Ondal Booms'!B:G,3,FALSE)) -> 0 | G36: Oxygen Count | H36: =(COUNTIF(K30:Y39,"Oxygen")) -> 0 | J36: 4 Left | Z36: =15-COUNTIFS(K36:Y36,"") -> 0
A37: Medical Gas | B37: =IF(OR(SUM(H36:H42)=0,ISBLANK(SUM(H36:H42))),"",SUM(H36:H42)&" Outlets") | C37: =IF(OR(ISBLANK(B37),B37=""),0,VLOOKUP(B37,'Ondal Booms'!B:G,4,FALSE)) -> 0 | D37: =IF(OR(ISBLANK(B37),B37=""),0,VLOOKUP(B37,'Ondal Booms'!B:G,2,FALSE)) -> 0 | E37: =IF(OR(ISBLANK(B37),B37=""),0,VLOOKUP(B37,'Ondal Booms'!B:G,3,FALSE)) -> 0 | G37: Med Air Count | H37: =COUNTIF(K30:Y39,"Medical Air") -> 0 | J37: 4 Right | Z37: =15-COUNTIFS(K37:Y37,"") -> 0 | AE37: =COUNTIF(K38,"(2) Duplexes")+COUNTIF(Y38,"(2) Duplexes") -> 0 | AF37: =COUNTIF(Q38:S38,"(2) Duplexes") -> 0 | AG37: =COUNTIF(K38,"(3) Duplexes")+COUNTIF(Y38,"(3) Duplexes") -> 0 | AH37: =COUNTIF(Q38:S38,"(3) Duplexes") -> 0
A38: # of Outlet Circuits | C38: =IF(OR(ISBLANK(B38),B38=""),0,VLOOKUP(B38,'Ondal Booms'!B:G,4,FALSE)) -> 0 | D38: =IF(OR(ISBLANK(B38),B38=""),0,VLOOKUP(B38,'Ondal Booms'!B:G,2,FALSE)) -> 0 | E38: =IF(OR(ISBLANK(B38),B38=""),0,VLOOKUP(B38,'Ondal Booms'!B:G,3,FALSE)) -> 0 | G38: Nitrous Count | H38: =COUNTIF(K30:Y39,"Nitrous Oxide") -> 0 | J38: 5 Left | Z38: =15-COUNTIFS(K38:Y38,"") -> 0
A39: Shelf (500mm) | C39: =IF(OR(ISBLANK(B39),B39=""),0,VLOOKUP(B39,'Ondal Booms'!B:G,4,FALSE)) -> 0 | D39: =IF(OR(ISBLANK(B39),B39=""),0,VLOOKUP(B39,'Ondal Booms'!B:G,2,FALSE)) -> 0 | E39: =IF(OR(ISBLANK(B39),B39=""),0,VLOOKUP(B39,'Ondal Booms'!B:G,3,FALSE)) -> 0 | G39: WAGD Count | H39: =COUNTIF(K30:Y39,"WAGD") -> 0 | J39: 5 Right | Z39: =15-COUNTIFS(K39:Y39,"") -> 0
A40: Shelf (750mm) | C40: =IF(OR(ISBLANK(B40),B40=""),0,VLOOKUP(B40,'Ondal Booms'!B:G,4,FALSE)) -> 0 | D40: =IF(OR(ISBLANK(B40),B40=""),0,VLOOKUP(B40,'Ondal Booms'!B:G,2,FALSE)) -> 0 | E40: =IF(OR(ISBLANK(B40),B40=""),0,VLOOKUP(B40,'Ondal Booms'!B:G,3,FALSE)) -> 0 | G40: Vacuum Count | H40: =COUNTIF(K30:Y39,"Vacuum") -> 0
A41: Accessory 1 | C41: =IF(OR(ISBLANK(B41),B41=""),0,VLOOKUP(B41,'Ondal Booms'!B:G,4,FALSE)) -> 0 | D41: =IF(OR(ISBLANK(B41),B41=""),0,VLOOKUP(B41,'Ondal Booms'!B:G,2,FALSE)) -> 0 | E41: =IF(OR(ISBLANK(B41),B41=""),0,VLOOKUP(B41,'Ondal Booms'!B:G,3,FALSE)) -> 0 | G41: Nitrogen Count | H41: =COUNTIF(K30:Y39,"Nitrogen") -> 0
A42: Accessory 2 | C42: =IF(OR(ISBLANK(B42),B42=""),0,VLOOKUP(B42,'Ondal Booms'!B:G,4,FALSE)) -> 0 | D42: =IF(OR(ISBLANK(B42),B42=""),0,VLOOKUP(B42,'Ondal Booms'!B:G,2,FALSE)) -> 0 | E42: =IF(OR(ISBLANK(B42),B42=""),0,VLOOKUP(B42,'Ondal Booms'!B:G,3,FALSE)) -> 0 | G42: CO2 Count | H42: =COUNTIF(K30:Y39,"Carbon Dioxide") -> 0
A43: Accessory 3 | C43: =IF(OR(ISBLANK(B43),B43=""),0,VLOOKUP(B43,'Ondal Booms'!B:G,4,FALSE)) -> 0 | D43: =IF(OR(ISBLANK(B43),B43=""),0,VLOOKUP(B43,'Ondal Booms'!B:G,2,FALSE)) -> 0 | E43: =IF(OR(ISBLANK(B43),B43=""),0,VLOOKUP(B43,'Ondal Booms'!B:G,3,FALSE)) -> 0
A44: Accessory 4 | C44: =IF(OR(ISBLANK(B44),B44=""),0,VLOOKUP(B44,'Ondal Booms'!B:G,4,FALSE)) -> 0 | D44: =IF(OR(ISBLANK(B44),B44=""),0,VLOOKUP(B44,'Ondal Booms'!B:G,2,FALSE)) -> 0 | E44: =IF(OR(ISBLANK(B44),B44=""),0,VLOOKUP(B44,'Ondal Booms'!B:G,3,FALSE)) -> 0
A45: Accessory 5 | C45: =IF(OR(ISBLANK(B45),B45=""),0,VLOOKUP(B45,'Ondal Booms'!B:G,4,FALSE)) -> 0 | D45: =IF(OR(ISBLANK(B45),B45=""),0,VLOOKUP(B45,'Ondal Booms'!B:G,2,FALSE)) -> 0 | E45: =IF(OR(ISBLANK(B45),B45=""),0,VLOOKUP(B45,'Ondal Booms'!B:G,3,FALSE)) -> 0
A46: Accessory 6 | C46: =IF(OR(ISBLANK(B46),B46=""),0,VLOOKUP(B46,'Ondal Booms'!B:G,4,FALSE)) -> 0 | D46: =IF(OR(ISBLANK(B46),B46=""),0,VLOOKUP(B46,'Ondal Booms'!B:G,2,FALSE)) -> 0 | E46: =IF(OR(ISBLANK(B46),B46=""),0,VLOOKUP(B46,'Ondal Booms'!B:G,3,FALSE)) -> 0
A47: Accessory 7 | C47: =IF(OR(ISBLANK(B47),B47=""),0,VLOOKUP(B47,'Ondal Booms'!B:G,4,FALSE)) -> 0 | D47: =IF(OR(ISBLANK(B47),B47=""),0,VLOOKUP(B47,'Ondal Booms'!B:G,2,FALSE)) -> 0 | E47: =IF(OR(ISBLANK(B47),B47=""),0,VLOOKUP(B47,'Ondal Booms'!B:G,3,FALSE)) -> 0
A49: Errors? | B49: =IF(OR(ISBLANK(B30),B30=""),"", IF(OR(AND(B35="200mm Service Head",SUM(Z32:Z39)>0),AND(B35="400mm Service Head",SUM(Z34:Z39)>0),AND(B35="600mm Service Head",SUM(Z36:Z39)>0),AND(B35="800mm Service Head",SUM(Z38:Z39)>0)),"Select Longer Service Head or Remove Services", IF(AND(RIGHT(B33,2)="XL",RIGHT(B32,2)<>"XL"),"BOTTOM XL ARM REQUIRES TOP XL ARM", IF(OR(ISBLANK(#REF!),ISBLANK(B31),ISBLANK(B32),ISBLANK(B33),ISBLANK(B34),ISBLANK(B35),ISBLANK(B39),ISBLANK(B40),ISBLANK(B38)),"Missing Selections for Configuration", IF(AND(B35="Large Monitor Carrier",B33<>"Spring Articulating"),"Large Monitor Requires Spring Bottom Arm", IF(OR(AND(RIGHT(B31,2)="XL",RIGHT(B32,2)<>"XL"),AND(RIGHT(B32,2)="XL",RIGHT(B31,2)<>"XL")),"Both Top Arm and Ceiling Flange Must Be XL", IF(COUNTIF(AE29:AH37,1)>1,"Mismatch Electrical Configuration", "")))))) )
C50: IMAGINE LIST | D50: ONDAL LIST | E50: ONDAL SALES
A51: Equipment List Price | B51: =IF(OR(B30="",ISBLANK(B30)),"NO CONFIGURATION SELECTED",C51) -> NO CONFIGURATION SELECTED | C51: =SUM(C30:C47) -> 0 | D51: =SUM(D30:D47) -> 0 | E51: =SUM(E30:E47) -> 0 | J51: ="<-- EXPAND TO SHOW OPTIONS / SERVICE HEAD" -> <-- EXPAND TO SHOW OPTIONS / SERVICE HEAD
A53: LIGHT (SINGLE OR TANDEM) | B53: SELECTION | C53: IMAGINE LIST | D53: SIMEON LIST | E53: SIMEON COG
A54: Model | B54: =IF(AND(ISBLANK(B57),ISBLANK(B58),ISBLANK(B59)),"", IF(B55="Upgrade Only","UPGRADE", IF(RIGHT(B57,4)="(3P)","(3P) ","")& IF(ISBLANK(B57),"",VLOOKUP(B57,'Simeon Lights'!C:H,2,FALSE))& IF(ISBLANK(B58),""," / "&VLOOKUP(B58,'Simeon Lights'!C:H,2,FALSE))& IF(ISBLANK(B59),""," / "&VLOOKUP(B59,'Simeon Lights'!C:H,2,FALSE)))) | C54: =IF(ISBLANK(B57),0,(VLOOKUP(B54,'Simeon Lights'!C:J,6,FALSE))) -> 0 | D54: =IF(ISBLANK(B57),0,(VLOOKUP(B54,'Simeon Lights'!C:J,4,FALSE))) -> 0 | E54: =IF(ISBLANK(B57),0,(VLOOKUP(B54,'Simeon Lights'!C:J,5,FALSE))) -> 0
A55: Ceiling Cover | C55: =IF(ISBLANK(B55),0,VLOOKUP(B55,'Simeon Lights'!C:J,6,FALSE)) -> 0 | D55: =IF(ISBLANK(B55),0,VLOOKUP(B55,'Simeon Lights'!C:J,4,FALSE)) -> 0 | E55: =IF(ISBLANK(B55),0,VLOOKUP(B55,'Simeon Lights'!C:J,5,FALSE)) -> 0
A56: Ceiling Drop Tube | C56: =IF(ISBLANK(B56),0,VLOOKUP(B56,'Simeon Lights'!C:J,6,FALSE)) -> 0 | D56: =IF(ISBLANK(B56),0,VLOOKUP(B56,'Simeon Lights'!C:J,4,FALSE)) -> 0 | E56: =IF(ISBLANK(B56),0,VLOOKUP(B56,'Simeon Lights'!C:J,5,FALSE)) -> 0
A57: Arm 1 (Top Arm) | C57: =IF(ISBLANK(B57),0,VLOOKUP(B57,'Simeon Lights'!C:J,6,FALSE)) -> 0 | D57: =IF(ISBLANK(B57),0,VLOOKUP(B57,'Simeon Lights'!C:J,4,FALSE)) -> 0 | E57: =IF(ISBLANK(B57),0,VLOOKUP(B57,'Simeon Lights'!C:J,5,FALSE)) -> 0
A58: Arm 2 | C58: =IF(ISBLANK(B58),0,VLOOKUP(B58,'Simeon Lights'!C:J,6,FALSE)) -> 0 | D58: =IF(ISBLANK(B58),0,VLOOKUP(B58,'Simeon Lights'!C:J,4,FALSE)) -> 0 | E58: =IF(ISBLANK(B58),0,VLOOKUP(B58,'Simeon Lights'!C:J,5,FALSE)) -> 0
A59: Arm 3 | C59: =IF(ISBLANK(B59),0,VLOOKUP(B59,'Simeon Lights'!C:J,6,FALSE)) -> 0 | D59: =IF(ISBLANK(B59),0,VLOOKUP(B59,'Simeon Lights'!C:J,4,FALSE)) -> 0 | E59: =IF(ISBLANK(B59),0,VLOOKUP(B59,'Simeon Lights'!C:J,5,FALSE)) -> 0
A60: Wall Control | C60: =IF(ISBLANK(B60),0,VLOOKUP(B60,'Simeon Lights'!C:J,6,FALSE)) -> 0 | D60: =IF(ISBLANK(B60),0,VLOOKUP(B60,'Simeon Lights'!C:J,4,FALSE)) -> 0 | E60: =IF(ISBLANK(B60),0,VLOOKUP(B60,'Simeon Lights'!C:J,5,FALSE)) -> 0
A61: Integration Control | C61: =IF(ISBLANK(B61),0,VLOOKUP(B61,'Simeon Lights'!C:J,6,FALSE)) -> 0 | D61: =IF(ISBLANK(B61),0,VLOOKUP(B61,'Simeon Lights'!C:J,4,FALSE)) -> 0 | E61: =IF(ISBLANK(B61),0,VLOOKUP(B61,'Simeon Lights'!C:J,5,FALSE)) -> 0
A62: In-Light Camera | C62: =IF(ISBLANK(B62),0,VLOOKUP(B62,'Simeon Lights'!C:J,6,FALSE)) -> 0 | D62: =IF(ISBLANK(B62),0,VLOOKUP(B62,'Simeon Lights'!C:J,4,FALSE)) -> 0 | E62: =IF(ISBLANK(B62),0,VLOOKUP(B62,'Simeon Lights'!C:J,5,FALSE)) -> 0
A63: Disposable Adpaters | C63: =IF(ISBLANK(B63),0,VLOOKUP(B63,'Simeon Lights'!C:J,6,FALSE)) -> 0 | D63: =IF(ISBLANK(B63),0,VLOOKUP(B63,'Simeon Lights'!C:J,4,FALSE)) -> 0 | E63: =IF(ISBLANK(B63),0,VLOOKUP(B63,'Simeon Lights'!C:J,5,FALSE)) -> 0
A65: Errors? | B65: =IF(AND(ISBLANK(B57),ISBLANK(B58),ISBLANK(B59)),"", IF(AND(ISBLANK(B57),B58<>""),"ARM 1 MISSING", IF(AND(ISBLANK(B57),B59<>""),"ARM 1 MISSING", IF(ISBLANK(B58)&ISBLANK(B59)="TRUEFALSE","ARM 2 MISSING", IF(AND(B57<>"",B58="32in Flat Panel",B59<>""),"FP CANNOT BE MIDDLE ARM", IF(OR(ISBLANK(B55),ISBLANK(B56),ISBLANK(B60),ISBLANK(B61),ISBLANK(B62),ISBLANK(B63)),"Missing Selections",""))))))
C66: IMAGINE LIST | D66: SIMEON LIST | E66: SIMEON COG
A67: Equipment List Price | B67: =IF(OR(ISBLANK(B57),ISBLANK(B58)&ISBLANK(B59)="TRUEFALSE"),"NO CONFIGURATION SELECTED",IF(B65<>"","ERROR IN CONFIGURATION",IF(B57="",0,SUM(C54:C63)))) -> NO CONFIGURATION SELECTED | C67: =SUM(C54:C65) -> 0 | D67: =SUM(D54:D65) -> 0 | E67: =SUM(E54:E65) -> 0 | J67: ="<-- EXPAND TO SHOW OPTIONS" -> <-- EXPAND TO SHOW OPTIONS
B69: CONFIGRATION LIST PRICE | E69: TOTAL COG
A70: Total List Price | B70: =IF(OR(B27="Error in Configuration",B27="No Configuration Selected"),0,B27)+IF(OR(B51="Error in Configuration",B51="No Configuration Selected"),0,B51)+IF(OR(B67="Error in Configuration",B67="No Configuration Selected"),0,B67) -> 37708.775 | E70: =SUM(E67+E51+E27) -> 11312.632

Sheet Config #5
A1: CONFIGURATION #5 | B1: DESCRIPTION
A2: Configuration Name
A4: BOOM (SINGLE OR TANDEM) | B4: SELECTION | C4: IMAGINE LIST | D4: ONDAL LIST | E4: ONDAL COG | G4: HV Services | H4: Count | J4: Layer | K4: Selection | L4: FRONT | Q4: Selection | S4: Selection | T4: BACK | Y4: Selection | AE4: =COUNTIF(K5,"(2) Duplexes")+COUNTIF(Y5,"(2) Duplexes") -> 0 | AF4: =COUNTIF(Q5:S5,"(2) Duplexes") -> 0 | AG4: =COUNTIF(K5,"(3) Duplexes")+COUNTIF(Y5,"(3) Duplexes") -> 0 | AH4: =COUNTIF(Q5:S5,"(3) Duplexes") -> 0
A5: Model | B5: =IF(OR(ISBLANK(B8),ISBLANK(B9)),"",IF(ISBLANK(B9),0,(VLOOKUP(B9,'Ondal Booms'!B:F,5,FALSE)))&IF(ISBLANK(B8),0,(VLOOKUP(B8,'Ondal Booms'!B:F,5,FALSE)))) | C5: =IF(OR(ISBLANK(B5),B5=""),0,VLOOKUP(B5,'Ondal Booms'!B:G,4,FALSE)) -> 0 | D5: =IF(OR(ISBLANK(B5),B5=""),0,VLOOKUP(B5,'Ondal Booms'!B:G,2,FALSE)) -> 0 | E5: =IF(OR(ISBLANK(B5),B5=""),0,VLOOKUP(B5,'Ondal Booms'!B:G,3,FALSE)) -> 0 | G5: Duplex Count | H5: =COUNTIF(K5:Y14,"(2) Duplexes")*2+COUNTIF(K5:Y14,"(3) Duplexes")*3 -> 0 | J5: 1 Left | Z5: =15-COUNTIFS(K5:Y5,"") -> 0
A6: Ceiling Cover | C6: =IF(OR(ISBLANK(B6),B6=""),0,VLOOKUP(B6,'Ondal Booms'!B:G,4,FALSE)) -> 0 | D6: =IF(OR(ISBLANK(B6),B6=""),0,VLOOKUP(B6,'Ondal Booms'!B:G,2,FALSE)) -> 0 | E6: =IF(OR(ISBLANK(B6),B6=""),0,VLOOKUP(B6,'Ondal Booms'!B:G,3,FALSE)) -> 0 | J6: 1 Right | Z6: =15-COUNTIFS(K6:Y6,"") -> 0 | AE6: =COUNTIF(K7,"(2) Duplexes")+COUNTIF(Y7,"(2) Duplexes") -> 0 | AF6: =COUNTIF(Q7:S7,"(2) Duplexes") -> 0 | AG6: =COUNTIF(K7,"(3) Duplexes")+COUNTIF(Y7,"(3) Duplexes") -> 0 | AH6: =COUNTIF(Q7:S7,"(3) Duplexes") -> 0
A7: Ceiling Flange | C7: =IF(OR(ISBLANK(B7),B7=""),0,VLOOKUP(B7,'Ondal Booms'!B:G,4,FALSE)) -> 0 | D7: =IF(OR(ISBLANK(B7),B7=""),0,VLOOKUP(B7,'Ondal Booms'!B:G,2,FALSE)) -> 0 | E7: =IF(OR(ISBLANK(B7),B7=""),0,VLOOKUP(B7,'Ondal Booms'!B:G,3,FALSE)) -> 0 | G7: LV Services | H7: Count | J7: 2 Left | Z7: =15-COUNTIFS(K7:Y7,"") -> 0
A8: Top Arm | C8: =IF(OR(ISBLANK(B8),B8=""),0,VLOOKUP(B8,'Ondal Booms'!B:G,4,FALSE)) -> 0 | D8: =IF(OR(ISBLANK(B8),B8=""),0,VLOOKUP(B8,'Ondal Booms'!B:G,2,FALSE)) -> 0 | E8: =IF(OR(ISBLANK(B8),B8=""),0,VLOOKUP(B8,'Ondal Booms'!B:G,3,FALSE)) -> 0 | G8: Data Count | H8: =(COUNTIF(K5:Y14,"Data")) -> 0 | J8: 2 Right | Z8: =15-COUNTIFS(K8:Y8,"") -> 0 | AE8: =COUNTIF(K9,"(2) Duplexes")+COUNTIF(Y9,"(2) Duplexes") -> 0 | AF8: =COUNTIF(Q9:S9,"(2) Duplexes") -> 0 | AG8: =COUNTIF(K9,"(3) Duplexes")+COUNTIF(Y9,"(3) Duplexes") -> 0 | AH8: =COUNTIF(Q9:S9,"(3) Duplexes") -> 0
A9: Bottom Arm | C9: =IF(OR(ISBLANK(B9),B9=""),0,VLOOKUP(B9,'Ondal Booms'!B:G,4,FALSE)) -> 0 | D9: =IF(OR(ISBLANK(B9),B9=""),0,VLOOKUP(B9,'Ondal Booms'!B:G,2,FALSE)) -> 0 | E9: =IF(OR(ISBLANK(B9),B9=""),0,VLOOKUP(B9,'Ondal Booms'!B:G,3,FALSE)) -> 0 | G9: Storz 4in1 Count | H9: =(COUNTIF(K5:Y14,"Storz 4in1")) -> 0 | J9: 3 Left | Z9: =15-COUNTIFS(K9:Y9,"") -> 0
A10: Column Tube | C10: =IF(OR(ISBLANK(B10),B10=""),0,VLOOKUP(B10,'Ondal Booms'!B:G,4,FALSE)) -> 0 | D10: =IF(OR(ISBLANK(B10),B10=""),0,VLOOKUP(B10,'Ondal Booms'!B:G,2,FALSE)) -> 0 | E10: =IF(OR(ISBLANK(B10),B10=""),0,VLOOKUP(B10,'Ondal Booms'!B:G,3,FALSE)) -> 0 | J10: 3 Right | Z10: =15-COUNTIFS(K10:Y10,"") -> 0 | AE10: =COUNTIF(K11,"(2) Duplexes")+COUNTIF(Y11,"(2) Duplexes") -> 0 | AF10: =COUNTIF(Q11:S11,"(2) Duplexes") -> 0 | AG10: =COUNTIF(K11,"(3) Duplexes")+COUNTIF(Y11,"(3) Duplexes") -> 0 | AH10: =COUNTIF(Q11:S11,"(3) Duplexes") -> 0
A11: Service Head | C11: =IF(OR(ISBLANK(B11),B11=""),0,VLOOKUP(B11,'Ondal Booms'!B:G,4,FALSE)) -> 0 | D11: =IF(OR(ISBLANK(B11),B11=""),0,VLOOKUP(B11,'Ondal Booms'!B:G,2,FALSE)) -> 0 | E11: =IF(OR(ISBLANK(B11),B11=""),0,VLOOKUP(B11,'Ondal Booms'!B:G,3,FALSE)) -> 0 | G11: Medical Gases | H11: Count | J11: 4 Left | Z11: =15-COUNTIFS(K11:Y11,"") -> 0
A12: Electrical | B12: =IF(OR(H5=0,ISBLANK(H5)),"",H5&" Duplexes") | C12: =IF(OR(ISBLANK(B12),B12=""),0,VLOOKUP(B12,'Ondal Booms'!B:G,4,FALSE)) -> 0 | D12: =IF(OR(ISBLANK(B12),B12=""),0,VLOOKUP(B12,'Ondal Booms'!B:G,2,FALSE)) -> 0 | E12: =IF(OR(ISBLANK(B12),B12=""),0,VLOOKUP(B12,'Ondal Booms'!B:G,3,FALSE)) -> 0 | G12: Oxygen Count | H12: =(COUNTIF(K5:Y14,"Oxygen")) -> 0 | J12: 4 Right | Z12: =15-COUNTIFS(K12:Y12,"") -> 0 | AE12: =COUNTIF(K13,"(2) Duplexes")+COUNTIF(Y13,"(2) Duplexes") -> 0 | AF12: =COUNTIF(Q13:S13,"(2) Duplexes") -> 0 | AG12: =COUNTIF(K13,"(3) Duplexes")+COUNTIF(Y13,"(3) Duplexes") -> 0 | AH12: =COUNTIF(Q13:S13,"(3) Duplexes") -> 0
A13: Medical Gas | B13: =IF(OR(SUM(H12:H18)=0,ISBLANK(SUM(H12:H18))),"",SUM(H12:H18)&" Outlets") | C13: =IF(OR(ISBLANK(B13),B13=""),0,VLOOKUP(B13,'Ondal Booms'!B:G,4,FALSE)) -> 0 | D13: =IF(OR(ISBLANK(B13),B13=""),0,VLOOKUP(B13,'Ondal Booms'!B:G,2,FALSE)) -> 0 | E13: =IF(OR(ISBLANK(B13),B13=""),0,VLOOKUP(B13,'Ondal Booms'!B:G,3,FALSE)) -> 0 | G13: Med Air Count | H13: =COUNTIF(K5:Y14,"Medical Air") -> 0 | J13: 5 Left | Z13: =15-COUNTIFS(K13:Y13,"") -> 0
A14: # of Outlet Circuits | C14: =IF(OR(ISBLANK(B14),B14=""),0,VLOOKUP(B14,'Ondal Booms'!B:G,4,FALSE)) -> 0 | D14: =IF(OR(ISBLANK(B14),B14=""),0,VLOOKUP(B14,'Ondal Booms'!B:G,2,FALSE)) -> 0 | E14: =IF(OR(ISBLANK(B14),B14=""),0,VLOOKUP(B14,'Ondal Booms'!B:G,3,FALSE)) -> 0 | G14: Nitrous Count | H14: =COUNTIF(K5:Y14,"Nitrous Oxide") -> 0 | J14: 5 Right | Z14: =15-COUNTIFS(K14:Y14,"") -> 0
A15: Shelf (500mm) | C15: =IF(OR(ISBLANK(B15),B15=""),0,VLOOKUP(B15,'Ondal Booms'!B:G,4,FALSE)) -> 0 | D15: =IF(OR(ISBLANK(B15),B15=""),0,VLOOKUP(B15,'Ondal Booms'!B:G,2,FALSE)) -> 0 | E15: =IF(OR(ISBLANK(B15),B15=""),0,VLOOKUP(B15,'Ondal Booms'!B:G,3,FALSE)) -> 0 | G15: WAGD Count | H15: =COUNTIF(K5:Y14,"WAGD") -> 0
A16: Shelf (750mm) | C16: =IF(OR(ISBLANK(B16),B16=""),0,VLOOKUP(B16,'Ondal Booms'!B:G,4,FALSE)) -> 0 | D16: =IF(OR(ISBLANK(B16),B16=""),0,VLOOKUP(B16,'Ondal Booms'!B:G,2,FALSE)) -> 0 | E16: =IF(OR(ISBLANK(B16),B16=""),0,VLOOKUP(B16,'Ondal Booms'!B:G,3,FALSE)) -> 0 | G16: Vacuum Count | H16: =COUNTIF(K5:Y14,"Vacuum") -> 0
A17: Accessory 1 | C17: =IF(OR(ISBLANK(B17),B17=""),0,VLOOKUP(B17,'Ondal Booms'!B:G,4,FALSE)) -> 0 | D17: =IF(OR(ISBLANK(B17),B17=""),0,VLOOKUP(B17,'Ondal Booms'!B:G,2,FALSE)) -> 0 | E17: =IF(OR(ISBLANK(B17),B17=""),0,VLOOKUP(B17,'Ondal Booms'!B:G,3,FALSE)) -> 0 | G17: Nitrogen Count | H17: =COUNTIF(K5:Y14,"Nitrogen") -> 0
A18: Accessory 2 | C18: =IF(OR(ISBLANK(B18),B18=""),0,VLOOKUP(B18,'Ondal Booms'!B:G,4,FALSE)) -> 0 | D18: =IF(OR(ISBLANK(B18),B18=""),0,VLOOKUP(B18,'Ondal Booms'!B:G,2,FALSE)) -> 0 | E18: =IF(OR(ISBLANK(B18),B18=""),0,VLOOKUP(B18,'Ondal Booms'!B:G,3,FALSE)) -> 0 | G18: CO2 Count | H18: =COUNTIF(K5:Y14,"Carbon Dioxide") -> 0
A19: Accessory 3 | C19: =IF(OR(ISBLANK(B19),B19=""),0,VLOOKUP(B19,'Ondal Booms'!B:G,4,FALSE)) -> 0 | D19: =IF(OR(ISBLANK(B19),B19=""),0,VLOOKUP(B19,'Ondal Booms'!B:G,2,FALSE)) -> 0 | E19: =IF(OR(ISBLANK(B19),B19=""),0,VLOOKUP(B19,'Ondal Booms'!B:G,3,FALSE)) -> 0
A20: Accessory 4 | C20: =IF(OR(ISBLANK(B20),B20=""),0,VLOOKUP(B20,'Ondal Booms'!B:G,4,FALSE)) -> 0 | D20: =IF(OR(ISBLANK(B20),B20=""),0,VLOOKUP(B20,'Ondal Booms'!B:G,2,FALSE)) -> 0 | E20: =IF(OR(ISBLANK(B20),B20=""),0,VLOOKUP(B20,'Ondal Booms'!B:G,3,FALSE)) -> 0
A21: Accessory 5 | C21: =IF(OR(ISBLANK(B21),B21=""),0,VLOOKUP(B21,'Ondal Booms'!B:G,4,FALSE)) -> 0 | D21: =IF(OR(ISBLANK(B21),B21=""),0,VLOOKUP(B21,'Ondal Booms'!B:G,2,FALSE)) -> 0 | E21: =IF(OR(ISBLANK(B21),B21=""),0,VLOOKUP(B21,'Ondal Booms'!B:G,3,FALSE)) -> 0
A22: Accessory 6 | C22: =IF(OR(ISBLANK(B22),B22=""),0,VLOOKUP(B22,'Ondal Booms'!B:G,4,FALSE)) -> 0 | D22: =IF(OR(ISBLANK(B22),B22=""),0,VLOOKUP(B22,'Ondal Booms'!B:G,2,FALSE)) -> 0 | E22: =IF(OR(ISBLANK(B22),B22=""),0,VLOOKUP(B22,'Ondal Booms'!B:G,3,FALSE)) -> 0
A23: Accessory 7 | C23: =IF(OR(ISBLANK(B23),B23=""),0,VLOOKUP(B23,'Ondal Booms'!B:G,4,FALSE)) -> 0 | D23: =IF(OR(ISBLANK(B23),B23=""),0,VLOOKUP(B23,'Ondal Booms'!B:G,2,FALSE)) -> 0 | E23: =IF(OR(ISBLANK(B23),B23=""),0,VLOOKUP(B23,'Ondal Booms'!B:G,3,FALSE)) -> 0
A25: Errors? | B25: =IF(OR(ISBLANK(B5),B5=""),"", IF(OR(AND(B11="200mm Service Head",SUM(Z7:Z14)>0),AND(B11="400mm Service Head",SUM(Z9:Z14)>0),AND(B11="600mm Service Head",SUM(Z11:Z14)>0),AND(B11="800mm Service Head",SUM(Z13:Z14)>0)),"Select Longer Service Head or Remove Services", IF(AND(RIGHT(B9,2)="XL",RIGHT(B8,2)<>"XL"),"BOTTOM XL ARM REQUIRES TOP XL ARM", IF(OR(ISBLANK(B6),ISBLANK(B7),ISBLANK(B8),ISBLANK(B9),ISBLANK(B10),ISBLANK(B11),ISBLANK(B15),ISBLANK(B16),ISBLANK(B14)),"Missing Selections for Configuration", IF(AND(B11="Large Monitor Carrier",B9<>"Spring Articulating"),"Large Monitor Requires Spring Bottom Arm", IF(OR(AND(RIGHT(B7,2)="XL",RIGHT(B8,2)<>"XL"),AND(RIGHT(B8,2)="XL",RIGHT(B7,2)<>"XL")),"Both Top Arm and Ceiling Flange Must Be XL", IF(COUNTIF(AE4:AH12,1)>1,"Mismatch Electrical Configuration", "")))))) )
C26: IMAGINE LIST | D26: ONDAL LIST | E26: ONDAL SALES
A27: Equipment List Price | B27: =IF(OR(B6="",ISBLANK(B6)),"NO CONFIGURATION SELECTED",C27) -> NO CONFIGURATION SELECTED | C27: =SUM(C5:C23) -> 0 | D27: =SUM(D5:D23) -> 0 | E27: =SUM(E5:E23) -> 0 | J27: ="<-- EXPAND TO SHOW OPTIONS / SERVICE HEAD" -> <-- EXPAND TO SHOW OPTIONS / SERVICE HEAD
AE28: =COUNTIF(K30,"(2) Duplexes")+COUNTIF(Y30,"(2) Duplexes") -> 0 | AF28: =COUNTIF(Q30:S30,"(2) Duplexes") -> 0 | AG28: =COUNTIF(K30,"(3) Duplexes")+COUNTIF(Y30,"(3) Duplexes") -> 0 | AH28: =COUNTIF(Q30:S30,"(3) Duplexes") -> 0
A29: BOOM (TANDEM 2ND ONLY) | B29: SELECTION | C29: IMAGINE LIST | D29: ONDAL LIST | E29: ONDAL COG | G29: HV Services | H29: Count | J29: Layer | K29: Selection | L29: FRONT | Q29: Selection | S29: Selection | T29: BACK | Y29: Selection
A30: Model | B30: =IF(OR(ISBLANK(B32),ISBLANK(B33)),"",IF(ISBLANK(B33),0,(VLOOKUP(B33,'Ondal Booms'!B:F,5,FALSE)))&IF(ISBLANK(B32),0,(VLOOKUP(B32,'Ondal Booms'!B:F,5,FALSE)))) | C30: =IF(OR(ISBLANK(B30),B30=""),0,VLOOKUP(B30,'Ondal Booms'!B:G,4,FALSE)) -> 0 | D30: =IF(OR(ISBLANK(B30),B30=""),0,VLOOKUP(B30,'Ondal Booms'!B:G,2,FALSE)) -> 0 | E30: =IF(OR(ISBLANK(B30),B30=""),0,VLOOKUP(B30,'Ondal Booms'!B:G,3,FALSE)) -> 0 | G30: Duplex Count | H30: =COUNTIF(K30:Y39,"(2) Duplexes")*2+COUNTIF(K30:Y39,"(3) Duplexes")*3 -> 0 | J30: 1 Left | Z30: =15-COUNTIFS(K30:Y30,"") -> 0
A31: Ceiling Flange | C31: =IF(OR(ISBLANK(B31),B31=""),0,VLOOKUP(B31,'Ondal Booms'!B:G,4,FALSE)) -> 0 | D31: =IF(OR(ISBLANK(B31),B31=""),0,VLOOKUP(B31,'Ondal Booms'!B:G,2,FALSE)) -> 0 | E31: =IF(OR(ISBLANK(B31),B31=""),0,VLOOKUP(B31,'Ondal Booms'!B:G,3,FALSE)) -> 0 | G31: LV Services | H31: Count | J31: 1 Right | Z31: =15-COUNTIFS(K31:Y31,"") -> 0 | AE31: =COUNTIF(K32,"(2) Duplexes")+COUNTIF(Y32,"(2) Duplexes") -> 0 | AF31: =COUNTIF(Q32:S32,"(2) Duplexes") -> 0 | AG31: =COUNTIF(K32,"(3) Duplexes")+COUNTIF(Y32,"(3) Duplexes") -> 0 | AH31: =COUNTIF(Q32:S32,"(3) Duplexes") -> 0
A32: Top Arm | C32: =IF(OR(ISBLANK(B32),B32=""),0,VLOOKUP(B32,'Ondal Booms'!B:G,4,FALSE)) -> 0 | D32: =IF(OR(ISBLANK(B32),B32=""),0,VLOOKUP(B32,'Ondal Booms'!B:G,2,FALSE)) -> 0 | E32: =IF(OR(ISBLANK(B32),B32=""),0,VLOOKUP(B32,'Ondal Booms'!B:G,3,FALSE)) -> 0 | G32: Data Count | H32: =(COUNTIF(K30:Y39,"Data")) -> 0 | J32: 2 Left | Z32: =15-COUNTIFS(K32:Y32,"") -> 0
A33: Bottom Arm | C33: =IF(OR(ISBLANK(B33),B33=""),0,VLOOKUP(B33,'Ondal Booms'!B:G,4,FALSE)) -> 0 | D33: =IF(OR(ISBLANK(B33),B33=""),0,VLOOKUP(B33,'Ondal Booms'!B:G,2,FALSE)) -> 0 | E33: =IF(OR(ISBLANK(B33),B33=""),0,VLOOKUP(B33,'Ondal Booms'!B:G,3,FALSE)) -> 0 | G33: Storz 4in1 Count | H33: =(COUNTIF(K30:Y39,"Storz 4in1")) -> 0 | J33: 2 Right | Z33: =15-COUNTIFS(K33:Y33,"") -> 0 | AE33: =COUNTIF(K34,"(2) Duplexes")+COUNTIF(Y34,"(2) Duplexes") -> 0 | AF33: =COUNTIF(Q34:S34,"(2) Duplexes") -> 0 | AG33: =COUNTIF(K34,"(3) Duplexes")+COUNTIF(Y34,"(3) Duplexes") -> 0 | AH33: =COUNTIF(Q34:S34,"(3) Duplexes") -> 0
A34: Column Tube | C34: =IF(OR(ISBLANK(B34),B34=""),0,VLOOKUP(B34,'Ondal Booms'!B:G,4,FALSE)) -> 0 | D34: =IF(OR(ISBLANK(B34),B34=""),0,VLOOKUP(B34,'Ondal Booms'!B:G,2,FALSE)) -> 0 | E34: =IF(OR(ISBLANK(B34),B34=""),0,VLOOKUP(B34,'Ondal Booms'!B:G,3,FALSE)) -> 0 | J34: 3 Left | Z34: =15-COUNTIFS(K34:Y34,"") -> 0
A35: Service Head | C35: =IF(OR(ISBLANK(B35),B35=""),0,VLOOKUP(B35,'Ondal Booms'!B:G,4,FALSE)) -> 0 | D35: =IF(OR(ISBLANK(B35),B35=""),0,VLOOKUP(B35,'Ondal Booms'!B:G,2,FALSE)) -> 0 | E35: =IF(OR(ISBLANK(B35),B35=""),0,VLOOKUP(B35,'Ondal Booms'!B:G,3,FALSE)) -> 0 | G35: Medical Gases | H35: Count | J35: 3 Right | Z35: =15-COUNTIFS(K35:Y35,"") -> 0 | AE35: =COUNTIF(K36,"(2) Duplexes")+COUNTIF(Y36,"(2) Duplexes") -> 0 | AF35: =COUNTIF(Q36:S36,"(2) Duplexes") -> 0 | AG35: =COUNTIF(K36,"(3) Duplexes")+COUNTIF(Y36,"(3) Duplexes") -> 0 | AH35: =COUNTIF(Q36:S36,"(3) Duplexes") -> 0
A36: Electrical | B36: =IF(OR(H30=0,ISBLANK(H30)),"",H30&" Duplexes") | C36: =IF(OR(ISBLANK(B36),B36=""),0,VLOOKUP(B36,'Ondal Booms'!B:G,4,FALSE)) -> 0 | D36: =IF(OR(ISBLANK(B36),B36=""),0,VLOOKUP(B36,'Ondal Booms'!B:G,2,FALSE)) -> 0 | E36: =IF(OR(ISBLANK(B36),B36=""),0,VLOOKUP(B36,'Ondal Booms'!B:G,3,FALSE)) -> 0 | G36: Oxygen Count | H36: =(COUNTIF(K30:Y39,"Oxygen")) -> 0 | J36: 4 Left | Z36: =15-COUNTIFS(K36:Y36,"") -> 0
A37: Medical Gas | B37: =IF(OR(SUM(H36:H42)=0,ISBLANK(SUM(H36:H42))),"",SUM(H36:H42)&" Outlets") | C37: =IF(OR(ISBLANK(B37),B37=""),0,VLOOKUP(B37,'Ondal Booms'!B:G,4,FALSE)) -> 0 | D37: =IF(OR(ISBLANK(B37),B37=""),0,VLOOKUP(B37,'Ondal Booms'!B:G,2,FALSE)) -> 0 | E37: =IF(OR(ISBLANK(B37),B37=""),0,VLOOKUP(B37,'Ondal Booms'!B:G,3,FALSE)) -> 0 | G37: Med Air Count | H37: =COUNTIF(K30:Y39,"Medical Air") -> 0 | J37: 4 Right | Z37: =15-COUNTIFS(K37:Y37,"") -> 0 | AE37: =COUNTIF(K38,"(2) Duplexes")+COUNTIF(Y38,"(2) Duplexes") -> 0 | AF37: =COUNTIF(Q38:S38,"(2) Duplexes") -> 0 | AG37: =COUNTIF(K38,"(3) Duplexes")+COUNTIF(Y38,"(3) Duplexes") -> 0 | AH37: =COUNTIF(Q38:S38,"(3) Duplexes") -> 0
A38: # of Outlet Circuits | C38: =IF(OR(ISBLANK(B38),B38=""),0,VLOOKUP(B38,'Ondal Booms'!B:G,4,FALSE)) -> 0 | D38: =IF(OR(ISBLANK(B38),B38=""),0,VLOOKUP(B38,'Ondal Booms'!B:G,2,FALSE)) -> 0 | E38: =IF(OR(ISBLANK(B38),B38=""),0,VLOOKUP(B38,'Ondal Booms'!B:G,3,FALSE)) -> 0 | G38: Nitrous Count | H38: =COUNTIF(K30:Y39,"Nitrous Oxide") -> 0 | J38: 5 Left | Z38: =15-COUNTIFS(K38:Y38,"") -> 0
A39: Shelf (500mm) | C39: =IF(OR(ISBLANK(B39),B39=""),0,VLOOKUP(B39,'Ondal Booms'!B:G,4,FALSE)) -> 0 | D39: =IF(OR(ISBLANK(B39),B39=""),0,VLOOKUP(B39,'Ondal Booms'!B:G,2,FALSE)) -> 0 | E39: =IF(OR(ISBLANK(B39),B39=""),0,VLOOKUP(B39,'Ondal Booms'!B:G,3,FALSE)) -> 0 | G39: WAGD Count | H39: =COUNTIF(K30:Y39,"WAGD") -> 0 | J39: 5 Right | Z39: =15-COUNTIFS(K39:Y39,"") -> 0
A40: Shelf (750mm) | C40: =IF(OR(ISBLANK(B40),B40=""),0,VLOOKUP(B40,'Ondal Booms'!B:G,4,FALSE)) -> 0 | D40: =IF(OR(ISBLANK(B40),B40=""),0,VLOOKUP(B40,'Ondal Booms'!B:G,2,FALSE)) -> 0 | E40: =IF(OR(ISBLANK(B40),B40=""),0,VLOOKUP(B40,'Ondal Booms'!B:G,3,FALSE)) -> 0 | G40: Vacuum Count | H40: =COUNTIF(K30:Y39,"Vacuum") -> 0
A41: Accessory 1 | C41: =IF(OR(ISBLANK(B41),B41=""),0,VLOOKUP(B41,'Ondal Booms'!B:G,4,FALSE)) -> 0 | D41: =IF(OR(ISBLANK(B41),B41=""),0,VLOOKUP(B41,'Ondal Booms'!B:G,2,FALSE)) -> 0 | E41: =IF(OR(ISBLANK(B41),B41=""),0,VLOOKUP(B41,'Ondal Booms'!B:G,3,FALSE)) -> 0 | G41: Nitrogen Count | H41: =COUNTIF(K30:Y39,"Nitrogen") -> 0
A42: Accessory 2 | C42: =IF(OR(ISBLANK(B42),B42=""),0,VLOOKUP(B42,'Ondal Booms'!B:G,4,FALSE)) -> 0 | D42: =IF(OR(ISBLANK(B42),B42=""),0,VLOOKUP(B42,'Ondal Booms'!B:G,2,FALSE)) -> 0 | E42: =IF(OR(ISBLANK(B42),B42=""),0,VLOOKUP(B42,'Ondal Booms'!B:G,3,FALSE)) -> 0 | G42: CO2 Count | H42: =COUNTIF(K30:Y39,"Carbon Dioxide") -> 0
A43: Accessory 3 | C43: =IF(OR(ISBLANK(B43),B43=""),0,VLOOKUP(B43,'Ondal Booms'!B:G,4,FALSE)) -> 0 | D43: =IF(OR(ISBLANK(B43),B43=""),0,VLOOKUP(B43,'Ondal Booms'!B:G,2,FALSE)) -> 0 | E43: =IF(OR(ISBLANK(B43),B43=""),0,VLOOKUP(B43,'Ondal Booms'!B:G,3,FALSE)) -> 0
A44: Accessory 4 | C44: =IF(OR(ISBLANK(B44),B44=""),0,VLOOKUP(B44,'Ondal Booms'!B:G,4,FALSE)) -> 0 | D44: =IF(OR(ISBLANK(B44),B44=""),0,VLOOKUP(B44,'Ondal Booms'!B:G,2,FALSE)) -> 0 | E44: =IF(OR(ISBLANK(B44),B44=""),0,VLOOKUP(B44,'Ondal Booms'!B:G,3,FALSE)) -> 0
A45: Accessory 5 | C45: =IF(OR(ISBLANK(B45),B45=""),0,VLOOKUP(B45,'Ondal Booms'!B:G,4,FALSE)) -> 0 | D45: =IF(OR(ISBLANK(B45),B45=""),0,VLOOKUP(B45,'Ondal Booms'!B:G,2,FALSE)) -> 0 | E45: =IF(OR(ISBLANK(B45),B45=""),0,VLOOKUP(B45,'Ondal Booms'!B:G,3,FALSE)) -> 0
A46: Accessory 6 | C46: =IF(OR(ISBLANK(B46),B46=""),0,VLOOKUP(B46,'Ondal Booms'!B:G,4,FALSE)) -> 0 | D46: =IF(OR(ISBLANK(B46),B46=""),0,VLOOKUP(B46,'Ondal Booms'!B:G,2,FALSE)) -> 0 | E46: =IF(OR(ISBLANK(B46),B46=""),0,VLOOKUP(B46,'Ondal Booms'!B:G,3,FALSE)) -> 0
A47: Accessory 7 | C47: =IF(OR(ISBLANK(B47),B47=""),0,VLOOKUP(B47,'Ondal Booms'!B:G,4,FALSE)) -> 0 | D47: =IF(OR(ISBLANK(B47),B47=""),0,VLOOKUP(B47,'Ondal Booms'!B:G,2,FALSE)) -> 0 | E47: =IF(OR(ISBLANK(B47),B47=""),0,VLOOKUP(B47,'Ondal Booms'!B:G,3,FALSE)) -> 0
A49: Errors? | B49: =IF(OR(ISBLANK(B30),B30=""),"", IF(OR(AND(B35="200mm Service Head",SUM(Z32:Z39)>0),AND(B35="400mm Service Head",SUM(Z34:Z39)>0),AND(B35="600mm Service Head",SUM(Z36:Z39)>0),AND(B35="800mm Service Head",SUM(Z38:Z39)>0)),"Select Longer Service Head or Remove Services", IF(AND(RIGHT(B33,2)="XL",RIGHT(B32,2)<>"XL"),"BOTTOM XL ARM REQUIRES TOP XL ARM", IF(OR(ISBLANK(#REF!),ISBLANK(B31),ISBLANK(B32),ISBLANK(B33),ISBLANK(B34),ISBLANK(B35),ISBLANK(B39),ISBLANK(B40),ISBLANK(B38)),"Missing Selections for Configuration", IF(AND(B35="Large Monitor Carrier",B33<>"Spring Articulating"),"Large Monitor Requires Spring Bottom Arm", IF(OR(AND(RIGHT(B31,2)="XL",RIGHT(B32,2)<>"XL"),AND(RIGHT(B32,2)="XL",RIGHT(B31,2)<>"XL")),"Both Top Arm and Ceiling Flange Must Be XL", IF(COUNTIF(AE29:AH37,1)>1,"Mismatch Electrical Configuration", "")))))) )
C50: IMAGINE LIST | D50: ONDAL LIST | E50: ONDAL SALES
A51: Equipment List Price | B51: =IF(OR(B30="",ISBLANK(B30)),"NO CONFIGURATION SELECTED",C51) -> NO CONFIGURATION SELECTED | C51: =SUM(C30:C47) -> 0 | D51: =SUM(D30:D47) -> 0 | E51: =SUM(E30:E47) -> 0 | J51: ="<-- EXPAND TO SHOW OPTIONS / SERVICE HEAD" -> <-- EXPAND TO SHOW OPTIONS / SERVICE HEAD
A53: LIGHT (SINGLE OR TANDEM) | B53: SELECTION | C53: IMAGINE LIST | D53: SIMEON LIST | E53: SIMEON COG
A54: Model | B54: =IF(AND(ISBLANK(B57),ISBLANK(B58),ISBLANK(B59)),"", IF(B55="Upgrade Only","UPGRADE", IF(RIGHT(B57,4)="(3P)","(3P) ","")& IF(ISBLANK(B57),"",VLOOKUP(B57,'Simeon Lights'!C:H,2,FALSE))& IF(ISBLANK(B58),""," / "&VLOOKUP(B58,'Simeon Lights'!C:H,2,FALSE))& IF(ISBLANK(B59),""," / "&VLOOKUP(B59,'Simeon Lights'!C:H,2,FALSE)))) | C54: =IF(ISBLANK(B57),0,(VLOOKUP(B54,'Simeon Lights'!C:J,6,FALSE))) -> 0 | D54: =IF(ISBLANK(B57),0,(VLOOKUP(B54,'Simeon Lights'!C:J,4,FALSE))) -> 0 | E54: =IF(ISBLANK(B57),0,(VLOOKUP(B54,'Simeon Lights'!C:J,5,FALSE))) -> 0
A55: Ceiling Cover | C55: =IF(ISBLANK(B55),0,VLOOKUP(B55,'Simeon Lights'!C:J,6,FALSE)) -> 0 | D55: =IF(ISBLANK(B55),0,VLOOKUP(B55,'Simeon Lights'!C:J,4,FALSE)) -> 0 | E55: =IF(ISBLANK(B55),0,VLOOKUP(B55,'Simeon Lights'!C:J,5,FALSE)) -> 0
A56: Ceiling Drop Tube | C56: =IF(ISBLANK(B56),0,VLOOKUP(B56,'Simeon Lights'!C:J,6,FALSE)) -> 0 | D56: =IF(ISBLANK(B56),0,VLOOKUP(B56,'Simeon Lights'!C:J,4,FALSE)) -> 0 | E56: =IF(ISBLANK(B56),0,VLOOKUP(B56,'Simeon Lights'!C:J,5,FALSE)) -> 0
A57: Arm 1 (Top Arm) | C57: =IF(ISBLANK(B57),0,VLOOKUP(B57,'Simeon Lights'!C:J,6,FALSE)) -> 0 | D57: =IF(ISBLANK(B57),0,VLOOKUP(B57,'Simeon Lights'!C:J,4,FALSE)) -> 0 | E57: =IF(ISBLANK(B57),0,VLOOKUP(B57,'Simeon Lights'!C:J,5,FALSE)) -> 0
A58: Arm 2 | C58: =IF(ISBLANK(B58),0,VLOOKUP(B58,'Simeon Lights'!C:J,6,FALSE)) -> 0 | D58: =IF(ISBLANK(B58),0,VLOOKUP(B58,'Simeon Lights'!C:J,4,FALSE)) -> 0 | E58: =IF(ISBLANK(B58),0,VLOOKUP(B58,'Simeon Lights'!C:J,5,FALSE)) -> 0
A59: Arm 3 | C59: =IF(ISBLANK(B59),0,VLOOKUP(B59,'Simeon Lights'!C:J,6,FALSE)) -> 0 | D59: =IF(ISBLANK(B59),0,VLOOKUP(B59,'Simeon Lights'!C:J,4,FALSE)) -> 0 | E59: =IF(ISBLANK(B59),0,VLOOKUP(B59,'Simeon Lights'!C:J,5,FALSE)) -> 0
A60: Wall Control | C60: =IF(ISBLANK(B60),0,VLOOKUP(B60,'Simeon Lights'!C:J,6,FALSE)) -> 0 | D60: =IF(ISBLANK(B60),0,VLOOKUP(B60,'Simeon Lights'!C:J,4,FALSE)) -> 0 | E60: =IF(ISBLANK(B60),0,VLOOKUP(B60,'Simeon Lights'!C:J,5,FALSE)) -> 0
A61: Integration Control | C61: =IF(ISBLANK(B61),0,VLOOKUP(B61,'Simeon Lights'!C:J,6,FALSE)) -> 0 | D61: =IF(ISBLANK(B61),0,VLOOKUP(B61,'Simeon Lights'!C:J,4,FALSE)) -> 0 | E61: =IF(ISBLANK(B61),0,VLOOKUP(B61,'Simeon Lights'!C:J,5,FALSE)) -> 0
A62: In-Light Camera | C62: =IF(ISBLANK(B62),0,VLOOKUP(B62,'Simeon Lights'!C:J,6,FALSE)) -> 0 | D62: =IF(ISBLANK(B62),0,VLOOKUP(B62,'Simeon Lights'!C:J,4,FALSE)) -> 0 | E62: =IF(ISBLANK(B62),0,VLOOKUP(B62,'Simeon Lights'!C:J,5,FALSE)) -> 0
A63: Disposable Adpaters | C63: =IF(ISBLANK(B63),0,VLOOKUP(B63,'Simeon Lights'!C:J,6,FALSE)) -> 0 | D63: =IF(ISBLANK(B63),0,VLOOKUP(B63,'Simeon Lights'!C:J,4,FALSE)) -> 0 | E63: =IF(ISBLANK(B63),0,VLOOKUP(B63,'Simeon Lights'!C:J,5,FALSE)) -> 0
A65: Errors? | B65: =IF(AND(ISBLANK(B57),ISBLANK(B58),ISBLANK(B59)),"", IF(AND(ISBLANK(B57),B58<>""),"ARM 1 MISSING", IF(AND(ISBLANK(B57),B59<>""),"ARM 1 MISSING", IF(ISBLANK(B58)&ISBLANK(B59)="TRUEFALSE","ARM 2 MISSING", IF(AND(B57<>"",B58="32in Flat Panel",B59<>""),"FP CANNOT BE MIDDLE ARM", IF(OR(ISBLANK(B55),ISBLANK(B56),ISBLANK(B60),ISBLANK(B61),ISBLANK(B62),ISBLANK(B63)),"Missing Selections",""))))))
C66: IMAGINE LIST | D66: SIMEON LIST | E66: SIMEON COG
A67: Equipment List Price | B67: =IF(OR(ISBLANK(B57),ISBLANK(B58)&ISBLANK(B59)="TRUEFALSE"),"NO CONFIGURATION SELECTED",IF(B65<>"","ERROR IN CONFIGURATION",IF(B57="",0,SUM(C54:C63)))) -> NO CONFIGURATION SELECTED | C67: =SUM(C54:C65) -> 0 | D67: =SUM(D54:D65) -> 0 | E67: =SUM(E54:E65) -> 0 | J67: ="<-- EXPAND TO SHOW OPTIONS" -> <-- EXPAND TO SHOW OPTIONS
B69: CONFIGRATION LIST PRICE | E69: TOTAL COG
A70: Total List Price | B70: =IF(OR(B27="Error in Configuration",B27="No Configuration Selected"),0,B27)+IF(OR(B51="Error in Configuration",B51="No Configuration Selected"),0,B51)+IF(OR(B67="Error in Configuration",B67="No Configuration Selected"),0,B67) -> 0 | E70: =SUM(E67,E51,E27) -> 0

Sheet Config #6
A1: CONFIGURATION #6 | B1: DESCRIPTION
A2: Configuration Name
A4: BOOM (SINGLE OR TANDEM) | B4: SELECTION | C4: IMAGINE LIST | D4: ONDAL LIST | E4: ONDAL COG | G4: HV Services | H4: Count | J4: Layer | K4: Selection | L4: FRONT | Q4: Selection | S4: Selection | T4: BACK | Y4: Selection | AE4: =COUNTIF(K5,"(2) Duplexes")+COUNTIF(Y5,"(2) Duplexes") -> 0 | AF4: =COUNTIF(Q5:S5,"(2) Duplexes") -> 0 | AG4: =COUNTIF(K5,"(3) Duplexes")+COUNTIF(Y5,"(3) Duplexes") -> 0 | AH4: =COUNTIF(Q5:S5,"(3) Duplexes") -> 0
A5: Model | B5: =IF(OR(ISBLANK(B8),ISBLANK(B9)),"",IF(ISBLANK(B9),0,(VLOOKUP(B9,'Ondal Booms'!B:F,5,FALSE)))&IF(ISBLANK(B8),0,(VLOOKUP(B8,'Ondal Booms'!B:F,5,FALSE)))) | C5: =IF(OR(ISBLANK(B5),B5=""),0,VLOOKUP(B5,'Ondal Booms'!B:G,4,FALSE)) -> 0 | D5: =IF(OR(ISBLANK(B5),B5=""),0,VLOOKUP(B5,'Ondal Booms'!B:G,2,FALSE)) -> 0 | E5: =IF(OR(ISBLANK(B5),B5=""),0,VLOOKUP(B5,'Ondal Booms'!B:G,3,FALSE)) -> 0 | G5: Duplex Count | H5: =COUNTIF(K5:Y14,"(2) Duplexes")*2+COUNTIF(K5:Y14,"(3) Duplexes")*3 -> 0 | J5: 1 Left | Z5: =15-COUNTIFS(K5:Y5,"") -> 0
A6: Ceiling Cover | C6: =IF(OR(ISBLANK(B6),B6=""),0,VLOOKUP(B6,'Ondal Booms'!B:G,4,FALSE)) -> 0 | D6: =IF(OR(ISBLANK(B6),B6=""),0,VLOOKUP(B6,'Ondal Booms'!B:G,2,FALSE)) -> 0 | E6: =IF(OR(ISBLANK(B6),B6=""),0,VLOOKUP(B6,'Ondal Booms'!B:G,3,FALSE)) -> 0 | J6: 1 Right | Z6: =15-COUNTIFS(K6:Y6,"") -> 0 | AE6: =COUNTIF(K7,"(2) Duplexes")+COUNTIF(Y7,"(2) Duplexes") -> 0 | AF6: =COUNTIF(Q7:S7,"(2) Duplexes") -> 0 | AG6: =COUNTIF(K7,"(3) Duplexes")+COUNTIF(Y7,"(3) Duplexes") -> 0 | AH6: =COUNTIF(Q7:S7,"(3) Duplexes") -> 0
A7: Ceiling Flange | C7: =IF(OR(ISBLANK(B7),B7=""),0,VLOOKUP(B7,'Ondal Booms'!B:G,4,FALSE)) -> 0 | D7: =IF(OR(ISBLANK(B7),B7=""),0,VLOOKUP(B7,'Ondal Booms'!B:G,2,FALSE)) -> 0 | E7: =IF(OR(ISBLANK(B7),B7=""),0,VLOOKUP(B7,'Ondal Booms'!B:G,3,FALSE)) -> 0 | G7: LV Services | H7: Count | J7: 2 Left | Z7: =15-COUNTIFS(K7:Y7,"") -> 0
A8: Top Arm | C8: =IF(OR(ISBLANK(B8),B8=""),0,VLOOKUP(B8,'Ondal Booms'!B:G,4,FALSE)) -> 0 | D8: =IF(OR(ISBLANK(B8),B8=""),0,VLOOKUP(B8,'Ondal Booms'!B:G,2,FALSE)) -> 0 | E8: =IF(OR(ISBLANK(B8),B8=""),0,VLOOKUP(B8,'Ondal Booms'!B:G,3,FALSE)) -> 0 | G8: Data Count | H8: =(COUNTIF(K5:Y14,"Data")) -> 0 | J8: 2 Right | Z8: =15-COUNTIFS(K8:Y8,"") -> 0 | AE8: =COUNTIF(K9,"(2) Duplexes")+COUNTIF(Y9,"(2) Duplexes") -> 0 | AF8: =COUNTIF(Q9:S9,"(2) Duplexes") -> 0 | AG8: =COUNTIF(K9,"(3) Duplexes")+COUNTIF(Y9,"(3) Duplexes") -> 0 | AH8: =COUNTIF(Q9:S9,"(3) Duplexes") -> 0
A9: Bottom Arm | C9: =IF(OR(ISBLANK(B9),B9=""),0,VLOOKUP(B9,'Ondal Booms'!B:G,4,FALSE)) -> 0 | D9: =IF(OR(ISBLANK(B9),B9=""),0,VLOOKUP(B9,'Ondal Booms'!B:G,2,FALSE)) -> 0 | E9: =IF(OR(ISBLANK(B9),B9=""),0,VLOOKUP(B9,'Ondal Booms'!B:G,3,FALSE)) -> 0 | G9: Storz 4in1 Count | H9: =(COUNTIF(K5:Y14,"Storz 4in1")) -> 0 | J9: 3 Left | Z9: =15-COUNTIFS(K9:Y9,"") -> 0
A10: Column Tube | C10: =IF(OR(ISBLANK(B10),B10=""),0,VLOOKUP(B10,'Ondal Booms'!B:G,4,FALSE)) -> 0 | D10: =IF(OR(ISBLANK(B10),B10=""),0,VLOOKUP(B10,'Ondal Booms'!B:G,2,FALSE)) -> 0 | E10: =IF(OR(ISBLANK(B10),B10=""),0,VLOOKUP(B10,'Ondal Booms'!B:G,3,FALSE)) -> 0 | J10: 3 Right | Z10: =15-COUNTIFS(K10:Y10,"") -> 0 | AE10: =COUNTIF(K11,"(2) Duplexes")+COUNTIF(Y11,"(2) Duplexes") -> 0 | AF10: =COUNTIF(Q11:S11,"(2) Duplexes") -> 0 | AG10: =COUNTIF(K11,"(3) Duplexes")+COUNTIF(Y11,"(3) Duplexes") -> 0 | AH10: =COUNTIF(Q11:S11,"(3) Duplexes") -> 0
A11: Service Head | C11: =IF(OR(ISBLANK(B11),B11=""),0,VLOOKUP(B11,'Ondal Booms'!B:G,4,FALSE)) -> 0 | D11: =IF(OR(ISBLANK(B11),B11=""),0,VLOOKUP(B11,'Ondal Booms'!B:G,2,FALSE)) -> 0 | E11: =IF(OR(ISBLANK(B11),B11=""),0,VLOOKUP(B11,'Ondal Booms'!B:G,3,FALSE)) -> 0 | G11: Medical Gases | H11: Count | J11: 4 Left | Z11: =15-COUNTIFS(K11:Y11,"") -> 0
A12: Electrical | B12: =IF(OR(H5=0,ISBLANK(H5)),"",H5&" Duplexes") | C12: =IF(OR(ISBLANK(B12),B12=""),0,VLOOKUP(B12,'Ondal Booms'!B:G,4,FALSE)) -> 0 | D12: =IF(OR(ISBLANK(B12),B12=""),0,VLOOKUP(B12,'Ondal Booms'!B:G,2,FALSE)) -> 0 | E12: =IF(OR(ISBLANK(B12),B12=""),0,VLOOKUP(B12,'Ondal Booms'!B:G,3,FALSE)) -> 0 | G12: Oxygen Count | H12: =(COUNTIF(K5:Y14,"Oxygen")) -> 0 | J12: 4 Right | Z12: =15-COUNTIFS(K12:Y12,"") -> 0 | AE12: =COUNTIF(K13,"(2) Duplexes")+COUNTIF(Y13,"(2) Duplexes") -> 0 | AF12: =COUNTIF(Q13:S13,"(2) Duplexes") -> 0 | AG12: =COUNTIF(K13,"(3) Duplexes")+COUNTIF(Y13,"(3) Duplexes") -> 0 | AH12: =COUNTIF(Q13:S13,"(3) Duplexes") -> 0
A13: Medical Gas | B13: =IF(OR(SUM(H12:H18)=0,ISBLANK(SUM(H12:H18))),"",SUM(H12:H18)&" Outlets") | C13: =IF(OR(ISBLANK(B13),B13=""),0,VLOOKUP(B13,'Ondal Booms'!B:G,4,FALSE)) -> 0 | D13: =IF(OR(ISBLANK(B13),B13=""),0,VLOOKUP(B13,'Ondal Booms'!B:G,2,FALSE)) -> 0 | E13: =IF(OR(ISBLANK(B13),B13=""),0,VLOOKUP(B13,'Ondal Booms'!B:G,3,FALSE)) -> 0 | G13: Med Air Count | H13: =COUNTIF(K5:Y14,"Medical Air") -> 0 | J13: 5 Left | Z13: =15-COUNTIFS(K13:Y13,"") -> 0
A14: # of Outlet Circuits | C14: =IF(OR(ISBLANK(B14),B14=""),0,VLOOKUP(B14,'Ondal Booms'!B:G,4,FALSE)) -> 0 | D14: =IF(OR(ISBLANK(B14),B14=""),0,VLOOKUP(B14,'Ondal Booms'!B:G,2,FALSE)) -> 0 | E14: =IF(OR(ISBLANK(B14),B14=""),0,VLOOKUP(B14,'Ondal Booms'!B:G,3,FALSE)) -> 0 | G14: Nitrous Count | H14: =COUNTIF(K5:Y14,"Nitrous Oxide") -> 0 | J14: 5 Right | Z14: =15-COUNTIFS(K14:Y14,"") -> 0
A15: Shelf (500mm) | C15: =IF(OR(ISBLANK(B15),B15=""),0,VLOOKUP(B15,'Ondal Booms'!B:G,4,FALSE)) -> 0 | D15: =IF(OR(ISBLANK(B15),B15=""),0,VLOOKUP(B15,'Ondal Booms'!B:G,2,FALSE)) -> 0 | E15: =IF(OR(ISBLANK(B15),B15=""),0,VLOOKUP(B15,'Ondal Booms'!B:G,3,FALSE)) -> 0 | G15: WAGD Count | H15: =COUNTIF(K5:Y14,"WAGD") -> 0
A16: Shelf (750mm) | C16: =IF(OR(ISBLANK(B16),B16=""),0,VLOOKUP(B16,'Ondal Booms'!B:G,4,FALSE)) -> 0 | D16: =IF(OR(ISBLANK(B16),B16=""),0,VLOOKUP(B16,'Ondal Booms'!B:G,2,FALSE)) -> 0 | E16: =IF(OR(ISBLANK(B16),B16=""),0,VLOOKUP(B16,'Ondal Booms'!B:G,3,FALSE)) -> 0 | G16: Vacuum Count | H16: =COUNTIF(K5:Y14,"Vacuum") -> 0
A17: Accessory 1 | C17: =IF(OR(ISBLANK(B17),B17=""),0,VLOOKUP(B17,'Ondal Booms'!B:G,4,FALSE)) -> 0 | D17: =IF(OR(ISBLANK(B17),B17=""),0,VLOOKUP(B17,'Ondal Booms'!B:G,2,FALSE)) -> 0 | E17: =IF(OR(ISBLANK(B17),B17=""),0,VLOOKUP(B17,'Ondal Booms'!B:G,3,FALSE)) -> 0 | G17: Nitrogen Count | H17: =COUNTIF(K5:Y14,"Nitrogen") -> 0
A18: Accessory 2 | C18: =IF(OR(ISBLANK(B18),B18=""),0,VLOOKUP(B18,'Ondal Booms'!B:G,4,FALSE)) -> 0 | D18: =IF(OR(ISBLANK(B18),B18=""),0,VLOOKUP(B18,'Ondal Booms'!B:G,2,FALSE)) -> 0 | E18: =IF(OR(ISBLANK(B18),B18=""),0,VLOOKUP(B18,'Ondal Booms'!B:G,3,FALSE)) -> 0 | G18: CO2 Count | H18: =COUNTIF(K5:Y14,"Carbon Dioxide") -> 0
A19: Accessory 3 | C19: =IF(OR(ISBLANK(B19),B19=""),0,VLOOKUP(B19,'Ondal Booms'!B:G,4,FALSE)) -> 0 | D19: =IF(OR(ISBLANK(B19),B19=""),0,VLOOKUP(B19,'Ondal Booms'!B:G,2,FALSE)) -> 0 | E19: =IF(OR(ISBLANK(B19),B19=""),0,VLOOKUP(B19,'Ondal Booms'!B:G,3,FALSE)) -> 0
A20: Accessory 4 | C20: =IF(OR(ISBLANK(B20),B20=""),0,VLOOKUP(B20,'Ondal Booms'!B:G,4,FALSE)) -> 0 | D20: =IF(OR(ISBLANK(B20),B20=""),0,VLOOKUP(B20,'Ondal Booms'!B:G,2,FALSE)) -> 0 | E20: =IF(OR(ISBLANK(B20),B20=""),0,VLOOKUP(B20,'Ondal Booms'!B:G,3,FALSE)) -> 0
A21: Accessory 5 | C21: =IF(OR(ISBLANK(B21),B21=""),0,VLOOKUP(B21,'Ondal Booms'!B:G,4,FALSE)) -> 0 | D21: =IF(OR(ISBLANK(B21),B21=""),0,VLOOKUP(B21,'Ondal Booms'!B:G,2,FALSE)) -> 0 | E21: =IF(OR(ISBLANK(B21),B21=""),0,VLOOKUP(B21,'Ondal Booms'!B:G,3,FALSE)) -> 0
A22: Accessory 6 | C22: =IF(OR(ISBLANK(B22),B22=""),0,VLOOKUP(B22,'Ondal Booms'!B:G,4,FALSE)) -> 0 | D22: =IF(OR(ISBLANK(B22),B22=""),0,VLOOKUP(B22,'Ondal Booms'!B:G,2,FALSE)) -> 0 | E22: =IF(OR(ISBLANK(B22),B22=""),0,VLOOKUP(B22,'Ondal Booms'!B:G,3,FALSE)) -> 0
A23: Accessory 7 | C23: =IF(OR(ISBLANK(B23),B23=""),0,VLOOKUP(B23,'Ondal Booms'!B:G,4,FALSE)) -> 0 | D23: =IF(OR(ISBLANK(B23),B23=""),0,VLOOKUP(B23,'Ondal Booms'!B:G,2,FALSE)) -> 0 | E23: =IF(OR(ISBLANK(B23),B23=""),0,VLOOKUP(B23,'Ondal Booms'!B:G,3,FALSE)) -> 0
A25: Errors? | B25: =IF(OR(ISBLANK(B5),B5=""),"", IF(OR(AND(B11="200mm Service Head",SUM(Z7:Z14)>0),AND(B11="400mm Service Head",SUM(Z9:Z14)>0),AND(B11="600mm Service Head",SUM(Z11:Z14)>0),AND(B11="800mm Service Head",SUM(Z13:Z14)>0)),"Select Longer Service Head or Remove Services", IF(AND(RIGHT(B9,2)="XL",RIGHT(B8,2)<>"XL"),"BOTTOM XL ARM REQUIRES TOP XL ARM", IF(OR(ISBLANK(B6),ISBLANK(B7),ISBLANK(B8),ISBLANK(B9),ISBLANK(B10),ISBLANK(B11),ISBLANK(B15),ISBLANK(B16),ISBLANK(B14)),"Missing Selections for Configuration", IF(AND(B11="Large Monitor Carrier",B9<>"Spring Articulating"),"Large Monitor Requires Spring Bottom Arm", IF(OR(AND(RIGHT(B7,2)="XL",RIGHT(B8,2)<>"XL"),AND(RIGHT(B8,2)="XL",RIGHT(B7,2)<>"XL")),"Both Top Arm and Ceiling Flange Must Be XL", IF(COUNTIF(AE4:AH12,1)>1,"Mismatch Electrical Configuration", "")))))) )
C26: IMAGINE LIST | D26: ONDAL LIST | E26: ONDAL SALES
A27: Equipment List Price | B27: =IF(OR(B6="",ISBLANK(B6)),"NO CONFIGURATION SELECTED",C27) -> NO CONFIGURATION SELECTED | C27: =SUM(C5:C23) -> 0 | D27: =SUM(D5:D23) -> 0 | E27: =SUM(E5:E23) -> 0 | J27: ="<-- EXPAND TO SHOW OPTIONS / SERVICE HEAD" -> <-- EXPAND TO SHOW OPTIONS / SERVICE HEAD
AE28: =COUNTIF(K30,"(2) Duplexes")+COUNTIF(Y30,"(2) Duplexes") -> 0 | AF28: =COUNTIF(Q30:S30,"(2) Duplexes") -> 0 | AG28: =COUNTIF(K30,"(3) Duplexes")+COUNTIF(Y30,"(3) Duplexes") -> 0 | AH28: =COUNTIF(Q30:S30,"(3) Duplexes") -> 0
A29: BOOM (TANDEM 2ND ONLY) | B29: SELECTION | C29: IMAGINE LIST | D29: ONDAL LIST | E29: ONDAL COG | G29: HV Services | H29: Count | J29: Layer | K29: Selection | L29: FRONT | Q29: Selection | S29: Selection | T29: BACK | Y29: Selection
A30: Model | B30: =IF(OR(ISBLANK(B32),ISBLANK(B33)),"",IF(ISBLANK(B33),0,(VLOOKUP(B33,'Ondal Booms'!B:F,5,FALSE)))&IF(ISBLANK(B32),0,(VLOOKUP(B32,'Ondal Booms'!B:F,5,FALSE)))) | C30: =IF(OR(ISBLANK(B30),B30=""),0,VLOOKUP(B30,'Ondal Booms'!B:G,4,FALSE)) -> 0 | D30: =IF(OR(ISBLANK(B30),B30=""),0,VLOOKUP(B30,'Ondal Booms'!B:G,2,FALSE)) -> 0 | E30: =IF(OR(ISBLANK(B30),B30=""),0,VLOOKUP(B30,'Ondal Booms'!B:G,3,FALSE)) -> 0 | G30: Duplex Count | H30: =COUNTIF(K30:Y39,"(2) Duplexes")*2+COUNTIF(K30:Y39,"(3) Duplexes")*3 -> 0 | J30: 1 Left | Z30: =15-COUNTIFS(K30:Y30,"") -> 0
A31: Ceiling Flange | C31: =IF(OR(ISBLANK(B31),B31=""),0,VLOOKUP(B31,'Ondal Booms'!B:G,4,FALSE)) -> 0 | D31: =IF(OR(ISBLANK(B31),B31=""),0,VLOOKUP(B31,'Ondal Booms'!B:G,2,FALSE)) -> 0 | E31: =IF(OR(ISBLANK(B31),B31=""),0,VLOOKUP(B31,'Ondal Booms'!B:G,3,FALSE)) -> 0 | G31: LV Services | H31: Count | J31: 1 Right | Z31: =15-COUNTIFS(K31:Y31,"") -> 0 | AE31: =COUNTIF(K32,"(2) Duplexes")+COUNTIF(Y32,"(2) Duplexes") -> 0 | AF31: =COUNTIF(Q32:S32,"(2) Duplexes") -> 0 | AG31: =COUNTIF(K32,"(3) Duplexes")+COUNTIF(Y32,"(3) Duplexes") -> 0 | AH31: =COUNTIF(Q32:S32,"(3) Duplexes") -> 0
A32: Top Arm | C32: =IF(OR(ISBLANK(B32),B32=""),0,VLOOKUP(B32,'Ondal Booms'!B:G,4,FALSE)) -> 0 | D32: =IF(OR(ISBLANK(B32),B32=""),0,VLOOKUP(B32,'Ondal Booms'!B:G,2,FALSE)) -> 0 | E32: =IF(OR(ISBLANK(B32),B32=""),0,VLOOKUP(B32,'Ondal Booms'!B:G,3,FALSE)) -> 0 | G32: Data Count | H32: =(COUNTIF(K30:Y39,"Data")) -> 0 | J32: 2 Left | Z32: =15-COUNTIFS(K32:Y32,"") -> 0
A33: Bottom Arm | C33: =IF(OR(ISBLANK(B33),B33=""),0,VLOOKUP(B33,'Ondal Booms'!B:G,4,FALSE)) -> 0 | D33: =IF(OR(ISBLANK(B33),B33=""),0,VLOOKUP(B33,'Ondal Booms'!B:G,2,FALSE)) -> 0 | E33: =IF(OR(ISBLANK(B33),B33=""),0,VLOOKUP(B33,'Ondal Booms'!B:G,3,FALSE)) -> 0 | G33: Storz 4in1 Count | H33: =(COUNTIF(K30:Y39,"Storz 4in1")) -> 0 | J33: 2 Right | Z33: =15-COUNTIFS(K33:Y33,"") -> 0 | AE33: =COUNTIF(K34,"(2) Duplexes")+COUNTIF(Y34,"(2) Duplexes") -> 0 | AF33: =COUNTIF(Q34:S34,"(2) Duplexes") -> 0 | AG33: =COUNTIF(K34,"(3) Duplexes")+COUNTIF(Y34,"(3) Duplexes") -> 0 | AH33: =COUNTIF(Q34:S34,"(3) Duplexes") -> 0
A34: Column Tube | C34: =IF(OR(ISBLANK(B34),B34=""),0,VLOOKUP(B34,'Ondal Booms'!B:G,4,FALSE)) -> 0 | D34: =IF(OR(ISBLANK(B34),B34=""),0,VLOOKUP(B34,'Ondal Booms'!B:G,2,FALSE)) -> 0 | E34: =IF(OR(ISBLANK(B34),B34=""),0,VLOOKUP(B34,'Ondal Booms'!B:G,3,FALSE)) -> 0 | J34: 3 Left | Z34: =15-COUNTIFS(K34:Y34,"") -> 0
A35: Service Head | C35: =IF(OR(ISBLANK(B35),B35=""),0,VLOOKUP(B35,'Ondal Booms'!B:G,4,FALSE)) -> 0 | D35: =IF(OR(ISBLANK(B35),B35=""),0,VLOOKUP(B35,'Ondal Booms'!B:G,2,FALSE)) -> 0 | E35: =IF(OR(ISBLANK(B35),B35=""),0,VLOOKUP(B35,'Ondal Booms'!B:G,3,FALSE)) -> 0 | G35: Medical Gases | H35: Count | J35: 3 Right | Z35: =15-COUNTIFS(K35:Y35,"") -> 0 | AE35: =COUNTIF(K36,"(2) Duplexes")+COUNTIF(Y36,"(2) Duplexes") -> 0 | AF35: =COUNTIF(Q36:S36,"(2) Duplexes") -> 0 | AG35: =COUNTIF(K36,"(3) Duplexes")+COUNTIF(Y36,"(3) Duplexes") -> 0 | AH35: =COUNTIF(Q36:S36,"(3) Duplexes") -> 0
A36: Electrical | B36: =IF(OR(H30=0,ISBLANK(H30)),"",H30&" Duplexes") | C36: =IF(OR(ISBLANK(B36),B36=""),0,VLOOKUP(B36,'Ondal Booms'!B:G,4,FALSE)) -> 0 | D36: =IF(OR(ISBLANK(B36),B36=""),0,VLOOKUP(B36,'Ondal Booms'!B:G,2,FALSE)) -> 0 | E36: =IF(OR(ISBLANK(B36),B36=""),0,VLOOKUP(B36,'Ondal Booms'!B:G,3,FALSE)) -> 0 | G36: Oxygen Count | H36: =(COUNTIF(K30:Y39,"Oxygen")) -> 0 | J36: 4 Left | Z36: =15-COUNTIFS(K36:Y36,"") -> 0
A37: Medical Gas | B37: =IF(OR(SUM(H36:H42)=0,ISBLANK(SUM(H36:H42))),"",SUM(H36:H42)&" Outlets") | C37: =IF(OR(ISBLANK(B37),B37=""),0,VLOOKUP(B37,'Ondal Booms'!B:G,4,FALSE)) -> 0 | D37: =IF(OR(ISBLANK(B37),B37=""),0,VLOOKUP(B37,'Ondal Booms'!B:G,2,FALSE)) -> 0 | E37: =IF(OR(ISBLANK(B37),B37=""),0,VLOOKUP(B37,'Ondal Booms'!B:G,3,FALSE)) -> 0 | G37: Med Air Count | H37: =COUNTIF(K30:Y39,"Medical Air") -> 0 | J37: 4 Right | Z37: =15-COUNTIFS(K37:Y37,"") -> 0 | AE37: =COUNTIF(K38,"(2) Duplexes")+COUNTIF(Y38,"(2) Duplexes") -> 0 | AF37: =COUNTIF(Q38:S38,"(2) Duplexes") -> 0 | AG37: =COUNTIF(K38,"(3) Duplexes")+COUNTIF(Y38,"(3) Duplexes") -> 0 | AH37: =COUNTIF(Q38:S38,"(3) Duplexes") -> 0
A38: # of Outlet Circuits | C38: =IF(OR(ISBLANK(B38),B38=""),0,VLOOKUP(B38,'Ondal Booms'!B:G,4,FALSE)) -> 0 | D38: =IF(OR(ISBLANK(B38),B38=""),0,VLOOKUP(B38,'Ondal Booms'!B:G,2,FALSE)) -> 0 | E38: =IF(OR(ISBLANK(B38),B38=""),0,VLOOKUP(B38,'Ondal Booms'!B:G,3,FALSE)) -> 0 | G38: Nitrous Count | H38: =COUNTIF(K30:Y39,"Nitrous Oxide") -> 0 | J38: 5 Left | Z38: =15-COUNTIFS(K38:Y38,"") -> 0
A39: Shelf (500mm) | C39: =IF(OR(ISBLANK(B39),B39=""),0,VLOOKUP(B39,'Ondal Booms'!B:G,4,FALSE)) -> 0 | D39: =IF(OR(ISBLANK(B39),B39=""),0,VLOOKUP(B39,'Ondal Booms'!B:G,2,FALSE)) -> 0 | E39: =IF(OR(ISBLANK(B39),B39=""),0,VLOOKUP(B39,'Ondal Booms'!B:G,3,FALSE)) -> 0 | G39: WAGD Count | H39: =COUNTIF(K30:Y39,"WAGD") -> 0 | J39: 5 Right | Z39: =15-COUNTIFS(K39:Y39,"") -> 0
A40: Shelf (750mm) | C40: =IF(OR(ISBLANK(B40),B40=""),0,VLOOKUP(B40,'Ondal Booms'!B:G,4,FALSE)) -> 0 | D40: =IF(OR(ISBLANK(B40),B40=""),0,VLOOKUP(B40,'Ondal Booms'!B:G,2,FALSE)) -> 0 | E40: =IF(OR(ISBLANK(B40),B40=""),0,VLOOKUP(B40,'Ondal Booms'!B:G,3,FALSE)) -> 0 | G40: Vacuum Count | H40: =COUNTIF(K30:Y39,"Vacuum") -> 0
A41: Accessory 1 | C41: =IF(OR(ISBLANK(B41),B41=""),0,VLOOKUP(B41,'Ondal Booms'!B:G,4,FALSE)) -> 0 | D41: =IF(OR(ISBLANK(B41),B41=""),0,VLOOKUP(B41,'Ondal Booms'!B:G,2,FALSE)) -> 0 | E41: =IF(OR(ISBLANK(B41),B41=""),0,VLOOKUP(B41,'Ondal Booms'!B:G,3,FALSE)) -> 0 | G41: Nitrogen Count | H41: =COUNTIF(K30:Y39,"Nitrogen") -> 0
A42: Accessory 2 | C42: =IF(OR(ISBLANK(B42),B42=""),0,VLOOKUP(B42,'Ondal Booms'!B:G,4,FALSE)) -> 0 | D42: =IF(OR(ISBLANK(B42),B42=""),0,VLOOKUP(B42,'Ondal Booms'!B:G,2,FALSE)) -> 0 | E42: =IF(OR(ISBLANK(B42),B42=""),0,VLOOKUP(B42,'Ondal Booms'!B:G,3,FALSE)) -> 0 | G42: CO2 Count | H42: =COUNTIF(K30:Y39,"Carbon Dioxide") -> 0
A43: Accessory 3 | C43: =IF(OR(ISBLANK(B43),B43=""),0,VLOOKUP(B43,'Ondal Booms'!B:G,4,FALSE)) -> 0 | D43: =IF(OR(ISBLANK(B43),B43=""),0,VLOOKUP(B43,'Ondal Booms'!B:G,2,FALSE)) -> 0 | E43: =IF(OR(ISBLANK(B43),B43=""),0,VLOOKUP(B43,'Ondal Booms'!B:G,3,FALSE)) -> 0
A44: Accessory 4 | C44: =IF(OR(ISBLANK(B44),B44=""),0,VLOOKUP(B44,'Ondal Booms'!B:G,4,FALSE)) -> 0 | D44: =IF(OR(ISBLANK(B44),B44=""),0,VLOOKUP(B44,'Ondal Booms'!B:G,2,FALSE)) -> 0 | E44: =IF(OR(ISBLANK(B44),B44=""),0,VLOOKUP(B44,'Ondal Booms'!B:G,3,FALSE)) -> 0
A45: Accessory 5 | C45: =IF(OR(ISBLANK(B45),B45=""),0,VLOOKUP(B45,'Ondal Booms'!B:G,4,FALSE)) -> 0 | D45: =IF(OR(ISBLANK(B45),B45=""),0,VLOOKUP(B45,'Ondal Booms'!B:G,2,FALSE)) -> 0 | E45: =IF(OR(ISBLANK(B45),B45=""),0,VLOOKUP(B45,'Ondal Booms'!B:G,3,FALSE)) -> 0
A46: Accessory 6 | C46: =IF(OR(ISBLANK(B46),B46=""),0,VLOOKUP(B46,'Ondal Booms'!B:G,4,FALSE)) -> 0 | D46: =IF(OR(ISBLANK(B46),B46=""),0,VLOOKUP(B46,'Ondal Booms'!B:G,2,FALSE)) -> 0 | E46: =IF(OR(ISBLANK(B46),B46=""),0,VLOOKUP(B46,'Ondal Booms'!B:G,3,FALSE)) -> 0
A47: Accessory 7 | C47: =IF(OR(ISBLANK(B47),B47=""),0,VLOOKUP(B47,'Ondal Booms'!B:G,4,FALSE)) -> 0 | D47: =IF(OR(ISBLANK(B47),B47=""),0,VLOOKUP(B47,'Ondal Booms'!B:G,2,FALSE)) -> 0 | E47: =IF(OR(ISBLANK(B47),B47=""),0,VLOOKUP(B47,'Ondal Booms'!B:G,3,FALSE)) -> 0
A49: Errors? | B49: =IF(OR(ISBLANK(B30),B30=""),"", IF(OR(AND(B35="200mm Service Head",SUM(Z32:Z39)>0),AND(B35="400mm Service Head",SUM(Z34:Z39)>0),AND(B35="600mm Service Head",SUM(Z36:Z39)>0),AND(B35="800mm Service Head",SUM(Z38:Z39)>0)),"Select Longer Service Head or Remove Services", IF(AND(RIGHT(B33,2)="XL",RIGHT(B32,2)<>"XL"),"BOTTOM XL ARM REQUIRES TOP XL ARM", IF(OR(ISBLANK(#REF!),ISBLANK(B31),ISBLANK(B32),ISBLANK(B33),ISBLANK(B34),ISBLANK(B35),ISBLANK(B39),ISBLANK(B40),ISBLANK(B38)),"Missing Selections for Configuration", IF(AND(B35="Large Monitor Carrier",B33<>"Spring Articulating"),"Large Monitor Requires Spring Bottom Arm", IF(OR(AND(RIGHT(B31,2)="XL",RIGHT(B32,2)<>"XL"),AND(RIGHT(B32,2)="XL",RIGHT(B31,2)<>"XL")),"Both Top Arm and Ceiling Flange Must Be XL", IF(COUNTIF(AE29:AH37,1)>1,"Mismatch Electrical Configuration", "")))))) )
C50: IMAGINE LIST | D50: ONDAL LIST | E50: ONDAL SALES
A51: Equipment List Price | B51: =IF(OR(B30="",ISBLANK(B30)),"NO CONFIGURATION SELECTED",C51) -> NO CONFIGURATION SELECTED | C51: =SUM(C30:C47) -> 0 | D51: =SUM(D30:D47) -> 0 | E51: =SUM(E30:E47) -> 0 | J51: ="<-- EXPAND TO SHOW OPTIONS / SERVICE HEAD" -> <-- EXPAND TO SHOW OPTIONS / SERVICE HEAD
A53: LIGHT (SINGLE OR TANDEM) | B53: SELECTION | C53: IMAGINE LIST | D53: SIMEON LIST | E53: SIMEON COG
A54: Model | B54: =IF(AND(ISBLANK(B57),ISBLANK(B58),ISBLANK(B59)),"", IF(B55="Upgrade Only","UPGRADE", IF(RIGHT(B57,4)="(3P)","(3P) ","")& IF(ISBLANK(B57),"",VLOOKUP(B57,'Simeon Lights'!C:H,2,FALSE))& IF(ISBLANK(B58),""," / "&VLOOKUP(B58,'Simeon Lights'!C:H,2,FALSE))& IF(ISBLANK(B59),""," / "&VLOOKUP(B59,'Simeon Lights'!C:H,2,FALSE)))) | C54: =IF(ISBLANK(B57),0,(VLOOKUP(B54,'Simeon Lights'!C:J,6,FALSE))) -> 0 | D54: =IF(ISBLANK(B57),0,(VLOOKUP(B54,'Simeon Lights'!C:J,4,FALSE))) -> 0 | E54: =IF(ISBLANK(B57),0,(VLOOKUP(B54,'Simeon Lights'!C:J,5,FALSE))) -> 0
A55: Ceiling Cover | C55: =IF(ISBLANK(B55),0,VLOOKUP(B55,'Simeon Lights'!C:J,6,FALSE)) -> 0 | D55: =IF(ISBLANK(B55),0,VLOOKUP(B55,'Simeon Lights'!C:J,4,FALSE)) -> 0 | E55: =IF(ISBLANK(B55),0,VLOOKUP(B55,'Simeon Lights'!C:J,5,FALSE)) -> 0
A56: Ceiling Drop Tube | C56: =IF(ISBLANK(B56),0,VLOOKUP(B56,'Simeon Lights'!C:J,6,FALSE)) -> 0 | D56: =IF(ISBLANK(B56),0,VLOOKUP(B56,'Simeon Lights'!C:J,4,FALSE)) -> 0 | E56: =IF(ISBLANK(B56),0,VLOOKUP(B56,'Simeon Lights'!C:J,5,FALSE)) -> 0
A57: Arm 1 (Top Arm) | C57: =IF(ISBLANK(B57),0,VLOOKUP(B57,'Simeon Lights'!C:J,6,FALSE)) -> 0 | D57: =IF(ISBLANK(B57),0,VLOOKUP(B57,'Simeon Lights'!C:J,4,FALSE)) -> 0 | E57: =IF(ISBLANK(B57),0,VLOOKUP(B57,'Simeon Lights'!C:J,5,FALSE)) -> 0
A58: Arm 2 | C58: =IF(ISBLANK(B58),0,VLOOKUP(B58,'Simeon Lights'!C:J,6,FALSE)) -> 0 | D58: =IF(ISBLANK(B58),0,VLOOKUP(B58,'Simeon Lights'!C:J,4,FALSE)) -> 0 | E58: =IF(ISBLANK(B58),0,VLOOKUP(B58,'Simeon Lights'!C:J,5,FALSE)) -> 0
A59: Arm 3 | C59: =IF(ISBLANK(B59),0,VLOOKUP(B59,'Simeon Lights'!C:J,6,FALSE)) -> 0 | D59: =IF(ISBLANK(B59),0,VLOOKUP(B59,'Simeon Lights'!C:J,4,FALSE)) -> 0 | E59: =IF(ISBLANK(B59),0,VLOOKUP(B59,'Simeon Lights'!C:J,5,FALSE)) -> 0
A60: Wall Control | C60: =IF(ISBLANK(B60),0,VLOOKUP(B60,'Simeon Lights'!C:J,6,FALSE)) -> 0 | D60: =IF(ISBLANK(B60),0,VLOOKUP(B60,'Simeon Lights'!C:J,4,FALSE)) -> 0 | E60: =IF(ISBLANK(B60),0,VLOOKUP(B60,'Simeon Lights'!C:J,5,FALSE)) -> 0
A61: Integration Control | C61: =IF(ISBLANK(B61),0,VLOOKUP(B61,'Simeon Lights'!C:J,6,FALSE)) -> 0 | D61: =IF(ISBLANK(B61),0,VLOOKUP(B61,'Simeon Lights'!C:J,4,FALSE)) -> 0 | E61: =IF(ISBLANK(B61),0,VLOOKUP(B61,'Simeon Lights'!C:J,5,FALSE)) -> 0
A62: In-Light Camera | C62: =IF(ISBLANK(B62),0,VLOOKUP(B62,'Simeon Lights'!C:J,6,FALSE)) -> 0 | D62: =IF(ISBLANK(B62),0,VLOOKUP(B62,'Simeon Lights'!C:J,4,FALSE)) -> 0 | E62: =IF(ISBLANK(B62),0,VLOOKUP(B62,'Simeon Lights'!C:J,5,FALSE)) -> 0
A63: Disposable Adpaters | C63: =IF(ISBLANK(B63),0,VLOOKUP(B63,'Simeon Lights'!C:J,6,FALSE)) -> 0 | D63: =IF(ISBLANK(B63),0,VLOOKUP(B63,'Simeon Lights'!C:J,4,FALSE)) -> 0 | E63: =IF(ISBLANK(B63),0,VLOOKUP(B63,'Simeon Lights'!C:J,5,FALSE)) -> 0
A65: Errors? | B65: =IF(AND(ISBLANK(B57),ISBLANK(B58),ISBLANK(B59)),"", IF(AND(ISBLANK(B57),B58<>""),"ARM 1 MISSING", IF(AND(ISBLANK(B57),B59<>""),"ARM 1 MISSING", IF(ISBLANK(B58)&ISBLANK(B59)="TRUEFALSE","ARM 2 MISSING", IF(AND(B57<>"",B58="32in Flat Panel",B59<>""),"FP CANNOT BE MIDDLE ARM", IF(OR(ISBLANK(B55),ISBLANK(B56),ISBLANK(B60),ISBLANK(B61),ISBLANK(B62),ISBLANK(B63)),"Missing Selections",""))))))
C66: IMAGINE LIST | D66: SIMEON LIST | E66: SIMEON COG
A67: Equipment List Price | B67: =IF(OR(ISBLANK(B57),ISBLANK(B58)&ISBLANK(B59)="TRUEFALSE"),"NO CONFIGURATION SELECTED",IF(B65<>"","ERROR IN CONFIGURATION",IF(B57="",0,SUM(C54:C63)))) -> NO CONFIGURATION SELECTED | C67: =SUM(C54:C65) -> 0 | D67: =SUM(D54:D65) -> 0 | E67: =SUM(E54:E65) -> 0 | J67: ="<-- EXPAND TO SHOW OPTIONS" -> <-- EXPAND TO SHOW OPTIONS
B69: CONFIGRATION LIST PRICE | E69: TOTAL COG
A70: Total List Price | B70: =IF(OR(B27="Error in Configuration",B27="No Configuration Selected"),0,B27)+IF(OR(B51="Error in Configuration",B51="No Configuration Selected"),0,B51)+IF(OR(B67="Error in Configuration",B67="No Configuration Selected"),0,B67) -> 0 | E70: =SUM(E67,E51,E27) -> 0

Sheet Config #7
A1: CONFIGURATION #7 | B1: DESCRIPTION
A2: Configuration Name
A4: BOOM (SINGLE OR TANDEM) | B4: SELECTION | C4: IMAGINE LIST | D4: ONDAL LIST | E4: ONDAL COG | G4: HV Services | H4: Count | J4: Layer | K4: Selection | L4: FRONT | Q4: Selection | S4: Selection | T4: BACK | Y4: Selection | AE4: =COUNTIF(K5,"(2) Duplexes")+COUNTIF(Y5,"(2) Duplexes") -> 0 | AF4: =COUNTIF(Q5:S5,"(2) Duplexes") -> 0 | AG4: =COUNTIF(K5,"(3) Duplexes")+COUNTIF(Y5,"(3) Duplexes") -> 0 | AH4: =COUNTIF(Q5:S5,"(3) Duplexes") -> 0
A5: Model | B5: =IF(OR(ISBLANK(B8),ISBLANK(B9)),"",IF(ISBLANK(B9),0,(VLOOKUP(B9,'Ondal Booms'!B:F,5,FALSE)))&IF(ISBLANK(B8),0,(VLOOKUP(B8,'Ondal Booms'!B:F,5,FALSE)))) | C5: =IF(OR(ISBLANK(B5),B5=""),0,VLOOKUP(B5,'Ondal Booms'!B:G,4,FALSE)) -> 0 | D5: =IF(OR(ISBLANK(B5),B5=""),0,VLOOKUP(B5,'Ondal Booms'!B:G,2,FALSE)) -> 0 | E5: =IF(OR(ISBLANK(B5),B5=""),0,VLOOKUP(B5,'Ondal Booms'!B:G,3,FALSE)) -> 0 | G5: Duplex Count | H5: =COUNTIF(K5:Y14,"(2) Duplexes")*2+COUNTIF(K5:Y14,"(3) Duplexes")*3 -> 0 | J5: 1 Left | Z5: =15-COUNTIFS(K5:Y5,"") -> 0
A6: Ceiling Cover | C6: =IF(OR(ISBLANK(B6),B6=""),0,VLOOKUP(B6,'Ondal Booms'!B:G,4,FALSE)) -> 0 | D6: =IF(OR(ISBLANK(B6),B6=""),0,VLOOKUP(B6,'Ondal Booms'!B:G,2,FALSE)) -> 0 | E6: =IF(OR(ISBLANK(B6),B6=""),0,VLOOKUP(B6,'Ondal Booms'!B:G,3,FALSE)) -> 0 | J6: 1 Right | Z6: =15-COUNTIFS(K6:Y6,"") -> 0 | AE6: =COUNTIF(K7,"(2) Duplexes")+COUNTIF(Y7,"(2) Duplexes") -> 0 | AF6: =COUNTIF(Q7:S7,"(2) Duplexes") -> 0 | AG6: =COUNTIF(K7,"(3) Duplexes")+COUNTIF(Y7,"(3) Duplexes") -> 0 | AH6: =COUNTIF(Q7:S7,"(3) Duplexes") -> 0
A7: Ceiling Flange | C7: =IF(OR(ISBLANK(B7),B7=""),0,VLOOKUP(B7,'Ondal Booms'!B:G,4,FALSE)) -> 0 | D7: =IF(OR(ISBLANK(B7),B7=""),0,VLOOKUP(B7,'Ondal Booms'!B:G,2,FALSE)) -> 0 | E7: =IF(OR(ISBLANK(B7),B7=""),0,VLOOKUP(B7,'Ondal Booms'!B:G,3,FALSE)) -> 0 | G7: LV Services | H7: Count | J7: 2 Left | Z7: =15-COUNTIFS(K7:Y7,"") -> 0
A8: Top Arm | C8: =IF(OR(ISBLANK(B8),B8=""),0,VLOOKUP(B8,'Ondal Booms'!B:G,4,FALSE)) -> 0 | D8: =IF(OR(ISBLANK(B8),B8=""),0,VLOOKUP(B8,'Ondal Booms'!B:G,2,FALSE)) -> 0 | E8: =IF(OR(ISBLANK(B8),B8=""),0,VLOOKUP(B8,'Ondal Booms'!B:G,3,FALSE)) -> 0 | G8: Data Count | H8: =(COUNTIF(K5:Y14,"Data")) -> 0 | J8: 2 Right | Z8: =15-COUNTIFS(K8:Y8,"") -> 0 | AE8: =COUNTIF(K9,"(2) Duplexes")+COUNTIF(Y9,"(2) Duplexes") -> 0 | AF8: =COUNTIF(Q9:S9,"(2) Duplexes") -> 0 | AG8: =COUNTIF(K9,"(3) Duplexes")+COUNTIF(Y9,"(3) Duplexes") -> 0 | AH8: =COUNTIF(Q9:S9,"(3) Duplexes") -> 0
A9: Bottom Arm | C9: =IF(OR(ISBLANK(B9),B9=""),0,VLOOKUP(B9,'Ondal Booms'!B:G,4,FALSE)) -> 0 | D9: =IF(OR(ISBLANK(B9),B9=""),0,VLOOKUP(B9,'Ondal Booms'!B:G,2,FALSE)) -> 0 | E9: =IF(OR(ISBLANK(B9),B9=""),0,VLOOKUP(B9,'Ondal Booms'!B:G,3,FALSE)) -> 0 | G9: Storz 4in1 Count | H9: =(COUNTIF(K5:Y14,"Storz 4in1")) -> 0 | J9: 3 Left | Z9: =15-COUNTIFS(K9:Y9,"") -> 0
A10: Column Tube | C10: =IF(OR(ISBLANK(B10),B10=""),0,VLOOKUP(B10,'Ondal Booms'!B:G,4,FALSE)) -> 0 | D10: =IF(OR(ISBLANK(B10),B10=""),0,VLOOKUP(B10,'Ondal Booms'!B:G,2,FALSE)) -> 0 | E10: =IF(OR(ISBLANK(B10),B10=""),0,VLOOKUP(B10,'Ondal Booms'!B:G,3,FALSE)) -> 0 | J10: 3 Right | Z10: =15-COUNTIFS(K10:Y10,"") -> 0 | AE10: =COUNTIF(K11,"(2) Duplexes")+COUNTIF(Y11,"(2) Duplexes") -> 0 | AF10: =COUNTIF(Q11:S11,"(2) Duplexes") -> 0 | AG10: =COUNTIF(K11,"(3) Duplexes")+COUNTIF(Y11,"(3) Duplexes") -> 0 | AH10: =COUNTIF(Q11:S11,"(3) Duplexes") -> 0
A11: Service Head | C11: =IF(OR(ISBLANK(B11),B11=""),0,VLOOKUP(B11,'Ondal Booms'!B:G,4,FALSE)) -> 0 | D11: =IF(OR(ISBLANK(B11),B11=""),0,VLOOKUP(B11,'Ondal Booms'!B:G,2,FALSE)) -> 0 | E11: =IF(OR(ISBLANK(B11),B11=""),0,VLOOKUP(B11,'Ondal Booms'!B:G,3,FALSE)) -> 0 | G11: Medical Gases | H11: Count | J11: 4 Left | Z11: =15-COUNTIFS(K11:Y11,"") -> 0
A12: Electrical | B12: =IF(OR(H5=0,ISBLANK(H5)),"",H5&" Duplexes") | C12: =IF(OR(ISBLANK(B12),B12=""),0,VLOOKUP(B12,'Ondal Booms'!B:G,4,FALSE)) -> 0 | D12: =IF(OR(ISBLANK(B12),B12=""),0,VLOOKUP(B12,'Ondal Booms'!B:G,2,FALSE)) -> 0 | E12: =IF(OR(ISBLANK(B12),B12=""),0,VLOOKUP(B12,'Ondal Booms'!B:G,3,FALSE)) -> 0 | G12: Oxygen Count | H12: =(COUNTIF(K5:Y14,"Oxygen")) -> 0 | J12: 4 Right | Z12: =15-COUNTIFS(K12:Y12,"") -> 0 | AE12: =COUNTIF(K13,"(2) Duplexes")+COUNTIF(Y13,"(2) Duplexes") -> 0 | AF12: =COUNTIF(Q13:S13,"(2) Duplexes") -> 0 | AG12: =COUNTIF(K13,"(3) Duplexes")+COUNTIF(Y13,"(3) Duplexes") -> 0 | AH12: =COUNTIF(Q13:S13,"(3) Duplexes") -> 0
A13: Medical Gas | B13: =IF(OR(SUM(H12:H18)=0,ISBLANK(SUM(H12:H18))),"",SUM(H12:H18)&" Outlets") | C13: =IF(OR(ISBLANK(B13),B13=""),0,VLOOKUP(B13,'Ondal Booms'!B:G,4,FALSE)) -> 0 | D13: =IF(OR(ISBLANK(B13),B13=""),0,VLOOKUP(B13,'Ondal Booms'!B:G,2,FALSE)) -> 0 | E13: =IF(OR(ISBLANK(B13),B13=""),0,VLOOKUP(B13,'Ondal Booms'!B:G,3,FALSE)) -> 0 | G13: Med Air Count | H13: =COUNTIF(K5:Y14,"Medical Air") -> 0 | J13: 5 Left | Z13: =15-COUNTIFS(K13:Y13,"") -> 0
A14: # of Outlet Circuits | C14: =IF(OR(ISBLANK(B14),B14=""),0,VLOOKUP(B14,'Ondal Booms'!B:G,4,FALSE)) -> 0 | D14: =IF(OR(ISBLANK(B14),B14=""),0,VLOOKUP(B14,'Ondal Booms'!B:G,2,FALSE)) -> 0 | E14: =IF(OR(ISBLANK(B14),B14=""),0,VLOOKUP(B14,'Ondal Booms'!B:G,3,FALSE)) -> 0 | G14: Nitrous Count | H14: =COUNTIF(K5:Y14,"Nitrous Oxide") -> 0 | J14: 5 Right | Z14: =15-COUNTIFS(K14:Y14,"") -> 0
A15: Shelf (500mm) | C15: =IF(OR(ISBLANK(B15),B15=""),0,VLOOKUP(B15,'Ondal Booms'!B:G,4,FALSE)) -> 0 | D15: =IF(OR(ISBLANK(B15),B15=""),0,VLOOKUP(B15,'Ondal Booms'!B:G,2,FALSE)) -> 0 | E15: =IF(OR(ISBLANK(B15),B15=""),0,VLOOKUP(B15,'Ondal Booms'!B:G,3,FALSE)) -> 0 | G15: WAGD Count | H15: =COUNTIF(K5:Y14,"WAGD") -> 0
A16: Shelf (750mm) | C16: =IF(OR(ISBLANK(B16),B16=""),0,VLOOKUP(B16,'Ondal Booms'!B:G,4,FALSE)) -> 0 | D16: =IF(OR(ISBLANK(B16),B16=""),0,VLOOKUP(B16,'Ondal Booms'!B:G,2,FALSE)) -> 0 | E16: =IF(OR(ISBLANK(B16),B16=""),0,VLOOKUP(B16,'Ondal Booms'!B:G,3,FALSE)) -> 0 | G16: Vacuum Count | H16: =COUNTIF(K5:Y14,"Vacuum") -> 0
A17: Accessory 1 | C17: =IF(OR(ISBLANK(B17),B17=""),0,VLOOKUP(B17,'Ondal Booms'!B:G,4,FALSE)) -> 0 | D17: =IF(OR(ISBLANK(B17),B17=""),0,VLOOKUP(B17,'Ondal Booms'!B:G,2,FALSE)) -> 0 | E17: =IF(OR(ISBLANK(B17),B17=""),0,VLOOKUP(B17,'Ondal Booms'!B:G,3,FALSE)) -> 0 | G17: Nitrogen Count | H17: =COUNTIF(K5:Y14,"Nitrogen") -> 0
A18: Accessory 2 | C18: =IF(OR(ISBLANK(B18),B18=""),0,VLOOKUP(B18,'Ondal Booms'!B:G,4,FALSE)) -> 0 | D18: =IF(OR(ISBLANK(B18),B18=""),0,VLOOKUP(B18,'Ondal Booms'!B:G,2,FALSE)) -> 0 | E18: =IF(OR(ISBLANK(B18),B18=""),0,VLOOKUP(B18,'Ondal Booms'!B:G,3,FALSE)) -> 0 | G18: CO2 Count | H18: =COUNTIF(K5:Y14,"Carbon Dioxide") -> 0
A19: Accessory 3 | C19: =IF(OR(ISBLANK(B19),B19=""),0,VLOOKUP(B19,'Ondal Booms'!B:G,4,FALSE)) -> 0 | D19: =IF(OR(ISBLANK(B19),B19=""),0,VLOOKUP(B19,'Ondal Booms'!B:G,2,FALSE)) -> 0 | E19: =IF(OR(ISBLANK(B19),B19=""),0,VLOOKUP(B19,'Ondal Booms'!B:G,3,FALSE)) -> 0
A20: Accessory 4 | C20: =IF(OR(ISBLANK(B20),B20=""),0,VLOOKUP(B20,'Ondal Booms'!B:G,4,FALSE)) -> 0 | D20: =IF(OR(ISBLANK(B20),B20=""),0,VLOOKUP(B20,'Ondal Booms'!B:G,2,FALSE)) -> 0 | E20: =IF(OR(ISBLANK(B20),B20=""),0,VLOOKUP(B20,'Ondal Booms'!B:G,3,FALSE)) -> 0
A21: Accessory 5 | C21: =IF(OR(ISBLANK(B21),B21=""),0,VLOOKUP(B21,'Ondal Booms'!B:G,4,FALSE)) -> 0 | D21: =IF(OR(ISBLANK(B21),B21=""),0,VLOOKUP(B21,'Ondal Booms'!B:G,2,FALSE)) -> 0 | E21: =IF(OR(ISBLANK(B21),B21=""),0,VLOOKUP(B21,'Ondal Booms'!B:G,3,FALSE)) -> 0
A22: Accessory 6 | C22: =IF(OR(ISBLANK(B22),B22=""),0,VLOOKUP(B22,'Ondal Booms'!B:G,4,FALSE)) -> 0 | D22: =IF(OR(ISBLANK(B22),B22=""),0,VLOOKUP(B22,'Ondal Booms'!B:G,2,FALSE)) -> 0 | E22: =IF(OR(ISBLANK(B22),B22=""),0,VLOOKUP(B22,'Ondal Booms'!B:G,3,FALSE)) -> 0
A23: Accessory 7 | C23: =IF(OR(ISBLANK(B23),B23=""),0,VLOOKUP(B23,'Ondal Booms'!B:G,4,FALSE)) -> 0 | D23: =IF(OR(ISBLANK(B23),B23=""),0,VLOOKUP(B23,'Ondal Booms'!B:G,2,FALSE)) -> 0 | E23: =IF(OR(ISBLANK(B23),B23=""),0,VLOOKUP(B23,'Ondal Booms'!B:G,3,FALSE)) -> 0
A25: Errors? | B25: =IF(OR(ISBLANK(B5),B5=""),"", IF(OR(AND(B11="200mm Service Head",SUM(Z7:Z14)>0),AND(B11="400mm Service Head",SUM(Z9:Z14)>0),AND(B11="600mm Service Head",SUM(Z11:Z14)>0),AND(B11="800mm Service Head",SUM(Z13:Z14)>0)),"Select Longer Service Head or Remove Services", IF(AND(RIGHT(B9,2)="XL",RIGHT(B8,2)<>"XL"),"BOTTOM XL ARM REQUIRES TOP XL ARM", IF(OR(ISBLANK(B6),ISBLANK(B7),ISBLANK(B8),ISBLANK(B9),ISBLANK(B10),ISBLANK(B11),ISBLANK(B15),ISBLANK(B16),ISBLANK(B14)),"Missing Selections for Configuration", IF(AND(B11="Large Monitor Carrier",B9<>"Spring Articulating"),"Large Monitor Requires Spring Bottom Arm", IF(OR(AND(RIGHT(B7,2)="XL",RIGHT(B8,2)<>"XL"),AND(RIGHT(B8,2)="XL",RIGHT(B7,2)<>"XL")),"Both Top Arm and Ceiling Flange Must Be XL", IF(COUNTIF(AE4:AH12,1)>1,"Mismatch Electrical Configuration", "")))))) )
C26: IMAGINE LIST | D26: ONDAL LIST | E26: ONDAL SALES
A27: Equipment List Price | B27: =IF(OR(B6="",ISBLANK(B6)),"NO CONFIGURATION SELECTED",C27) -> NO CONFIGURATION SELECTED | C27: =SUM(C5:C23) -> 0 | D27: =SUM(D5:D23) -> 0 | E27: =SUM(E5:E23) -> 0 | J27: ="<-- EXPAND TO SHOW OPTIONS / SERVICE HEAD" -> <-- EXPAND TO SHOW OPTIONS / SERVICE HEAD
AE28: =COUNTIF(K30,"(2) Duplexes")+COUNTIF(Y30,"(2) Duplexes") -> 0 | AF28: =COUNTIF(Q30:S30,"(2) Duplexes") -> 0 | AG28: =COUNTIF(K30,"(3) Duplexes")+COUNTIF(Y30,"(3) Duplexes") -> 0 | AH28: =COUNTIF(Q30:S30,"(3) Duplexes") -> 0
A29: BOOM (TANDEM 2ND ONLY) | B29: SELECTION | C29: IMAGINE LIST | D29: ONDAL LIST | E29: ONDAL COG | G29: HV Services | H29: Count | J29: Layer | K29: Selection | L29: FRONT | Q29: Selection | S29: Selection | T29: BACK | Y29: Selection
A30: Model | B30: =IF(OR(ISBLANK(B32),ISBLANK(B33)),"",IF(ISBLANK(B33),0,(VLOOKUP(B33,'Ondal Booms'!B:F,5,FALSE)))&IF(ISBLANK(B32),0,(VLOOKUP(B32,'Ondal Booms'!B:F,5,FALSE)))) | C30: =IF(OR(ISBLANK(B30),B30=""),0,VLOOKUP(B30,'Ondal Booms'!B:G,4,FALSE)) -> 0 | D30: =IF(OR(ISBLANK(B30),B30=""),0,VLOOKUP(B30,'Ondal Booms'!B:G,2,FALSE)) -> 0 | E30: =IF(OR(ISBLANK(B30),B30=""),0,VLOOKUP(B30,'Ondal Booms'!B:G,3,FALSE)) -> 0 | G30: Duplex Count | H30: =COUNTIF(K30:Y39,"(2) Duplexes")*2+COUNTIF(K30:Y39,"(3) Duplexes")*3 -> 0 | J30: 1 Left | Z30: =15-COUNTIFS(K30:Y30,"") -> 0
A31: Ceiling Flange | C31: =IF(OR(ISBLANK(B31),B31=""),0,VLOOKUP(B31,'Ondal Booms'!B:G,4,FALSE)) -> 0 | D31: =IF(OR(ISBLANK(B31),B31=""),0,VLOOKUP(B31,'Ondal Booms'!B:G,2,FALSE)) -> 0 | E31: =IF(OR(ISBLANK(B31),B31=""),0,VLOOKUP(B31,'Ondal Booms'!B:G,3,FALSE)) -> 0 | G31: LV Services | H31: Count | J31: 1 Right | Z31: =15-COUNTIFS(K31:Y31,"") -> 0 | AE31: =COUNTIF(K32,"(2) Duplexes")+COUNTIF(Y32,"(2) Duplexes") -> 0 | AF31: =COUNTIF(Q32:S32,"(2) Duplexes") -> 0 | AG31: =COUNTIF(K32,"(3) Duplexes")+COUNTIF(Y32,"(3) Duplexes") -> 0 | AH31: =COUNTIF(Q32:S32,"(3) Duplexes") -> 0
A32: Top Arm | C32: =IF(OR(ISBLANK(B32),B32=""),0,VLOOKUP(B32,'Ondal Booms'!B:G,4,FALSE)) -> 0 | D32: =IF(OR(ISBLANK(B32),B32=""),0,VLOOKUP(B32,'Ondal Booms'!B:G,2,FALSE)) -> 0 | E32: =IF(OR(ISBLANK(B32),B32=""),0,VLOOKUP(B32,'Ondal Booms'!B:G,3,FALSE)) -> 0 | G32: Data Count | H32: =(COUNTIF(K30:Y39,"Data")) -> 0 | J32: 2 Left | Z32: =15-COUNTIFS(K32:Y32,"") -> 0
A33: Bottom Arm | C33: =IF(OR(ISBLANK(B33),B33=""),0,VLOOKUP(B33,'Ondal Booms'!B:G,4,FALSE)) -> 0 | D33: =IF(OR(ISBLANK(B33),B33=""),0,VLOOKUP(B33,'Ondal Booms'!B:G,2,FALSE)) -> 0 | E33: =IF(OR(ISBLANK(B33),B33=""),0,VLOOKUP(B33,'Ondal Booms'!B:G,3,FALSE)) -> 0 | G33: Storz 4in1 Count | H33: =(COUNTIF(K30:Y39,"Storz 4in1")) -> 0 | J33: 2 Right | Z33: =15-COUNTIFS(K33:Y33,"") -> 0 | AE33: =COUNTIF(K34,"(2) Duplexes")+COUNTIF(Y34,"(2) Duplexes") -> 0 | AF33: =COUNTIF(Q34:S34,"(2) Duplexes") -> 0 | AG33: =COUNTIF(K34,"(3) Duplexes")+COUNTIF(Y34,"(3) Duplexes") -> 0 | AH33: =COUNTIF(Q34:S34,"(3) Duplexes") -> 0
A34: Column Tube | C34: =IF(OR(ISBLANK(B34),B34=""),0,VLOOKUP(B34,'Ondal Booms'!B:G,4,FALSE)) -> 0 | D34: =IF(OR(ISBLANK(B34),B34=""),0,VLOOKUP(B34,'Ondal Booms'!B:G,2,FALSE)) -> 0 | E34: =IF(OR(ISBLANK(B34),B34=""),0,VLOOKUP(B34,'Ondal Booms'!B:G,3,FALSE)) -> 0 | J34: 3 Left | Z34: =15-COUNTIFS(K34:Y34,"") -> 0
A35: Service Head | C35: =IF(OR(ISBLANK(B35),B35=""),0,VLOOKUP(B35,'Ondal Booms'!B:G,4,FALSE)) -> 0 | D35: =IF(OR(ISBLANK(B35),B35=""),0,VLOOKUP(B35,'Ondal Booms'!B:G,2,FALSE)) -> 0 | E35: =IF(OR(ISBLANK(B35),B35=""),0,VLOOKUP(B35,'Ondal Booms'!B:G,3,FALSE)) -> 0 | G35: Medical Gases | H35: Count | J35: 3 Right | Z35: =15-COUNTIFS(K35:Y35,"") -> 0 | AE35: =COUNTIF(K36,"(2) Duplexes")+COUNTIF(Y36,"(2) Duplexes") -> 0 | AF35: =COUNTIF(Q36:S36,"(2) Duplexes") -> 0 | AG35: =COUNTIF(K36,"(3) Duplexes")+COUNTIF(Y36,"(3) Duplexes") -> 0 | AH35: =COUNTIF(Q36:S36,"(3) Duplexes") -> 0
