Workbook

Sheet 3D Compatible Boom Pricing
A1: Part Number | B1: Configuration | D1: Imagine List Price | E1: Imagine Sales Price | K1: Boom Options | U1: Ceiling Flange (E)
A2: 211-101-001 | B2: Powered Boom, Top Arm 600mm, SH 200mm | D2: 32984.453 | E2: 16492.227 | G2: Sections | H2: Part Number | J2: Boom Discount | L2: Model (A) | M2: Service Head | U2: for standard models
A3: 211-102-001 | B3: Powered Boom, Top Arm 800mm, SH 200mm | D3: 32984.453 | E3: 16492.227 | G3: Powered Model | H3: 211-XXX-XXX | J3: 0.5 | K3: Standard Top Arm | L3: Powered | N3: 600 | O3: 800 | P3: 1000 | Q3: 1200 | R3: 1400 | S3: 1600 | U3: 100mm | V3: 0 | Y3: Key | AC3: Price Increase | AD3: 600 | AE3: 800 | AF3: 1000 | AG3: 1200 | AH3: 1400 | AI3: 1600
A4: 211-103-001 | B4: Powered Boom, Top Arm 1000mm, SH 200mm | D4: 32984.453 | E4: 16492.227 | G4: Spring Model | H4: 212-XXX-XXX | K4: Powered Bottom Arm | L4: 35398.8 | M4: 200 | N4: 35398.8 | O4: 35398.8 | P4: 35398.8 | Q4: 35398.8 | R4: na | S4: na | U4: 300mm | V4: 251.81 | Y4: Model | AA4: A | AC4: 200 | AH4: 1591.55 | AI4: 3291.97
A5: 211-104-001 | B5: Powered Boom, Top Arm 1200mm, SH 200mm | D5: 32984.453 | E5: 16492.227 | G5: Fixed Model | H5: 213-XXX-XXX | K5: (articulating - 1000mm) | M5: 400 | N5: 37373.71 | O5: 37373.71 | P5: 37373.71 | Q5: 37373.71 | R5: na | S5: na | U5: 500mm | V5: 493.73 | Y5: Service Head Length | AA5: B | AC5: 400 | AD5: 1974.91 | AE5: 1974.91 | AF5: 1974.91 | AG5: 1974.91 | AH5: 3566.86 | AI5: 5266.88
A6: 211-101-002 | B6: Powered Boom, Top Arm 600mm, SH 400mm | D6: 34959.36 | E6: 17479.68 | G6: Large Monitor Mount | H6: 212-XXX-XXX-301 | M6: 600 | N6: 39353.55 | O6: 39353.55 | P6: 39353.55 | Q6: 39353.55 | R6: na | S6: na | U6: for XL+ models | Y6: Top Arm Length | AC6: 600 | AD6: 3954.75 | AE6: 3954.75 | AF6: 3954.75 | AG6: 3954.75 | AH6: 5546.3 | AI6: 7246.72
A7: 211-102-002 | B7: Powered Boom, Top Arm 800mm, SH 400mm | D7: 34959.36 | E7: 17479.68 | G7: Top Arm (600mm-1200mm) | H7: XXX-101-XXX (etc) | M7: 800 | N7: 41392.67 | O7: 41392.67 | P7: 41392.67 | Q7: 41392.67 | R7: na | S7: na | U7: 100mm | V7: 0 | Y7: Ceiling Flange | AA7: D | AC7: 800 | AD7: 5993.87 | AE7: 5993.87 | AF7: 5993.87 | AG7: 5993.87 | AH7: 7585.42 | AI7: 9285.84
A8: 211-103-002 | B8: Powered Boom, Top Arm 1000mm, SH 400mm | D8: 34959.36 | E8: 17479.68 | G8: XL Top Arm | H8: XXX-111-XXX (etc) | M8: 1000 | N8: 43426.83 | O8: 43426.83 | P8: 43426.83 | Q8: 43426.83 | R8: na | S8: na | U8: 300mm | V8: 508.53 | Y8: Optional Services | AA8: C | AC8: 1000 | AD8: 8028.03 | AE8: 8028.03 | AF8: 8028.03 | AG8: 8028.03 | AH8: 9619.58 | AI8: 11320
A9: 211-104-002 | B9: Powered Boom, Top Arm 1200mm, SH 400mm | D9: 34959.36 | E9: 17479.68 | G9: XL Bottom Arm | H9: XXX-XXX-101-XXX (etc) | U9: 500mm | V9: 1214.59 | Y9: Light Options | AA9: E
A10: 211-101-003 | B10: Powered Boom, Top Arm 600mm, SH 600mm | D10: 36939.2 | E10: 18469.6 | G10: Service Head (200mm - 1000mm) | H10: XXX-XXX-001 (etc) | K10: XL Top Arm | L10: Powered XL | N10: 600 | O10: 800 | P10: 1000 | Q10: 1200 | R10: 1400 | S10: 1600 | Y10: Optional Light Accessories | AA10: F
A11: 211-102-003 | B11: Powered Boom, Top Arm 800mm, SH 600mm | D11: 36939.2 | E11: 18469.6 | G11: Accessories | H11: 600-XXX | K11: Powered Bottom Arm | L11: 39326.43 | M11: 200 | N11: 39326.43 | O11: 39326.43 | P11: 39326.43 | Q11: 39326.43 | R11: 40917.98 | S11: 42618.4 | Y11: Not in the Tool
A12: 211-103-003 | B12: Powered Boom, Top Arm 1000mm, SH 600mm | D12: 36939.2 | E12: 18469.6 | K12: (articulating - 1000mm) | M12: 400 | N12: 41301.34 | O12: 41301.34 | P12: 41301.34 | Q12: 41301.34 | R12: 42893.29 | S12: 44593.31 | U12: Services / Accessories (D - if applicable) | W12: optional
A13: 211-104-003 | B13: Powered Boom, Top Arm 1200mm, SH 600mm | D13: 36939.2 | E13: 18469.6 | M13: 600 | N13: 43281.18 | O13: 43281.18 | P13: 43281.18 | Q13: 43281.18 | R13: 44872.73 | S13: 46573.15 | U13: Med-Gas | V13: 790 | W13: per gas addition | Y13: Total Price = A + B + C + D + E + F
A14: 211-101-004 | B14: Powered Boom, Top Arm 600mm, SH 800mm | D14: 38978.32 | E14: 19489.16 | M14: 800 | N14: 45320.3 | O14: 45320.3 | P14: 45320.3 | Q14: 45320.3 | R14: 46911.85 | S14: 48612.27 | U14: Electrical (2 duplexes) | V14: 543.12 | W14: per layer
A15: 211-102-004 | B15: Powered Boom, Top Arm 800mm, SH 800mm | D15: 38978.32 | E15: 19489.16 | G15: Shipping & Installation | M15: 1000 | N15: 47354.46 | O15: 47354.46 | P15: 47354.46 | Q15: 47354.46 | R15: 48946.01 | S15: 50646.43 | U15: Electrical (3 duplexes) | V15: 997.33 | W15: per layer
A16: 211-103-004 | B16: Powered Boom, Top Arm 1000mm, SH 800mm | D16: 38978.32 | E16: 19489.16 | U16: Data | V16: 0
A17: 211-104-004 | B17: Powered Boom, Top Arm 1200mm, SH 800mm | D17: 38978.32 | E17: 19489.16 | K17: Standard Top Arm | L17: Spring | N17: 600 | O17: 800 | P17: 1000 | Q17: 1200 | R17: 1400 | S17: 1600 | U17: Nitrogen Regulator | V17: 2105.92 | W17: per boom
A18: 211-101-005 | B18: Powered Boom, Top Arm 600mm, SH 1000mm | D18: 41012.48 | E18: 20506.24 | K18: Spring Bottom Arm | L18: 33594.72 | M18: 200 | N18: 33594.72 | O18: 33594.72 | P18: 33594.72 | Q18: 33594.72 | R18: na | S18: na | U18: Data Pass thru | V18: 770.21333 | W18: per boom
A19: 211-102-005 | B19: Powered Boom, Top Arm 800mm, SH 1000mm | D19: 41012.48 | E19: 20506.24 | K19: (articulating - 1000mm) | M19: 400 | N19: 35569.63 | O19: 35569.63 | P19: 35569.63 | Q19: 35569.63 | R19: na | S19: na | U19: Tandem Mount with 1 future boom option | V19: 3393.2067 | W19: per mount
A20: 211-103-005 | B20: Powered Boom, Top Arm 1000mm, SH 1000mm | D20: 41012.48 | E20: 20506.24 | M20: 600 | N20: 37549.47 | O20: 37549.47 | P20: 37549.47 | Q20: 37549.47 | R20: na | S20: na | U20: Rails
A21: 211-104-005 | B21: Powered Boom, Top Arm 1200mm, SH 1000mm | D21: 41012.48 | E21: 20506.24 | M21: 800 | N21: 39588.59 | O21: 39588.59 | P21: 39588.59 | Q21: 39588.59 | R21: na | S21: na | U21: Shelfs | V21: 1344.6222 | W21: per shelf
M22: 1000 | N22: 41622.75 | O22: 41622.75 | P22: 41622.75 | Q22: 41622.75 | R22: na | S22: na
A23: 211-111-001 | B23: Powered Boom, XL Top Arm 600mm, SH 200mm | D23: 36912.08 | E23: 18456.04
A24: 211-112-001 | B24: Powered Boom, XL Top Arm 800mm, SH 200mm | D24: 36912.08 | E24: 18456.04 | K24: XL Top Arm | L24: Spring XL | N24: 600 | O24: 800 | P24: 1000 | Q24: 1200 | R24: 1400 | S24: 1600
A25: 211-113-001 | B25: Powered Boom, XL Top Arm 1000mm, SH 200mm | D25: 36912.08 | E25: 18456.04 | K25: Spring Bottom Arm | L25: 38315.52 | M25: 200 | N25: 38315.52 | O25: 38315.52 | P25: 38315.52 | Q25: 38315.52 | R25: 39907.07 | S25: 41607.49
A26: 211-114-001 | B26: Powered Boom, XL Top Arm 1200mm, SH 200mm | D26: 36912.08 | E26: 18456.04 | K26: (articulating - 1000mm) | M26: 400 | N26: 40290.43 | O26: 40290.43 | P26: 40290.43 | Q26: 40290.43 | R26: 41882.38 | S26: 43582.4
A27: 211-115-001 | B27: Powered Boom, XL Top Arm 1400mm, SH 200mm | D27: 38503.627 | E27: 19251.813 | M27: 600 | N27: 42270.27 | O27: 42270.27 | P27: 42270.27 | Q27: 42270.27 | R27: 43861.82 | S27: 45562.24
A28: 211-116-001 | B28: Powered Boom, XL Top Arm 1600mm, SH 200mm | D28: 40204.053 | E28: 20102.027 | M28: 800 | N28: 44309.39 | O28: 44309.39 | P28: 44309.39 | Q28: 44309.39 | R28: 45900.94 | S28: 47601.36
A29: 211-111-002 | B29: Powered Boom, XL Top Arm 600mm, SH 400mm | D29: 38886.987 | E29: 19443.493 | M29: 1000 | N29: 46343.55 | O29: 46343.55 | P29: 46343.55 | Q29: 46343.55 | R29: 47935.1 | S29: 49635.52
A30: 211-112-002 | B30: Powered Boom, XL Top Arm 800mm, SH 400mm | D30: 38886.987 | E30: 19443.493
A31: 211-113-002 | B31: Powered Boom, XL Top Arm 1000mm, SH 400mm | D31: 38886.987 | E31: 19443.493 | K31: Standard Top Arm | L31: Fixed | N31: 600 | O31: 800 | P31: 1000 | Q31: 1200 | R31: 1400 | S31: 1600 | U31: Incorporate "sales price" and discounted List price
A32: 211-114-002 | B32: Powered Boom, XL Top Arm 1200mm, SH 400mm | D32: 38886.987 | E32: 19443.493 | K32: Standard Fixeed Arm (1000mm) | L32: 23781.02 | M32: 200 | N32: 23781.02 | O32: 23781.02 | P32: 23781.02 | Q32: 23781.02 | R32: na | S32: na
A33: 211-115-002 | B33: Powered Boom, XL Top Arm 1400mm, SH 400mm | D33: 40478.533 | E33: 20239.267 | M33: 400 | N33: 25755.93 | O33: 25755.93 | P33: 25755.93 | Q33: 25755.93 | R33: na | S33: na
A34: 211-116-002 | B34: Powered Boom, XL Top Arm 1600mm, SH 400mm | D34: 42178.96 | E34: 21089.48 | M34: 600 | N34: 27735.77 | O34: 27735.77 | P34: 27735.77 | Q34: 27735.77 | R34: na | S34: na
A35: 211-111-003 | B35: Powered Boom, XL Top Arm 600mm, SH 600mm | D35: 40866.827 | E35: 20433.413 | M35: 800 | N35: 29774.89 | O35: 29774.89 | P35: 29774.89 | Q35: 29774.89 | R35: na | S35: na
A36: 211-112-003 | B36: Powered Boom, XL Top Arm 800mm, SH 600mm | D36: 40866.827 | E36: 20433.413 | M36: 1000 | N36: 31809.05 | O36: 31809.05 | P36: 31809.05 | Q36: 31809.05 | R36: na | S36: na
A37: 211-113-003 | B37: Powered Boom, XL Top Arm 1000mm, SH 600mm | D37: 40866.827 | E37: 20433.413
A38: 211-114-003 | B38: Powered Boom, XL Top Arm 1200mm, SH 600mm | D38: 40866.827 | E38: 20433.413 | K38: XL Top Arm | L38: Fixed XL | N38: 600 | O38: 800 | P38: 1000 | Q38: 1200 | R38: 1400 | S38: 1600
A39: 211-115-003 | B39: Powered Boom, XL Top Arm 1400mm, SH 600mm | D39: 42458.373 | E39: 21229.187 | K39: Standard Fixeed Arm (1000mm) | L39: 27382.03 | M39: 200 | N39: 27382.03 | O39: 27382.03 | P39: 27382.03 | Q39: 27382.03 | R39: 28973.58 | S39: 30674
A40: 211-116-003 | B40: Powered Boom, XL Top Arm 1600mm, SH 600mm | D40: 44158.8 | E40: 22079.4 | M40: 400 | N40: 29356.94 | O40: 29356.94 | P40: 29356.94 | Q40: 29356.94 | R40: 30948.89 | S40: 32648.91
A41: 211-111-004 | B41: Powered Boom, XL Top Arm 600mm, SH 800mm | D41: 42905.947 | E41: 21452.973 | M41: 600 | N41: 31336.78 | O41: 31336.78 | P41: 31336.78 | Q41: 31336.78 | R41: 32928.33 | S41: 34628.75
A42: 211-112-004 | B42: Powered Boom, XL Top Arm 800mm, SH 800mm | D42: 42905.947 | E42: 21452.973 | M42: 800 | N42: 33375.9 | O42: 33375.9 | P42: 33375.9 | Q42: 33375.9 | R42: 34967.45 | S42: 36667.87
A43: 211-113-004 | B43: Powered Boom, XL Top Arm 1000mm, SH 800mm | D43: 42905.947 | E43: 21452.973 | M43: 1000 | N43: 35410.06 | O43: 35410.06 | P43: 35410.06 | Q43: 35410.06 | R43: 37001.61 | S43: 38702.03
A44: 211-114-004 | B44: Powered Boom, XL Top Arm 1200mm, SH 800mm | D44: 42905.947 | E44: 21452.973
A45: 211-115-004 | B45: Powered Boom, XL Top Arm 1400mm, SH 800mm | D45: 44497.493 | E45: 22248.747 | K45: XXL Top Arm | L45: Fixed XXL | N45: 600 | O45: 800 | P45: 1000 | Q45: 1200 | R45: 1400 | S45: 1600
A46: 211-116-004 | B46: Powered Boom, XL Top Arm 1600mm, SH 800mm | D46: 46197.92 | E46: 23098.96 | K46: Standard Fixeed Arm (1000mm) | L46: 31047.26 | M46: 200 | N46: 31047.26 | O46: 31047.26 | P46: 31047.26 | Q46: 31047.26 | R46: 32638.81 | S46: 34339.23
A47: 211-111-005 | B47: Powered Boom, XL Top Arm 600mm, SH 1000mm | D47: 44940.107 | E47: 22470.053 | M47: 400 | N47: 33022.17 | O47: 33022.17 | P47: 33022.17 | Q47: 33022.17 | R47: 34614.12 | S47: 36314.14
A48: 211-112-005 | B48: Powered Boom, XL Top Arm 800mm, SH 1000mm | D48: 44940.107 | E48: 22470.053 | M48: 600 | N48: 35002.01 | O48: 35002.01 | P48: 35002.01 | Q48: 35002.01 | R48: 36593.56 | S48: 38293.98
A49: 211-113-005 | B49: Powered Boom, XL Top Arm 1000mm, SH 1000mm | D49: 44940.107 | E49: 22470.053 | M49: 800 | N49: 37041.13 | O49: 37041.13 | P49: 37041.13 | Q49: 37041.13 | R49: 38632.68 | S49: 40333.1
A50: 211-114-005 | B50: Powered Boom, XL Top Arm 1200mm, SH 1000mm | D50: 44940.107 | E50: 22470.053 | M50: 1000 | N50: 39075.29 | O50: 39075.29 | P50: 39075.29 | Q50: 39075.29 | R50: 40666.84 | S50: 42367.26
A51: 211-115-005 | B51: Powered Boom, XL Top Arm 1400mm, SH 1000mm | D51: 46531.653 | E51: 23265.827
A52: 211-116-005 | B52: Powered Boom, XL Top Arm 1600mm, SH 1000mm | D52: 48232.08 | E52: 24116.04 | K52: XL Top Arm | L52: Large Monitor | N52: 600 | O52: 800 | P52: 1000 | Q52: 1200 | R52: 1400 | S52: 1600
K53: Spring Bottom Arm | L53: 48126.24 | N53: 48126.24 | O53: 48126.24 | P53: 48126.24 | Q53: 48126.24 | R53: 49717.79 | S53: 51418.21
A54: 212-101-001 | B54: Spring Boom, Top Arm 600mm, SH 200mm | D54: 31180.373 | E54: 15590.187 | K54: (articulating - 1000mm)
A55: 212-102-001 | B55: Spring Boom, Top Arm 800mm, SH 200mm | D55: 31180.373 | E55: 15590.187
A56: 212-103-001 | B56: Spring Boom, Top Arm 1000mm, SH 200mm | D56: 31180.373 | E56: 15590.187
A57: 212-104-001 | B57: Spring Boom, Top Arm 1200mm, SH 200mm | D57: 31180.373 | E57: 15590.187
A58: 212-101-002 | B58: Spring Boom, Top Arm 600mm, SH 400mm | D58: 33155.28 | E58: 16577.64
A59: 212-102-002 | B59: Spring Boom, Top Arm 800mm, SH 400mm | D59: 33155.28 | E59: 16577.64
A60: 212-103-002 | B60: Spring Boom, Top Arm 1000mm, SH 400mm | D60: 33155.28 | E60: 16577.64
A61: 212-104-002 | B61: Spring Boom, Top Arm 1200mm, SH 400mm | D61: 33155.28 | E61: 16577.64
A62: 212-101-003 | B62: Spring Boom, Top Arm 600mm, SH 600mm | D62: 35135.12 | E62: 17567.56
A63: 212-102-003 | B63: Spring Boom, Top Arm 800mm, SH 600mm | D63: 35135.12 | E63: 17567.56
A64: 212-103-003 | B64: Spring Boom, Top Arm 1000mm, SH 600mm | D64: 35135.12 | E64: 17567.56
A65: 212-104-003 | B65: Spring Boom, Top Arm 1200mm, SH 600mm | D65: 35135.12 | E65: 17567.56
A66: 212-101-004 | B66: Spring Boom, Top Arm 600mm, SH 800mm | D66: 37174.24 | E66: 18587.12
... A493: 213-112-111-005 | B493: Fixed Boom, XL Top 800mm, XL Bottom Arm 600mm, SH 1000mm | D493: 36663.6 | E493: 18331.8
A494: 213-113-111-005 | B494: Fixed Boom, XL Top 1000mm, XL Bottom Arm 600mm, SH 1000mm | D494: 36663.6 | E494: 18331.8 | K494: 0
A495: 213-114-111-005 | B495: Fixed Boom, XL Top 1200mm, XL Bottom Arm 600mm, SH 1000mm | D495: 36663.6 | E495: 18331.8 | K495: 0
A496: 213-115-111-005 | B496: Fixed Boom, XL Top 1400mm, XL Bottom Arm 600mm, SH 1000mm | D496: 38255.147 | E496: 19127.573 | K496: 0
A497: 213-116-111-005 | B497: Fixed Boom, XL Top 1600mm, XL Bottom Arm 600mm, SH 1000mm | D497: 39955.573 | E497: 19977.787 | K497: 0
A498: 213-111-112-001 | B498: Fixed Boom, XL Top 600mm, XL Bottom Arm 800mm, SH 200mm | D498: 28632.907 | E498: 14316.453 | K498: 0
A499: 213-112-112-001 | B499: Fixed Boom, XL Top 800mm, XL Bottom Arm 800mm, SH 200mm | D499: 28632.907 | E499: 14316.453
A500: 213-113-112-001 | B500: Fixed Boom, XL Top 1000mm, XL Bottom Arm 800mm, SH 200mm | D500: 28632.907 | E500: 14316.453 | K500: 0
A501: 213-114-112-001 | B501: Fixed Boom, XL Top 1200mm, XL Bottom Arm 800mm, SH 200mm | D501: 28632.907 | E501: 14316.453 | K501: 0
A502: 213-115-112-001 | B502: Fixed Boom, XL Top 1400mm, XL Bottom Arm 800mm, SH 200mm | D502: 30224.453 | E502: 15112.227 | K502: 0
A503: 213-116-112-001 | B503: Fixed Boom, XL Top 1600mm, XL Bottom Arm 800mm, SH 200mm | D503: 31924.88 | E503: 15962.44 | K503: 0
A504: 213-111-112-002 | B504: Fixed Boom, XL Top 600mm, XL Bottom Arm 800mm, SH 400mm | D504: 30607.813 | E504: 15303.907 | K504: 0
A505: 213-112-112-002 | B505: Fixed Boom, XL Top 800mm, XL Bottom Arm 800mm, SH 400mm | D505: 30607.813 | E505: 15303.907 | K505: 0
A506: 213-113-112-002 | B506: Fixed Boom, XL Top 1000mm, XL Bottom Arm 800mm, SH 400mm | D506: 30607.813 | E506: 15303.907 | K506: 0
A507: 213-114-112-002 | B507: Fixed Boom, XL Top 1200mm, XL Bottom Arm 800mm, SH 400mm | D507: 30607.813 | E507: 15303.907 | K507: 0
A508: 213-115-112-002 | B508: Fixed Boom, XL Top 1400mm, XL Bottom Arm 800mm, SH 400mm | D508: 32199.36 | E508: 16099.68 | K508: 0
A509: 213-116-112-002 | B509: Fixed Boom, XL Top 1600mm, XL Bottom Arm 800mm, SH 400mm | D509: 33899.787 | E509: 16949.893 | K509: 0
A510: 213-111-112-003 | B510: Fixed Boom, XL Top 600mm, XL Bottom Arm 800mm, SH 600mm | D510: 32587.653 | E510: 16293.827 | K510: 0
A511: 213-112-112-003 | B511: Fixed Boom, XL Top 800mm, XL Bottom Arm 800mm, SH 600mm | D511: 32587.653 | E511: 16293.827 | K511: 0
... A529: 213-112-113-001 | B529: Fixed Boom, XL Top 800mm, XL Bottom Arm 1000mm, SH 200mm | D529: 28632.907 | E529: 14316.453 | K529: 0
A530: 213-113-113-001 | B530: Fixed Boom, XL Top 1000mm, XL Bottom Arm 1000mm, SH 200mm | D530: 28632.907 | E530: 14316.453
A531: 213-114-113-001 | B531: Fixed Boom, XL Top 1200mm, XL Bottom Arm 1000mm, SH 200mm | D531: 28632.907 | E531: 14316.453 | K531: 0
A532: 213-115-113-001 | B532: Fixed Boom, XL Top 1400mm, XL Bottom Arm 1000mm, SH 200mm | D532: 30224.453 | E532: 15112.227 | K532: 0
A533: 213-116-113-001 | B533: Fixed Boom, XL Top 1600mm, XL Bottom Arm 1000mm, SH 200mm | D533: 31924.88 | E533: 15962.44 | K533: 0
A534: 213-111-113-002 | B534: Fixed Boom, XL Top 600mm, XL Bottom Arm 1000mm, SH 400mm | D534: 30607.813 | E534: 15303.907 | K534: 0
A535: 213-112-113-002 | B535: Fixed Boom, XL Top 800mm, XL Bottom Arm 1000mm, SH 400mm | D535: 30607.813 | E535: 15303.907 | K535: 0
A536: 213-113-113-002 | B536: Fixed Boom, XL Top 1000mm, XL Bottom Arm 1000mm, SH 400mm | D536: 30607.813 | E536: 15303.907 | K536: 0
A537: 213-114-113-002 | B537: Fixed Boom, XL Top 1200mm, XL Bottom Arm 1000mm, SH 400mm | D537: 30607.813 | E537: 15303.907 | K537: 0
A538: 213-115-113-002 | B538: Fixed Boom, XL Top 1400mm, XL Bottom Arm 1000mm, SH 400mm | D538: 32199.36 | E538: 16099.68 | K538: 0
A539: 213-116-113-002 | B539: Fixed Boom, XL Top 1600mm, XL Bottom Arm 1000mm, SH 400mm | D539: 33899.787 | E539: 16949.893 | K539: 0
A540: 213-111-113-003 | B540: Fixed Boom, XL Top 600mm, XL Bottom Arm 1000mm, SH 600mm | D540: 32587.653 | E540: 16293.827 | K540: 0
A541: 213-112-113-003 | B541: Fixed Boom, XL Top 800mm, XL Bottom Arm 1000mm, SH 600mm | D541: 32587.653 | E541: 16293.827 | K541: 0
A542: 213-113-113-003 | B542: Fixed Boom, XL Top 1000mm, XL Bottom Arm 1000mm, SH 600mm | D542: 32587.653 | E542: 16293.827 | K542: 0
... A560: 213-113-114-001 | B560: Fixed Boom, XL Top 1000mm, XL Bottom Arm 1200mm, SH 200mm | D560: 28632.907 | E560: 14316.453 | K560: 0
...

Sheet 3D Compatible Light Pricing
A1: Part Number | B1: Configuration | C1: Current 3D Tool Config (Top to bottom) | D1: Imagine List Price | E1: Imagine Sales Price | G1: Sections | H1: Part Number
A2: 111-001111 | B2: 7000 - LED | C2: U|ONE | D2: 37407.7 | E2: =D2*$H$11 -> 18703.85 | G2: 7000/ U|ONE Lights and all variations | H2: 111
A3: 111-001112 | B3: 7000 - LED / LED | C3: U|ONE, U|ONE | D3: 73942.55 | E3: =D3*$H$11 -> 36971.275 | G3: No light configs (not including booms) | H3: 112
A4: 111-001113 | B4: 7000 - LED / LED / LED | C4: U|ONE, U|ONE, U|ONE | D4: 106014.52 | E4: =D4*$H$11 -> 53007.258 | G4: 8000/ U|002 Lights and all variations | H4: 113
A5: 111-001114 | B5: 7000 - LED / FP | C5: U|ONE, Flat Panel | D5: 54751.183 | E5: =D5*$H$11 -> 27375.592 | G5: Sim.Flex | H5: 114
A6: 111-001115 | B6: 7000 - FP / LED | C6: Flat Panel, U|ONE | D6: 54376.533 | E6: =D6*$H$11 -> 27188.267 | G6: Drop Down Options | H6: 115
A7: 111-001116 | B7: 7000 - LED / LED / FP | C7: U|ONE, U|ONE, Flat Panel | D7: 89254.35 | E7: =D7*$H$11 -> 44627.175 | G7: Light Exchange | H7: 116
A8: 111-001117 | B8: 7000 - LED / LS | C8: U|ONE, Lead Shield | D8: 63174.183 | E8: =D8*$H$11 -> 31587.092 | G8: Shipping & Installation | H8: 117
A9: 111-001118 | B9: 7000 - LED / LED / LS | C9: U|ONE, U|ONE, Lead Shield | D9: 95246.15 | E9: =D9*$H$11 -> 47623.075
A10: 111-001119 | B10: 7000 LC - LED | C10: U|ONE (Low Ceiling) | D10: 39936.433 | E10: =D10*$H$11 -> 19968.217 | H10: Light Discount
A11: 111-001120 | B11: 7000 LC - LED / LED | C11: U|ONE (Low Ceiling), U|ONE (Low Ceiling) | D11: 79000.017 | E11: =D11*$H$11 -> 39500.008 | H11: 0.5
A12: 111-001121 | B12: 7000 LC - LED / LED / LED | C12: U|ONE (Low Ceiling), U|ONE (Low Ceiling), U|ONE (Low Ceiling) | D12: 113600.72 | E12: =D12*$H$11 -> 56800.358
A13: 111-001122 | B13: 7000 LC - LED / FP | C13: U|ONE (Low Ceiling), Flat Panel | D13: 57279.917 | E13: =D13*$H$11 -> 28639.958
A14: 111-001123 | B14: 7000 LC - FP / LED | C14: Flat Panel, U|ONE (Low Ceiling) | D14: 56905.267 | E14: =D14*$H$11 -> 28452.633
A15: 111-001124 | B15: 7000 LC - LED / LED / FP | C15: U|ONE (Low Ceiling), U|ONE (Low Ceiling), Flat Panel | D15: 94311.817 | E15: =D15*$H$11 -> 47155.908
A16: 111-001125 | B16: 7000 LC - LED / LS | C16: U|ONE (Low Ceiling), Lead Sheild | D16: 65702.917 | E16: =D16*$H$11 -> 32851.458
A17: 111-001126 | B17: 7000 LC - LED / LED / LS | C17: U|ONE (Low Ceiling), U|ONE (Low Ceiling), Lead Sheild | D17: 100303.62 | E17: =D17*$H$11 -> 50151.808
A18: 112-001111 | B18: No Lights - FP | C18: Flat Panel | D18: 20611 | E18: =D18*$H$11 -> 10305.5
A19: 112-001112 | B19: No Lights - LS | C19: Lead Sheild | D19: 26639.333 | E19: =D19*$H$11 -> 13319.667
A20: 112-001113 | B20: No Lights - FP / FP | C20: Flat Panel, Flat Panel | D20: 38481.933 | E20: =D20*$H$11 -> 19240.967
A21: 112-001114 | B21: No Lights - LS / LS | C21: Lead Sheild, Lead Sheild | D21: 52405.817 | E21: =D21*$H$11 -> 26202.908
A22: 112-001115 | B22: No Lights - FP / LS | C22: Flat Panel, Lead Sheild | D22: 43608.167 | E22: =D22*$H$11 -> 21804.083
A23: 112-001116 | B23: No Lights - LS / FP | C23: Lead Sheild, Flat Panel | D23: 43982.817 | E23: =D23*$H$11 -> 21991.408
... A56: 113-001126 | B56: Future Light LC - LED / LED / LS | C56: U|003 LC , U|003 LC , Lead Sheild | D56: 0 | E56: =D56*$H$11 -> 0
A59: Additional Model Options (Price should be assigned to sim.flex models in addition to model price) | D59: Imagine List Price | E59: Imagine Sales Price
A60: 114-001111 | B60: Sim.Flex (1 Arm) | C60: Assign when sim.flex option is selected (with 1 arm) | D60: 5833.3333 | E60: =D60*$H$11 -> 2916.6667
A61: 114-001112 | B61: Sim.Flex (2 Arms) | C61: Assign when sim.flex option is selected (with 2 arms) | D61: 9166.6667 | E61: =D61*$H$11 -> 4583.3333
A62: 114-001113 | B62: Sim.Flex (3 Arms) | C62: Assign when sim.flex option is selected (with 3 arms) | D62: 12500 | E62: =D62*$H$11 -> 6250
E63: =D63*$H$11 -> 0
A64: Additional Options (Drop Down) | G64: Example
A65: Part Number | B65: Option | D65: Imagine List Price | E65: Imagine Sales Price | G65: Light Single / Tandem | H65: Options
B66: Ceiling Cover | G66: Ceiling Cover
A67: 115-001111 | B67: Single Light (Standard) | D67: 1563.2167 | E67: =D67*$H$11 -> 781.60833 | G67: Wall Control
A68: 115-001112 | B68: Single Light (Universal) | D68: 3398.9667 | E68: =D68*$H$11 -> 1699.4833 | G68: Integration Control
A69: 115-001113 | B69: Tandem (1st Position) | D69: 5807.6533 | E69: =D69*$H$11 -> 2903.8267 | G69: In-Light Camera
A70: 115-001114 | B70: Tandem (2nd Position) | D70: 0 | E70: =D70*$H$11 -> 0 | G70: Disposable Adpaters
B71: Wall Control
B72: Wall Control in Seperate Config | D72: 0 | E72: =D72*$H$11 -> 0
A73: 115-001115 | B73: Wall Control (Single) | D73: 4710.4167 | E73: =D73*$H$11 -> 2355.2083
A74: 115-001116 | B74: Wall Control (Dual) | D74: 2146.85 | E74: =D74*$H$11 -> 1073.425
A75: 115-001117 | B75: Wall Control (Triple) | D75: 3205.7 | E75: =D75*$H$11 -> 1602.85
A76: 115-001118 | B76: Wall Control (Touch) | D76: 4854.2333 | E76: =D76*$H$11 -> 2427.1167
A77: 115-001119 | B77: Wall Control (Single w/ Cam) | D77: 3324.75 | E77: =D77*$H$11 -> 1662.375
A78: 115-001120 | B78: Wall Control (Dual w/ Cam) | D78: 4666.9667 | E78: =D78*$H$11 -> 2333.4833
A79: 115-001121 | B79: Wall Control (Triple w/ Cam) | D79: 6171.0667 | E79: =D79*$H$11 -> 3085.5333
B80: Integration Control
B81: None | D81: 0 | E81: =D81*$H$11 -> 0
A82: 115-001122 | B82: Storz Integration Control | D82: 3082.9833 | E82: =D82*$H$11 -> 1541.4917
B83: In-Light Camera
B84: None | D84: 0 | E84: =D84*$H$11 -> 0
A85: 115-001123 | B85: Wired Prep | D85: 5661.2 | E85: =D85*$H$11 -> 2830.6
A86: 115-001124 | B86: Wired | D86: 30796.98 | E86: =D86*$H$11 -> 15398.49
A87: 115-001125 | B87: Wireless | D87: 43025.2 | E87: =D87*$H$11 -> 21512.6
B88: Disposable Adapter
B89: None | D89: 0 | E89: =D89*$H$11 -> 0
A90: 115-001126 | B90: Screw-On | D90: 420 | E90: =D90*$H$11 -> 210
A91: 115-001127 | B91: Slip-On | D91: 1488.9333 | E91: =D91*$H$11 -> 744.46667
B92: Exchange
B93: None | D93: 0 | E93: =D93*$H$11 -> 0
A94: 116-001111 | B94: Yes, 1 Light Exchange | D94: 25000 | E94: =D94*$H$11 -> 12500
A95: 116-001112 | B95: Yes, 2 Light Exchange | D95: 50000 | E95: =D95*$H$11 -> 25000
A96: 116-001113 | B96: Yes, 3 Light Exchange | D96: 75000 | E96: =D96*$H$11 -> 37500
A98: Additional Line Items | D98: Imagine List Price | E98: Imagine Sales Price
A99: 117-001111 | B99: Installation (Lights) | D99: 3000 | E99: =D99*(1-0.5) -> 1500
A100: 117-001112 | B100: Shipping (Lights) | D100: 1000 | E100: =D100*(1-0.5) -> 500

Sheet 2025_03_28 3D Boom Pricing
A1: Part Number | B1: Configuration | D1: Imagine List Price | E1: Imagine Sales Price | K1: Boom Options | U1: Ceiling Flange (E)
A2: 211-101-001 | B2: Powered Boom, Top Arm 600mm, SH 200mm | D2: ='2025_03_28 Boom Pricing'!$E$4+'2025_03_28 Boom Pricing'!$E$23+'2025_03_28 Boom Pricing'!$E$38+'2025_03_28 Boom Pricing'!$E$46 -> 32984.453 | E2: =D2*(1-0.5) -> 16492.227 | G2: Sections | H2: Part Number | J2: Boom Discount | L2: Model (A) | M2: Service Head | U2: for standard models
A3: 211-102-001 | B3: Powered Boom, Top Arm 800mm, SH 200mm | D3: ='2025_03_28 Boom Pricing'!$E$4+'2025_03_28 Boom Pricing'!$E$23+'2025_03_28 Boom Pricing'!$E$39+'2025_03_28 Boom Pricing'!$E$46 -> 32984.453 | E3: =D3*(1-0.5) -> 16492.227 | G3: Powered Model | H3: 211-XXX-XXX | J3: 0.5 | K3: Standard Top Arm | L3: Powered | N3: 600 | O3: 800 | P3: 1000 | Q3: 1200 | R3: 1400 | S3: 1600 | U3: 100mm | V3: 0 | Y3: Key | AC3: Price Increase | AD3: 600 | AE3: 800 | AF3: 1000 | AG3: 1200 | AH3: 1400 | AI3: 1600
A4: 211-103-001 | B4: Powered Boom, Top Arm 1000mm, SH 200mm | D4: ='2025_03_28 Boom Pricing'!$E$4+'2025_03_28 Boom Pricing'!$E$23+'2025_03_28 Boom Pricing'!$E$40+'2025_03_28 Boom Pricing'!$E$46 -> 32984.453 | E4: =D4*(1-0.5) -> 16492.227 | G4: Spring Model | H4: 212-XXX-XXX | K4: Powered Bottom Arm | L4: 35398.8 | M4: 200 | N4: =SUM($L$4+AD4) -> 35398.8 | O4: =SUM($L$4+AE4) -> 35398.8 | P4: =SUM($L$4+AF4) -> 35398.8 | Q4: =SUM($L$4+AG4) -> 35398.8 | R4: na | S4: na | U4: 300mm | V4: 251.81 | Y4: Model | AA4: A | AC4: 200 | AH4: 1591.55 | AI4: 3291.97
A5: 211-104-001 | B5: Powered Boom, Top Arm 1200mm, SH 200mm | D5: ='2025_03_28 Boom Pricing'!$E$4+'2025_03_28 Boom Pricing'!$E$23+'2025_03_28 Boom Pricing'!$E$41+'2025_03_28 Boom Pricing'!$E$46 -> 32984.453 | E5: =D5*(1-0.5) -> 16492.227 | G5: Fixed Model | H5: 213-XXX-XXX | K5: (articulating - 1000mm) | M5: 400 | N5: =SUM($L$4+AD5) -> 37373.71 | O5: =SUM($L$4+AE5) -> 37373.71 | P5: =SUM($L$4+AF5) -> 37373.71 | Q5: =SUM($L$4+AG5) -> 37373.71 | R5: na | S5: na | U5: 500mm | V5: 493.73 | Y5: Service Head Length | AA5: B | AC5: 400 | AD5: 1974.91 | AE5: 1974.91 | AF5: 1974.91 | AG5: 1974.91 | AH5: =SUM(1974.91+1591.95) -> 3566.86 | AI5: =SUM(3291.97+1974.91) -> 5266.88
A6: 211-101-002 | B6: Powered Boom, Top Arm 600mm, SH 400mm | D6: ='2025_03_28 Boom Pricing'!$E$4+'2025_03_28 Boom Pricing'!$E$24+'2025_03_28 Boom Pricing'!$E$38+'2025_03_28 Boom Pricing'!$E$46 -> 34959.36 | E6: =D6*(1-0.5) -> 17479.68 | G6: Fixed XL Model | H6: 313- | M6: 600 | N6: =SUM($L$4+AD6) -> 39353.55 | O6: =SUM($L$4+AE6) -> 39353.55 | P6: =SUM($L$4+AF6) -> 39353.55 | Q6: =SUM($L$4+AG6) -> 39353.55 | R6: na | S6: na | U6: for XL+ models | Y6: Top Arm Length | AC6: 600 | AD6: 3954.75 | AE6: 3954.75 | AF6: 3954.75 | AG6: 3954.75 | AH6: =SUM(3954.75+1591.55) -> 5546.3 | AI6: =SUM(3291.97+3954.75) -> 7246.72
A7: 211-102-002 | B7: Powered Boom, Top Arm 800mm, SH 400mm | D7: ='2025_03_28 Boom Pricing'!$E$4+'2025_03_28 Boom Pricing'!$E$24+'2025_03_28 Boom Pricing'!$E$39+'2025_03_28 Boom Pricing'!$E$46 -> 34959.36 | E7: =D7*(1-0.5) -> 17479.68 | G7: Fixed XXL Model | H7: 413-XXX-XXX | M7: 800 | N7: =SUM($L$4+AD7) -> 41392.67 | O7: =SUM($L$4+AE7) -> 41392.67 | P7: =SUM($L$4+AF7) -> 41392.67 | Q7: =SUM($L$4+AG7) -> 41392.67 | R7: na | S7: na | U7: 100mm | V7: 0 | Y7: Ceiling Flange | AA7: D | AC7: 800 | AD7: 5993.87 | AE7: 5993.87 | AF7: 5993.87 | AG7: 5993.87 | AH7: =SUM(5993.87+1591.55) -> 7585.42 | AI7: =SUM(5993.87+3291.97) -> 9285.84
A8: 211-103-002 | B8: Powered Boom, Top Arm 1000mm, SH 400mm | D8: ='2025_03_28 Boom Pricing'!$E$4+'2025_03_28 Boom Pricing'!$E$24+'2025_03_28 Boom Pricing'!$E$40+'2025_03_28 Boom Pricing'!$E$46 -> 34959.36 | E8: =D8*(1-0.5) -> 17479.68 | G8: Top Arm (600mm-1200mm) | H8: XXX-101-XXX (etc) | M8: 1000 | N8: =SUM($L$4+AD8) -> 43426.83 | O8: =SUM($L$4+AE8) -> 43426.83 | P8: =SUM($L$4+AF8) -> 43426.83 | Q8: =SUM($L$4+AG8) -> 43426.83 | R8: na | S8: na | U8: 300mm | V8: 508.53 | Y8: Optional Services | AA8: C | AC8: 1000 | AD8: 8028.03 | AE8: 8028.03 | AF8: 8028.03 | AG8: 8028.03 | AH8: 9619.58 | AI8: 11320
A9: 211-104-002 | B9: Powered Boom, Top Arm 1200mm, SH 400mm | D9: ='2025_03_28 Boom Pricing'!$E$4+'2025_03_28 Boom Pricing'!$E$24+'2025_03_28 Boom Pricing'!$E$41+'2025_03_28 Boom Pricing'!$E$46 -> 34959.36 | E9: =D9*(1-0.5) -> 17479.68 | G9: XL Top Arm | H9: XXX-111-XXX (etc) | U9: 500mm | V9: 1214.59 | Y9: Light Options | AA9: E
A10: 211-101-003 | B10: Powered Boom, Top Arm 600mm, SH 600mm | D10: ='2025_03_28 Boom Pricing'!$E$4+'2025_03_28 Boom Pricing'!$E$25+'2025_03_28 Boom Pricing'!$E$38+'2025_03_28 Boom Pricing'!$E$46 -> 36939.2 | E10: =D10*(1-0.5) -> 18469.6 | G10: XL Bottom Arm | H10: XXX-XXX-101-XXX (etc) | K10: XL Top Arm | L10: Powered XL | N10: 600 | O10: 800 | P10: 1000 | Q10: 1200 | R10: 1400 | S10: 1600 | Y10: Optional Light Accessories | AA10: F
A11: 211-102-003 | B11: Powered Boom, Top Arm 800mm, SH 600mm | D11: ='2025_03_28 Boom Pricing'!$E$4+'2025_03_28 Boom Pricing'!$E$25+'2025_03_28 Boom Pricing'!$E$39+'2025_03_28 Boom Pricing'!$E$46 -> 36939.2 | E11: =D11*(1-0.5) -> 18469.6 | G11: Service Head (200mm - 1000mm) | H11: XXX-XXX-001 (etc) | K11: Powered Bottom Arm | L11: 39326.43 | M11: 200 | N11: =SUM($L$11+AD4) -> 39326.43 | O11: =SUM($L$11+AE4) -> 39326.43 | P11: =SUM($L$11+AF4) -> 39326.43 | Q11: =SUM($L$11+AG4) -> 39326.43 | R11: =SUM($L$11+AH4) -> 40917.98 | S11: =SUM($L$11+AI4) -> 42618.4 | Y11: Not in the Tool
A12: 211-103-003 | B12: Powered Boom, Top Arm 1000mm, SH 600mm | D12: ='2025_03_28 Boom Pricing'!$E$4+'2025_03_28 Boom Pricing'!$E$25+'2025_03_28 Boom Pricing'!$E$40+'2025_03_28 Boom Pricing'!$E$46 -> 36939.2 | E12: =D12*(1-0.5) -> 18469.6 | K12: (articulating - 1000mm) | M12: 400 | N12: =SUM($L$11+AD5) -> 41301.34 | O12: =SUM($L$11+AE5) -> 41301.34 | P12: =SUM($L$11+AF5) -> 41301.34 | Q12: =SUM($L$11+AG5) -> 41301.34 | R12: =SUM($L$11+AH5) -> 42893.29 | S12: =SUM($L$11+AI5) -> 44593.31 | U12: Services / Accessories (D - if applicable) | W12: optional
A13: 211-104-003 | B13: Powered Boom, Top Arm 1200mm, SH 600mm | D13: ='2025_03_28 Boom Pricing'!$E$4+'2025_03_28 Boom Pricing'!$E$25+'2025_03_28 Boom Pricing'!$E$41+'2025_03_28 Boom Pricing'!$E$46 -> 36939.2 | E13: =D13*(1-0.5) -> 18469.6 | M13: 600 | N13: =SUM($L$11+AD6) -> 43281.18 | O13: =SUM($L$11+AE6) -> 43281.18 | P13: =SUM($L$11+AF6) -> 43281.18 | Q13: =SUM($L$11+AG6) -> 43281.18 | R13: =SUM($L$11+AH6) -> 44872.73 | S13: =SUM($L$11+AI6) -> 46573.15 | U13: Med-Gas | V13: 790 | W13: per gas addition | Y13: Total Price = A + B + C + D + E + F
A14: 211-101-004 | B14: Powered Boom, Top Arm 600mm, SH 800mm | D14: ='2025_03_28 Boom Pricing'!$E$4+'2025_03_28 Boom Pricing'!$E$26+'2025_03_28 Boom Pricing'!$E$38+'2025_03_28 Boom Pricing'!$E$46 -> 38978.32 | E14: =D14*(1-0.5) -> 19489.16 | M14: 800 | N14: =SUM($L$11+AD7) -> 45320.3 | O14: =SUM($L$11+AE7) -> 45320.3 | P14: =SUM($L$11+AF7) -> 45320.3 | Q14: =SUM($L$11+AG7) -> 45320.3 | R14: =SUM($L$11+AH7) -> 46911.85 | S14: =SUM($L$11+AI7) -> 48612.27 | U14: Electrical (2 duplexes) | V14: 543.12 | W14: per layer
A15: 211-102-004 | B15: Powered Boom, Top Arm 800mm, SH 800mm | D15: ='2025_03_28 Boom Pricing'!$E$4+'2025_03_28 Boom Pricing'!$E$26+'2025_03_28 Boom Pricing'!$E$39+'2025_03_28 Boom Pricing'!$E$46 -> 38978.32 | E15: =D15*(1-0.5) -> 19489.16 | G15: Shipping & Installation | M15: 1000 | N15: =SUM($L$11+AD8) -> 47354.46 | O15: =SUM($L$11+AE8) -> 47354.46 | P15: =SUM($L$11+AF8) -> 47354.46 | Q15: =SUM($L$11+AG8) -> 47354.46 | R15: =SUM($L$11+AH8) -> 48946.01 | S15: =SUM($L$11+AI8) -> 50646.43 | U15: Electrical (3 duplexes) | V15: 997.33 | W15: per layer
A16: 211-103-004 | B16: Powered Boom, Top Arm 1000mm, SH 800mm | D16: ='2025_03_28 Boom Pricing'!$E$4+'2025_03_28 Boom Pricing'!$E$26+'2025_03_28 Boom Pricing'!$E$40+'2025_03_28 Boom Pricing'!$E$46 -> 38978.32 | E16: =D16*(1-0.5) -> 19489.16 | U16: Data | V16: 0
A17: 211-104-004 | B17: Powered Boom, Top Arm 1200mm, SH 800mm | D17: ='2025_03_28 Boom Pricing'!$E$4+'2025_03_28 Boom Pricing'!$E$26+'2025_03_28 Boom Pricing'!$E$41+'2025_03_28 Boom Pricing'!$E$46 -> 38978.32 | E17: =D17*(1-0.5) -> 19489.16 | K17: Standard Top Arm | L17: Spring | N17: 600 | O17: 800 | P17: 1000 | Q17: 1200 | R17: 1400 | S17: 1600 | U17: Nitrogen Regulator | V17: 2105.92 | W17: per boom
A18: 211-101-005 | B18: Powered Boom, Top Arm 600mm, SH 1000mm | D18: ='2025_03_28 Boom Pricing'!$E$4+'2025_03_28 Boom Pricing'!$E$27+'2025_03_28 Boom Pricing'!$E$38+'2025_03_28 Boom Pricing'!$E$46 -> 41012.48 | E18: =D18*(1-0.5) -> 20506.24 | K18: Spring Bottom Arm | L18: 33594.72 | M18: 200 | N18: =SUM($L$18+AD4) -> 33594.72 | O18: =SUM($L$18+AE4) -> 33594.72 | P18: =SUM($L$18+AF4) -> 33594.72 | Q18: =SUM($L$18+AG4) -> 33594.72 | R18: na | S18: na | U18: Data Pass thru | V18: 770.21333 | W18: per boom
A19: 211-102-005 | B19: Powered Boom, Top Arm 800mm, SH 1000mm | D19: ='2025_03_28 Boom Pricing'!$E$4+'2025_03_28 Boom Pricing'!$E$27+'2025_03_28 Boom Pricing'!$E$39+'2025_03_28 Boom Pricing'!$E$46 -> 41012.48 | E19: =D19*(1-0.5) -> 20506.24 | K19: (articulating - 1000mm) | M19: 400 | N19: =SUM($L$18+AD5) -> 35569.63 | O19: =SUM($L$18+AE5) -> 35569.63 | P19: =SUM($L$18+AF5) -> 35569.63 | Q19: =SUM($L$18+AG5) -> 35569.63 | R19: na | S19: na | U19: Tandem Mount with 1 future boom option | V19: 3393.2067 | W19: per mount
A20: 211-103-005 | B20: Powered Boom, Top Arm 1000mm, SH 1000mm | D20: ='2025_03_28 Boom Pricing'!$E$4+'2025_03_28 Boom Pricing'!$E$27+'2025_03_28 Boom Pricing'!$E$40+'2025_03_28 Boom Pricing'!$E$46 -> 41012.48 | E20: =D20*(1-0.5) -> 20506.24 | M20: 600 | N20: =SUM($L$18+AD6) -> 37549.47 | O20: =SUM($L$18+AE6) -> 37549.47 | P20: =SUM($L$18+AF6) -> 37549.47 | Q20: =SUM($L$18+AG6) -> 37549.47 | R20: na | S20: na | U20: Rails
A21: 211-104-005 | B21: Powered Boom, Top Arm 1200mm, SH 1000mm | D21: ='2025_03_28 Boom Pricing'!$E$4+'2025_03_28 Boom Pricing'!$E$27+'2025_03_28 Boom Pricing'!$E$41+'2025_03_28 Boom Pricing'!$E$46 -> 41012.48 | E21: =D21*(1-0.5) -> 20506.24 | M21: 800 | N21: =SUM($L$18+AD7) -> 39588.59 | O21: =SUM($L$18+AE7) -> 39588.59 | P21: =SUM($L$18+AF7) -> 39588.59 | Q21: =SUM($L$18+AG7) -> 39588.59 | R21: na | S21: na | U21: Shelfs | V21: 1344.6222 | W21: per shelf
M22: 1000 | N22: =SUM($L$18+AD8) -> 41622.75 | O22: =SUM($L$18+AE8) -> 41622.75 | P22: =SUM($L$18+AF8) -> 41622.75 | Q22: =SUM($L$18+AG8) -> 41622.75 | R22: na | S22: na
A23: 211-111-001 | B23: Powered Boom, XL Top Arm 600mm, SH 200mm | D23: ='2025_03_28 Boom Pricing'!$E$5+'2025_03_28 Boom Pricing'!$E$23+'2025_03_28 Boom Pricing'!$E$38+'2025_03_28 Boom Pricing'!$E$46 -> 36912.08 | E23: =D23*(1-0.5) -> 18456.04
A24: 211-112-001 | B24: Powered Boom, XL Top Arm 800mm, SH 200mm | D24: ='2025_03_28 Boom Pricing'!$E$5+'2025_03_28 Boom Pricing'!$E$23+'2025_03_28 Boom Pricing'!$E$39+'2025_03_28 Boom Pricing'!$E$46 -> 36912.08 | E24: =D24*(1-0.5) -> 18456.04 | K24: XL Top Arm | L24: Spring XL | N24: 600 | O24: 800 | P24: 1000 | Q24: 1200 | R24: 1400 | S24: 1600
A25: 211-113-001 | B25: Powered Boom, XL Top Arm 1000mm, SH 200mm | D25: ='2025_03_28 Boom Pricing'!$E$5+'2025_03_28 Boom Pricing'!$E$23+'2025_03_28 Boom Pricing'!$E$40+'2025_03_28 Boom Pricing'!$E$46 -> 36912.08 | E25: =D25*(1-0.5) -> 18456.04 | K25: Spring Bottom Arm | L25: 38315.52 | M25: 200 | N25: =SUM($L$25+AD4) -> 38315.52 | O25: =SUM($L$25+AE4) -> 38315.52 | P25: =SUM($L$25+AF4) -> 38315.52 | Q25: =SUM($L$25+AG4) -> 38315.52 | R25: =SUM($L$25+AH4) -> 39907.07 | S25: =SUM($L$25+AI4) -> 41607.49
A26: 211-114-001 | B26: Powered Boom, XL Top Arm 1200mm, SH 200mm | D26: ='2025_03_28 Boom Pricing'!$E$5+'2025_03_28 Boom Pricing'!$E$23+'2025_03_28 Boom Pricing'!$E$41+'2025_03_28 Boom Pricing'!$E$46 -> 36912.08 | E26: =D26*(1-0.5) -> 18456.04 | K26: (articulating - 1000mm) | M26: 400 | N26: =SUM($L$25+AD5) -> 40290.43 | O26: =SUM($L$25+AE5) -> 40290.43 | P26: =SUM($L$25+AF5) -> 40290.43 | Q26: =SUM($L$25+AG5) -> 40290.43 | R26: =SUM($L$25+AH5) -> 41882.38 | S26: =SUM($L$25+AI5) -> 43582.4
A27: 211-115-001 | B27: Powered Boom, XL Top Arm 1400mm, SH 200mm | D27: ='2025_03_28 Boom Pricing'!$E$5+'2025_03_28 Boom Pricing'!$E$23+'2025_03_28 Boom Pricing'!$E$42+'2025_03_28 Boom Pricing'!$E$46 -> 38503.627 | E27: =D27*(1-0.5) -> 19251.813 | M27: 600 | N27: =SUM($L$25+AD6) -> 42270.27 | O27: =SUM($L$25+AE6) -> 42270.27 | P27: =SUM($L$25+AF6) -> 42270.27 | Q27: =SUM($L$25+AG6) -> 42270.27 | R27: =SUM($L$25+AH6) -> 43861.82 | S27: =SUM($L$25+AI6) -> 45562.24
A28: 211-116-001 | B28: Powered Boom, XL Top Arm 1600mm, SH 200mm | D28: ='2025_03_28 Boom Pricing'!$E$5+'2025_03_28 Boom Pricing'!$E$23+'2025_03_28 Boom Pricing'!$E$43+'2025_03_28 Boom Pricing'!$E$46 -> 40204.053 | E28: =D28*(1-0.5) -> 20102.027 | M28: 800 | N28: =SUM($L$25+AD7) -> 44309.39 | O28: =SUM($L$25+AE7) -> 44309.39 | P28: =SUM($L$25+AF7) -> 44309.39 | Q28: =SUM($L$25+AG7) -> 44309.39 | R28: =SUM($L$25+AH7) -> 45900.94 | S28: =SUM($L$25+AI7) -> 47601.36
A29: 211-111-002 | B29: Powered Boom, XL Top Arm 600mm, SH 400mm | D29: ='2025_03_28 Boom Pricing'!$E$5+'2025_03_28 Boom Pricing'!$E$24+'2025_03_28 Boom Pricing'!$E$38+'2025_03_28 Boom Pricing'!$E$46 -> 38886.987 | E29: =D29*(1-0.5) -> 19443.493 | M29: 1000 | N29: =SUM($L$25+AD8) -> 46343.55 | O29: =SUM($L$25+AE8) -> 46343.55 | P29: =SUM($L$25+AF8) -> 46343.55 | Q29: =SUM($L$25+AG8) -> 46343.55 | R29: =SUM($L$25+AH8) -> 47935.1 | S29: =SUM($L$25+AI8) -> 49635.52
A30: 211-112-002 | B30: Powered Boom, XL Top Arm 800mm, SH 400mm | D30: ='2025_03_28 Boom Pricing'!$E$5+'2025_03_28 Boom Pricing'!$E$24+'2025_03_28 Boom Pricing'!$E$39+'2025_03_28 Boom Pricing'!$E$46 -> 38886.987 | E30: =D30*(1-0.5) -> 19443.493
A31: 211-113-002 | B31: Powered Boom, XL Top Arm 1000mm, SH 400mm | D31: ='2025_03_28 Boom Pricing'!$E$5+'2025_03_28 Boom Pricing'!$E$24+'2025_03_28 Boom Pricing'!$E$40+'2025_03_28 Boom Pricing'!$E$46 -> 38886.987 | E31: =D31*(1-0.5) -> 19443.493 | K31: Standard Top Arm | L31: Fixed | N31: 600 | O31: 800 | P31: 1000 | Q31: 1200 | R31: 1400 | S31: 1600 | U31: Incorporate "sales price" and discounted List price
A32: 211-114-002 | B32: Powered Boom, XL Top Arm 1200mm, SH 400mm | D32: ='2025_03_28 Boom Pricing'!$E$5+'2025_03_28 Boom Pricing'!$E$24+'2025_03_28 Boom Pricing'!$E$41+'2025_03_28 Boom Pricing'!$E$46 -> 38886.987 | E32: =D32*(1-0.5) -> 19443.493 | K32: Standard Fixeed Arm (1000mm) | L32: 23781.02 | M32: 200 | N32: =SUM($L$32+AD4) -> 23781.02 | O32: =SUM($L$32+AE4) -> 23781.02 | P32: =SUM($L$32+AF4) -> 23781.02 | Q32: =SUM($L$32+AG4) -> 23781.02 | R32: na | S32: na
A33: 211-115-002 | B33: Powered Boom, XL Top Arm 1400mm, SH 400mm | D33: ='2025_03_28 Boom Pricing'!$E$5+'2025_03_28 Boom Pricing'!$E$24+'2025_03_28 Boom Pricing'!$E$42+'2025_03_28 Boom Pricing'!$E$46 -> 40478.533 | E33: =D33*(1-0.5) -> 20239.267 | M33: 400 | N33: =SUM($L$32+AD5) -> 25755.93 | O33: =SUM($L$32+AE5) -> 25755.93 | P33: =SUM($L$32+AF5) -> 25755.93 | Q33: =SUM($L$32+AG5) -> 25755.93 | R33: na | S33: na
A34: 211-116-002 | B34: Powered Boom, XL Top Arm 1600mm, SH 400mm | D34: ='2025_03_28 Boom Pricing'!$E$5+'2025_03_28 Boom Pricing'!$E$24+'2025_03_28 Boom Pricing'!$E$43+'2025_03_28 Boom Pricing'!$E$46 -> 42178.96 | E34: =D34*(1-0.5) -> 21089.48 | M34: 600 | N34: =SUM($L$32+AD6) -> 27735.77 | O34: =SUM($L$32+AE6) -> 27735.77 | P34: =SUM($L$32+AF6) -> 27735.77 | Q34: =SUM($L$32+AG6) -> 27735.77 | R34: na | S34: na
A35: 211-111-003 | B35: Powered Boom, XL Top Arm 600mm, SH 600mm | D35: ='2025_03_28 Boom Pricing'!$E$5+'2025_03_28 Boom Pricing'!$E$25+'2025_03_28 Boom Pricing'!$E$38+'2025_03_28 Boom Pricing'!$E$46 -> 40866.827 | E35: =D35*(1-0.5) -> 20433.413 | M35: 800 | N35: =SUM($L$32+AD7) -> 29774.89 | O35: =SUM($L$32+AE7) -> 29774.89 | P35: =SUM($L$32+AF7) -> 29774.89 | Q35: =SUM($L$32+AG7) -> 29774.89 | R35: na | S35: na
A36: 211-112-003 | B36: Powered Boom, XL Top Arm 800mm, SH 600mm | D36: ='2025_03_28 Boom Pricing'!$E$5+'2025_03_28 Boom Pricing'!$E$25+'2025_03_28 Boom Pricing'!$E$39+'2025_03_28 Boom Pricing'!$E$46 -> 40866.827 | E36: =D36*(1-0.5) -> 20433.413 | M36: 1000 | N36: =SUM($L$32+AD8) -> 31809.05 | O36: =SUM($L$32+AE8) -> 31809.05 | P36: =SUM($L$32+AF8) -> 31809.05 | Q36: =SUM($L$32+AG8) -> 31809.05 | R36: na | S36: na
A37: 211-113-003 | B37: Powered Boom, XL Top Arm 1000mm, SH 600mm | D37: ='2025_03_28 Boom Pricing'!$E$5+'2025_03_28 Boom Pricing'!$E$25+'2025_03_28 Boom Pricing'!$E$40+'2025_03_28 Boom Pricing'!$E$46 -> 40866.827 | E37: =D37*(1-0.5) -> 20433.413
A38: 211-114-003 | B38: Powered Boom, XL Top Arm 1200mm, SH 600mm | D38: ='2025_03_28 Boom Pricing'!$E$5+'2025_03_28 Boom Pricing'!$E$25+'2025_03_28 Boom Pricing'!$E$41+'2025_03_28 Boom Pricing'!$E$46 -> 40866.827 | E38: =D38*(1-0.5) -> 20433.413 | K38: XL Top Arm | L38: Fixed XL | N38: 600 | O38: 800 | P38: 1000 | Q38: 1200 | R38: 1400 | S38: 1600
A39: 211-115-003 | B39: Powered Boom, XL Top Arm 1400mm, SH 600mm | D39: ='2025_03_28 Boom Pricing'!$E$5+'2025_03_28 Boom Pricing'!$E$25+'2025_03_28 Boom Pricing'!$E$42+'2025_03_28 Boom Pricing'!$E$46 -> 42458.373 | E39: =D39*(1-0.5) -> 21229.187 | K39: Standard Fixeed Arm (1000mm) | L39: 27382.03 | M39: 200 | N39: =SUM($L$39+AD4) -> 27382.03 | O39: =SUM($L$39+AE4) -> 27382.03 | P39: =SUM($L$39+AF4) -> 27382.03 | Q39: =SUM($L$39+AG4) -> 27382.03 | R39: =SUM($L$39+AH4) -> 28973.58 | S39: =SUM($L$39+AI4) -> 30674
A40: 211-116-003 | B40: Powered Boom, XL Top Arm 1600mm, SH 600mm | D40: ='2025_03_28 Boom Pricing'!$E$5+'2025_03_28 Boom Pricing'!$E$25+'2025_03_28 Boom Pricing'!$E$43+'2025_03_28 Boom Pricing'!$E$46 -> 44158.8 | E40: =D40*(1-0.5) -> 22079.4 | M40: 400 | N40: =SUM($L$39+AD5) -> 29356.94 | O40: =SUM($L$39+AE5) -> 29356.94 | P40: =SUM($L$39+AF5) -> 29356.94 | Q40: =SUM($L$39+AG5) -> 29356.94 | R40: =SUM($L$39+AH5) -> 30948.89 | S40: =SUM($L$39+AI5) -> 32648.91
A41: 211-111-004 | B41: Powered Boom, XL Top Arm 600mm, SH 800mm | D41: ='2025_03_28 Boom Pricing'!$E$5+'2025_03_28 Boom Pricing'!$E$26+'2025_03_28 Boom Pricing'!$E$38+'2025_03_28 Boom Pricing'!$E$46 -> 42905.947 | E41: =D41*(1-0.5) -> 21452.973 | M41: 600 | N41: =SUM($L$39+AD6) -> 31336.78 | O41: =SUM($L$39+AE6) -> 31336.78 | P41: =SUM($L$39+AF6) -> 31336.78 | Q41: =SUM($L$39+AG6) -> 31336.78 | R41: =SUM($L$39+AH6) -> 32928.33 | S41: =SUM($L$39+AI6) -> 34628.75
A42: 211-112-004 | B42: Powered Boom, XL Top Arm 800mm, SH 800mm | D42: ='2025_03_28 Boom Pricing'!$E$5+'2025_03_28 Boom Pricing'!$E$26+'2025_03_28 Boom Pricing'!$E$39+'2025_03_28 Boom Pricing'!$E$46 -> 42905.947 | E42: =D42*(1-0.5) -> 21452.973 | M42: 800 | N42: =SUM($L$39+AD7) -> 33375.9 | O42: =SUM($L$39+AE7) -> 33375.9 | P42: =SUM($L$39+AF7) -> 33375.9 | Q42: =SUM($L$39+AG7) -> 33375.9 | R42: =SUM($L$39+AH7) -> 34967.45 | S42: =SUM($L$39+AI7) -> 36667.87
A43: 211-113-004 | B43: Powered Boom, XL Top Arm 1000mm, SH 800mm | D43: ='2025_03_28 Boom Pricing'!$E$5+'2025_03_28 Boom Pricing'!$E$26+'2025_03_28 Boom Pricing'!$E$40+'2025_03_28 Boom Pricing'!$E$46 -> 42905.947 | E43: =D43*(1-0.5) -> 21452.973 | M43: 1000 | N43: =SUM($L$39+AD8) -> 35410.06 | O43: =SUM($L$39+AE8) -> 35410.06 | P43: =SUM($L$39+AF8) -> 35410.06 | Q43: =SUM($L$39+AG8) -> 35410.06 | R43: =SUM($L$39+AH8) -> 37001.61 | S43: =SUM($L$39+AI8) -> 38702.03
A44: 211-114-004 | B44: Powered Boom, XL Top Arm 1200mm, SH 800mm | D44: ='2025_03_28 Boom Pricing'!$E$5+'2025_03_28 Boom Pricing'!$E$26+'2025_03_28 Boom Pricing'!$E$41+'2025_03_28 Boom Pricing'!$E$46 -> 42905.947 | E44: =D44*(1-0.5) -> 21452.973
A45: 211-115-004 | B45: Powered Boom, XL Top Arm 1400mm, SH 800mm | D45: ='2025_03_28 Boom Pricing'!$E$5+'2025_03_28 Boom Pricing'!$E$26+'2025_03_28 Boom Pricing'!$E$42+'2025_03_28 Boom Pricing'!$E$46 -> 44497.493 | E45: =D45*(1-0.5) -> 22248.747 | K45: XXL Top Arm | L45: Fixed XXL | N45: 600 | O45: 800 | P45: 1000 | Q45: 1200 | R45: 1400 | S45: 1600
A46: 211-116-004 | B46: Powered Boom, XL Top Arm 1600mm, SH 800mm | D46: ='2025_03_28 Boom Pricing'!$E$5+'2025_03_28 Boom Pricing'!$E$26+'2025_03_28 Boom Pricing'!$E$43+'2025_03_28 Boom Pricing'!$E$46 -> 46197.92 | E46: =D46*(1-0.5) -> 23098.96 | K46: Standard Fixeed Arm (1000mm) | L46: 31047.26 | M46: 200 | N46: =SUM($L$46+AD4) -> 31047.26 | O46: =SUM($L$46+AE4) -> 31047.26 | P46: =SUM($L$46+AF4) -> 31047.26 | Q46: =SUM($L$46+AG4) -> 31047.26 | R46: =SUM($L$46+AH4) -> 32638.81 | S46: =SUM($L$46+AI4) -> 34339.23
A47: 211-111-005 | B47: Powered Boom, XL Top Arm 600mm, SH 1000mm | D47: ='2025_03_28 Boom Pricing'!$E$5+'2025_03_28 Boom Pricing'!$E$27+'2025_03_28 Boom Pricing'!$E$38+'2025_03_28 Boom Pricing'!$E$46 -> 44940.107 | E47: =D47*(1-0.5) -> 22470.053 | M47: 400 | N47: =SUM($L$46+AD5) -> 33022.17 | O47: =SUM($L$46+AE5) -> 33022.17 | P47: =SUM($L$46+AF5) -> 33022.17 | Q47: =SUM($L$46+AG5) -> 33022.17 | R47: =SUM($L$46+AH5) -> 34614.12 | S47: =SUM($L$46+AI5) -> 36314.14
A48: 211-112-005 | B48: Powered Boom, XL Top Arm 800mm, SH 1000mm | D48: ='2025_03_28 Boom Pricing'!$E$5+'2025_03_28 Boom Pricing'!$E$27+'2025_03_28 Boom Pricing'!$E$39+'2025_03_28 Boom Pricing'!$E$46 -> 44940.107 | E48: =D48*(1-0.5) -> 22470.053 | M48: 600 | N48: =SUM($L$46+AD6) -> 35002.01 | O48: =SUM($L$46+AE6) -> 35002.01 | P48: =SUM($L$46+AF6) -> 35002.01 | Q48: =SUM($L$46+AG6) -> 35002.01 | R48: =SUM($L$46+AH6) -> 36593.56 | S48: =SUM($L$46+AI6) -> 38293.98
A49: 211-113-005 | B49: Powered Boom, XL Top Arm 1000mm, SH 1000mm | D49: ='2025_03_28 Boom Pricing'!$E$5+'2025_03_28 Boom Pricing'!$E$27+'2025_03_28 Boom Pricing'!$E$40+'2025_03_28 Boom Pricing'!$E$46 -> 44940.107 | E49: =D49*(1-0.5) -> 22470.053 | M49: 800 | N49: =SUM($L$46+AD7) -> 37041.13 | O49: =SUM($L$46+AE7) -> 37041.13 | P49: =SUM($L$46+AF7) -> 37041.13 | Q49: =SUM($L$46+AG7) -> 37041.13 | R49: =SUM($L$46+AH7) -> 38632.68 | S49: =SUM($L$46+AI7) -> 40333.1
A50: 211-114-005 | B50: Powered Boom, XL Top Arm 1200mm, SH 1000mm | D50: ='2025_03_28 Boom Pricing'!$E$5+'2025_03_28 Boom Pricing'!$E$27+'2025_03_28 Boom Pricing'!$E$41+'2025_03_28 Boom Pricing'!$E$46 -> 44940.107 | E50: =D50*(1-0.5) -> 22470.053 | M50: 1000 | N50: =SUM($L$46+AD8) -> 39075.29 | O50: =SUM($L$46+AE8) -> 39075.29 | P50: =SUM($L$46+AF8) -> 39075.29 | Q50: =SUM($L$46+AG8) -> 39075.29 | R50: =SUM($L$46+AH8) -> 40666.84 | S50: =SUM($L$46+AI8) -> 42367.26
A51: 211-115-005 | B51: Powered Boom, XL Top Arm 1400mm, SH 1000mm | D51: ='2025_03_28 Boom Pricing'!$E$5+'2025_03_28 Boom Pricing'!$E$27+'2025_03_28 Boom Pricing'!$E$42+'2025_03_28 Boom Pricing'!$E$46 -> 46531.653 | E51: =D51*(1-0.5) -> 23265.827
A52: 211-116-005 | B52: Powered Boom, XL Top Arm 1600mm, SH 1000mm | D52: ='2025_03_28 Boom Pricing'!$E$5+'2025_03_28 Boom Pricing'!$E$27+'2025_03_28 Boom Pricing'!$E$43+'2025_03_28 Boom Pricing'!$E$46 -> 48232.08 | E52: =D52*(1-0.5) -> 24116.04 | K52: XL Top Arm | L52: Large Monitor | N52: 600 | O52: 800 | P52: 1000 | Q52: 1200 | R52: 1400 | S52: 1600
K53: Spring Bottom Arm | L53: 48126.24 | N53: =SUM($L$53+AD4) -> 48126.24 | O53: =SUM($L$53+AE4) -> 48126.24 | P53: =SUM($L$53+AF4) -> 48126.24 | Q53: =SUM($L$53+AG4) -> 48126.24 | R53: =SUM($L$53+AH4) -> 49717.79 | S53: =SUM($L$53+AI4) -> 51418.21
A54: 212-101-001 | B54: Spring Boom, Top Arm 600mm, SH 200mm | D54: ='2025_03_28 Boom Pricing'!$E$6+'2025_03_28 Boom Pricing'!$E$23+'2025_03_28 Boom Pricing'!$E$38+'2025_03_28 Boom Pricing'!$E$46 -> 31180.373 | E54: =D54*(1-0.5) -> 15590.187 | K54: (articulating - 1000mm)
A55: 212-102-001 | B55: Spring Boom, Top Arm 800mm, SH 200mm | D55: ='2025_03_28 Boom Pricing'!$E$6+'2025_03_28 Boom Pricing'!$E$23+'2025_03_28 Boom Pricing'!$E$39+'2025_03_28 Boom Pricing'!$E$46 -> 31180.373 | E55: =D55*(1-0.5) -> 15590.187
A56: 212-103-001 | B56: Spring Boom, Top Arm 1000mm, SH 200mm | D56: ='2025_03_28 Boom Pricing'!$E$6+'2025_03_28 Boom Pricing'!$E$23+'2025_03_28 Boom Pricing'!$E$40+'2025_03_28 Boom Pricing'!$E$46 -> 31180.373 | E56: =D56*(1-0.5) -> 15590.187
A57: 212-104-001 | B57: Spring Boom, Top Arm 1200mm, SH 200mm | D57: ='2025_03_28 Boom Pricing'!$E$6+'2025_03_28 Boom Pricing'!$E$23+'2025_03_28 Boom Pricing'!$E$41+'2025_03_28 Boom Pricing'!$E$46 -> 31180.373 | E57: =D57*(1-0.5) -> 15590.187
A58: 212-101-002 | B58: Spring Boom, Top Arm 600mm, SH 400mm | D58: ='2025_03_28 Boom Pricing'!$E$6+'2025_03_28 Boom Pricing'!$E$24+'2025_03_28 Boom Pricing'!$E$38+'2025_03_28 Boom Pricing'!$E$46 -> 33155.28 | E58: =D58*(1-0.5) -> 16577.64
A59: 212-102-002 | B59: Spring Boom, Top Arm 800mm, SH 400mm | D59: ='2025_03_28 Boom Pricing'!$E$6+'2025_03_28 Boom Pricing'!$E$24+'2025_03_28 Boom Pricing'!$E$39+'2025_03_28 Boom Pricing'!$E$46 -> 33155.28 | E59: =D59*(1-0.5) -> 16577.64
A60: 212-103-002 | B60: Spring Boom, Top Arm 1000mm, SH 400mm | D60: ='2025_03_28 Boom Pricing'!$E$6+'2025_03_28 Boom Pricing'!$E$24+'2025_03_28 Boom Pricing'!$E$40+'2025_03_28 Boom Pricing'!$E$46 -> 33155.28 | E60: =D60*(1-0.5) -> 16577.64
A61: 212-104-002 | B61: Spring Boom, Top Arm 1200mm, SH 400mm | D61: ='2025_03_28 Boom Pricing'!$E$6+'2025_03_28 Boom Pricing'!$E$24+'2025_03_28 Boom Pricing'!$E$41+'2025_03_28 Boom Pricing'!$E$46 -> 33155.28 | E61: =D61*(1-0.5) -> 16577.64
A62: 212-101-003 | B62: Spring Boom, Top Arm 600mm, SH 600mm | D62: ='2025_03_28 Boom Pricing'!$E$6+'2025_03_28 Boom Pricing'!$E$25+'2025_03_28 Boom Pricing'!$E$38+'2025_03_28 Boom Pricing'!$E$46 -> 35135.12 | E62: =D62*(1-0.5) -> 17567.56
A63: 212-102-003 | B63: Spring Boom, Top Arm 800mm, SH 600mm | D63: ='2025_03_28 Boom Pricing'!$E$6+'2025_03_28 Boom Pricing'!$E$25+'2025_03_28 Boom Pricing'!$E$39+'2025_03_28 Boom Pricing'!$E$46 -> 35135.12 | E63: =D63*(1-0.5) -> 17567.56
A64: 212-103-003 | B64: Spring Boom, Top Arm 1000mm, SH 600mm | D64: ='2025_03_28 Boom Pricing'!$E$6+'2025_03_28 Boom Pricing'!$E$25+'2025_03_28 Boom Pricing'!$E$40+'2025_03_28 Boom Pricing'!$E$46 -> 35135.12 | E64: =D64*(1-0.5) -> 17567.56
A65: 212-104-003 | B65: Spring Boom, Top Arm 1200mm, SH 600mm | D65: ='2025_03_28 Boom Pricing'!$E$6+'2025_03_28 Boom Pricing'!$E$25+'2025_03_28 Boom Pricing'!$E$41+'2025_03_28 Boom Pricing'!$E$46 -> 35135.12 | E65: =D65*(1-0.5) -> 17567.56
A66: 212-101-004 | B66: Spring Boom, Top Arm 600mm, SH 800mm | D66: ='2025_03_28 Boom Pricing'!$E$6+'2025_03_28 Boom Pricing'!$E$26+'2025_03_28 Boom Pricing'!$E$38+'2025_03_28 Boom Pricing'!$E$46 -> 37174.24 | E66: =D66*(1-0.5) -> 18587.12
A67: 212-102-004 | B67: Spring Boom, Top Arm 800mm, SH 800mm | D67: ='2025_03_28 Boom Pricing'!$E$6+'2025_03_28 Boom Pricing'!$E$26+'2025_03_28 Boom Pricing'!$E$39+'2025_03_28 Boom Pricing'!$E$46 -> 37174.24 | E67: =D67*(1-0.5) -> 18587.12
A68: 212-103-004 | B68: Spring Boom, Top Arm 1000mm, SH 800mm | D68: ='2025_03_28 Boom Pricing'!$E$6+'2025_03_28 Boom Pricing'!$E$26+'2025_03_28 Boom Pricing'!$E$40+'2025_03_28 Boom Pricing'!$E$46 -> 37174.24 | E68: =D68*(1-0.5) -> 18587.12
A69: 212-104-004 | B69: Spring Boom, Top Arm 1200mm, SH 800mm | D69: ='2025_03_28 Boom Pricing'!$E$6+'2025_03_28 Boom Pricing'!$E$26+'2025_03_28 Boom Pricing'!$E$41+'2025_03_28 Boom Pricing'!$E$46 -> 37174.24 | E69: =D69*(1-0.5) -> 18587.12
A70: 212-101-005 | B70: Spring Boom, Top Arm 600mm, SH 1000mm | D70: ='2025_03_28 Boom Pricing'!$E$6+'2025_03_28 Boom Pricing'!$E$27+'2025_03_28 Boom Pricing'!$E$38+'2025_03_28 Boom Pricing'!$E$46 -> 39208.4 | E70: =D70*(1-0.5) -> 19604.2
A71: 212-102-005 | B71: Spring Boom, Top Arm 800mm, SH 1000mm | D71: ='2025_03_28 Boom Pricing'!$E$6+'2025_03_28 Boom Pricing'!$E$27+'2025_03_28 Boom Pricing'!$E$39+'2025_03_28 Boom Pricing'!$E$46 -> 39208.4 | E71: =D71*(1-0.5) -> 19604.2
A72: 212-103-005 | B72: Spring Boom, Top Arm 1000mm, SH 1000mm | D72: ='2025_03_28 Boom Pricing'!$E$6+'2025_03_28 Boom Pricing'!$E$27+'2025_03_28 Boom Pricing'!$E$40+'2025_03_28 Boom Pricing'!$E$46 -> 39208.4 | E72: =D72*(1-0.5) -> 19604.2
A73: 212-104-005 | B73: Spring Boom, Top Arm 1200mm, SH 1000mm | D73: ='2025_03_28 Boom Pricing'!$E$6+'2025_03_28 Boom Pricing'!$E$27+'2025_03_28 Boom Pricing'!$E$41+'2025_03_28 Boom Pricing'!$E$46 -> 39208.4 | E73: =D73*(1-0.5) -> 19604.2
A75: 212-111-001 | B75: Spring Boom, XL Top Arm 600mm, SH 200mm | D75: ='2025_03_28 Boom Pricing'!$E$7+'2025_03_28 Boom Pricing'!$E$23+'2025_03_28 Boom Pricing'!$E$38+'2025_03_28 Boom Pricing'!$E$46 -> 35901.173 | E75: =D75*(1-0.5) -> 17950.587
A76: 212-112-001 | B76: Spring Boom, XL Top Arm 800mm, SH 200mm | D76: ='2025_03_28 Boom Pricing'!$E$7+'2025_03_28 Boom Pricing'!$E$23+'2025_03_28 Boom Pricing'!$E$39+'2025_03_28 Boom Pricing'!$E$46 -> 35901.173 | E76: =D76*(1-0.5) -> 17950.587
A77: 212-113-001 | B77: Spring Boom, XL Top Arm 1000mm, SH 200mm | D77: ='2025_03_28 Boom Pricing'!$E$7+'2025_03_28 Boom Pricing'!$E$23+'2025_03_28 Boom Pricing'!$E$40+'2025_03_28 Boom Pricing'!$E$46 -> 35901.173 | E77: =D77*(1-0.5) -> 17950.587
A78: 212-114-001 | B78: Spring Boom, XL Top Arm 1200mm, SH 200mm | D78: ='2025_03_28 Boom Pricing'!$E$7+'2025_03_28 Boom Pricing'!$E$23+'2025_03_28 Boom Pricing'!$E$41+'2025_03_28 Boom Pricing'!$E$46 -> 35901.173 | E78: =D78*(1-0.5) -> 17950.587
A79: 212-115-001 | B79: Spring Boom, XL Top Arm 1400mm, SH 200mm | D79: ='2025_03_28 Boom Pricing'!$E$7+'2025_03_28 Boom Pricing'!$E$23+'2025_03_28 Boom Pricing'!$E$42+'2025_03_28 Boom Pricing'!$E$46 -> 37492.72 | E79: =D79*(1-0.5) -> 18746.36
A80: 212-116-001 | B80: Spring Boom, XL Top Arm 1600mm, SH 200mm | D80: ='2025_03_28 Boom Pricing'!$E$7+'2025_03_28 Boom Pricing'!$E$23+'2025_03_28 Boom Pricing'!$E$43+'2025_03_28 Boom Pricing'!$E$46 -> 39193.147 | E80: =D80*(1-0.5) -> 19596.573
A81: 212-111-002 | B81: Spring Boom, XL Top Arm 600mm, SH 400mm | D81: ='2025_03_28 Boom Pricing'!$E$7+'2025_03_28 Boom Pricing'!$E$24+'2025_03_28 Boom Pricing'!$E$38+'2025_03_28 Boom Pricing'!$E$46 -> 37876.08 | E81: =D81*(1-0.5) -> 18938.04
A82: 212-112-002 | B82: Spring Boom, XL Top Arm 800mm, SH 400mm | D82: ='2025_03_28 Boom Pricing'!$E$7+'2025_03_28 Boom Pricing'!$E$24+'2025_03_28 Boom Pricing'!$E$39+'2025_03_28 Boom Pricing'!$E$46 -> 37876.08 | E82: =D82*(1-0.5) -> 18938.04
A83: 212-113-002 | B83: Spring Boom, XL Top Arm 1000mm, SH 400mm | D83: ='2025_03_28 Boom Pricing'!$E$7+'2025_03_28 Boom Pricing'!$E$24+'2025_03_28 Boom Pricing'!$E$40+'2025_03_28 Boom Pricing'!$E$46 -> 37876.08 | E83: =D83*(1-0.5) -> 18938.04
A84: 212-114-002 | B84: Spring Boom, XL Top Arm 1200mm, SH 400mm | D84: ='2025_03_28 Boom Pricing'!$E$7+'2025_03_28 Boom Pricing'!$E$24+'2025_03_28 Boom Pricing'!$E$41+'2025_03_28 Boom Pricing'!$E$46 -> 37876.08 | E84: =D84*(1-0.5) -> 18938.04
A85: 212-115-002 | B85: Spring Boom, XL Top Arm 1400mm, SH 400mm | D85: ='2025_03_28 Boom Pricing'!$E$7+'2025_03_28 Boom Pricing'!$E$24+'2025_03_28 Boom Pricing'!$E$42+'2025_03_28 Boom Pricing'!$E$46 -> 39467.627 | E85: =D85*(1-0.5) -> 19733.813
A86: 212-116-002 | B86: Spring Boom, XL Top Arm 1600mm, SH 400mm | D86: ='2025_03_28 Boom Pricing'!$E$7+'2025_03_28 Boom Pricing'!$E$24+'2025_03_28 Boom Pricing'!$E$43+'2025_03_28 Boom Pricing'!$E$46 -> 41168.053 | E86: =D86*(1-0.5) -> 20584.027
A87: 212-111-003 | B87: Spring Boom, XL Top Arm 600mm, SH 600mm | D87: ='2025_03_28 Boom Pricing'!$E$7+'2025_03_28 Boom Pricing'!$E$25+'2025_03_28 Boom Pricing'!$E$38+'2025_03_28 Boom Pricing'!$E$46 -> 39855.92 | E87: =D87*(1-0.5) -> 19927.96
A88: 212-112-003 | B88: Spring Boom, XL Top Arm 800mm, SH 600mm | D88: ='2025_03_28 Boom Pricing'!$E$7+'2025_03_28 Boom Pricing'!$E$25+'2025_03_28 Boom Pricing'!$E$39+'2025_03_28 Boom Pricing'!$E$46 -> 39855.92 | E88: =D88*(1-0.5) -> 19927.96
A89: 212-113-003 | B89: Spring Boom, XL Top Arm 1000mm, SH 600mm | D89: ='2025_03_28 Boom Pricing'!$E$7+'2025_03_28 Boom Pricing'!$E$25+'2025_03_28 Boom Pricing'!$E$40+'2025_03_28 Boom Pricing'!$E$46 -> 39855.92 | E89: =D89*(1-0.5) -> 19927.96
A90: 212-114-003 | B90: Spring Boom, XL Top Arm 1200mm, SH 600mm | D90: ='2025_03_28 Boom Pricing'!$E$7+'2025_03_28 Boom Pricing'!$E$25+'2025_03_28 Boom Pricing'!$E$41+'2025_03_28 Boom Pricing'!$E$46 -> 39855.92 | E90: =D90*(1-0.5) -> 19927.96
A91: 212-115-003 | B91: Spring Boom, XL Top Arm 1400mm, SH 600mm | D91: ='2025_03_28 Boom Pricing'!$E$7+'2025_03_28 Boom Pricing'!$E$25+'2025_03_28 Boom Pricing'!$E$42+'2025_03_28 Boom Pricing'!$E$46 -> 41447.467 | E91: =D91*(1-0.5) -> 20723.733
A92: 212-116-003 | B92: Spring Boom, XL Top Arm 1600mm, SH 600mm | D92: ='2025_03_28 Boom Pricing'!$E$7+'2025_03_28 Boom Pricing'!$E$25+'2025_03_28 Boom Pricing'!$E$43+'2025_03_28 Boom Pricing'!$E$46 -> 43147.893 | E92: =D92*(1-0.5) -> 21573.947
A93: 212-111-004 | B93: Spring Boom, XL Top Arm 600mm, SH 800mm | D93: ='2025_03_28 Boom Pricing'!$E$7+'2025_03_28 Boom Pricing'!$E$26+'2025_03_28 Boom Pricing'!$E$38+'2025_03_28 Boom Pricing'!$E$46 -> 41895.04 | E93: =D93*(1-0.5) -> 20947.52
A94: 212-112-004 | B94: Spring Boom, XL Top Arm 800mm, SH 800mm | D94: ='2025_03_28 Boom Pricing'!$E$7+'2025_03_28 Boom Pricing'!$E$26+'2025_03_28 Boom Pricing'!$E$39+'2025_03_28 Boom Pricing'!$E$46 -> 41895.04 | E94: =D94*(1-0.5) -> 20947.52
A95: 212-113-004 | B95: Spring Boom, XL Top Arm 1000mm, SH 800mm | D95: ='2025_03_28 Boom Pricing'!$E$7+'2025_03_28 Boom Pricing'!$E$26+'2025_03_28 Boom Pricing'!$E$40+'2025_03_28 Boom Pricing'!$E$46 -> 41895.04 | E95: =D95*(1-0.5) -> 20947.52
A96: 212-114-004 | B96: Spring Boom, XL Top Arm 1200mm, SH 800mm | D96: ='2025_03_28 Boom Pricing'!$E$7+'2025_03_28 Boom Pricing'!$E$26+'2025_03_28 Boom Pricing'!$E$41+'2025_03_28 Boom Pricing'!$E$46 -> 41895.04 | E96: =D96*(1-0.5) -> 20947.52
A97: 212-115-004 | B97: Spring Boom, XL Top Arm 1400mm, SH 800mm | D97: ='2025_03_28 Boom Pricing'!$E$7+'2025_03_28 Boom Pricing'!$E$26+'2025_03_28 Boom Pricing'!$E$42+'2025_03_28 Boom Pricing'!$E$46 -> 43486.587 | E97: =D97*(1-0.5) -> 21743.293
A98: 212-116-004 | B98: Spring Boom, XL Top Arm 1600mm, SH 800mm | D98: ='2025_03_28 Boom Pricing'!$E$7+'2025_03_28 Boom Pricing'!$E$26+'2025_03_28 Boom Pricing'!$E$43+'2025_03_28 Boom Pricing'!$E$46 -> 45187.013 | E98: =D98*(1-0.5) -> 22593.507
A99: 212-111-005 | B99: Spring Boom, XL Top Arm 600mm, SH 1000mm | D99: ='2025_03_28 Boom Pricing'!$E$7+'2025_03_28 Boom Pricing'!$E$27+'2025_03_28 Boom Pricing'!$E$38+'2025_03_28 Boom Pricing'!$E$46 -> 43929.2 | E99: =D99*(1-0.5) -> 21964.6
A100: 212-112-005 | B100: Spring Boom, XL Top Arm 800mm, SH 1000mm | D100: ='2025_03_28 Boom Pricing'!$E$7+'2025_03_28 Boom Pricing'!$E$27+'2025_03_28 Boom Pricing'!$E$39+'2025_03_28 Boom Pricing'!$E$46 -> 43929.2 | E100: =D100*(1-0.5) -> 21964.6
A101: 212-113-005 | B101: Spring Boom, XL Top Arm 1000mm, SH 1000mm | D101: ='2025_03_28 Boom Pricing'!$E$7+'2025_03_28 Boom Pricing'!$E$27+'2025_03_28 Boom Pricing'!$E$40+'2025_03_28 Boom Pricing'!$E$46 -> 43929.2 | E101: =D101*(1-0.5) -> 21964.6
...

Sheet 2025_03_28 Boom Pricing
A1: Base Model
B2: Base Model | C2: Ondal List Price | D2: Imagine Cost | E2: Imagine List Price | G2: XL Arm? | H2: Articulating? | I2: Ondal Discount
B4: Boom - Powered Bottom Arm | C4: ='[1]Ondal Configs'!C2 -> 12369.17 | D4: =C4*(1-$I$4) -> 9895.336 | E4: =D4/(1-0.4)*2 -> 32984.453 | F4: 1000mm | G4: No | H4: Yes | I4: 0.2
B5: Boom - Arm (Powered XL) | C5: ='[1]Ondal Configs'!D2 -> 13842.03 | D5: =C5*(1-$I$4) -> 11073.624 | E5: =D5/(1-0.4)*2 -> 36912.08 | F5: 1000mm | G5: Yes | H5: Yes
B6: Boom - Spring Bottom Arm | C6: ='[1]Ondal Configs'!E2 -> 11692.64 | D6: =C6*(1-$I$4) -> 9354.112 | E6: =D6/(1-0.4)*2 -> 31180.373 | F6: 1000mm | G6: No | H6: Yes
B7: Boom - Spring Bottom Arm (XL) | C7: ='[1]Ondal Configs'!F2 -> 13462.94 | D7: =C7*(1-$I$4) -> 10770.352 | E7: =D7/(1-0.4)*2 -> 35901.173 | F7: 1000mm | G7: Yes | H7: Yes
B8: Boom - Fixed Bottom Arm | C8: ='[1]Ondal Configs'!G2 -> 8012.5 | D8: =C8*(1-$I$4) -> 6410 | E8: =D8/(1-0.4)*2 -> 21366.667 | F8: 1000mm | G8: No | H8: No
B9: Boom - Fixed Bottom Arm (XL) | C9: ='[1]Ondal Configs'!H2 -> 9362.88 | D9: =C9*(1-$I$4) -> 7490.304 | E9: =D9/(1-0.4)*2 -> 24967.68 | F9: 1000mm | G9: Yes | H9: No
B10: Fixed XXL | C10: ='[1]Ondal Configs'!I2 -> 10737.34 | D10: =C10*(1-$I$4) -> 8589.872 | E10: =D10/(1-0.4)*2 -> 28632.907 | G10: Yes | H10: No
B11: Large Monitor Boom | C11: 17141.96 | D11: =C11*(1-$I$4) -> 13713.568 | E11: =D11/(1-0.4)*2 -> 45711.893 | G11: Yes | H11: Yes
B12: Large Monitor Boom XL | C12: 19004 | D12: =C12*(1-$I$4) -> 15203.2 | E12: =D12/(1-0.4)*2 -> 50677.333 | G12: Yes | H12: Yes
B13: ="'Future' Boom" -> 'Future' Boom | C13: 0 | D13: =C13*(1-$I$4) -> 0 | E13: =D13/(1-0.4)*2 -> 0 | G13: No | H13: No
A15: Ondal Options | B15: Ceiling Cover | C15: Ondal List Price | D15: Imagine Cost | E15: Imagine List Price
I16: Placeholder
A17: 11-300-603 | B17: Boom - Single Square Ceiling Cover | C17: =SUM(C166:C168) -> 1536.74 | D17: =C17*(1-$I$4) -> 1229.392 | E17: =D17/(1-0.4)*2 -> 4097.9733 | I17: Future Boom | J17: 0
A18: 11-300-611 | B18: Tandem (1st Position) | C18: =SUM(C166:C168) -> 1536.74 | D18: =C18*(1-$I$4) -> 1229.392 | E18: =D18/(1-0.4)*2 -> 4097.9733
A19: 11-300-612 | B19: Tandem (2nd Position) | C19: 0 | D19: =C19*(1-$I$4) -> 0 | E19: =D19/(1-0.4)*2 -> 0
B21: Service Head
B23: Boom - Service Head | C23: 0 | D23: =C23*(1-$I$4) -> 0 | E23: =D23/(1-0.4)*2 -> 0 | F23: 200mm
B24: Boom - Service Head | C24: =C100+$C$130*2 -> 740.59 | D24: =C24*(1-$I$4) -> 592.472 | E24: =D24/(1-0.4)*2 -> 1974.9067 | F24: 400mm
B25: Boom - Service Head | C25: =C101+$C$130*4 -> 1483.03 | D25: =C25*(1-$I$4) -> 1186.424 | E25: =D25/(1-0.4)*2 -> 3954.7467 | F25: 600mm
B26: Boom - Service Head | C26: =C102+$C$130*6 -> 2247.7 | D26: =C26*(1-$I$4) -> 1798.16 | E26: =D26/(1-0.4)*2 -> 5993.8667 | F26: 800mm
B27: Boom - Service Head | C27: =C103+$C$130*8 -> 3010.51 | D27: =C27*(1-$I$4) -> 2408.408 | E27: =D27/(1-0.4)*2 -> 8028.0267 | F27: 1000mm
B28: Ceiling Tube
B30: Boom - Ceiling Flange | C30: 0 | D30: =C30*(1-$I$4) -> 0 | E30: =D30/(1-0.4)*2 -> 0 | F30: 100mm
B31: Boom - Ceiling Flange | C31: =C106 -> 94.43 | D31: =C31*(1-$I$4) -> 75.544 | E31: =D31/(1-0.4)*2 -> 251.81333 | F31: 300mm
B32: Boom - Ceiling Flange | C32: =C107 -> 185.15 | D32: =C32*(1-$I$4) -> 148.12 | E32: =D32/(1-0.4)*2 -> 493.73333 | F32: 500mm
B33: Boom - Ceiling Flange (XL) | C33: =C104 -> 0 | D33: =C33*(1-$I$4) -> 0 | E33: =D33/(1-0.4)*2 -> 0 | F33: 100mm
B34: Boom - Ceiling Flange (XL) | C34: =C110 -> 190.7 | D34: =C34*(1-$I$4) -> 152.56 | E34: =D34/(1-0.4)*2 -> 508.53333 | F34: 300mm
B35: Boom - Ceiling Flange (XL) | C35: =C111 -> 455.47 | D35: =C35*(1-$I$4) -> 364.376 | E35: =D35/(1-0.4)*2 -> 1214.5867 | F35: 500mm
B36: Top Arm
B38: Boom - Fixed Top Arm | C38: 0 | D38: =C38*(1-$I$4) -> 0 | E38: =D38/(1-0.4)*2 -> 0 | F38: 600mm
B39: Boom - Fixed Top Arm | C39: 0 | D39: =C39*(1-$I$4) -> 0 | E39: =D39/(1-0.4)*2 -> 0 | F39: 800mm
B40: Boom - Fixed Top Arm | C40: 0 | D40: =C40*(1-$I$4) -> 0 | E40: =D40/(1-0.4)*2 -> 0 | F40: 1000mm
B41: Boom - Fixed Top Arm | C41: 0 | D41: =C41*(1-$I$4) -> 0 | E41: =D41/(1-0.4)*2 -> 0 | F41: 1200mm
B42: Boom - Fixed Top Arm | C42: =C122 -> 596.83 | D42: =C42*(1-$I$4) -> 477.464 | E42: =D42/(1-0.4)*2 -> 1591.5467 | F42: 1400mm
B43: Boom - Fixed Top Arm | C43: =C123 -> 1234.49 | D43: =C43*(1-$I$4) -> 987.592 | E43: =D43/(1-0.4)*2 -> 3291.9733 | F43: 1600mm
B44: Bottom Arm
B46: Articulating Bottom Arm | C46: 0 | D46: =C46*(1-$I$4) -> 0 | E46: =D46/(1-0.4)*2 -> 0
B47: Bottom Arm | C47: 1 | D47: =C47*(1-$I$4) -> 0.8 | E47: =D47/(1-0.4)*2 -> 2.6666667 | F47: 600mm
B48: Bottom Arm | C48: 0 | D48: =C48*(1-$I$4) -> 0 | E48: =D48/(1-0.4)*2 -> 0 | F48: 800mm
B49: Bottom Arm | C49: 0 | D49: =C49*(1-$I$4) -> 0 | E49: =D49/(1-0.4)*2 -> 0 | F49: 1000mm
B50: Bottom Arm | C50: 0 | D50: =C50*(1-$I$4) -> 0 | E50: =D50/(1-0.4)*2 -> 0 | F50: 1200mm
B52: Services
B53: Data/Blank | E53: 0
B54: Medical Gas | C54: =C131-C130 -> 296.25 | D54: =C54*(1-$I$4) -> 237 | E54: =D54/(1-0.4)*2 -> 790
B55: Electrical (4 Duplex) | C55: =C135-C130 -> 203.67 | D55: =C55*(1-$I$4) -> 162.936 | E55: =D55/(1-0.4)*2 -> 543.12
B56: Electrical (6 Duplex) | C56: =C137-C130 -> 374 | D56: =C56*(1-$I$4) -> 299.2 | E56: =D56/(1-0.4)*2 -> 997.33333
B57: Nitrogen Regulator | C57: =C140 -> 789.72 | D57: =C57*(1-$I$4) -> 631.776 | E57: =D57/(1-0.4)*2 -> 2105.92
B58: Front Pass Thru | C58: =C141 -> 288.83 | D58: =C58*(1-$I$4) -> 231.064 | E58: =D58/(1-0.4)*2 -> 770.21333
B59: Cicruits
B61: No Circuits | C61: 0 | D61: =C61*(1-$I$4) -> 0 | E61: =D61/(1-0.4)*2 -> 0
B62: (1) Circuit | C62: 0 | D62: =C62*(1-$I$4) -> 0 | E62: =D62/(1-0.4)*2 -> 0
B63: (2) Circuits | C63: 0 | D63: =C63*(1-$I$4) -> 0 | E63: =D63/(1-0.4)*2 -> 0
B64: (3) Circuits | C64: 0 | D64: =C64*(1-$I$4) -> 0 | E64: =D64/(1-0.4)*2 -> 0
B65: (4) Circuits | C65: 0 | D65: =C65*(1-$I$4) -> 0 | E65: =D65/(1-0.4)*2 -> 0
B66: (5) Circuits | C66: 0 | D66: =C66*(1-$I$4) -> 0 | E66: =D66/(1-0.4)*2 -> 0
B67: (6) Circuits | C67: 0 | D67: =C67*(1-$I$4) -> 0 | E67: =D67/(1-0.4)*2 -> 0
B68: Shelves
B70: No 750mm Shelves | C70: 0 | D70: =C70*(1-$I$4) -> 0 | E70: =D70/(1-0.4)*2 -> 0
B71: (1) 750mm Shelf | C71: =SUM(C149*3,C150,C147)/3 -> 767.14333 | D71: =C71*(1-$I$4) -> 613.71467 | E71: =D71/(1-0.4)*2 -> 2045.7156
B72: (2) 750mm Shelfs | C72: =SUM(C149*3,C150,C147)/3*2 -> 1534.2867 | D72: =C72*(1-$I$4) -> 1227.4293 | E72: =D72/(1-0.4)*2 -> 4091.4311
B73: (3) 750mm Shelfs | C73: =SUM(C149*3,C150,C147)/3*3 -> 2301.43 | D73: =C73*(1-$I$4) -> 1841.144 | E73: =D73/(1-0.4)*2 -> 6137.1467
B74: (4) 750mm Shelfs | C74: =SUM(C149*3,C150,C147)/3*4 -> 3068.5733 | D74: =C74*(1-$I$4) -> 2454.8587 | E74: =D74/(1-0.4)*2 -> 8182.8622
B77: No 500mm Shelves | C77: 0 | D77: =C77*(1-$I$4) -> 0 | E77: =D77/(1-0.4)*2 -> 0
B78: (1) 500mm Shelf | C78: =SUM(C148*3,C150,C147)/3 -> 504.23333 | D78: =C78*(1-$I$4) -> 403.38667 | E78: =D78/(1-0.4)*2 -> 1344.6222
B79: (2) 500mm Shelfs | C79: =SUM(C148*3,C150,C147)/3*2 -> 1008.4667 | D79: =C79*(1-$I$4) -> 806.77333 | E79: =D79/(1-0.4)*2 -> 2689.2444
B80: (3) 500mm Shelfs | C80: =SUM(C148*3,C150,C147)/3*3 -> 1512.7 | D80: =C80*(1-$I$4) -> 1210.16 | E80: =D80/(1-0.4)*2 -> 4033.8667
B81: (4) 500mm Shelfs | C81: =SUM(C148*3,C150,C147)/3*4 -> 2016.9333 | D81: =C81*(1-$I$4) -> 1613.5467 | E81: =D81/(1-0.4)*2 -> 5378.4889
A83: Ondal Accessories | C83: Ondal List Price | D83: Imagine Cost | E83: Imagine List Price
C84: 0 | D84: =C84*(1-$I$4) -> 0 | E84: =D84/(1-0.4)*2 -> 0
B85: Straight Rail | C85: =12456.19-C4 -> 87.02 | D85: =C85*(1-$I$4) -> 69.616 | E85: =D85/(1-0.4)*2 -> 232.05333 | F85: 600mm
B86: Single Drawer for Shelf | C86: =C151 -> 453.62 | D86: =C86*(1-$I$4) -> 362.896 | E86: =D86/(1-0.4)*2 -> 1209.6533
B87: Double Drawer for Shelf | C87: =C152 -> 862.8 | D87: =C87*(1-$I$4) -> 690.24 | E87: =D87/(1-0.4)*2 -> 2300.8
B88: Keyboard Drawer for Shelf | C88: =C153 -> 738.12 | D88: =C88*(1-$I$4) -> 590.496 | E88: =D88/(1-0.4)*2 -> 1968.32
B89: Small Basket | C89: =C156 -> 161.08 | D89: =C89*(1-$I$4) -> 128.864 | E89: =D89/(1-0.4)*2 -> 429.54667
B90: Small Basket - Deep | C90: =C157 -> 138.86 | D90: =C90*(1-$I$4) -> 111.088 | E90: =D90/(1-0.4)*2 -> 370.29333
B91: Universal Hook | C91: =C158 -> 107.39 | D91: =C91*(1-$I$4) -> 85.912 | E91: =D91/(1-0.4)*2 -> 286.37333
B92: Oxygen Tank Holder | C92: =C159 -> 731.34 | D92: =C92*(1-$I$4) -> 585.072 | E92: =D92/(1-0.4)*2 -> 1950.24
B93: Light (Top Arm or Service Head) | C93: =C161 -> 559.15 | D93: =C93*(1-$I$4) -> 447.32 | E93: =D93/(1-0.4)*2 -> 1491.0667
B94: Large Monitor Rear Monitor Mounts | C94: 935.02 | D94: =C94*(1-$I$4) -> 748.016 | E94: =D94/(1-0.4)*2 -> 2493.3867
A97: Ondal Options | C97: Ondal List Price | D97: Imagine Cost | E97: Imagine List Price
A99: Service Head | B99: 200mm | C99: 0 | D99: =C99*(1-$I$4) -> 0 | E99: =D99/(1-0.4)*2 -> 0
B100: 400mm | C100: =12535.8-C4 -> 166.63 | D100: =C100*(1-$I$4) -> 133.304 | E100: =D100/(1-0.4)*2 -> 444.34667
B101: 600mm | C101: =12704.28-C4 -> 335.11 | D101: =C101*(1-$I$4) -> 268.088 | E101: =D101/(1-0.4)*2 -> 893.62667
B102: 800mm | C102: =12894.99-C4 -> 525.82 | D102: =C102*(1-$I$4) -> 420.656 | E102: =D102/(1-0.4)*2 -> 1402.1867
B103: 1000mm | C103: =13083.84-C4 -> 714.67 | D103: =C103*(1-$I$4) -> 571.736 | E103: =D103/(1-0.4)*2 -> 1905.7867
A104: Ceiling Tube
B105: 100mm | C105: 0 | D105: =C105*(1-$I$4) -> 0 | E105: =D105/(1-0.4)*2 -> 0
B106: 300mm | C106: =12463.6-C4 -> 94.43 | D106: =C106*(1-$I$4) -> 75.544 | E106: =D106/(1-0.4)*2 -> 251.81333
B107: 500mm | C107: =12554.32-C4 -> 185.15 | D107: =C107*(1-$I$4) -> 148.12 | E107: =D107/(1-0.4)*2 -> 493.73333
A108: Ceiling Tube XL
B109: 100mm | C109: 0 | D109: =C109*(1-$I$4) -> 0 | E109: =D109/(1-0.4)*2 -> 0
B110: 300mm | C110: =14032.73-C5 -> 190.7 | D110: =C110*(1-$I$4) -> 152.56 | E110: =D110/(1-0.4)*2 -> 508.53333
B111: 500mm | C111: =14297.5-C5 -> 455.47 | D111: =C111*(1-$I$4) -> 364.376 | E111: =D111/(1-0.4)*2 -> 1214.5867
A112: Top Arm
B113: 600mm | C113: =12100.89-C4 -> -268.28 | D113: =C113*(1-$I$4) -> -214.624 | E113: =D113/(1-0.4)*2 -> -715.41333
B114: 800mm | C114: =12151.44-C4 -> -217.73 | D114: =C114*(1-$I$4) -> -174.184 | E114: =D114/(1-0.4)*2 -> -580.61333
B115: 1000mm | C115: =12209.76-C4 -> -159.41 | D115: =C115*(1-$I$4) -> -127.528 | E115: =D115/(1-0.4)*2 -> -425.09333
B116: 1200mm | C116: 0 | D116: =C116*(1-$I$4) -> 0 | E116: =D116/(1-0.4)*2 -> 0
...

Sheet 2025_03_28 3D Light Pricing
A1: Part Number | B1: Configuration | C1: Current 3D Tool Config (Top to bottom) | D1: Imagine List Price | E1: Imagine Sales Price | G1: Sections | H1: Part Number
A2: 111-001111 | B2: 7000 - LED | C2: Lights - U | ONE | D2: ='2025_03_28 Light Pricing'!$H$4+'2025_03_28 Light Pricing'!H23 -> 37407.7 | E2: =D2*$H$11 -> 18703.85 | G2: 7000/ U|ONE Lights and all variations | H2: 111
A3: 111-001112 | B3: 7000 - LED / LED | C3: Lights - U | ONE Lights - U | ONE | D3: ='2025_03_28 Light Pricing'!$H$5+'2025_03_28 Light Pricing'!H23+'2025_03_28 Light Pricing'!H23 -> 73942.55 | E3: =D3*$H$11 -> 36971.275 | G3: No light configs (not including booms) | H3: 112
A4: 111-001113 | B4: 7000 - LED / LED / LED | C4: Lights -U|ONE,Lights - U|ONE,Lights - U|ONE | D4: ='2025_03_28 Light Pricing'!$H$6+'2025_03_28 Light Pricing'!H23+'2025_03_28 Light Pricing'!H23+'2025_03_28 Light Pricing'!H23 -> 106014.52 | E4: =D4*$H$11 -> 53007.258 | G4: 8000/ U|002 Lights and all variations | H4: 113
A5: 111-001114 | B5: 7000 - LED / FP | C5: Lights -U|ONE, Lights - Flat Panel Carrier | D5: ='2025_03_28 Light Pricing'!$H$7+'2025_03_28 Light Pricing'!H23+'2025_03_28 Light Pricing'!$H$27 -> 54751.183 | E5: =D5*$H$11 -> 27375.592 | G5: Sim.Flex | H5: 114
A6: 111-001115 | B6: 7000 - FP / LED | C6: Lights - Flat Panel Carrier, Lights -U|ONE | D6: ='2025_03_28 Light Pricing'!$H$8+'2025_03_28 Light Pricing'!$H$27+'2025_03_28 Light Pricing'!H23 -> 54376.533 | E6: =D6*$H$11 -> 27188.267 | G6: Drop Down Options | H6: 115
A7: 111-001116 | B7: 7000 - LED / LED / FP | C7: Lights -U|ONE,Lights - U|ONE,Lights - Flat Panel Carrier | D7: ='2025_03_28 Light Pricing'!$H$9+'2025_03_28 Light Pricing'!H23+'2025_03_28 Light Pricing'!H23+'2025_03_28 Light Pricing'!$H$27 -> 89254.35 | E7: =D7*$H$11 -> 44627.175 | G7: Light Exchange | H7: 116
A8: 111-001117 | B8: 7000 - LED / LS | C8: Lights -U|ONE, Lights - Flat Panel Carrier | D8: ='2025_03_28 Light Pricing'!$H$10+'2025_03_28 Light Pricing'!H23+'2025_03_28 Light Pricing'!$H$28 -> 63174.183 | E8: =D8*$H$11 -> 31587.092 | G8: Shipping & Installation | H8: 117
A9: 111-001118 | B9: 7000 - LED / LED / LS | C9: Lights -U|ONE, Lights - U|ONE, Lights - Flat Panel Carrier | D9: ='2025_03_28 Light Pricing'!$H$11+'2025_03_28 Light Pricing'!H23+'2025_03_28 Light Pricing'!H23+'2025_03_28 Light Pricing'!$H$28 -> 95246.15 | E9: =D9*$H$11 -> 47623.075
A10: 111-001119 | B10: 7000 LC - LED | C10: Lights - U|ONE (Low Ceiling) | D10: ='2025_03_28 Light Pricing'!$H$4+'2025_03_28 Light Pricing'!H25 -> 39936.433 | E10: =D10*$H$11 -> 19968.217 | H10: Light Discount
A11: 111-001120 | B11: 7000 LC - LED / LED | C11: Lights - U|ONE (Low Ceiling),Lights - U|ONE (Low Ceiling) | D11: ='2025_03_28 Light Pricing'!$H$5+'2025_03_28 Light Pricing'!H25+'2025_03_28 Light Pricing'!H25 -> 79000.017 | E11: =D11*$H$11 -> 39500.008 | H11: 0.5
A12: 111-001121 | B12: 7000 LC - LED / LED / LED | C12: Lights - U|ONE (Low Ceiling),Lights - U|ONE (Low Ceiling),Lights - U|ONE (Low Ceiling) | D12: ='2025_03_28 Light Pricing'!$H$6+'2025_03_28 Light Pricing'!H25+'2025_03_28 Light Pricing'!H25+'2025_03_28 Light Pricing'!H25 -> 113600.72 | E12: =D12*$H$11 -> 56800.358
A13: 111-001122 | B13: 7000 LC - LED / FP | C13: Lights - U|ONE (Low Ceiling), Lights - Flat Panel Carrier | D13: ='2025_03_28 Light Pricing'!$H$7+'2025_03_28 Light Pricing'!H25+'2025_03_28 Light Pricing'!$H$27 -> 57279.917 | E13: =D13*$H$11 -> 28639.958
A14: 111-001123 | B14: 7000 LC - FP / LED | C14: Lights - Flat Panel Carrier, Lights - U|ONE (Low Ceiling) | D14: ='2025_03_28 Light Pricing'!$H$8+'2025_03_28 Light Pricing'!$H$27+'2025_03_28 Light Pricing'!H25 -> 56905.267 | E14: =D14*$H$11 -> 28452.633
A15: 111-001124 | B15: 7000 LC - LED / LED / FP | C15: Lights - U|ONE (Low Ceiling),Lights - U|ONE (Low Ceiling), Lights - Flat Panel Carrier | D15: ='2025_03_28 Light Pricing'!$H$9+'2025_03_28 Light Pricing'!H25+'2025_03_28 Light Pricing'!H25+'2025_03_28 Light Pricing'!$H$27 -> 94311.817 | E15: =D15*$H$11 -> 47155.908
A16: 111-001125 | B16: 7000 LC - LED / LS | C16: Lights - U|ONE (Low Ceiling), Lights - Flat Panel Carrier | D16: ='2025_03_28 Light Pricing'!$H$10+'2025_03_28 Light Pricing'!H25+'2025_03_28 Light Pricing'!$H$28 -> 65702.917 | E16: =D16*$H$11 -> 32851.458
A17: 111-001126 | B17: 7000 LC - LED / LED / LS | C17: Lights - U|ONE (Low Ceiling),Lights - U|ONE (Low Ceiling), Lights - Flat Panel Carrier | D17: ='2025_03_28 Light Pricing'!$H$11+'2025_03_28 Light Pricing'!H25+'2025_03_28 Light Pricing'!H25+'2025_03_28 Light Pricing'!$H$28 -> 100303.62 | E17: =D17*$H$11 -> 50151.808
A18: 112-001111 | B18: No Lights - FP | C18: Lights - Flat Panel Carrier | D18: ='2025_03_28 Light Pricing'!H12+'2025_03_28 Light Pricing'!H27 -> 20611 | E18: =D18*$H$11 -> 10305.5
A19: 112-001112 | B19: No Lights - LS | C19: Lights - Lead Shield | D19: ='2025_03_28 Light Pricing'!H13+'2025_03_28 Light Pricing'!H28 -> 26639.333 | E19: =D19*$H$11 -> 13319.667
A20: 112-001113 | B20: No Lights - FP / FP | C20: Lights - Flat Panel Carrier, Lights - Flat Panel Carrier | D20: ='2025_03_28 Light Pricing'!H14+'2025_03_28 Light Pricing'!H27+'2025_03_28 Light Pricing'!H27 -> 38481.933 | E20: =D20*$H$11 -> 19240.967
A21: 112-001114 | B21: No Lights - LS / LS | C21: Lights - Lead Shield, Lights - Lead Shield | D21: ='2025_03_28 Light Pricing'!H15+'2025_03_28 Light Pricing'!H28+'2025_03_28 Light Pricing'!H28 -> 52405.817 | E21: =D21*$H$11 -> 26202.908
A22: 112-001115 | B22: No Lights - FP / LS | C22: Lights - Flat Panel Carrier, Lights - Lead Shield | D22: ='2025_03_28 Light Pricing'!H16+'2025_03_28 Light Pricing'!H27+'2025_03_28 Light Pricing'!H28 -> 43608.167 | E22: =D22*$H$11 -> 21804.083
A23: 112-001116 | B23: No Lights - LS / FP | C23: Lights - Lead Shield, Lights - Flat Panel Carrier | D23: ='2025_03_28 Light Pricing'!H17+'2025_03_28 Light Pricing'!H28+'2025_03_28 Light Pricing'!H27 -> 43982.817 | E23: =D23*$H$11 -> 21991.408
A24: 112-001117 | B24: No Lights - TC FP (Ondal) | C24: TC Flat Panel (no model currently in the tool) | D24: ='2025_03_28 Light Pricing'!H33 -> 22500 | E24: =D24*$H$11 -> 11250
A25: 113-001111 | B25: 8000 - LED | C25: Lights - U|002 Standard | D25: ='2025_03_28 Light Pricing'!$H$4+'2025_03_28 Light Pricing'!$H$26 -> 41940.133 | E25: =D25*$H$11 -> 20970.067
A26: 113-001112 | B26: 8000 - LED / LED | C26: Lights - U|002,Lights - U|002 | D26: ='2025_03_28 Light Pricing'!$H$5+'2025_03_28 Light Pricing'!$H$26+'2025_03_28 Light Pricing'!$H$26 -> 83007.417 | E26: =D26*$H$11 -> 41503.708
A27: 113-001113 | B27: 8000 - LED / LED / LED | C27: Lights - U|002,Lights - U|002, Lights - U|002 | D27: ='2025_03_28 Light Pricing'!$H$6+'2025_03_28 Light Pricing'!$H$26+'2025_03_28 Light Pricing'!$H$26+'2025_03_28 Light Pricing'!$H$26 -> 119611.82 | E27: =D27*$H$11 -> 59805.908
A28: 113-001114 | B28: 8000 - LED / FP | C28: Lights - U|002, Lights - Flat Panel Carrier | D28: ='2025_03_28 Light Pricing'!$H$7+'2025_03_28 Light Pricing'!$H$26+'2025_03_28 Light Pricing'!$H$27 -> 59283.617 | E28: =D28*$H$11 -> 29641.808
A29: 113-001115 | B29: 8000 - FP / LED | C29: Lights - Flat Panel Carrier,Lights - U|002 | D29: ='2025_03_28 Light Pricing'!$H$8+'2025_03_28 Light Pricing'!$H$27+'2025_03_28 Light Pricing'!$H$26 -> 58908.967 | E29: =D29*$H$11 -> 29454.483
A30: 113-001116 | B30: 8000 - LED / LED / FP | C30: Lights - U|002,Lights - U|002, Lights - Flat Panel Carrier | D30: ='2025_03_28 Light Pricing'!$H$9+'2025_03_28 Light Pricing'!$H$26+'2025_03_28 Light Pricing'!$H$26+'2025_03_28 Light Pricing'!$H$27 -> 98319.217 | E30: =D30*$H$11 -> 49159.608
A31: 113-001117 | B31: 8000 - LED / LS | C31: Lights - U|002, Lights - Flat Panel Carrier | D31: ='2025_03_28 Light Pricing'!$H$10+'2025_03_28 Light Pricing'!$H$26+'2025_03_28 Light Pricing'!$H$28 -> 67706.617 | E31: =D31*$H$11 -> 33853.308
A32: 113-001118 | B32: 8000 - LED / LED / LS | C32: Lights - U|002, Lights - U|002, Lights - Lead Shield | D32: ='2025_03_28 Light Pricing'!$H$11+'2025_03_28 Light Pricing'!$H$26+'2025_03_28 Light Pricing'!$H$26+'2025_03_28 Light Pricing'!$H$28 -> 104311.02 | E32: =D32*$H$11 -> 52155.508
A33: 113-001119 | B33: 8000 LC - LED | C33: Lights - U | 002 (Low Ceiling) | D33: ='2025_03_28 Light Pricing'!$H$4+'2025_03_28 Light Pricing'!$H$26 -> 41940.133 | E33: =D33*$H$11 -> 20970.067
A34: 113-001120 | B34: 8000 LC - LED / LED | C34: Lights - U|002 LC, Lights - U|002 LC | D34: ='2025_03_28 Light Pricing'!$H$5+'2025_03_28 Light Pricing'!$H$26+'2025_03_28 Light Pricing'!$H$26 -> 83007.417 | E34: =D34*$H$11 -> 41503.708
A35: 113-001121 | B35: 8000 LC - LED / LED / LED | C35: Lights - U|002LC ,Lights - U|002 LC,Lights - U|002 LC | D35: ='2025_03_28 Light Pricing'!$H$6+'2025_03_28 Light Pricing'!$H$26+'2025_03_28 Light Pricing'!$H$26+'2025_03_28 Light Pricing'!$H$26 -> 119611.82 | E35: =D35*$H$11 -> 59805.908
A36: 113-001122 | B36: 8000 LC - LED / FP | C36: Lights - U|002 LC, Lights - Flat Panel Carrier | D36: ='2025_03_28 Light Pricing'!$H$7+'2025_03_28 Light Pricing'!$H$26+'2025_03_28 Light Pricing'!$H$27 -> 59283.617 | E36: =D36*$H$11 -> 29641.808
A37: 113-001123 | B37: 8000 LC - FP / LED | C37: Lights - Flat Panel Carrier, U|002 LC | D37: ='2025_03_28 Light Pricing'!$H$8+'2025_03_28 Light Pricing'!$H$27+'2025_03_28 Light Pricing'!$H$26 -> 58908.967 | E37: =D37*$H$11 -> 29454.483
A38: 113-001124 | B38: 8000 LC - LED / LED / FP | C38: Lights - U|002 LC, Lights - U|002 LC, Lights - Flat Panel Carrier | D38: ='2025_03_28 Light Pricing'!$H$9+'2025_03_28 Light Pricing'!$H$26+'2025_03_28 Light Pricing'!$H$26+'2025_03_28 Light Pricing'!$H$27 -> 98319.217 | E38: =D38*$H$11 -> 49159.608
A39: 113-001125 | B39: 8000 LC - LED / LS | C39: Lights - U|002 LC, Lights - Flat Panel Carrier | D39: ='2025_03_28 Light Pricing'!$H$10+'2025_03_28 Light Pricing'!$H$26+'2025_03_28 Light Pricing'!$H$28 -> 67706.617 | E39: =D39*$H$11 -> 33853.308
A40: 113-001126 | B40: 8000 LC - LED / LED / LS | C40: Lights - U|002LC ,Lights - U|002LC , Lights - Lead Shield | D40: ='2025_03_28 Light Pricing'!$H$11+'2025_03_28 Light Pricing'!$H$26+'2025_03_28 Light Pricing'!$H$26+'2025_03_28 Light Pricing'!$H$28 -> 104311.02 | E40: =D40*$H$11 -> 52155.508
A41: 113-001111 | B41: Future Light - LED | C41: U|003 | D41: 0 | E41: =D41*$H$11 -> 0
A42: 113-001112 | B42: Future Light - LED / LED | C42: U|003, U|003 | D42: 0 | E42: =D42*$H$11 -> 0
A43: 113-001113 | B43: Future Light - LED / LED / LED | C43: U|003, U|003, U|003 | D43: 0 | E43: =D43*$H$11 -> 0
A44: 113-001114 | B44: Future Light - LED / FP | C44: U|003, Flat Panel | D44: 0 | E44: =D44*$H$11 -> 0
A45: 113-001115 | B45: Future Light - FP / LED | C45: Flat Panel, U|003 | D45: 0 | E45: =D45*$H$11 -> 0
A46: 113-001116 | B46: Future Light - LED / LED / FP | C46: U|003, U|003, Flat Panel | D46: 0 | E46: =D46*$H$11 -> 0
A47: 113-001117 | B47: Future Light - LED / LS | C47: U|003, Flat Panel | D47: 0 | E47: =D47*$H$11 -> 0
A48: 113-001118 | B48: Future Light - LED / LED / LS | C48: U|003, U|003, Lead Sheild | D48: 0 | E48: =D48*$H$11 -> 0
A49: 113-001119 | B49: Future Light LC - LED | C49: U|003 LC | D49: 0 | E49: =D49*$H$11 -> 0
A50: 113-001120 | B50: Future Light LC - LED / LED | C50: U|003 LC, U|003 LC | D50: 0 | E50: =D50*$H$11 -> 0
A51: 113-001121 | B51: Future Light LC - LED / LED / LED | C51: U|003LC , U|003 LC, U|003 LC | D51: 0 | E51: =D51*$H$11 -> 0
A52: 113-001122 | B52: Future Light LC - LED / FP | C52: U|003 LC, Flat Panel | D52: 0 | E52: =D52*$H$11 -> 0
... A56: 113-001126 | B56: Future Light LC - LED / LED / LS | C56: U|003 LC , U|003 LC , Lead Sheild | D56: 0 | E56: =D56*$H$11 -> 0
A59: Additional Model Options | D59: Imagine List Price | E59: Imagine Sales Price
A60: 114-001111 | B60: Lights - Horizontal Arm (SimFlex) | C60: Assign when sim.flex option is selected (with 1 arm) | D60: ='2025_03_28 Light Pricing'!H83 -> 5833.3333 | E60: =D60*$H$11 -> 2916.6667
A61: 114-001112 | B61: Sim.Flex (2 Arms) | C61: Assign when sim.flex option is selected (with 2 arms) | D61: ='2025_03_28 Light Pricing'!H84 -> 9166.6667 | E61: =D61*$H$11 -> 4583.3333
A62: 114-001113 | B62: Sim.Flex (3 Arms) | C62: Assign when sim.flex option is selected (with 3 arms) | D62: ='2025_03_28 Light Pricing'!H85 -> 12500 | E62: =D62*$H$11 -> 6250
E63: =D63*$H$11 -> 0
A64: Additional Options (Drop Down) | G64: Example
A65: Part Number | B65: Option | D65: Imagine List Price | E65: Imagine Sales Price | G65: Light Single / Tandem | H65: Options
B66: Ceiling Cover | G66: Ceiling Cover
A67: 115-001111 | B67: Lights - Single Ceiling Cover (Slim) | D67: ='2025_03_28 Light Pricing'!H89 -> 1563.2167 | E67: =D67*$H$11 -> 781.60833 | G67: Wall Control
A68: 115-001112 | B68: Lights - Single Ceiling Cover (Standard) | D68: ='2025_03_28 Light Pricing'!H90 -> 3398.9667 | E68: =D68*$H$11 -> 1699.4833 | G68: Integration Control
A69: 115-001113 | B69: Tandem (1st Position) | D69: ='2025_03_28 Light Pricing'!H91 -> 5807.6533 | E69: =D69*$H$11 -> 2903.8267 | G69: In-Light Camera
A70: 115-001114 | B70: Tandem (2nd Position) | D70: ='2025_03_28 Light Pricing'!H92 -> 0 | E70: =D70*$H$11 -> 0 | G70: Disposable Adpaters
B71: Wall Control
B72: Wall Control in Seperate Config | D72: ='2025_03_28 Light Pricing'!H53 -> 0 | E72: =D72*$H$11 -> 0
A73: 115-001115 | B73: Wall Control (Single) | D73: ='2025_03_28 Light Pricing'!H54 -> 4710.4167 | E73: =D73*$H$11 -> 2355.2083
A74: 115-001116 | B74: Wall Control (Dual) | D74: ='2025_03_28 Light Pricing'!H55 -> 2146.85 | E74: =D74*$H$11 -> 1073.425
A75: 115-001117 | B75: Wall Control (Triple) | D75: ='2025_03_28 Light Pricing'!H56 -> 3205.7 | E75: =D75*$H$11 -> 1602.85
A76: 115-001118 | B76: Wall Control (Touch) | D76: ='2025_03_28 Light Pricing'!H57 -> 4854.2333 | E76: =D76*$H$11 -> 2427.1167
A77: 115-001119 | B77: Wall Control (Single w/ Cam) | D77: ='2025_03_28 Light Pricing'!H58 -> 3324.75 | E77: =D77*$H$11 -> 1662.375
A78: 115-001120 | B78: Wall Control (Dual w/ Cam) | D78: ='2025_03_28 Light Pricing'!H59 -> 4666.9667 | E78: =D78*$H$11 -> 2333.4833
A79: 115-001121 | B79: Wall Control (Triple w/ Cam) | D79: ='2025_03_28 Light Pricing'!H60 -> 6171.0667 | E79: =D79*$H$11 -> 3085.5333
B80: Integration Control
B81: None | D81: ='2025_03_28 Light Pricing'!H64 -> 0 | E81: =D81*$H$11 -> 0
A82: 115-001122 | B82: Storz Integration Control | D82: ='2025_03_28 Light Pricing'!H65 -> 3082.9833 | E82: =D82*$H$11 -> 1541.4917
B83: In-Light Camera
B84: None | D84: ='2025_03_28 Light Pricing'!H69 -> 0 | E84: =D84*$H$11 -> 0
A85: 115-001123 | B85: Wired Prep | D85: ='2025_03_28 Light Pricing'!H70 -> 5661.2 | E85: =D85*$H$11 -> 2830.6
A86: 115-001124 | B86: Wired | D86: ='2025_03_28 Light Pricing'!H71 -> 30796.98 | E86: =D86*$H$11 -> 15398.49
A87: 115-001125 | B87: Wireless | D87: ='2025_03_28 Light Pricing'!H72 -> 43025.2 | E87: =D87*$H$11 -> 21512.6
B88: Disposable Adapter
B89: None | D89: ='2025_03_28 Light Pricing'!H76 -> 0 | E89: =D89*$H$11 -> 0
A90: 115-001126 | B90: Screw-On | D90: ='2025_03_28 Light Pricing'!H77 -> 420 | E90: =D90*$H$11 -> 210
A91: 115-001127 | B91: Slip-On | D91: ='2025_03_28 Light Pricing'!H78 -> 1488.9333 | E91: =D91*$H$11 -> 744.46667
B92: Exchange
B93: None | D93: 0 | E93: =D93*$H$11 -> 0
A94: 116-001111 | B94: Yes, 1 Light Exchange | D94: 25000 | E94: =D94*$H$11 -> 12500
A95: 116-001112 | B95: Yes, 2 Light Exchange | D95: 50000 | E95: =D95*$H$11 -> 25000
A96: 116-001113 | B96: Yes, 3 Light Exchange | D96: 75000 | E96: =D96*$H$11 -> 37500
A98: Additional Line Items | D98: Imagine List Price | E98: Imagine Sales Price
A99: 117-001111 | B99: Installation (Lights) | D99: ='2025_03_28 Light Pricing'!H96 -> 3000 | E99: =D99*(1-0.5) -> 1500
A100: 117-001112 | B100: Shipping (Lights) | D100: ='2025_03_28 Light Pricing'!H100 -> 1000 | E100: =D100*(1-0.5) -> 500

Sheet 2025_03_28 Light Pricing
A1: Base Model(s) | D1: 0
B2: Part # | C2: Base Model | D2: # of Arms | E2: # of Lights | F2: TC Mount? | G2: Imagine Cost | H2: Imagine List Price | J2: Ceiling Tube | K2: Central Axis | L2: Turning Cover
B4: 11-100-101 | C4: LED | D4: 1 | E4: 1 | F4: No | G4: =SUM(J4:L4) -> 2075.235 | H4: =G4/(1-0.4)*2 -> 6917.45 | J4: =F195 -> 381.6 | K4: =F108 -> 1693.635 | L4: 0
B5: 11-100-102 | C5: LED / LED | D5: 2 | E5: 2 | F5: No | G5: =SUM(J5:L5) -> 3888.615 | H5: =G5/(1-0.4)*2 -> 12962.05 | J5: =F196 -> 381.6 | K5: =F117 -> 3507.015 | L5: 0
B6: 11-100-103 | C6: LED / LED / LED | D6: 3 | E6: 3 | F6: No | G6: =SUM(J6:L6) -> 4363.13 | H6: =G6/(1-0.4)*2 -> 14543.767 | J6: =F197 -> 381.6 | K6: =F124 -> 3981.53 | L6: 0
B7: 11-100-104 | C7: LED / FP | D7: 2 | E7: 1 | F7: No | G7: =SUM(J7:L7) -> 2889.055 | H7: =G7/(1-0.4)*2 -> 9630.1833 | J7: =F198 -> 381.6 | K7: =F115 -> 2311.44 | L7: =F158 -> 196.015
B8: 11-100-105 | C8: FP / LED | D8: 2 | E8: 1 | F8: No | G8: =SUM(J8:L8) -> 2776.66 | H8: =G8/(1-0.4)*2 -> 9255.5333 | J8: =F199 -> 381.6 | K8: =F116 -> 2395.06 | L8: 0
B9: 11-100-106 | C9: LED / LED / FP | D9: 3 | E9: 2 | F9: No | G9: =SUM(J9:L9) -> 4092.93 | H9: =G9/(1-0.4)*2 -> 13643.1 | J9: =F200 -> 381.6 | K9: =F123 -> 3515.315 | L9: =F158 -> 196.015
B10: 11-100-107 | C10: LED / LS | D10: 2 | E10: 1 | F10: No | G10: =SUM(J10:L10) -> 3888.615 | H10: =G10/(1-0.4)*2 -> 12962.05 | J10: =F201 -> 381.6 | K10: =F117 -> 3507.015 | L10: 0
B11: 11-100-108 | C11: LED / LED / LS | D11: 3 | E11: 2 | F11: No | G11: =SUM(J11:L11) -> 4363.13 | H11: =G11/(1-0.4)*2 -> 14543.767 | J11: =F202 -> 381.6 | K11: =F124 -> 3981.53 | L11: 0
B12: 11-100-109 | C12: FP | D12: 1 | E12: 0 | F12: No | G12: =SUM(J12:L12) -> 1794.075 | H12: =G12/(1-0.4)*2 -> 5980.25 | J12: =F203 -> 381.6 | K12: =F109 -> 1412.475 | L12: 0
B13: 11-100-110 | C13: LS | D13: 1 | E13: 0 | F13: No | G13: =SUM(J13:L13) -> 2075.235 | H13: =G13/(1-0.4)*2 -> 6917.45 | J13: =F204 -> 381.6 | K13: =F108 -> 1693.635 | L13: 0
B14: 11-100-111 | C14: FP / FP | D14: 2 | E14: 0 | F14: No | G14: =SUM(J14:L14) -> 2766.13 | H14: =G14/(1-0.4)*2 -> 9220.4333 | J14: =F205 -> 381.6 | K14: =F118 -> 2188.515 | L14: =F158 -> 196.015
B15: 11-100-112 | C15: LS / LS | D15: 2 | E15: 0 | F15: No | G15: =SUM(J15:L15) -> 3888.615 | H15: =G15/(1-0.4)*2 -> 12962.05 | J15: =F206 -> 381.6 | K15: =F117 -> 3507.015 | L15: 0
B16: 11-100-113 | C16: FP / LS | D16: 2 | E16: 0 | F16: No | G16: =SUM(J16:L16) -> 2776.66 | H16: =G16/(1-0.4)*2 -> 9255.5333 | J16: =F207 -> 381.6 | K16: =F116 -> 2395.06 | L16: 0
B17: 11-100-114 | C17: LS / FP | D17: 2 | E17: 0 | F17: No | G17: =SUM(J17:L17) -> 2889.055 | H17: =G17/(1-0.4)*2 -> 9630.1833 | J17: =F208 -> 381.6 | K17: =F115 -> 2311.44 | L17: =F158 -> 196.015
B18: 11-100-115 | C18: LED (3P) | D18: 1 | E18: 1 | F18: No | G18: =SUM(J18:L18) -> 1427.065 | H18: =G18/(1-0.4)*2 -> 4756.8833 | J18: =F209 -> 381.6 | K18: =F110 -> 1045.465 | L18: 0
A20: Priced Option(s)
B21: Part # | C21: Arm Selections | G21: Imagine Cost | H21: Imagine List Price | J21: Spring Arm | K21: Lighthead | L21: Flat Panel | M21: Lead Shield | N21: Power Supply | O21: Power Cable | P21: Control Cable
B23: 11-200-101 | C23: ="7000 Standard" -> 7000 Standard | D23: LED | G23: =SUM(J23:P23) -> 9147.075 | H23: =G23/(1-0.4)*2 -> 30490.25 | J23: =F129 -> 1162.445 | K23: =F140 -> 7008.815 | L23: 0 | M23: 0 | N23: =$F$163 -> 807.76 | O23: =$F$164 -> 99.705 | P23: =$F$165 -> 68.35
B24: 11-200-103 | C24: ="8000 Standard" -> 8000 Standard | D24: LED | G24: =SUM(J24:P24) -> 9756.54 | H24: =G24/(1-0.4)*2 -> 32521.8 | J24: =F129 -> 1162.445 | K24: =F136 -> 7618.28 | L24: 0 | M24: 0 | N24: =$F$163 -> 807.76 | O24: =$F$164 -> 99.705 | P24: =$F$165 -> 68.35
B25: 11-200-102 | C25: 7000 Low Ceiling | D25: LED | G25: =SUM(J25:P25) -> 9905.695 | H25: =G25/(1-0.4)*2 -> 33018.983 | J25: =F130 -> 2017.16 | K25: =F141 -> 6912.72 | L25: 0 | M25: 0 | N25: =$F$163 -> 807.76 | O25: =$F$164 -> 99.705 | P25: =$F$165 -> 68.35
B26: 11-200-104 | C26: 8000 Low Ceiling | D26: LED | G26: =SUM(J26:P26) -> 10506.805 | H26: =G26/(1-0.4)*2 -> 35022.683 | J26: =F130 -> 2017.16 | K26: =F137 -> 7513.83 | L26: 0 | M26: 0 | N26: =$F$163 -> 807.76 | O26: =$F$164 -> 99.705 | P26: =$F$165 -> 68.35
B27: 11-200-105 | C27: 32" Flat Panel | D27: FP | G27: =SUM(J27:P27) -> 4389.225 | H27: =G27/(1-0.4)*2 -> 14630.75 | J27: =F131 -> 2007.095 | K27: =F183 -> 2382.13 | L27: 0 | M27: 0 | N27: 0 | O27: 0 | P27: 0
B28: 11-200-106 | C28: Lead Shield | D28: LED | G28: =SUM(J28:P28) -> 5916.565 | H28: =G28/(1-0.4)*2 -> 19721.883 | J28: =F129 -> 1162.445 | K28: =F186 -> 4754.12 | L28: 0 | M28: 0 | N28: 0 | O28: 0 | P28: 0
B29: 11-200-107 | C29: 500 Standard (3P) | D29: LED | G29: =SUM(J29:P29) -> 5788.945 | H29: =G29/(1-0.4)*2 -> 19296.483 | J29: =F127 -> 609.045 | K29: =F145 -> 4204.085 | L29: 0 | M29: 0 | N29: =$F$163 -> 807.76 | O29: =$F$164 -> 99.705 | P29: =$F$165 -> 68.35
B30: 11-200-107 | C30: 500 Low Ceiling (3P) | D30: LED | G30: =SUM(J30:P30) -> 6280.505 | H30: =G30/(1-0.4)*2 -> 20935.017 | J30: =F128 -> 1196.705 | K30: =F146 -> 4107.985 | L30: 0 | M30: 0 | N30: =$F$163 -> 807.76 | O30: =$F$164 -> 99.705 | P30: =$F$165 -> 68.35
B31: 11-200-108 | C31: 8000 Standard (3P) | D31: LED | G31: =SUM(J31:P31) -> 5788.945 | H31: =G31/(1-0.4)*2 -> 19296.483 | J31: =F127 -> 609.045 | K31: =F145 -> 4204.085 | L31: 0 | M31: 0 | N31: =$F$163 -> 807.76 | O31: =$F$164 -> 99.705 | P31: =$F$165 -> 68.35
B32: 11-200-108 | C32: 8000 Low Ceiling (3P) | D32: LED | G32: =SUM(J32:P32) -> 6280.505 | H32: =G32/(1-0.4)*2 -> 20935.017 | J32: =F128 -> 1196.705 | K32: =F146 -> 4107.985 | L32: 0 | M32: 0 | N32: =$F$163 -> 807.76 | O32: =$F$164 -> 99.705 | P32: =$F$165 -> 68.35
B33: 11-200-109 | C33: FP (TC-Ondal) | G33: =SUM(J33:P33) -> 6750 | H33: =G33/(1-0.4)*2 -> 22500 | J33: 0 | K33: =F189 -> 6750 | L33: 0 | M33: 0 | N33: 0 | O33: 0 | P33: 0
B34: 11-200-110 | C34: LED Upgrade | G34: =SUM(J34:P34) -> 7500 | H34: =G34/(1-0.4)*2 -> 25000 | J34: 0 | K34: 7500 | L34: 0 | M34: 0 | N34: 0 | O34: 0 | P34: 0
B35: 11-200-111 | C35: 4500 Exam Light | G35: =SUM(J35:P35) -> 3615.183 | H35: =G35/(1-0.4)*2 -> 12050.61 | J35: 0 | K35: =F149 -> 3615.183 | L35: 0 | M35: 0 | N35: 0 | O35: 0 | P35: 0
C37: Ceiling Drop Tubes | G37: Imagine Cost | H37: Imagine List Price
B39: 11-300-001 | C39: 150mm | G39: =SUM(J39:P39) -> 0 | H39: =G39/(1-0.4)*2 -> 0 | J39: 0 | K39: 0 | L39: 0 | M39: 0 | N39: 0 | O39: 0 | P39: 0
B40: 11-300-002 | C40: 200mm | G40: =SUM(J40:P40) -> 0 | H40: =G40/(1-0.4)*2 -> 0 | J40: 0 | K40: 0 | L40: 0 | M40: 0 | N40: 0 | O40: 0 | P40: 0
B41: 11-300-003 | C41: 250mm | G41: =SUM(J41:P41) -> 0 | H41: =G41/(1-0.4)*2 -> 0 | J41: 0 | K41: 0 | L41: 0 | M41: 0 | N41: 0 | O41: 0 | P41: 0
B42: 11-300-004 | C42: 300mm | G42: =SUM(J42:P42) -> 0 | H42: =G42/(1-0.4)*2 -> 0 | J42: 0 | K42: 0 | L42: 0 | M42: 0 | N42: 0 | O42: 0 | P42: 0
B43: 11-300-005 | C43: 350mm | G43: =SUM(J43:P43) -> 0 | H43: =G43/(1-0.4)*2 -> 0 | J43: 0 | K43: 0 | L43: 0 | M43: 0 | N43: 0 | O43: 0 | P43: 0
B44: 11-300-006 | C44: 400mm | G44: =SUM(J44:P44) -> 0 | H44: =G44/(1-0.4)*2 -> 0 | J44: 0 | K44: 0 | L44: 0 | M44: 0 | N44: 0 | O44: 0 | P44: 0
B45: 11-300-007 | C45: 450mm | G45: =SUM(J45:P45) -> 0 | H45: =G45/(1-0.4)*2 -> 0 | J45: 0 | K45: 0 | L45: 0 | M45: 0 | N45: 0 | O45: 0 | P45: 0
B46: 11-300-008 | C46: 500mm | G46: =SUM(J46:P46) -> 0 | H46: =G46/(1-0.4)*2 -> 0 | J46: 0 | K46: 0 | L46: 0 | M46: 0 | N46: 0 | O46: 0 | P46: 0
B47: 11-300-009 | C47: Ondal TC Flange | G47: =SUM(J47:P47) -> 0 | H47: =G47/(1-0.4)*2 -> 0 | J47: 0 | K47: 0 | L47: 0 | M47: 0 | N47: 0 | O47: 0 | P47: 0
B48: 11-300-010 | C48: Lighthead Upgrade Only | G48: =SUM(J48:P48) -> 0 | H48: =G48/(1-0.4)*2 -> 0 | J48: 0 | K48: 0 | L48: 0 | M48: 0 | N48: 0 | O48: 0
B50: Part # | C50: Wall Control | G50: Imagine Cost | H50: Imagine List Price | J50: Handle Adapter | K50: Lintex Parts | L50: Wall Control | M50: Installation | N50: Sim.Flex Arms | O50: Mounting Plate | P50: Ceiling Cover
C52: No Wall Control | G52: =SUM(J52:P52) -> 0 | H52: =G52/(1-0.4)*2 -> 0 | J52: 0 | K52: 0 | L52: 0 | M52: 0 | N52: 0 | O52: 0
B53: 11-300-101 | C53: Wall Control in Separate Config | G53: =SUM(J53:P53) -> 0 | H53: =G53/(1-0.4)*2 -> 0 | J53: 0 | K53: 0 | L53: 0 | M53: 0 | N53: 0 | O53: 0
B54: 11-300-102 | C54: Wall Control (Touch) | G54: =SUM(J54:P54) -> 1413.125 | H54: =G54/(1-0.4)*2 -> 4710.4167 | J54: 0 | K54: 0 | L54: =F168 -> 1413.125 | M54: 0 | N54: 0 | O54: 0 | P54: 0
B55: 11-300-103 | C55: Wall Control (Single) | G55: =SUM(J55:P55) -> 644.055 | H55: =G55/(1-0.4)*2 -> 2146.85 | J55: 0 | K55: 0 | L55: =F169 -> 644.055 | M55: 0 | N55: 0 | O55: 0 | P55: 0
B56: 11-300-104 | C56: Wall Control (Dual) | G56: =SUM(J56:P56) -> 961.71 | H56: =G56/(1-0.4)*2 -> 3205.7 | J56: 0 | K56: 0 | L56: =F170 -> 961.71 | M56: 0 | N56: 0 | O56: 0 | P56: 0
B57: 11-300-105 | C57: Wall Control (Triple) | G57: =SUM(J57:P57) -> 1456.27 | H57: =G57/(1-0.4)*2 -> 4854.2333 | J57: 0 | K57: 0 | L57: =F171 -> 1456.27 | M57: 0 | N57: 0 | O57: 0 | P57: 0
B58: 11-300-106 | C58: Wall Control (Single w/ Cam) | G58: =SUM(J58:P58) -> 997.425 | H58: =G58/(1-0.4)*2 -> 3324.75 | J58: 0 | K58: 0 | L58: =F172 -> 997.425 | M58: 0 | N58: 0 | O58: 0 | P58: 0
B59: 11-300-107 | C59: Wall Control (Dual w/ Cam) | G59: =SUM(J59:P59) -> 1400.09 | H59: =G59/(1-0.4)*2 -> 4666.9667 | J59: 0 | K59: 0 | L59: =F173 -> 1400.09 | M59: 0 | N59: 0 | O59: 0 | P59: 0
B60: 11-300-108 | C60: Wall Control (Triple w/ Cam) | G60: =SUM(J60:P60) -> 1851.32 | H60: =G60/(1-0.4)*2 -> 6171.0667 | J60: 0 | K60: 0 | L60: =F174 -> 1851.32 | M60: 0 | N60: 0 | O60: 0 | P60: 0
C62: Device Control | G62: Imagine Cost | H62: Imagine List Price
C64: No Integration Control | G64: =SUM(J64:P64) -> 0 | H64: =G64/(1-0.4)*2 -> 0 | J64: 0 | K64: 0 | L64: 0 | M64: 0 | N64: 0 | O64: 0 | P64: 0
B65: 11-300-201 | C65: Storz Integration Control | G65: =SUM(J65:P65) -> 924.895 | H65: =G65/(1-0.4)*2 -> 3082.9833 | J65: 0 | K65: 0 | L65: =F192 -> 924.895 | M65: 0 | N65: 0 | O65: 0 | P65: 0
C67: In-Light Camera | G67: Imagine Cost | H67: Imagine List Price
C69: No Camera Prep | G69: =SUM(J69:P69) -> 0 | H69: =G69/(1-0.4)*2 -> 0 | J69: 0 | K69: 0 | L69: 0 | M69: 0 | N69: 0 | O69: 0
B70: 11-300-301 | C70: Wired Camera Prep | G70: =SUM(J70:P70) -> 1698.36 | H70: =G70/(1-0.4)*2 -> 5661.2 | J70: 0 | K70: 0 | L70: =F177 -> 1698.36 | M70: 0 | N70: 0 | O70: 0 | P70: 0
B71: 11-300-302 | C71: Wired Camera | G71: =SUM(J71:P71) -> 9239.094 | H71: =G71/(1-0.4)*2 -> 30796.98 | J71: 0 | K71: 0 | L71: =F178 -> 9239.094 | M71: 0 | N71: 0 | O71: 0 | P71: 0
B72: 11-300-303 | C72: Wireless Camera | G72: =SUM(J72:P72) -> 12907.56 | H72: =G72/(1-0.4)*2 -> 43025.2 | J72: 0 | K72: 0 | L72: =F179 -> 12907.56 | M72: 0 | N72: 0 | O72: 0 | P72: 0
C74: Disposable Adapters | G74: Imagine Cost | H74: Imagine List Price
C76: No Handle Adapter(s) | G76: =SUM(J76:P76) -> 0 | H76: =G76/(1-0.4)*2 -> 0 | J76: 0 | K76: 0 | L76: 0 | M76: 0 | N76: 0 | O76: 0 | P76: 0
B77: 11-300-401 | C77: Screw-On Adapter(s) | G77: =SUM(J77:P77) -> 126 | H77: =G77/(1-0.4)*2 -> 420 | J77: 0 | K77: =F154 -> 126 | L77: 0 | M77: 0 | N77: 0 | O77: 0 | P77: 0
B78: 11-300-402 | C78: Slip-On Adapter(s) | G78: =SUM(J78:P78) -> 446.68 | H78: =G78/(1-0.4)*2 -> 1488.9333 | J78: =F152 -> 348.24 | K78: =F153 -> 98.44 | L78: 0 | M78: 0 | N78: 0 | O78: 0 | P78: 0
C80: Sim.Flex Arm(s) | G80: Imagine Cost | H80: Imagine List Price
C82: Standard Armset | G82: =SUM(J82:P82) -> 0 | H82: 0 | J82: 0 | K82: 0 | L82: 0 | M82: 0 | N82: 0 | O82: 0 | P82: 0
B83: 11-300-501 | C83: Sim.Flex (1 Arm) | G83: =SUM(J83:P83) -> 1750 | H83: =G83/(1-0.4)*2 -> 5833.3333 | J83: 0 | K83: 0 | L83: 0 | M83: 0 | N83: 1750 | O83: 0 | P83: 0
B84: 11-300-502 | C84: Sim.Flex (2 Arms) | G84: =SUM(J84:P84) -> 2750 | H84: =G84/(1-0.4)*2 -> 9166.6667 | J84: 0 | K84: 0 | L84: 0 | M84: 0 | N84: 2750 | O84: 0 | P84: 0
B85: 11-300-503 | C85: Sim.Flex (3 Arms) | G85: =SUM(J85:P85) -> 3750 | H85: =G85/(1-0.4)*2 -> 12500 | J85: 0 | K85: 0 | L85: 0 | M85: 0 | N85: 3750 | O85: 0 | P85: 0
C87: Pre-Installation | G87: Imagine Cost | H87: Imagine List Price
B89: 11-300-601 | C89: Single Light (Standard) | G89: =SUM(J89:P89) -> 468.965 | H89: =G89/(1-0.4)*2 -> 1563.2167 | J89: 0 | K89: 0 | L89: 0 | M89: 0 | N89: 0 | O89: =F157 -> 169.7 | P89: =F159 -> 299.265
B90: 11-300-602 | C90: Single Light (Universal) | G90: =SUM(J90:P90) -> 1019.69 | H90: =G90/(1-0.4)*2 -> 3398.9667 | J90: 0 | K90: 0 | L90: 0 | M90: 0 | N90: 0 | O90: =F157 -> 169.7 | P90: =F160 -> 849.99
B91: 11-300-611 | C91: Tandem (1st Position) | G91: =SUM('[2]Ondal Booms'!D166:D171) -> 1742.296 | H91: =G91/(1-0.4)*2 -> 5807.6533 | J91: 0 | K91: 0 | L91: 0 | M91: 0 | N91: 0 | O91: =D155 -> 0 | P91: =D156 -> 0
B92: 11-300-612 | C92: Tandem (2nd Position) | G92: =SUM(J92:P92) -> 0 | H92: =G92/(1-0.4)*2 -> 0 | J92: 0 | K92: 0 | L92: 0 | M92: 0 | N92: 0 | O92: =D156 -> 0 | P92: 0
C94: Installation | G94: Imagine Cost | H94: Imagine List Price
B96: 11-400-101 | C96: Installation | G96: 900 | H96: =G96/(1-0.4)*2 -> 3000 | J96: 0 | K96: 0 | L96: 0 | M96: 1000 | N96: 0 | O96: 0 | P96: 0
C98: Shipping | G98: Imagine Cost | H98: Imagine List Price
B100: 11-500-101 | C100: Shipping | G100: 300 | H100: =G100/(1-0.4)*2 -> 1000 | J100: 0 | K100: 0 | L100: 0 | M100: 500 | N100: 0 | O100: 0 | P100: 0
A103: SIMEON PART NUMBERS
B105: Single Armsets | C105: Description | D105: Simeon 2024 List Price | E105: Simeon 2025 List Price | F105: Imagine Sales Price | G105: Notes
B106: 111-0017102 | C106: Central axis single - 9-pole | D106: 2715.32 | E106: 3280.9 | F106: =D106*(1-$D$254) -> 1357.66 | G106: LED (Standard)
B107: 111-0017104 | C107: Central axis single - TFT AC3000 | D107: 2657.42 | E107: 2493.5 | F107: =D107*(1-$D$254) -> 1328.71 | G107: FP (Standard)
B108: 111-0017139 | C108: Central axis single - 9-pole SL 1300mm | D108: 3387.27 | E108: 3439.49 | F108: =D108*(1-$D$254) -> 1693.635 | G108: LED (Extended)
B109: 111-0017156 | C109: Central axis single - TFT AC3000 SL 1062mm | D109: 2824.95 | E109: 2739.12 | F109: =D109*(1-$D$254) -> 1412.475 | G109: FP (Extended)
B110: 111-0017142 | C110: Central axis single - 3-pole SL 1040mm | D110: 2090.93 | E110: 2174.78 | F110: =D110*(1-$D$254) -> 1045.465 | G110: LED (3-Pole)
B112: Dual Armsets | G112: Notes
B113: 111-0017171 | C113: Central axis double - 9-pole / TFT AC3000 | D113: 4622.88 | E113: 5108.88 | F113: =D113*(1-$D$254) -> 2311.44 | G113: FP/LED (Standard)
B114: 111-0017125 | C114: Central axis double - 9-pole / 9-pole | D114: 5022.15 | E114: 6155.71 | F114: =D114*(1-$D$254) -> 2511.075 | G114: LED/LED (Standard)
B115: 111-0017222 | C115: Central axis double - TFT AC3000 / 9pole | D115: 4622.88 | E115: 5170.85 | F115: =D115*(1-$D$254) -> 2311.44 | G115: LED/FP (Standard)
B116: 111-0017191 | C116: Central axis double - 9-pole SL 925mm / TFT AC3000 SL 1062mm | D116: 4790.12 | E116: 5149.68 | F116: =D116*(1-$D$254) -> 2395.06 | G116: FP/LED (Extended)
B117: 111-0017164 | C117: Central axis double - 9-pole SL 1150mm / 9-pole SL 1300mm | D117: 7014.03 | E117: 7123.87 | F117: =D117*(1-$D$254) -> 3507.015 | G117: LED/LED (Extended)
B118: 111-0017205 | C118: Central axis double - TFT AC3000 SL 822mm / TFT AC3000 SL 1062mm | D118: 4377.03 | E118: 4323.6 | F118: =D118*(1-$D$254) -> 2188.515 | G118: FP/FP (Extended)
B120: Triple Armsets
B121: 111-0017126 | C121: Central axis triple - 9-pole / 9-pole / 9-pole | D121: 7541.78 | E121: 9308.21 | F121: =D121*(1-$D$254) -> 3770.89 | G121: LED/LED/LED (Standard)
B122: 111-0017181 | C122: Central axis triple - 9-pole / 9-pole / TFT AC3000 | D122: 7030.63 | E122: 7913.86 | F122: =D122*(1-$D$254) -> 3515.315 | G122: FP/LED/LED (Standard)
B123: 111-0017132 | C123: Central axis triple - TFT AC3000 / 9-pole / 9-pole | D123: 7030.63 | E123: 8157.55 | F123: =D123*(1-$D$254) -> 3515.315 | G123: LED/LED/FP (Standard)
B124: 111-0017163 | C124: Central axis triple - 9-pole SL 925mm / 9-pole SL 1040mm / 9-pole SL 1150mm | D124: 7963.06 | E124: 9936.53 | F124: =D124*(1-$D$254) -> 3981.53 | G124: LED/LED/LED (Extended)
B126: Spring Arms
B127: 131-0017274 | C127: Spring arm 3-pole 10-20kg | D127: 1218.09 | E127: 1122.89 | F127: =D127*(1-$D$254) -> 609.045 | G127: 3-Pole Standard
...

Sheet Light Pricing
A2: Base Model | D2: # of Arms | E2: # of Lights | F2: TC Mount?
A3: Part Number | B3: Description | C3: ="" | D3: 0 | E3: 0 | G3: Simeon List Price | H3: Imagine Cost | I3: Imagine List Price | J3: Imagine Sales Price | L3: Mounting Plate | M3: Ceiling Tube | N3: Ceiling Cover | O3: Central Axis | P3: Turning Cover | Q3: Arm 1 Pkg | R3: Arm 2 Pkg | S3: Arm 3 Pkg | T3: Arm 4 Pkg
B4: 500 LC - LED (3P) | C4: =B4 -> 500 LC - LED (3P) | D4: 1 | E4: 1 | F4: No | G4: =SUM(L4:AA4) -> 16357.74 | H4: =G4*(1-0.5) -> 8178.87 | I4: =H4/(1-0.4)*2 -> 27262.9 | J4: =I4*(1-0.5) -> 13631.45 | L4: =$D$128 -> 598.53 | M4: 763.02 | N4: 344.25 | O4: =D96 -> 2090.93 | P4: 0 | Q4: =M72 -> 12561.01
B5: LED | C5: 8000 - LED | D5: 1 | E5: 1 | F5: No | G5: =SUM(L5:AA5) -> 24397.25 | H5: =G5*0.5 -> 12198.625 | I5: =H5/(1-0.4)*2 -> 40662.083 | J5: =I5*(1-0.5) -> 20331.042 | L5: =$D$128 -> 598.53 | M5: 763.02 | N5: 344.25 | O5: =D97 -> 3387.27 | P5: 0 | Q5: =M75 -> 19304.18
B6: LED / LED | C6: 8000 - LED / LED | D6: 2 | E6: 2 | F6: No | G6: =SUM(L6:AA6) -> 47328.19 | H6: =G6*0.5 -> 23664.095 | I6: =H6/(1-0.4)*2 -> 78880.317 | J6: =I6*(1-0.5) -> 39440.158 | L6: =$D$128 -> 598.53 | M6: 763.02 | N6: 344.25 | O6: =D101 -> 7014.03 | P6: 0 | Q6: =M75 -> 19304.18 | R6: =M75 -> 19304.18
B7: LED / LED / LED | C7: 8000 - LED / LED / LED | D7: 3 | E7: 3 | F7: No | G7: =SUM(L7:AA7) -> 67581.4 | H7: =G7*0.5 -> 33790.7 | I7: =H7/(1-0.4)*2 -> 112635.67 | J7: =I7*(1-0.5) -> 56317.833 | L7: =$D$128 -> 598.53 | M7: 763.02 | N7: 344.25 | O7: =D107 -> 7963.06 | P7: 0 | Q7: =M75 -> 19304.18 | R7: =M75 -> 19304.18 | S7: =M75 -> 19304.18
B8: LED / FP | C8: 8000 - LED / FP | D8: 2 | E8: 1 | F8: No | G8: =SUM(L8:AA8) -> 34866.25 | H8: =G8*0.5 -> 17433.125 | I8: =H8/(1-0.4)*2 -> 58110.417 | J8: =I8*(1-0.5) -> 29055.208 | L8: =$D$128 -> 598.53 | M8: 763.02 | N8: 344.25 | O8: =D103 -> 4622.88 | P8: 392.03 | Q8: =M75 -> 19304.18 | R8: =M78 -> 8841.36
B9: FP / LED | C9: 8000 - FP / LED | D9: 2 | E9: 1 | F9: No | G9: =SUM(L9:AA9) -> 34641.46 | H9: =G9*0.5 -> 17320.73 | I9: =H9/(1-0.4)*2 -> 57735.767 | J9: =I9*(1-0.5) -> 28867.883 | L9: =$D$128 -> 598.53 | M9: 763.02 | N9: 344.25 | O9: =D102 -> 4790.12 | P9: 0 | Q9: =M78 -> 8841.36 | R9: =M75 -> 19304.18
B10: LED / LED / FP | C10: 8000 - LED / LED / FP | D10: 3 | E10: 2 | F10: No | G10: =SUM(L10:AA10) -> 56578.18 | H10: =G10*0.5 -> 28289.09 | I10: =H10/(1-0.4)*2 -> 94296.967 | J10: =I10*(1-0.5) -> 47148.483 | L10: =$D$128 -> 598.53 | M10: 763.02 | N10: 344.25 | O10: =D109 -> 7030.63 | P10: 392.03 | Q10: =M75 -> 19304.18 | R10: =M75 -> 19304.18 | S10: =M78 -> 8841.36
B11: LED / LS | C11: 8000 - LED / LS | D11: 2 | E11: 1 | F11: No | G11: =SUM(L11:AA11) -> 46673.28 | H11: =G11*0.5 -> 23336.64 | I11: =H11/(1-0.4)*2 -> 77788.8 | J11: =I11*(1-0.5) -> 38894.4 | L11: =$D$128 -> 598.53 | M11: 763.02 | N11: 344.25 | O11: =D101 -> 7014.03 | P11: 0 | Q11: =M75 -> 19304.18 | R11: =M80 -> 18649.27
B12: LED / LED / LS | C12: 8000 - LED / LED / LS | D12: 3 | E12: 2 | F12: No | G12: =SUM(L12:AA12) -> 66926.49 | H12: =G12*0.5 -> 33463.245 | I12: =H12/(1-0.4)*2 -> 111544.15 | J12: =I12*(1-0.5) -> 55772.075 | L12: =$D$128 -> 598.53 | M12: 763.02 | N12: 344.25 | O12: =D107 -> 7963.06 | P12: 0 | Q12: =M75 -> 19304.18 | R12: =M75 -> 19304.18 | S12: =M80 -> 18649.27
B13: FP | C13: ="No Lights - "&B13 -> No Lights - FP | D13: 1 | E13: 0 | F13: No | G13: =SUM(L13:AA13) -> 13372.11 | H13: =G13*0.5 -> 6686.055 | I13: =H13/(1-0.4)*2 -> 22286.85 | J13: =I13*(1-0.5) -> 11143.425 | L13: =$D$128 -> 598.53 | M13: 763.02 | N13: 344.25 | O13: =D98 -> 2824.95 | P13: 0 | Q13: =M78 -> 8841.36
B14: LS | C14: ="No Lights - "&B14 -> No Lights - LS | D14: 1 | E14: 0 | F14: No | G14: =SUM(L14:AA14) -> 23742.34 | H14: =G14*0.5 -> 11871.17 | I14: =H14/(1-0.4)*2 -> 39570.567 | J14: =I14*(1-0.5) -> 19785.283 | L14: =$D$128 -> 598.53 | M14: 763.02 | N14: 344.25 | O14: =D97 -> 3387.27 | P14: 0 | Q14: =M80 -> 18649.27
B15: FP / FP | C15: ="No Lights - "&B15 -> No Lights - FP / FP | D15: 2 | E15: 0 | F15: No | G15: =SUM(L15:AA15) -> 24157.58 | H15: =G15*0.5 -> 12078.79 | I15: =H15/(1-0.4)*2 -> 40262.633 | J15: =I15*(1-0.5) -> 20131.317 | L15: =$D$128 -> 598.53 | M15: 763.02 | N15: 344.25 | O15: =D104 -> 4377.03 | P15: 392.03 | Q15: =M78 -> 8841.36 | R15: =M78 -> 8841.36
B16: LS / LS | C16: ="No Lights - "&B16 -> No Lights - LS / LS | D16: 2 | E16: 0 | F16: No | G16: =SUM(L16:AA16) -> 46018.37 | H16: =G16*0.5 -> 23009.185 | I16: =H16/(1-0.4)*2 -> 76697.283 | J16: =I16*(1-0.5) -> 38348.642 | L16: =$D$128 -> 598.53 | M16: 763.02 | N16: 344.25 | O16: =D101 -> 7014.03 | P16: 0 | Q16: =M80 -> 18649.27 | R16: =M80 -> 18649.27
B17: FP / LS | C17: ="No Lights - "&B17 -> No Lights - FP / LS | D17: 2 | E17: 0 | F17: No | G17: =SUM(L17:AA17) -> 33986.55 | H17: =G17*0.5 -> 16993.275 | I17: =H17/(1-0.4)*2 -> 56644.25 | J17: =I17*(1-0.5) -> 28322.125 | L17: =$D$128 -> 598.53 | M17: 763.02 | N17: 344.25 | O17: =D102 -> 4790.12 | P17: 0 | Q17: =M78 -> 8841.36 | R17: =M80 -> 18649.27
B18: LS / FP | C18: ="No Lights - "&B18 -> No Lights - LS / FP | D18: 2 | E18: 0 | F18: No | G18: =SUM(L18:AA18) -> 23412.07 | H18: =G18*0.5 -> 11706.035 | I18: =H18/(1-0.4)*2 -> 39020.117 | J18: =I18*(1-0.5) -> 19510.058 | L18: =$D$128 -> 598.53 | M18: 763.02 | N18: 344.25 | O18: =D103 -> 4622.88 | P18: 392.03 | Q18: =M79 -> 7850 | R18: =M78 -> 8841.36
B19: TC FP (Ondal) | C19: ="No Lights - "&B19 -> No Lights - TC FP (Ondal) | D19: 1 | E19: 0 | F19: Yes | G19: =SUM(L19:AA19) -> 7850 | H19: =G19*0.5 -> 3925 | I19: =H19/(1-0.4)*2 -> 13083.333 | J19: =I19*(1-0.5) -> 6541.6667 | Q19: =M79 -> 7850
B20: 4500 Exam Light | C20: =B20 -> 4500 Exam Light | D20: 0 | E20: 0 | F20: No | G20: =D112 -> 6573.06 | H20: =G20*0.55 -> 3615.183 | I20: =H20/(1-0.4)*2 -> 12050.61 | J20: =I20*(1-0.5) -> 6025.305
B21: (1) LIGHT EXCHANGE | C21: =B21 -> (1) LIGHT EXCHANGE | D21: 1 | E21: 1 | F21: No | G21: =SUM(L21:AA21) -> 15000 | H21: =G21*0.5 -> 7500 | I21: =H21/(1-0.4)*2 -> 25000 | J21: =I21*(1-0.5) -> 12500 | Q21: =M81 -> 15000
B22: (2) LIGHTS EXCHANGE | C22: =B22 -> (2) LIGHTS EXCHANGE | D22: 2 | E22: 2 | F22: No | G22: =SUM(L22:AA22) -> 30000 | H22: =G22*0.5 -> 15000 | I22: =H22/(1-0.4)*2 -> 50000 | J22: =I22*(1-0.5) -> 25000 | Q22: =M81 -> 15000 | R22: =M81 -> 15000
C23: 8000 LC - LED | D23: 1 | E23: 1 | F23: No | G23: =SUM(L23:AA23) -> 26106.68 | H23: =G23*0.5 -> 13053.34 | I23: =H23/(1-0.4)*2 -> 43511.133 | J23: =I23*(1-0.5) -> 21755.567 | L23: =$D$128 -> 598.53 | M23: 763.02 | N23: 344.25 | O23: =O5 -> 3387.27 | P23: 0 | Q23: =M76 -> 21013.61
C24: 8000 LC - LED / LED | D24: 2 | E24: 2 | F24: No | G24: =SUM(L24:AA24) -> 50747.05 | H24: =G24*0.5 -> 25373.525 | I24: =H24/(1-0.4)*2 -> 84578.417 | J24: =I24*(1-0.5) -> 42289.208 | L24: =$D$128 -> 598.53 | M24: 763.02 | N24: 344.25 | O24: =O6 -> 7014.03 | P24: 0 | Q24: =M76 -> 21013.61 | R24: =M76 -> 21013.61
C25: 8000 LC - LED / LED / LED | D25: 3 | E25: 3 | F25: No | G25: =SUM(L25:AA25) -> 72709.69 | H25: =G25*0.5 -> 36354.845 | I25: =H25/(1-0.4)*2 -> 121182.82 | J25: =I25*(1-0.5) -> 60591.408 | L25: =$D$128 -> 598.53 | M25: 763.02 | N25: 344.25 | O25: =O7 -> 7963.06 | P25: 0 | Q25: =M76 -> 21013.61 | R25: =M76 -> 21013.61 | S25: =M76 -> 21013.61
C26: 8000 LC - LED / FP | D26: 2 | E26: 1 | F26: No | G26: =SUM(L26:AA26) -> 36575.68 | H26: =G26*0.5 -> 18287.84 | I26: =H26/(1-0.4)*2 -> 60959.467 | J26: =I26*(1-0.5) -> 30479.733 | L26: =$D$128 -> 598.53 | M26: 763.02 | N26: 344.25 | O26: =O8 -> 4622.88 | P26: 392.03 | Q26: =M76 -> 21013.61 | R26: =M78 -> 8841.36
C27: 8000 LC - FP / LED | D27: 2 | E27: 1 | F27: No | G27: =SUM(L27:AA27) -> 36350.89 | H27: =G27*0.5 -> 18175.445 | I27: =H27/(1-0.4)*2 -> 60584.817 | J27: =I27*(1-0.5) -> 30292.408 | L27: =$D$128 -> 598.53 | M27: 763.02 | N27: 344.25 | O27: =O9 -> 4790.12 | P27: 0 | Q27: =M78 -> 8841.36 | R27: =M76 -> 21013.61
C28: 8000 LC - LED / LED / FP | D28: 3 | E28: 2 | F28: No | G28: =SUM(L28:AA28) -> 59997.04 | H28: =G28*0.5 -> 29998.52 | I28: =H28/(1-0.4)*2 -> 99995.067 | J28: =I28*(1-0.5) -> 49997.533 | L28: =$D$128 -> 598.53 | M28: 763.02 | N28: 344.25 | O28: =O10 -> 7030.63 | P28: 392.03 | Q28: =M76 -> 21013.61 | R28: =M76 -> 21013.61 | S28: =M78 -> 8841.36
C29: 8000 LC - LED / LS | D29: 2 | E29: 1 | F29: No | G29: =SUM(L29:AA29) -> 48382.71 | H29: =G29*0.5 -> 24191.355 | I29: =H29/(1-0.4)*2 -> 80637.85 | J29: =I29*(1-0.5) -> 40318.925 | L29: =$D$128 -> 598.53 | M29: 763.02 | N29: 344.25 | O29: =O11 -> 7014.03 | P29: 0 | Q29: =M76 -> 21013.61 | R29: =M80 -> 18649.27
C30: 8000 LC - LED / LED / LS | D30: 3 | E30: 2 | F30: No | G30: =SUM(L30:AA30) -> 70345.35 | H30: =G30*0.5 -> 35172.675 | I30: =H30/(1-0.4)*2 -> 117242.25 | J30: =I30*(1-0.5) -> 58621.125 | L30: =$D$128 -> 598.53 | M30: 763.02 | N30: 344.25 | O30: =O12 -> 7963.06 | P30: 0 | Q30: =M76 -> 21013.61 | R30: =M76 -> 21013.61 | S30: =M80 -> 18649.27
C31: 7000 - LED | D31: 1 | E31: 1 | F31: No | G31: =SUM(L31:AA31) -> 23387.22 | H31: =G31*0.5 -> 11693.61 | I31: =H31/(1-0.4)*2 -> 38978.7 | J31: =I31*(1-0.5) -> 19489.35 | L31: =$D$128 -> 598.53 | M31: 763.02 | N31: 344.25 | O31: =O5 -> 3387.27 | P31: 0 | Q31: =M73 -> 18294.15
C32: 7000 - LED / LED | D32: 2 | E32: 2 | F32: No | G32: =SUM(L32:AA32) -> 45308.13 | H32: =G32*0.5 -> 22654.065 | I32: =H32/(1-0.4)*2 -> 75513.55 | J32: =I32*(1-0.5) -> 37756.775 | L32: =$D$128 -> 598.53 | M32: 763.02 | N32: 344.25 | O32: =O6 -> 7014.03 | P32: 0 | Q32: =M73 -> 18294.15 | R32: =M73 -> 18294.15
C33: 7000 - LED / LED / LED | D33: 3 | E33: 3 | F33: No | G33: =SUM(L33:AA33) -> 64551.31 | H33: =G33*0.5 -> 32275.655 | I33: =H33/(1-0.4)*2 -> 107585.52 | J33: =I33*(1-0.5) -> 53792.758 | L33: =$D$128 -> 598.53 | M33: 763.02 | N33: 344.25 | O33: =O7 -> 7963.06 | P33: 0 | Q33: =M73 -> 18294.15 | R33: =M73 -> 18294.15 | S33: =M73 -> 18294.15
C34: 7000 - LED / FP | D34: 2 | E34: 1 | F34: No | G34: =SUM(L34:AA34) -> 33856.22 | H34: =G34*0.5 -> 16928.11 | I34: =H34/(1-0.4)*2 -> 56427.033 | J34: =I34*(1-0.5) -> 28213.517 | L34: =$D$128 -> 598.53 | M34: 763.02 | N34: 344.25 | O34: =O8 -> 4622.88 | P34: 392.03 | Q34: =M73 -> 18294.15 | R34: =+M78 -> 8841.36
C35: 7000 - FP / LED | D35: 2 | E35: 1 | F35: No | G35: =SUM(L35:AA35) -> 33631.43 | H35: =G35*0.5 -> 16815.715 | I35: =H35/(1-0.4)*2 -> 56052.383 | J35: =I35*(1-0.5) -> 28026.192 | L35: =$D$128 -> 598.53 | M35: 763.02 | N35: 344.25 | O35: =O9 -> 4790.12 | P35: 0 | Q35: =M78 -> 8841.36 | R35: =M73 -> 18294.15
C36: 7000 - LED / LED / FP | D36: 3 | E36: 2 | F36: No | G36: =SUM(L36:AA36) -> 54558.12 | H36: =G36*0.5 -> 27279.06 | I36: =H36/(1-0.4)*2 -> 90930.2 | J36: =I36*(1-0.5) -> 45465.1 | L36: =$D$128 -> 598.53 | M36: 763.02 | N36: 344.25 | O36: =O10 -> 7030.63 | P36: 392.03 | Q36: =M73 -> 18294.15 | R36: =M73 -> 18294.15 | S36: =M78 -> 8841.36
C37: 7000 - LED / LS | D37: 2 | E37: 1 | F37: No | G37: =SUM(L37:AA37) -> 45663.25 | H37: =G37*0.5 -> 22831.625 | I37: =H37/(1-0.4)*2 -> 76105.417 | J37: =I37*(1-0.5) -> 38052.708 | L37: =$D$128 -> 598.53 | M37: 763.02 | N37: 344.25 | O37: =O11 -> 7014.03 | P37: 0 | Q37: =M73 -> 18294.15 | R37: =M80 -> 18649.27
C38: 7000 - LED / LED / LS | D38: 3 | E38: 2 | F38: No | G38: =SUM(L38:AA38) -> 64906.43 | H38: =G38*0.5 -> 32453.215 | I38: =H38/(1-0.4)*2 -> 108177.38 | J38: =I38*(1-0.5) -> 54088.692 | L38: =$D$128 -> 598.53 | M38: 763.02 | N38: 344.25 | O38: =O12 -> 7963.06 | P38: 0 | Q38: =M73 -> 18294.15 | R38: =M73 -> 18294.15 | S38: =M80 -> 18649.27
C39: 7000 LC - LED | D39: 1 | E39: 1 | F39: No | G39: =SUM(L39:AA39) -> 24904.46 | H39: =G39*0.5 -> 12452.23 | I39: =H39/(1-0.4)*2 -> 41507.433 | J39: =I39*(1-0.5) -> 20753.717 | L39: =$D$128 -> 598.53 | M39: 763.02 | N39: 344.25 | O39: =O5 -> 3387.27 | P39: 0 | Q39: =M74 -> 19811.39
C40: 7000 LC - LED / LED | D40: 2 | E40: 2 | F40: No | G40: =SUM(L40:AA40) -> 48342.61 | H40: =G40*0.5 -> 24171.305 | I40: =H40/(1-0.4)*2 -> 80571.017 | J40: =I40*(1-0.5) -> 40285.508 | L40: =$D$128 -> 598.53 | M40: 763.02 | N40: 344.25 | O40: =O6 -> 7014.03 | P40: 0 | Q40: =M74 -> 19811.39 | R40: =M74 -> 19811.39
C41: 7000 LC - LED / LED / LED | D41: 3 | E41: 3 | F41: No | G41: =SUM(L41:AA41) -> 69103.03 | H41: =G41*0.5 -> 34551.515 | I41: =H41/(1-0.4)*2 -> 115171.72 | J41: =I41*(1-0.5) -> 57585.858 | L41: =$D$128 -> 598.53 | M41: 763.02 | N41: 344.25 | O41: =O7 -> 7963.06 | P41: 0 | Q41: =M74 -> 19811.39 | R41: =M74 -> 19811.39 | S41: =M74 -> 19811.39
C42: 7000 LC - LED / FP | D42: 2 | E42: 1 | F42: No | G42: =SUM(L42:AA42) -> 35373.46 | H42: =G42*0.5 -> 17686.73 | I42: =H42/(1-0.4)*2 -> 58955.767 | J42: =I42*(1-0.5) -> 29477.883 | L42: =$D$128 -> 598.53 | M42: 763.02 | N42: 344.25 | O42: =O8 -> 4622.88 | P42: 392.03 | Q42: =M74 -> 19811.39 | R42: =M78 -> 8841.36
C43: 7000 LC - FP / LED | D43: 2 | E43: 1 | F43: No | G43: =SUM(L43:AA43) -> 35148.67 | H43: =G43*0.5 -> 17574.335 | I43: =H43/(1-0.4)*2 -> 58581.117 | J43: =I43*(1-0.5) -> 29290.558 | L43: =$D$128 -> 598.53 | M43: 763.02 | N43: 344.25 | O43: =O9 -> 4790.12 | P43: 0 | Q43: =M78 -> 8841.36 | R43: =M74 -> 19811.39
C44: 7000 LC - LED / LED / FP | D44: 3 | E44: 2 | F44: No | G44: =SUM(L44:AA44) -> 57592.6 | H44: =G44*0.5 -> 28796.3 | I44: =H44/(1-0.4)*2 -> 95987.667 | J44: =I44*(1-0.5) -> 47993.833 | L44: =$D$128 -> 598.53 | M44: 763.02 | N44: 344.25 | O44: =O10 -> 7030.63 | P44: 392.03 | Q44: =M74 -> 19811.39 | R44: =M74 -> 19811.39 | S44: =+M78 -> 8841.36
C45: 7000 LC - LED / LS | D45: 2 | E45: 1 | F45: No | G45: =SUM(L45:AA45) -> 47180.49 | H45: =G45*0.5 -> 23590.245 | I45: =H45/(1-0.4)*2 -> 78634.15 | J45: =I45*(1-0.5) -> 39317.075 | L45: =$D$128 -> 598.53 | M45: 763.02 | N45: 344.25 | O45: =O11 -> 7014.03 | P45: 0 | Q45: =M74 -> 19811.39 | R45: =M80 -> 18649.27
C46: 7000 LC - LED / LED / LS | D46: 3 | E46: 2 | F46: No | G46: =SUM(L46:AA46) -> 58133 | H46: =G46*0.5 -> 29066.5 | I46: =H46/(1-0.4)*2 -> 96888.333 | J46: =I46*(1-0.5) -> 48444.167 | L46: =$D$128 -> 598.53 | M46: 763.02 | N46: 344.25 | O46: =O12 -> 7963.06 | P46: 0 | Q46: =M74 -> 19811.39 | R46: =M74 -> 19811.39 | S46: =+M78 -> 8841.36
C47: 8000 LC (3P) - LED | D47: 1 | E47: 1 | F47: No | G47: =SUM(L47:AA47) -> 23394.26 | H47: =G47*0.5 -> 11697.13 | I47: =H47/(1-0.4)*2 -> 38990.433 | J47: =I47*(1-0.5) -> 19495.217 | L47: =$D$128 -> 598.53 | M47: 763.02 | N47: 344.25 | O47: =O13 -> 2824.95 | P47: 0 | Q47: =M77 -> 18863.51
A49: Options / Price Drivers
A50: Part Number | B50: Description | D50: Simeon List | E50: 3rd Party | G50: Simeon List Price | H50: Imagine Cost | I50: Imagine List Price
B51: Wall Control (Single) | D51: 1994.85 | E51: 0 | G51: =SUM(D51:F51) -> 1994.85 | H51: =G51*0.5 -> 997.425 | I51: =H51/(1-0.4)*2 -> 3324.75
B52: Wall Control (Dual) | D52: 2800.18 | E52: 0 | G52: =SUM(D52:F52) -> 2800.18 | H52: =G52*0.5 -> 1400.09 | I52: =H52/(1-0.4)*2 -> 4666.9667
B53: Wall Control (Triple) | D53: 3702.64 | E53: 0 | G53: =SUM(D53:F53) -> 3702.64 | H53: =G53*0.5 -> 1851.32 | I53: =H53/(1-0.4)*2 -> 6171.0667
B54: Wall Control (Touch) | D54: =2826.25+(72.99*3) -> 3045.22 | E54: 0 | G54: =SUM(D54:F54) -> 3045.22 | H54: =G54*0.5 -> 1522.61 | I54: =H54/(1-0.4)*2 -> 5075.3667
B55: Wall Control (Single w/ Cam) | D55: 1994.85 | E55: 0 | G55: =SUM(D55:F55) -> 1994.85 | H55: =G55*0.5 -> 997.425 | I55: =H55/(1-0.4)*2 -> 3324.75
B56: Wall Control (Dual w/ Cam) | D56: 2800.18 | E56: 0 | G56: =SUM(D56:F56) -> 2800.18 | H56: =G56*0.5 -> 1400.09 | I56: =H56/(1-0.4)*2 -> 4666.9667
B57: Wall Control (Triple w/ Cam) | D57: 3702.64 | E57: 0 | G57: =SUM(D57:F57) -> 3702.64 | H57: =G57*0.5 -> 1851.32 | I57: =H57/(1-0.4)*2 -> 6171.0667
B58: Integration Control | D58: =1849.79+25.16*3 -> 1925.27 | E58: 0 | G58: =SUM(D58:F58) -> 1925.27 | H58: =G58*0.5 -> 962.635 | I58: =H58/(1-0.4)*2 -> 3208.7833
B59: Wired Prep | D59: 2830.6 | E59: 0 | G59: =SUM(D59:F59) -> 2830.6 | H59: =G59*0.5 -> 1415.3 | I59: =H59/(1-0.4)*2 -> 4717.6667
B60: Wired | D60: 15398.49 | E60: 0 | G60: =SUM(D60:F60) -> 15398.49 | H60: =G60*0.5 -> 7699.245 | I60: =H60/(1-0.4)*2 -> 25664.15
B61: Wireless | D61: 27173.82 | E61: 0 | G61: =SUM(D61:F61) -> 27173.82 | H61: =G61*0.5 -> 13586.91 | I61: =H61/(1-0.4)*2 -> 45289.7
B62: Screw-On | D62: 0 | E62: =D125 -> 252 | G62: =SUM(E62:F62) -> 252 | H62: =G62*0.5 -> 126 | I62: =H62/(1-0.4)*2 -> 420
B63: Slip-On | D63: =D123 -> 696.48 | E63: =D124 -> 196.88 | G63: =SUM(D63:F63) -> 893.36 | H63: =G63*0.5 -> 446.68 | I63: =H63/(1-0.4)*2 -> 1488.9333
B64: Installation | D64: 1500 | E64: 0 | G64: =SUM(D64:F64) -> 1500 | H64: =G64*0.5 -> 750 | I64: =H64/(1-0.4)*2 -> 2500
B65: Low Ceiling Lighthead Option | D65: =I76-I75 -> 0 | E65: 0 | G65: =SUM(D65:F65) -> 0 | H65: =G65*0.5 -> 0 | I65: =H65/(1-0.4)*2 -> 0
B66: Sim.Flex Custom Arm Option | D66: =3215.24 -> 3215.24 | E66: 0 | G66: =SUM(D66:F66) -> 3215.24 | H66: =G66*0.5 -> 1607.62 | I66: =H66/(1-0.4)*2 -> 5358.7333
A70: End Effectors
A71: Part Number | B71: Description | G71: Spring Arm | H71: End Item | I71: Power Supply | L71: Cables | M71: Total
B72: 500 LC (3P) | G72: =D119 -> 2393.41 | H72: =D93 -> 8215.97 | I72: 1615.52 | L72: =199.41+136.7 -> 336.11 | M72: =SUM(G72:L72) -> 12561.01
B73: ="7000" -> 7000 | G73: 2324.89 | H73: 14017.63 | I73: 1615.52 | L73: =199.41+136.7 -> 336.11 | M73: =SUM(G73:L73) -> 18294.15
B74: 7000 LC | G74: 4034.32 | H74: 13825.44 | I74: 1615.52 | L74: =199.41+136.7 -> 336.11 | M74: =SUM(G74:L74) -> 19811.39
B75: ="8000" -> 8000 | G75: 2324.89 | H75: 15027.66 | I75: 1615.52 | L75: =199.41+136.7 -> 336.11 | M75: =SUM(G75:L75) -> 19304.18
B76: 8000 LC | G76: 4034.32 | H76: 15027.66 | I76: 1615.52 | L76: =199.41+136.7 -> 336.11 | M76: =SUM(G76:L76) -> 21013.61
B77: 8000 LC (3P) | G77: =D119 -> 2393.41 | H77: =D116 -> 14518.47 | I77: 1615.52 | L77: =199.41+136.7 -> 336.11 | M77: =SUM(G77:L77) -> 18863.51
B78: FP | G78: 4014.19 | H78: 4764.26 | I78: 0 | L78: 62.91 | M78: =SUM(G78:L78) -> 8841.36
B79: FP (TC-Ondal) | G79: 0 | H79: =2*(3375+550) -> 7850 | I79: 0 | M79: =SUM(G79:L79) -> 7850
B80: LS | G80: 3649.27 | H80: 15000 | I80: 0 | M80: =SUM(G80:L80) -> 18649.27
B81: LED Upgrade | G81: 0 | H81: 15000 | I81: 0 | M81: =SUM(G81:L81) -> 15000
A83: 8000 LED
A87: 7000 LED
A91: 500 LED
A92: 141-0015615 | B92: Sim.LED 500 3-pole SC | D92: 8408.17
A93: 141-0015616 | B93: Sim.LED 500 3-pole SC low ceiling | D93: 8215.97
A95: Single Armsets
A96: 111-0017142 | B96: Central axis single - 3-pole SL 1040mm | D96: 2090.93
A97: 111-0017139 | B97: Central axis single - 9-pole SL 1300mm | D97: 3387.27
A98: 111-0017156 | B98: Central axis single - TFT AC3000 SL 1062mm | D98: 2824.95
A100: Dual Armsets
A101: 111-0017164 | B101: Central axis double - 9-pole SL 1150mm / 9-pole SL 1300mm | D101: 7014.03
A102: 111-0017191 | B102: Central axis double - 9-pole SL 925mm / TFT AC3000 SL 1062mm | D102: 4790.12
A103: 111-0017222 | B103: Central axis double - TFT AC3000 / 9pole | D103: 4622.88
A104: 111-0017205 | B104: Central axis double - TFT AC3000 SL 822mm / TFT AC3000 SL 1062mm | D104: 4377.03
A106: Triple Armsets
A107: 111-0017163 | B107: Central axis triple - 9-pole SL 925mm / 9-pole SL 1040mm / 9-pole SL 1150mm | D107: 7963.06
A108: 111-0017181 | B108: Central axis triple - 9-pole / 9-pole / TFT AC3000 | D108: 7030.63
A109: 111-0017132 | B109: Central axis triple - TFT AC3000 / 9-pole / 9-pole | D109: 7030.63
A111: Exam Lights
A112: 161-0013148 | B112: Sim.LED 4500 Ceiling version | D112: 6573.06
A114: 8000 Lightheads (3P)
A115: 141-0019525 | B115: Sim.LED 8000 SC 3p | D115: 14729.99
A116: 141-0019527 | B116: Sim.LED 8000 SC 3p low ceiling | D116: 14518.47
A118: Spring Arms (3P)
...

Sheet Boom Pricing
A1: Boom Options
B2: Model (A) | C2: Service Head
A3: Standard Top Arm | B3: Powered | D3: 600 | E3: 800 | F3: 1000 | G3: 1200 | H3: 1400 | I3: 1600 | K3: Ceiling Flange (E) | O3: Key | S3: Price Increase | T3: 600 | U3: 800 | V3: 1000 | W3: 1200 | X3: 1400 | Y3: 1600
A4: Powered Bottom Arm | B4: 35398.8 | C4: 200 | D4: =SUM($B$4+T4) -> 35398.8 | E4: =SUM($B$4+U4) -> 35398.8 | F4: =SUM($B$4+V4) -> 35398.8 | G4: =SUM($B$4+W4) -> 35398.8 | H4: na | I4: na | K4: for standard models | O4: Model | Q4: A | S4: 200 | X4: 1591.55 | Y4: 3291.97
A5: (articulating - 1000mm) | C5: 400 | D5: =SUM($B$4+T5) -> 37373.71 | E5: =SUM($B$4+U5) -> 37373.71 | F5: =SUM($B$4+V5) -> 37373.71 | G5: =SUM($B$4+W5) -> 37373.71 | H5: na | I5: na | K5: 100mm | L5: 0 | O5: Service Head Length | Q5: B | S5: 400 | T5: 1974.91 | U5: 1974.91 | V5: 1974.91 | W5: 1974.91 | X5: =SUM(1974.91+1591.95) -> 3566.86 | Y5: =SUM(3291.97+1974.91) -> 5266.88
C6: 600 | D6: =SUM($B$4+T6) -> 39353.55 | E6: =SUM($B$4+U6) -> 39353.55 | F6: =SUM($B$4+V6) -> 39353.55 | G6: =SUM($B$4+W6) -> 39353.55 | H6: na | I6: na | K6: 300mm | L6: 251.81 | O6: Top Arm Length | S6: 600 | T6: 3954.75 | U6: 3954.75 | V6: 3954.75 | W6: 3954.75 | X6: =SUM(3954.75+1591.55) -> 5546.3 | Y6: =SUM(3291.97+3954.75) -> 7246.72
C7: 800 | D7: =SUM($B$4+T7) -> 41392.67 | E7: =SUM($B$4+U7) -> 41392.67 | F7: =SUM($B$4+V7) -> 41392.67 | G7: =SUM($B$4+W7) -> 41392.67 | H7: na | I7: na | K7: 500mm | L7: 493.73 | O7: Ceiling Flange | Q7: D | S7: 800 | T7: 5993.87 | U7: 5993.87 | V7: 5993.87 | W7: 5993.87 | X7: =SUM(5993.87+1591.55) -> 7585.42 | Y7: =SUM(5993.87+3291.97) -> 9285.84
C8: 1000 | D8: =SUM($B$4+T8) -> 43426.83 | E8: =SUM($B$4+U8) -> 43426.83 | F8: =SUM($B$4+V8) -> 43426.83 | G8: =SUM($B$4+W8) -> 43426.83 | H8: na | I8: na | K8: for XL+ models | O8: Optional Services | Q8: C | S8: 1000 | T8: 8028.03 | U8: 8028.03 | V8: 8028.03 | W8: 8028.03 | X8: 9619.58 | Y8: 11320
K9: 100mm | L9: 0 | O9: Light Options | Q9: E
A10: XL Top Arm | B10: Powered XL | D10: 600 | E10: 800 | F10: 1000 | G10: 1200 | H10: 1400 | I10: 1600 | K10: 300mm | L10: 508.53 | O10: Optional Light Accessories | Q10: F
A11: Powered Bottom Arm | B11: 39326.43 | C11: 200 | D11: =SUM($B$11+T4) -> 39326.43 | E11: =SUM($B$11+U4) -> 39326.43 | F11: =SUM($B$11+V4) -> 39326.43 | G11: =SUM($B$11+W4) -> 39326.43 | H11: =SUM($B$11+X4) -> 40917.98 | I11: =SUM($B$11+Y4) -> 42618.4 | K11: 500mm | L11: 1214.59 | O11: Not in the Tool
A12: (articulating - 1000mm) | C12: 400 | D12: =SUM($B$11+T5) -> 41301.34 | E12: =SUM($B$11+U5) -> 41301.34 | F12: =SUM($B$11+V5) -> 41301.34 | G12: =SUM($B$11+W5) -> 41301.34 | H12: =SUM($B$11+X5) -> 42893.29 | I12: =SUM($B$11+Y5) -> 44593.31
C13: 600 | D13: =SUM($B$11+T6) -> 43281.18 | E13: =SUM($B$11+U6) -> 43281.18 | F13: =SUM($B$11+V6) -> 43281.18 | G13: =SUM($B$11+W6) -> 43281.18 | H13: =SUM($B$11+X6) -> 44872.73 | I13: =SUM($B$11+Y6) -> 46573.15 | O13: Total Price = A + B + C + D + E + F
C14: 800 | D14: =SUM($B$11+T7) -> 45320.3 | E14: =SUM($B$11+U7) -> 45320.3 | F14: =SUM($B$11+V7) -> 45320.3 | G14: =SUM($B$11+W7) -> 45320.3 | H14: =SUM($B$11+X7) -> 46911.85 | I14: =SUM($B$11+Y7) -> 48612.27 | K14: Services / Accessories (D - if applicable) | M14: optional
C15: 1000 | D15: =SUM($B$11+T8) -> 47354.46 | E15: =SUM($B$11+U8) -> 47354.46 | F15: =SUM($B$11+V8) -> 47354.46 | G15: =SUM($B$11+W8) -> 47354.46 | H15: =SUM($B$11+X8) -> 48946.01 | I15: =SUM($B$11+Y8) -> 50646.43 | K15: Med-Gas | L15: 790 | M15: per gas addition
K16: Electrical (2 duplexes) | L16: 543.12 | M16: per layer
A17: Standard Top Arm | B17: Spring | D17: 600 | E17: 800 | F17: 1000 | G17: 1200 | H17: 1400 | I17: 1600 | K17: Electrical (3 duplexes) | L17: 997.33 | M17: per layer
A18: Spring Bottom Arm | B18: 33594.72 | C18: 200 | D18: =SUM($B$18+T4) -> 33594.72 | E18: =SUM($B$18+U4) -> 33594.72 | F18: =SUM($B$18+V4) -> 33594.72 | G18: =SUM($B$18+W4) -> 33594.72 | H18: na | I18: na | K18: Data | L18: 0
A19: (articulating - 1000mm) | C19: 400 | D19: =SUM($B$18+T5) -> 35569.63 | E19: =SUM($B$18+U5) -> 35569.63 | F19: =SUM($B$18+V5) -> 35569.63 | G19: =SUM($B$18+W5) -> 35569.63 | H19: na | I19: na | K19: Nitrogen Regulator | L19: 2105.92 | M19: per boom
C20: 600 | D20: =SUM($B$18+T6) -> 37549.47 | E20: =SUM($B$18+U6) -> 37549.47 | F20: =SUM($B$18+V6) -> 37549.47 | G20: =SUM($B$18+W6) -> 37549.47 | H20: na | I20: na | K20: Data Pass thru | L20: 770.21333 | M20: per boom
C21: 800 | D21: =SUM($B$18+T7) -> 39588.59 | E21: =SUM($B$18+U7) -> 39588.59 | F21: =SUM($B$18+V7) -> 39588.59 | G21: =SUM($B$18+W7) -> 39588.59 | H21: na | I21: na | K21: Tandem Mount with 1 future boom option | L21: 3393.2067 | M21: per mount
C22: 1000 | D22: =SUM($B$18+T8) -> 41622.75 | E22: =SUM($B$18+U8) -> 41622.75 | F22: =SUM($B$18+V8) -> 41622.75 | G22: =SUM($B$18+W8) -> 41622.75 | H22: na | I22: na | K22: Rails
K23: Shelfs | L23: 1344.6222 | M23: per shelf
A24: XL Top Arm | B24: Spring XL | D24: 600 | E24: 800 | F24: 1000 | G24: 1200 | H24: 1400 | I24: 1600
A25: Spring Bottom Arm | B25: 38315.52 | C25: 200 | D25: =SUM($B$25+T4) -> 38315.52 | E25: =SUM($B$25+U4) -> 38315.52 | F25: =SUM($B$25+V4) -> 38315.52 | G25: =SUM($B$25+W4) -> 38315.52 | H25: =SUM($B$25+X4) -> 39907.07 | I25: =SUM($B$25+Y4) -> 41607.49
A26: (articulating - 1000mm) | C26: 400 | D26: =SUM($B$25+T5) -> 40290.43 | E26: =SUM($B$25+U5) -> 40290.43 | F26: =SUM($B$25+V5) -> 40290.43 | G26: =SUM($B$25+W5) -> 40290.43 | H26: =SUM($B$25+X5) -> 41882.38 | I26: =SUM($B$25+Y5) -> 43582.4
C27: 600 | D27: =SUM($B$25+T6) -> 42270.27 | E27: =SUM($B$25+U6) -> 42270.27 | F27: =SUM($B$25+V6) -> 42270.27 | G27: =SUM($B$25+W6) -> 42270.27 | H27: =SUM($B$25+X6) -> 43861.82 | I27: =SUM($B$25+Y6) -> 45562.24
C28: 800 | D28: =SUM($B$25+T7) -> 44309.39 | E28: =SUM($B$25+U7) -> 44309.39 | F28: =SUM($B$25+V7) -> 44309.39 | G28: =SUM($B$25+W7) -> 44309.39 | H28: =SUM($B$25+X7) -> 45900.94 | I28: =SUM($B$25+Y7) -> 47601.36
C29: 1000 | D29: =SUM($B$25+T8) -> 46343.55 | E29: =SUM($B$25+U8) -> 46343.55 | F29: =SUM($B$25+V8) -> 46343.55 | G29: =SUM($B$25+W8) -> 46343.55 | H29: =SUM($B$25+X8) -> 47935.1 | I29: =SUM($B$25+Y8) -> 49635.52
A31: Standard Top Arm | B31: Fixed | D31: 600 | E31: 800 | F31: 1000 | G31: 1200 | H31: 1400 | I31: 1600
A32: Standard Fixeed Arm (1000mm) | B32: 23781.02 | C32: 200 | D32: =SUM($B$32+T4) -> 23781.02 | E32: =SUM($B$32+U4) -> 23781.02 | F32: =SUM($B$32+V4) -> 23781.02 | G32: =SUM($B$32+W4) -> 23781.02 | H32: na | I32: na
C33: 400 | D33: =SUM($B$32+T5) -> 25755.93 | E33: =SUM($B$32+U5) -> 25755.93 | F33: =SUM($B$32+V5) -> 25755.93 | G33: =SUM($B$32+W5) -> 25755.93 | H33: na | I33: na
C34: 600 | D34: =SUM($B$32+T6) -> 27735.77 | E34: =SUM($B$32+U6) -> 27735.77 | F34: =SUM($B$32+V6) -> 27735.77 | G34: =SUM($B$32+W6) -> 27735.77 | H34: na | I34: na
C35: 800 | D35: =SUM($B$32+T7) -> 29774.89 | E35: =SUM($B$32+U7) -> 29774.89 | F35: =SUM($B$32+V7) -> 29774.89 | G35: =SUM($B$32+W7) -> 29774.89 | H35: na | I35: na
C36: 1000 | D36: =SUM($B$32+T8) -> 31809.05 | E36: =SUM($B$32+U8) -> 31809.05 | F36: =SUM($B$32+V8) -> 31809.05 | G36: =SUM($B$32+W8) -> 31809.05 | H36: na | I36: na
A38: XL Top Arm | B38: Fixed XL | D38: 600 | E38: 800 | F38: 1000 | G38: 1200 | H38: 1400 | I38: 1600
A39: Standard Fixeed Arm (1000mm) | B39: 27382.03 | C39: 200 | D39: =SUM($B$39+T4) -> 27382.03 | E39: =SUM($B$39+U4) -> 27382.03 | F39: =SUM($B$39+V4) -> 27382.03 | G39: =SUM($B$39+W4) -> 27382.03 | H39: =SUM($B$39+X4) -> 28973.58 | I39: =SUM($B$39+Y4) -> 30674
C40: 400 | D40: =SUM($B$39+T5) -> 29356.94 | E40: =SUM($B$39+U5) -> 29356.94 | F40: =SUM($B$39+V5) -> 29356.94 | G40: =SUM($B$39+W5) -> 29356.94 | H40: =SUM($B$39+X5) -> 30948.89 | I40: =SUM($B$39+Y5) -> 32648.91
C41: 600 | D41: =SUM($B$39+T6) -> 31336.78 | E41: =SUM($B$39+U6) -> 31336.78 | F41: =SUM($B$39+V6) -> 31336.78 | G41: =SUM($B$39+W6) -> 31336.78 | H41: =SUM($B$39+X6) -> 32928.33 | I41: =SUM($B$39+Y6) -> 34628.75
C42: 800 | D42: =SUM($B$39+T7) -> 33375.9 | E42: =SUM($B$39+U7) -> 33375.9 | F42: =SUM($B$39+V7) -> 33375.9 | G42: =SUM($B$39+W7) -> 33375.9 | H42: =SUM($B$39+X7) -> 34967.45 | I42: =SUM($B$39+Y7) -> 36667.87
C43: 1000 | D43: =SUM($B$39+T8) -> 35410.06 | E43: =SUM($B$39+U8) -> 35410.06 | F43: =SUM($B$39+V8) -> 35410.06 | G43: =SUM($B$39+W8) -> 35410.06 | H43: =SUM($B$39+X8) -> 37001.61 | I43: =SUM($B$39+Y8) -> 38702.03
A45: XXL Top Arm | B45: Fixed XXL | D45: 600 | E45: 800 | F45: 1000 | G45: 1200 | H45: 1400 | I45: 1600
A46: Standard Fixeed Arm (1000mm) | B46: 31047.26 | C46: 200 | D46: =SUM($B$46+T4) -> 31047.26 | E46: =SUM($B$46+U4) -> 31047.26 | F46: =SUM($B$46+V4) -> 31047.26 | G46: =SUM($B$46+W4) -> 31047.26 | H46: =SUM($B$46+X4) -> 32638.81 | I46: =SUM($B$46+Y4) -> 34339.23
C47: 400 | D47: =SUM($B$46+T5) -> 33022.17 | E47: =SUM($B$46+U5) -> 33022.17 | F47: =SUM($B$46+V5) -> 33022.17 | G47: =SUM($B$46+W5) -> 33022.17 | H47: =SUM($B$46+X5) -> 34614.12 | I47: =SUM($B$46+Y5) -> 36314.14
C48: 600 | D48: =SUM($B$46+T6) -> 35002.01 | E48: =SUM($B$46+U6) -> 35002.01 | F48: =SUM($B$46+V6) -> 35002.01 | G48: =SUM($B$46+W6) -> 35002.01 | H48: =SUM($B$46+X6) -> 36593.56 | I48: =SUM($B$46+Y6) -> 38293.98
C49: 800 | D49: =SUM($B$46+T7) -> 37041.13 | E49: =SUM($B$46+U7) -> 37041.13 | F49: =SUM($B$46+V7) -> 37041.13 | G49: =SUM($B$46+W7) -> 37041.13 | H49: =SUM($B$46+X7) -> 38632.68 | I49: =SUM($B$46+Y7) -> 40333.1
C50: 1000 | D50: =SUM($B$46+T8) -> 39075.29 | E50: =SUM($B$46+U8) -> 39075.29 | F50: =SUM($B$46+V8) -> 39075.29 | G50: =SUM($B$46+W8) -> 39075.29 | H50: =SUM($B$46+X8) -> 40666.84 | I50: =SUM($B$46+Y8) -> 42367.26
A52: XL Top Arm | B52: Large Monitor | D52: 600 | E52: 800 | F52: 1000 | G52: 1200 | H52: 1400 | I52: 1600
A53: Spring Bottom Arm | B53: 48126.24 | D53: =SUM($B$53+T4) -> 48126.24 | E53: =SUM($B$53+U4) -> 48126.24 | F53: =SUM($B$53+V4) -> 48126.24 | G53: =SUM($B$53+W4) -> 48126.24 | H53: =SUM($B$53+X4) -> 49717.79 | I53: =SUM($B$53+Y4) -> 51418.21
A54: (articulating - 1000mm)
